Workbook
Name ComponentIDs: 'Bausteine'!$A$2:$A$76
Name InfantryIDs: 'Infanterie'!$A$2:$A$4

Sheet Hinweise
A1: YMCA Modular – Kalibrierung
A2: Referenz | B2: Quellblock-Abgleich: 9d8a9dec (integrierter Game-Stand), siehe reference-audit.md.
A3: Status | B3: Experimentelle Zahlen; keine Spielregeln oder grafische/volle Verhaltensgleichheit.
A4: Eingaben | B4: Parameter und Bausteinwerte sind editierbar. Formeln berechnen Entwuerfe/Vergleich beim Öffnen neu.
A5: Preise | B5: Hardwarekosten minus CP-Anforderung mal globaler CP-Creditwert. Keine Sonderrabatte.
A6: Massenproduktion | B6: Separates Fertigungsmodul: vorläufig 95% aller Hardwarekosten, danach globaler CP-Abzug. Preisfit ist separate Studie.
A7: Arbeitsfluss | B7: catalog.json ist Quelle. export_excel.py erzeugt eine neue Momentaufnahme, kein Excel-Import.
A8: Schutz | B8: Exporter überschreibt keine bestehende Arbeitsmappe; für neue Daten neuen Dateinamen verwenden.
A9: Erweiterung | B9: Neue Bausteine/Designs in JSON eintragen und neu exportieren. Manuelles Zeilenanfügen wird nicht automatisch verdrahtet.
A10: Validierung | B10: Excel prüft nur elektrische/physische Grenzen; Rolle, Fraktion, Montage und Besatzungskosten-Konsistenz im Python-Rechner prüfen.
A11: Bunkerpreis | B11: Leeres Bunkermodul plus separat gewählte Startbesatzung. Infanteriepreise und Besatzungszeilen sind editierbar; Kosten/Masse werden einmal addiert.
A12: Aufsatzplatz | B12: Gatling, Bunker und Lautsprecher teilen roof. Vollständige Slot-/Fraktions-/Kapazitätsprüfung weiterhin im Python-Rechner.
A13: Grafikentwürfe | B13: Flame/Mortar Roof / draft sind nur Offline-Kalkulation. Sprites geprüft, Montage auf Overlord noch nicht. Kein Originalvergleich oder spielbarer Actor.
... A21: Referenzbedingungen | B21: Base states without isotope stability, horde, uranium or veterancy bonuses. Isotope stability now applies 90% received damage as well as death-explosion suppression; not modeled as extra HP.

Sheet Parameter
A1: Parameter | B1: Wert
A2: Credits pro CP | B2: 300
A3: Geschwindigkeitsexponent | B3: 0.5
A4: Katalogbudget | B4: 50

Sheet Bausteine
A1: ID | B1: Rolle | C1: Fraktionen | D1: Katalog-Tier | E1: CP | F1: Tech | G1: Hardwarepreis | H1: Masse kg | I1: Bedarf kWe | J1: Motor kWm | K1: Generator Wirkungsgrad | L1: Generator max kWe | M1: HP Chassis | N1: Panzerung | O1: Chassis Masse % | P1: Chassis HP % | Q1: Chassis Preis % | R1: Referenzmasse kg | S1: Referenzleistung kWm | T1: Referenztempo | U1: Max Tempo | V1: Max Masse kg | W1: Waffentraegerplaetze | X1: Zusatzplaetze | Y1: Salve | Z1: Schussabstand Ticks | AA1: Nachladen Ticks | AB1: Reichweite Zellen | AC1: Rohschaden | AD1: Hinweis | AE1: Quelle | AF1: Kompatibilitaet | AG1: Ausrüstung erlaubt | AH1: Waffen erlaubt | AI1: Munition erlaubt | AJ1: Anzeigename | AK1: Hardware Fertigung % | AL1: Munition Reichweite Override | AM1: Transportkapazitaet | AN1: Ausschluesse | AO1: Aufsatzplatz | AP1: Zusatztraeger erlaubt | AQ1: Infanterie erlaubt | AR1: Mindestreichweite Zellen | AS1: Feuerverzug Ticks | AT1: Standardfahrwerk | AU1: Fahrwerke erlaubt | AV1: Locomotor | AW1: Fahrwerkstyp | AX1: Fahrwerk Wenderate | AY1: Rumpf Wendelimit
A2: diesel-light | B2: drive | C2: ["gdi", "nod", "allies", "soviet"] | D2: 0 | E2: 0 | F2: 1 | G2: 60 | H2: 250 | I2: 0 | J2: 250 | K2: 0 | L2: 0 | M2: 0 | O2: 0 | P2: 0 | Q2: 0 | R2: 0 | S2: 0 | T2: 0 | U2: 0 | V2: 0 | W2: 0 | X2: 0 | Y2: 0 | Z2: 0 | AA2: 0 | AB2: 0 | AC2: 0 | AD2: New shared scout motor; all physical values experimental. | AJ2: Leichter Dieselmotor | AK2: 0 | AL2: 0 | AM2: 0 | AN2: 0 | AO2: 0 | AP2: 0 | AQ2: 0 | AR2: 0 | AS2: 0 | AT2: 0 | AU2: 0 | AV2: 0 | AW2: 0 | AX2: 0 | AY2: 0
A3: light | B3: armor | C3: ["gdi", "nod", "allies", "soviet"] | D3: 0 | E3: 0 | F3: 1 | G3: 0 | H3: 0 | I3: 0 | J3: 0 | K3: 0 | L3: 0 | M3: 0 | N3: Light | O3: 100 | P3: 100 | Q3: 100 | R3: 0 | S3: 0 | T3: 0 | U3: 0 | V3: 0 | W3: 0 | X3: 0 | Y3: 0 | Z3: 0 | AA3: 0 | AB3: 0 | AC3: 0 | AE3: ^LightArmor | AJ3: Leichte Panzerung | AK3: 0 | AL3: 0 | AM3: 0 | AN3: 0 | AO3: 0 | AP3: 0 | AQ3: 0 | AR3: 0 | AS3: 0 | AT3: 0 | AU3: 0 | AV3: 0 | AW3: 0 | AX3: 0 | AY3: 0
A4: scout-sensors | B4: equipment | C4: ["gdi", "nod"] | D4: 0 | E4: 0 | F4: 1 | G4: 50 | H4: 50 | I4: 5 | J4: 0 | K4: 0 | L4: 0 | M4: 0 | O4: 0 | P4: 0 | Q4: 0 | R4: 0 | S4: 0 | T4: 0 | U4: 0 | V4: 0 | W4: 0 | X4: 0 | Y4: 0 | Z4: 0 | AA4: 0 | AB4: 0 | AC4: 0 | AD4: Shared 50-credit proposal. Reuse detection/shroud traits, not detection simulated by calculator. | AE4: ^SensorEquipment | AJ4: Spähsensoren | AK4: 0 | AL4: 0 | AM4: 0 | AN4: 0 | AO4: 0 | AP4: 0 | AQ4: 0 | AR4: 0 | AS4: 0 | AT4: 0 | AU4: 0 | AV4: 0 | AW4: 0 | AX4: 0 | AY4: 0
A5: scout-mg-mount | B5: carrier | C5: ["gdi", "nod"] | D5: 0 | E5: 0 | F5: 1 | G5: 25 | H5: 100 | I5: 0 | J5: 0 | K5: 0 | L5: 0 | M5: 0 | O5: 0 | P5: 0 | Q5: 0 | R5: 0 | S5: 0 | T5: 0 | U5: 0 | V5: 0 | W5: 0 | X5: 0 | Y5: 5 | Z5: 0 | AA5: 30 | AB5: 0 | AC5: 0 | AE5: M60mgTD; HMMV / BGGY turrets | AH5: ["scout-mg"] | AJ5: Leichte MG-Lafette | AK5: 0 | AL5: 0 | AM5: 0 | AN5: 0 | AO5: 0 | AP5: 0 | AQ5: 0 | AR5: 0 | AS5: 0 | AT5: 0 | AU5: 0 | AV5: 0 | AW5: 0 | AX5: 0 | AY5: 0
A6: scout-mg | B6: weapon | C6: ["gdi", "nod"] | D6: 0 | E6: 0 | F6: 1 | G6: 65 | H6: 100 | I6: 0 | J6: 0 | K6: 0 | L6: 0 | M6: 0 | O6: 0 | P6: 0 | Q6: 0 | R6: 0 | S6: 0 | T6: 0 | U6: 0 | V6: 0 | W6: 0 | X6: 0 | Y6: 0 | Z6: 0 | AA6: 0 | AB6: 4 | AC6: 0 | AE6: M60mgTD | AI6: ["scout-mg-rounds"] | AJ6: Spähfahrzeug-MG | AK6: 0 | AL6: 0 | AM6: 0 | AN6: 0 | AO6: 0 | AP6: 0 | AQ6: 0 | AR6: 0 | AS6: 0 | AT6: 0 | AU6: 0 | AV6: 0 | AW6: 0 | AX6: 0 | AY6: 0
A7: scout-mg-rounds | B7: ammunition | C7: ["gdi", "nod"] | D7: 0 | E7: 0 | F7: 1 | G7: 25 | H7: 100 | I7: 0 | J7: 0 | K7: 0 | L7: 0 | M7: 0 | O7: 0 | P7: 0 | Q7: 0 | R7: 0 | S7: 0 | T7: 0 | U7: 0 | V7: 0 | W7: 0 | X7: 0 | Y7: 0 | Z7: 0 | AA7: 0 | AB7: 0 | AC7: 1000 | AE7: M60mgTD / ^LightMG / ^Bullet | AJ7: MG-Munition | AK7: 0 | AL7: 0 | AM7: 0 | AN7: 0 | AO7: 0 | AP7: 0 | AQ7: 0 | AR7: 0 | AS7: 0 | AT7: 0 | AU7: 0 | AV7: 0 | AW7: 0 | AX7: 0 | AY7: 0
A8: light-cannon-mount | B8: carrier | C8: ["nod", "soviet"] | D8: 0 | E8: 0 | F8: 1 | G8: 75 | H8: 500 | I8: 0 | J8: 0 | K8: 0 | L8: 0 | M8: 0 | O8: 0 | P8: 0 | Q8: 0 | R8: 0 | S8: 0 | T8: 0 | U8: 0 | V8: 0 | W8: 0 | X8: 0 | Y8: 1 | Z8: 0 | AA8: 36 | AB8: 0 | AC8: 0 | AE8: 30mm / LTNK / T-34 / Devil_Tank | AH8: ["light-cannon"] | AJ8: Leichter Kanonenturm | AK8: 0 | AL8: 0 | AM8: 0 | AN8: 0 | AO8: 0 | AP8: 0 | AQ8: 0 | AR8: 0 | AS8: 0 | AT8: 0 | AU8: 0 | AV8: 0 | AW8: 0 | AX8: 0 | AY8: 0
A9: light-cannon | B9: weapon | C9: ["nod", "soviet"] | D9: 0 | E9: 0 | F9: 1 | G9: 175 | H9: 500 | I9: 0 | J9: 0 | K9: 0 | L9: 0 | M9: 0 | O9: 0 | P9: 0 | Q9: 0 | R9: 0 | S9: 0 | T9: 0 | U9: 0 | V9: 0 | W9: 0 | X9: 0 | Y9: 0 | Z9: 0 | AA9: 0 | AB9: 4.75 | AC9: 0 | AE9: 30mm / 25mm / ^Cannon | AI9: ["light-tank-shell"] | AJ9: Leichte Panzerkanone | AK9: 0 | AL9: 0 | AM9: 0 | AN9: 0 | AO9: 0 | AP9: 0 | AQ9: 0 | AR9: 0 | AS9: 0 | AT9: 0 | AU9: 0 | AV9: 0 | AW9: 0 | AX9: 0 | AY9: 0
A10: light-tank-shell | B10: ammunition | C10: ["nod", "soviet"] | D10: 0 | E10: 0 | F10: 1 | G10: 50 | H10: 400 | I10: 0 | J10: 0 | K10: 0 | L10: 0 | M10: 0 | O10: 0 | P10: 0 | Q10: 0 | R10: 0 | S10: 0 | T10: 0 | U10: 0 | V10: 0 | W10: 0 | X10: 0 | Y10: 0 | Z10: 0 | AA10: 0 | AB10: 0 | AC10: 3500 | AD10: Existing versus table is NOT the medium ShellHeavy payload. | AE10: 30mm / ^Shell | AJ10: Leichte Panzergranaten | AK10: 0 | AL10: 0 | AM10: 0 | AN10: 0 | AO10: 0 | AP10: 0 | AQ10: 0 | AR10: 0 | AS10: 0 | AT10: 0 | AU10: 0 | AV10: 0 | AW10: 0 | AX10: 0 | AY10: 0
A11: medium-cannon-mount | B11: carrier | C11: ["gdi", "allies"] | D11: 0 | E11: 0 | F11: 1 | G11: 100 | H11: 500 | I11: 0 | J11: 0 | K11: 0 | L11: 0 | M11: 0 | O11: 0 | P11: 0 | Q11: 0 | R11: 0 | S11: 0 | T11: 0 | U11: 0 | V11: 0 | W11: 0 | X11: 0 | Y11: 1 | Z11: 0 | AA11: 50 | AB11: 0 | AC11: 0 | AE11: 90mm / 120mm | AH11: ["medium-cannon"] | AJ11: Mittlerer Kanonenturm | AK11: 0 | AL11: 0 | AM11: 0 | AN11: 0 | AO11: 0 | AP11: 0 | AQ11: 0 | AR11: 0 | AS11: 0 | AT11: 0 | AU11: 0 | AV11: 0 | AW11: 0 | AX11: 0 | AY11: 0
A12: soviet-twin-mount | B12: carrier | C12: ["soviet"] | D12: 0 | E12: 0 | F12: 2 | G12: 200 | H12: 1000 | I12: 0 | J12: 0 | K12: 0 | L12: 0 | M12: 0 | O12: 0 | P12: 0 | Q12: 0 | R12: 0 | S12: 0 | T12: 0 | U12: 0 | V12: 0 | W12: 0 | X12: 0 | Y12: 2 | Z12: 0 | AA12: 70 | AB12: 0 | AC12: 0 | AE12: 125mm / Heavy_Tank | AH12: ["medium-cannon"] | AJ12: Zwillings-Panzerkanonenturm | AK12: 0 | AL12: 0 | AM12: 0 | AN12: 0 | AO12: 0 | AP12: 0 | AQ12: 0 | AR12: 0 | AS12: 0 | AT12: 0 | AU12: 0 | AV12: 0 | AW12: 0 | AX12: 0 | AY12: 0
A13: medium-cannon | B13: weapon | C13: ["gdi", "allies", "soviet"] | D13: 0 | E13: 0 | F13: 1 | G13: 200 | H13: 500 | I13: 0 | J13: 0 | K13: 0 | L13: 0 | M13: 0 | O13: 0 | P13: 0 | Q13: 0 | R13: 0 | S13: 0 | T13: 0 | U13: 0 | V13: 0 | W13: 0 | X13: 0 | Y13: 0 | Z13: 0 | AA13: 0 | AB13: 4.75 | AC13: 0 | AD13: Shared scalar gun family. Carrier chooses single/twin cadence; full legacy source binding retains different reports and muzzle/recoil behavior. No caliber inferred for new designs. | AE13: 90mm / 120mm / 125mm | AI13: ["medium-tank-shell"] | AJ13: Mittlere Panzerkanone | AK13: 0 | AL13: 0 | AM13: 0 | AN13: 0 | AO13: 0 | AP13: 0 | AQ13: 0 | AR13: 0 | AS13: 0 | AT13: 0 | AU13: 0 | AV13: 0 | AW13: 0 | AX13: 0 | AY13: 0
A14: medium-tank-shell | B14: ammunition | C14: ["gdi", "allies", "soviet"] | D14: 0 | E14: 0 | F14: 1 | G14: 50 | H14: 400 | I14: 0 | J14: 0 | K14: 0 | L14: 0 | M14: 0 | O14: 0 | P14: 0 | Q14: 0 | R14: 0 | S14: 0 | T14: 0 | U14: 0 | V14: 0 | W14: 0 | X14: 0 | Y14: 0 | Z14: 0 | AA14: 0 | AB14: 0 | AC14: 4000 | AD14: Must reuse full existing versus/effect package; raw damage alone is not equivalence. | AE14: ^Cannon / ^ShellHeavy | AJ14: Panzergranaten gegen schwere Ziele | AK14: 0 | AL14: 0 | AM14: 0 | AN14: 0 | AO14: 0 | AP14: 0 | AQ14: 0 | AR14: 0 | AS14: 0 | AT14: 0 | AU14: 0 | AV14: 0 | AW14: 0 | AX14: 0 | AY14: 0
A15: field-artillery-mount | B15: carrier | C15: ["allies"] | D15: 0 | E15: 0 | F15: 1 | G15: 50 | H15: 500 | I15: 0 | J15: 0 | K15: 0 | L15: 0 | M15: 0 | O15: 0 | P15: 0 | Q15: 0 | R15: 0 | S15: 0 | T15: 0 | U15: 0 | V15: 0 | W15: 0 | X15: 0 | Y15: 1 | Z15: 0 | AA15: 60 | AB15: 0 | AC15: 0 | AD15: Fixed assembly, not a freely rotatable roof turret. | AE15: ARTY / AttackFrontal / 155mm | AH15: ["field-artillery"] | AJ15: Festes Artilleriegeschütz | AK15: 0 | AL15: 0 | AM15: 0 | AN15: 0 | AO15: 0 | AP15: 0 | AQ15: 0 | AR15: 0 | AS15: 0 | AT15: 0 | AU15: 0 | AV15: 0 | AW15: 0 | AX15: 0 | AY15: 0
A16: field-artillery | B16: weapon | C16: ["allies"] | D16: 0 | E16: 0 | F16: 1 | G16: 200 | H16: 700 | I16: 0 | J16: 0 | K16: 0 | L16: 0 | M16: 0 | O16: 0 | P16: 0 | Q16: 0 | R16: 0 | S16: 0 | T16: 0 | U16: 0 | V16: 0 | W16: 0 | X16: 0 | Y16: 0 | Z16: 0 | AA16: 0 | AB16: 14 | AC16: 0 | AE16: 155mm / ^Artillery / ^ShellArtillery | AI16: ["field-artillery-he"] | AJ16: Feldartillerie | AK16: 0 | AL16: 0 | AM16: 0 | AN16: 0 | AO16: 0 | AP16: 0 | AQ16: 0 | AR16: 4 | AS16: 0 | AT16: 0 | AU16: 0 | AV16: 0 | AW16: 0 | AX16: 0 | AY16: 0
A17: field-artillery-he | B17: ammunition | C17: ["allies"] | D17: 0 | E17: 0 | F17: 1 | G17: 50 | H17: 500 | I17: 0 | J17: 0 | K17: 0 | L17: 0 | M17: 0 | O17: 0 | P17: 0 | Q17: 0 | R17: 0 | S17: 0 | T17: 0 | U17: 0 | V17: 0 | W17: 0 | X17: 0 | Y17: 0 | Z17: 0 | AA17: 0 | AB17: 0 | AC17: 6500 | AD17: Not Juggernaut or mortar ammunition: preserve full projectile spread/effects and targeting. | AE17: 155mm | AJ17: Artillerie-Sprenggranaten | AK17: 0 | AL17: 0 | AM17: 0 | AN17: 0 | AO17: 0 | AP17: 0 | AQ17: 0 | AR17: 0 | AS17: 0 | AT17: 0 | AU17: 0 | AV17: 0 | AW17: 0 | AX17: 0 | AY17: 0
A18: humvee-hull | B18: chassis | C18: ["gdi"] | D18: 1 | E18: 0 | F18: 1 | G18: 125 | H18: 1600 | I18: 5 | J18: 0 | K18: 0 | L18: 0 | M18: 15000 | O18: 0 | P18: 0 | Q18: 0 | R18: 2500 | S18: 210 | T18: 157 | U18: 180 | V18: 6000 | W18: 1 | X18: 1 | Y18: 0 | Z18: 0 | AA18: 0 | AB18: 0 | AC18: 0 | AE18: HMMV | AF18: {"carrier": ["scout-mg-mount"], "drive": ["diesel-light"]} | AG18: ["scout-sensors"] | AJ18: Hum-Vee Rumpf | AK18: 0 | AL18: 0 | AM18: 0 | AN18: 0 | AO18: 0 | AP18: 0 | AQ18: 0 | AR18: 0 | AS18: 0 | AT18: wheels-light | AU18: ["wheels-light"] | AV18: 0 | AW18: 0 | AX18: 0 | AY18: 80
A19: buggy-hull | B19: chassis | C19: ["nod"] | D19: 1 | E19: 0 | F19: 1 | G19: 75 | H19: 1300 | I19: 5 | J19: 0 | K19: 0 | L19: 0 | M19: 14000 | O19: 0 | P19: 0 | Q19: 0 | R19: 2200 | S19: 210 | T19: 157 | U19: 180 | V19: 6000 | W19: 1 | X19: 1 | Y19: 0 | Z19: 0 | AA19: 0 | AB19: 0 | AC19: 0 | AE19: BGGY | AF19: {"carrier": ["scout-mg-mount"], "drive": ["diesel-light"]} | AG19: ["scout-sensors"] | AJ19: Buggy Rumpf | AK19: 0 | AL19: 0 | AM19: 0 | AN19: 0 | AO19: 0 | AP19: 0 | AQ19: 0 | AR19: 0 | AS19: 0 | AT19: wheels-light | AU19: ["wheels-light"] | AV19: 0 | AW19: 0 | AX19: 0 | AY19: 48
A20: nod-light-hull | B20: chassis | C20: ["nod"] | D20: 1 | E20: 0 | F20: 1 | G20: 125 | H20: 6500 | I20: 10 | J20: 0 | K20: 0 | L20: 0 | M20: 41250 | O20: 0 | P20: 0 | Q20: 0 | R20: 10000 | S20: 460 | T20: 100 | U20: 125 | V20: 18000 | W20: 1 | X20: 1 | Y20: 0 | Z20: 0 | AA20: 0 | AB20: 0 | AC20: 0 | AE20: LTNK | AF20: {"carrier": ["light-cannon-mount"], "drive": ["diesel"]} | AG20: [] | AJ20: Nod Leichtpanzerrumpf | AK20: 0 | AL20: 0 | AM20: 0 | AN20: 0 | AO20: 0 | AP20: 0 | AQ20: 0 | AR20: 0 | AS20: 0 | AT20: tracks-standard | AU20: ["tracks-standard"] | AV20: 0 | AW20: 0 | AX20: 0 | AY20: 48
A21: t34-hull | B21: chassis | C21: ["soviet"] | D21: 1 | E21: 0 | F21: 1 | G21: 100 | H21: 6500 | I21: 10 | J21: 0 | K21: 0 | L21: 0 | M21: 42000 | O21: 0 | P21: 0 | Q21: 0 | R21: 10000 | S21: 460 | T21: 100 | U21: 125 | V21: 18000 | W21: 1 | X21: 1 | Y21: 0 | Z21: 0 | AA21: 0 | AB21: 0 | AC21: 0 | AE21: T-34 | AF21: {"carrier": ["light-cannon-mount"], "drive": ["diesel"]} | AG21: [] | AJ21: T-34 Rumpf | AK21: 0 | AL21: 0 | AM21: 0 | AN21: 0 | AO21: 0 | AP21: 0 | AQ21: 0 | AR21: 0 | AS21: 0 | AT21: tracks-standard | AU21: ["tracks-standard"] | AV21: 0 | AW21: 0 | AX21: 0 | AY21: 48
A22: devil-hull | B22: chassis | C22: ["soviet"] | D22: 1 | E22: 0 | F22: 1 | G22: 200 | H22: 7000 | I22: 10 | J22: 0 | K22: 0 | L22: 0 | M22: 45000 | O22: 0 | P22: 0 | Q22: 0 | R22: 10500 | S22: 460 | T22: 90 | U22: 115 | V22: 18000 | W22: 1 | X22: 1 | Y22: 0 | Z22: 0 | AA22: 0 | AB22: 0 | AC22: 0 | AE22: Devil_Tank | AF22: {"carrier": ["light-cannon-mount"], "drive": ["diesel"]} | AG22: [] | AJ22: Devil-Tank Rumpf | AK22: 0 | AL22: 0 | AM22: 0 | AN22: 0 | AO22: 0 | AP22: 0 | AQ22: 0 | AR22: 0 | AS22: 0 | AT22: tracks-standard | AU22: ["tracks-standard"] | AV22: 0 | AW22: 0 | AX22: 0 | AY22: 48
A23: gdi-battle-hull | B23: chassis | C23: ["gdi"] | D23: 1 | E23: 0 | F23: 1 | G23: 350 | H23: 8000 | I23: 10 | J23: 0 | K23: 0 | L23: 0 | M23: 52000 | O23: 0 | P23: 0 | Q23: 0 | R23: 11500 | S23: 460 | T23: 82 | U23: 110 | V23: 20000 | W23: 1 | X23: 1 | Y23: 0 | Z23: 0 | AA23: 0 | AB23: 0 | AC23: 0 | AE23: MTNK | AF23: {"carrier": ["medium-cannon-mount"], "drive": ["diesel"]} | AG23: [] | AJ23: GDI Kampfpanzer-Rumpf | AK23: 0 | AL23: 0 | AM23: 0 | AN23: 0 | AO23: 0 | AP23: 0 | AQ23: 0 | AR23: 0 | AS23: 0 | AT23: tracks-standard | AU23: ["tracks-standard"] | AV23: 0 | AW23: 0 | AX23: 0 | AY23: 48
A24: allied-medium-hull | B24: chassis | C24: ["allies"] | D24: 1 | E24: 0 | F24: 1 | G24: 250 | H24: 7500 | I24: 10 | J24: 0 | K24: 0 | L24: 0 | M24: 45000 | O24: 0 | P24: 0 | Q24: 0 | R24: 11000 | S24: 460 | T24: 82 | U24: 110 | V24: 20000 | W24: 1 | X24: 1 | Y24: 0 | Z24: 0 | AA24: 0 | AB24: 0 | AC24: 0 | AD24: Shared scalar hull family for Challenger/Leclerc/Leopard; artwork remains bound to complete actor variant. 2TNK itself is not buildable. | AE24: 2TNK | AF24: {"carrier": ["medium-cannon-mount"], "drive": ["diesel"]} | AG24: [] | AJ24: Alliierter Kampfpanzer-Rumpf | AK24: 0 | AL24: 0 | AM24: 0 | AN24: 0 | AO24: 0 | AP24: 0 | AQ24: 0 | AR24: 0 | AS24: 0 | AT24: tracks-standard | AU24: ["tracks-standard"] | AV24: 0 | AW24: 0 | AX24: 0 | AY24: 48
A25: soviet-heavy-hull | B25: chassis | C25: ["soviet"] | D25: 2 | E25: 0 | F25: 2 | G25: 450 | H25: 11000 | I25: 10 | J25: 0 | K25: 0 | L25: 0 | M25: 65000 | O25: 0 | P25: 0 | Q25: 0 | R25: 15000 | S25: 460 | T25: 68 | U25: 95 | V25: 20000 | W25: 1 | X25: 2 | Y25: 0 | Z25: 0 | AA25: 0 | AB25: 0 | AC25: 0 | AE25: Heavy_Tank | AF25: {"carrier": ["soviet-twin-mount"], "drive": ["diesel"]} | AG25: [] | AJ25: Sowjetischer schwerer Panzerrumpf | AK25: 0 | AL25: 0 | AM25: 0 | AN25: 0 | AO25: 0 | AP25: 0 | AQ25: 0 | AR25: 0 | AS25: 0 | AT25: tracks-standard | AU25: ["tracks-standard"] | AV25: 0 | AW25: 0 | AX25: 0 | AY25: 48
A26: field-artillery-hull | B26: chassis | C26: ["allies"] | D26: 1 | E26: 0 | F26: 1 | G26: 75 | H26: 5000 | I26: 10 | J26: 0 | K26: 0 | L26: 0 | M26: 10000 | O26: 0 | P26: 0 | Q26: 0 | R26: 8300 | S26: 460 | T26: 56 | U26: 80 | V26: 14000 | W26: 1 | X26: 1 | Y26: 0 | Z26: 0 | AA26: 0 | AB26: 0 | AC26: 0 | AD26: Light armor despite tracked graphics. Fixed hull/gun artwork, no free turret replacement. | AE26: ARTY | AF26: {"carrier": ["field-artillery-mount"], "drive": ["diesel"]} | AG26: [] | AJ26: Leichter Artillerierumpf | AK26: 0 | AL26: 0 | AM26: 0 | AN26: 0 | AO26: 0 | AP26: 0 | AQ26: 0 | AR26: 0 | AS26: 0 | AT26: tracks-light-artillery | AU26: ["tracks-light-artillery"] | AV26: 0 | AW26: 0 | AX26: 0 | AY26: 16
A27: tracks-standard | B27: running_gear | C27: ["china", "gdi", "nod", "allies", "soviet"] | D27: 0 | E27: 0 | F27: 1 | G27: 100 | H27: 1500 | I27: 0 | J27: 0 | K27: 0 | L27: 0 | M27: 0 | O27: 0 | P27: 0 | Q27: 0 | R27: 0 | S27: 0 | T27: 0 | U27: 150 | V27: 20000 | W27: 0 | X27: 0 | Y27: 0 | Z27: 0 | AA27: 0 | AB27: 0 | AC27: 0 | AD27: Shared provisional mechanical allocation removed from old hull values, not an extra retrofit charge. Engine movement template unchanged; hull limits turning. | AJ27: Standard-Kettenlaufwerk | AK27: 0 | AL27: 0 | AM27: 0 | AN27: 0 | AO27: 0 | AP27: 0 | AQ27: 0 | AR27: 0 | AS27: 0 | AT27: 0 | AU27: 0 | AV27: tracked | AW27: tracks | AX27: 64 | AY27: 0
A28: tracks-superheavy | B28: running_gear | C28: ["china", "gdi", "soviet"] | D28: 0 | E28: 0 | F28: 2 | G28: 250 | H28: 5000 | I28: 0 | J28: 0 | K28: 0 | L28: 0 | M28: 0 | O28: 0 | P28: 0 | Q28: 0 | R28: 0 | S28: 0 | T28: 0 | U28: 90 | V28: 45000 | W28: 0 | X28: 0 | Y28: 0 | Z28: 0 | AA28: 0 | AB28: 0 | AC28: 0 | AJ28: Schwerlast-Kettenlaufwerk | AK28: 0 | AL28: 0 | AM28: 0 | AN28: 0 | AO28: 0 | AP28: 0 | AQ28: 0 | AR28: 0 | AS28: 0 | AT28: 0 | AU28: 0 | AV28: sheavytracked | AW28: tracks | AX28: 16 | AY28: 0
A29: walker-heavy | B29: running_gear | C29: ["gdi"] | D29: 0 | E29: 0 | F29: 3 | G29: 300 | H29: 3500 | I29: 0 | J29: 0 | K29: 0 | L29: 0 | M29: 0 | O29: 0 | P29: 0 | Q29: 0 | R29: 0 | S29: 0 | T29: 0 | U29: 50 | V29: 30000 | W29: 0 | X29: 0 | Y29: 0 | Z29: 0 | AA29: 0 | AB29: 0 | AC29: 0 | AD29: Juggernaut physically walks, but its existing engine Locomotor is sheavytracked. Artwork does not determine locomotor semantics. | AJ29: Schweres Schreitwerk | AK29: 0 | AL29: 0 | AM29: 0 | AN29: 0 | AO29: 0 | AP29: 0 | AQ29: 0 | AR29: 0 | AS29: 0 | AT29: 0 | AU29: 0 | AV29: sheavytracked | AW29: walker | AX29: 16 | AY29: 0
A30: wheels-light | B30: running_gear | C30: ["gdi", "nod", "allies", "soviet"] | D30: 0 | E30: 0 | F30: 1 | G30: 50 | H30: 300 | I30: 0 | J30: 0 | K30: 0 | L30: 0 | M30: 0 | O30: 0 | P30: 0 | Q30: 0 | R30: 0 | S30: 0 | T30: 0 | U30: 180 | V30: 6000 | W30: 0 | X30: 0 | Y30: 0 | Z30: 0 | AA30: 0 | AB30: 0 | AC30: 0 | AJ30: Leichtes Radfahrwerk | AK30: 0 | AL30: 0 | AM30: 0 | AN30: 0 | AO30: 0 | AP30: 0 | AQ30: 0 | AR30: 0 | AS30: 0 | AT30: 0 | AU30: 0 | AV30: wheeled | AW30: wheels | AX30: 80 | AY30: 0
A31: tracks-light-artillery | B31: running_gear | C31: ["allies"] | D31: 0 | E31: 0 | F31: 1 | G31: 75 | H31: 1000 | I31: 0 | J31: 0 | K31: 0 | L31: 0 | M31: 0 | O31: 0 | P31: 0 | Q31: 0 | R31: 0 | S31: 0 | T31: 0 | U31: 130 | V31: 14000 | W31: 0 | X31: 0 | Y31: 0 | Z31: 0 | AA31: 0 | AB31: 0 | AC31: 0 | AD31: No infantry crush: exact existing lighttracked locomotor, not ordinary tracked. | AJ31: Leichtes Kettenlaufwerk | AK31: 0 | AL31: 0 | AM31: 0 | AN31: 0 | AO31: 0 | AP31: 0 | AQ31: 0 | AR31: 0 | AS31: 0 | AT31: 0 | AU31: 0 | AV31: lighttracked | AW31: tracks | AX31: 64 | AY31: 0
A32: mortar-roof-carrier | B32: carrier | C32: ["china"] | D32: 1 | E32: 0 | F32: 3 | G32: 200 | H32: 400 | I32: 2 | J32: 0 | K32: 0 | L32: 0 | M32: 0 | O32: 0 | P32: 0 | Q32: 0 | R32: 0 | S32: 0 | T32: 0 | U32: 0 | V32: 0 | W32: 0 | X32: 0 | Y32: 1 | Z32: 0 | AA32: 60 | AB32: 0 | AC32: 0 | AD32: Experimental China gameplay carrier using existing artillery artwork, not Allied weapon access. Proposed 200-credit mount, 12 turn speed. Offset, scale, recoil and muzzle on Overlord not live-tested; infantry Mortar FireDelay 15 retained as a trial. | AE32: batf.artillery.turret / artytur.shp | AH32: ["roof-mortar"] | AJ32: Leichter Artillerie-Aufsatzturm | AK32: 0 | AL32: 0 | AM32: 0 | AN32: 0 | AO32: 0 | AP32: 0 | AQ32: 0 | AR32: 0 | AS32: 15 | AT32: 0 | AU32: 0 | AV32: 0 | AW32: 0 | AX32: 0 | AY32: 0
A33: roof-mortar | B33: weapon | C33: ["china"] | D33: 1 | E33: 0 | F33: 3 | G33: 350 | H33: 600 | I33: 3 | J33: 0 | K33: 0 | L33: 0 | M33: 0 | O33: 0 | P33: 0 | Q33: 0 | R33: 0 | S33: 0 | T33: 0 | U33: 0 | V33: 0 | W33: 0 | X33: 0 | Y33: 0 | Z33: 0 | AA33: 0 | AB33: 11 | AC33: 0 | AD33: Existing BulletCA: speed 166, launch angle 92, inaccuracy 768, BOMB image. New vehicle price, mass and power are proposals, not inferred from 150-credit infantry. | AE33: Mortar / MortarPrototype | AI33: ["mortar-he"] | AJ33: Leichter Fahrzeugmoerser | AK33: 0 | AL33: 0 | AM33: 0 | AN33: 0 | AO33: 0 | AP33: 0 | AQ33: 0 | AR33: 1 | AS33: 0 | AT33: 0 | AU33: 0 | AV33: 0 | AW33: 0 | AX33: 0 | AY33: 0
A34: mortar-he | B34: ammunition | C34: ["china"] | D34: 0 | E34: 0 | F34: 3 | G34: 100 | H34: 300 | I34: 0 | J34: 0 | K34: 0 | L34: 0 | M34: 0 | O34: 0 | P34: 0 | Q34: 0 | R34: 0 | S34: 0 | T34: 0 | U34: 0 | V34: 0 | W34: 0 | X34: 0 | Y34: 0 | Z34: 0 | AA34: 0 | AB34: 0 | AC34: 5500 | AD34: Raw primary damage only, not DPS. Full impact/smudge/water effects belong to existing payload template; no compiler yet. | AE34: MortarPrototype | AJ34: Moerser-Sprenggranaten | AK34: 0 | AL34: 0 | AM34: 0 | AN34: 0 | AO34: 0 | AP34: 0 | AQ34: 0 | AR34: 0 | AS34: 0 | AT34: 0 | AU34: 0 | AV34: 0 | AW34: 0 | AX34: 0 | AY34: 0
A35: overlord-chassis | B35: chassis | C35: ["china"] | D35: 3 | E35: 0 | F35: 2 | G35: 750 | H35: 20000 | I35: 10 | J35: 0 | K35: 0 | L35: 0 | M35: 95000 | O35: 0 | P35: 0 | Q35: 0 | R35: 32000 | S35: 960 | T35: 56 | U35: 70 | V35: 45000 | W35: 2 | X35: 3 | Y35: 0 | Z35: 0 | AA35: 0 | AB35: 0 | AC35: 0 | AD35: Main heavy carrier plus shared roof slot for an approved auxiliary carrier, bunker or speaker. Emperor 80% received-damage modifier is excluded from base state. | AE35: choverlord | AF35: {"carrier": ["heavy-twin-turret"], "drive": ["diesel-heavy", "diesel-heavy-boost"]} | AG35: ["pdl", "propaganda-speaker", "firing-bunker"] | AJ35: Schwerer Rumpf (Overlord) | AK35: 0 | AL35: 0 | AM35: 0 | AN35: 0 | AO35: 0 | AP35: {"slot": "roof", "carriers": ["gatling-roof-carrier"], "experimental_carriers": ["flame-turret", "mortar-roof-carrier"]} | AQ35: 0 | AR35: 0 | AS35: 0 | AT35: tracks-superheavy | AU35: ["tracks-superheavy"] | AV35: 0 | AW35: 0 | AX35: 0 | AY35: 8
A36: diesel-heavy | B36: drive | C36: ["china", "gdi", "soviet"] | D36: 1 | E36: 0 | F36: 2 | G36: 300 | H36: 2000 | I36: 0 | J36: 1000 | K36: 0 | L36: 0 | M36: 0 | O36: 0 | P36: 0 | Q36: 0 | R36: 0 | S36: 0 | T36: 0 | U36: 0 | V36: 0 | W36: 0 | X36: 0 | Y36: 0 | Z36: 0 | AA36: 0 | AB36: 0 | AC36: 0 | AD36: New provisional heavy family, not a formula derived from engine size. | AJ36: Schwerer Dieselmotor | AK36: 0 | AL36: 0 | AM36: 0 | AN36: 0 | AO36: 0 | AP36: 0 | AQ36: 0 | AR36: 0 | AS36: 0 | AT36: 0 | AU36: 0 | AV36: 0 | AW36: 0 | AX36: 0 | AY36: 0
A37: diesel-heavy-boost | B37: drive | C37: ["china", "gdi", "soviet"] | D37: 2 | E37: 0 | F37: 2 | G37: 400 | H37: 2000 | I37: 0 | J37: 1045 | K37: 0 | L37: 0 | M37: 0 | O37: 0 | P37: 0 | Q37: 0 | R37: 0 | S37: 0 | T37: 0 | U37: 0 | V37: 0 | W37: 0 | X37: 0 | Y37: 0 | Z37: 0 | AA37: 0 | AB37: 0 | AC37: 0 | AJ37: Leistungsgesteigerter schwerer Dieselmotor | AK37: 0 | AL37: 0 | AM37: 0 | AN37: 0 | AO37: 0 | AP37: 0 | AQ37: 0 | AR37: 0 | AS37: 0 | AT37: 0 | AU37: 0 | AV37: 0 | AW37: 0 | AX37: 0 | AY37: 0
A38: heavy-twin-turret | B38: carrier | C38: ["china"] | D38: 0 | E38: 0 | F38: 2 | G38: 250 | H38: 2000 | I38: 0 | J38: 0 | K38: 0 | L38: 0 | M38: 0 | O38: 0 | P38: 0 | Q38: 0 | R38: 0 | S38: 0 | T38: 0 | U38: 0 | V38: 0 | W38: 0 | X38: 0 | Y38: 2 | Z38: 6 | AA38: 90 | AB38: 0 | AC38: 0 | AD38: Normal, nuclear and speaker artwork bindings must select appropriate existing turret sequences; no claim of arbitrary visual interchangeability. | AE38: OverlordCannon | AH38: ["overlord-cannon"] | AJ38: Schwerer Zwillingsgeschützturm | AK38: 0 | AL38: 0 | AM38: 0 | AN38: 0 | AO38: 0 | AP38: 0 | AQ38: 0 | AR38: 0 | AS38: 0 | AT38: 0 | AU38: 0 | AV38: 0 | AW38: 0 | AX38: 0 | AY38: 0
A39: overlord-cannon | B39: weapon | C39: ["china"] | D39: 0 | E39: 0 | F39: 2 | G39: 300 | H39: 1500 | I39: 0 | J39: 0 | K39: 0 | L39: 0 | M39: 0 | O39: 0 | P39: 0 | Q39: 0 | R39: 0 | S39: 0 | T39: 0 | U39: 0 | V39: 0 | W39: 0 | X39: 0 | Y39: 0 | Z39: 0 | AA39: 0 | AB39: 5 | AC39: 0 | AE39: OverlordCannon | AI39: ["heavy-shell", "heavy-nuclear-shell"] | AJ39: Schwere Panzerkanone | AK39: 0 | AL39: 0 | AM39: 0 | AN39: 0 | AO39: 0 | AP39: 0 | AQ39: 0 | AR39: 0 | AS39: 0 | AT39: 0 | AU39: 0 | AV39: 0 | AW39: 0 | AX39: 0 | AY39: 0
A40: heavy-shell | B40: ammunition | C40: ["china"] | D40: 0 | E40: 0 | F40: 2 | G40: 150 | H40: 1500 | I40: 0 | J40: 0 | K40: 0 | L40: 0 | M40: 0 | O40: 0 | P40: 0 | Q40: 0 | R40: 0 | S40: 0 | T40: 0 | U40: 0 | V40: 0 | W40: 0 | X40: 0 | Y40: 0 | Z40: 0 | AA40: 0 | AB40: 0 | AC40: 8000 | AE40: OverlordCannon | AJ40: Schwere Panzergranaten | AK40: 0 | AL40: 0 | AM40: 0 | AN40: 0 | AO40: 0 | AP40: 0 | AQ40: 0 | AR40: 0 | AS40: 0 | AT40: 0 | AU40: 0 | AV40: 0 | AW40: 0 | AX40: 0 | AY40: 0
A41: heavy-nuclear-shell | B41: ammunition | C41: ["china"] | D41: 1 | E41: 1 | F41: 3 | G41: 950 | H41: 1500 | I41: 0 | J41: 0 | K41: 0 | L41: 0 | M41: 0 | O41: 0 | P41: 0 | Q41: 0 | R41: 0 | S41: 0 | T41: 0 | U41: 0 | V41: 0 | W41: 0 | X41: 0 | Y41: 0 | Z41: 0 | AA41: 0 | AB41: 0 | AC41: 24000 | AD41: Base nuclear Overlord price fits +800 hardware minus 300/CP. Full radiation/projectile/effect rules reused later; no nuclear motor implied. | AE41: OverlordCannonNuclear | AJ41: Schwere Nukleargranaten | AK41: 0 | AL41: 5.5 | AM41: 0 | AN41: 0 | AO41: 0 | AP41: 0 | AQ41: 0 | AR41: 0 | AS41: 0 | AT41: 0 | AU41: 0 | AV41: 0 | AW41: 0 | AX41: 0 | AY41: 0
A42: firing-bunker | B42: equipment | C42: ["china"] | D42: 1 | E42: 1 | F42: 3 | G42: 100 | H42: 600 | I42: 5 | J42: 0 | K42: 0 | L42: 0 | M42: 0 | O42: 0 | P42: 0 | Q42: 0 | R42: 0 | S42: 0 | T42: 0 | U42: 0 | V42: 0 | W42: 0 | X42: 0 | Y42: 0 | Z42: 0 | AA42: 0 | AB42: 0 | AC42: 0 | AD42: Empty module. Start crew is a separate design selection; price/mass added once. Empty cost/mass experimental. PDL composition uses ^AttackingCargoAndPDL; requires turretbunker artwork. | AE42: ^AttackingCargoAndTurret | AJ42: Besetzbarer Bunker | AK42: 0 | AL42: 0 | AM42: 4 | AN42: 0 | AO42: roof | AP42: 0 | AQ42: ["che1", "che3", "minigunner"] | AR42: 0 | AS42: 0 | AT42: 0 | AU42: 0 | AV42: 0 | AW42: 0 | AX42: 0 | AY42: 0
A43: gatling-roof-carrier | B43: carrier | C43: ["china"] | D43: 1 | E43: 1 | F43: 3 | G43: 50 | H43: 300 | I43: 5 | J43: 0 | K43: 0 | L43: 0 | M43: 0 | O43: 0 | P43: 0 | Q43: 0 | R43: 0 | S43: 0 | T43: 0 | U43: 0 | V43: 0 | W43: 0 | X43: 0 | Y43: 1 | Z43: 0 | AA43: 12 | AB43: 0 | AC43: 0 | AD43: Shares gatling weapon/ammunition. Complete legacy behavior includes sensor equipment, ground/AA spin-up and turretgat sprite; 50-credit carrier allocation is a provisional fit, not intrinsic market value. | AE43: ^ChinaGatlingOverlord + ^SensorEquipment | AH43: ["gatling-gun"] | AJ43: Gatling-Aufsatzturm | AK43: 0 | AL43: 0 | AM43: 0 | AN43: 0 | AO43: 0 | AP43: 0 | AQ43: 0 | AR43: 0 | AS43: 0 | AT43: 0 | AU43: 0 | AV43: 0 | AW43: 0 | AX43: 0 | AY43: 0
A44: propaganda-speaker | B44: equipment | C44: ["china"] | D44: 1 | E44: 1 | F44: 3 | G44: 500 | H44: 500 | I44: 20 | J44: 0 | K44: 0 | L44: 0 | M44: 0 | O44: 0 | P44: 0 | Q44: 0 | R44: 0 | S44: 0 | T44: 0 | U44: 0 | V44: 0 | W44: 0 | X44: 0 | Y44: 0 | Z44: 0 | AA44: 0 | AB44: 0 | AC44: 0 | AD44: Existing aura/upgrade traits to reuse. +500 hardware minus 300/CP fits base price; mass and load deliberately expose speed residuals. | AE44: ^PropagandaSpeaker | AJ44: Propagandalautsprecher | AK44: 0 | AL44: 0 | AM44: 0 | AN44: 0 | AO44: roof | AP44: 0 | AQ44: 0 | AR44: 0 | AS44: 0 | AT44: 0 | AU44: 0 | AV44: 0 | AW44: 0 | AX44: 0 | AY44: 0
A45: battlemaster | B45: chassis | C45: ["china"] | D45: 1 | E45: 0 | F45: 1 | G45: 400 | H45: 6500 | I45: 10 | J45: 0 | K45: 0 | L45: 0 | M45: 40000 | O45: 0 | P45: 0 | Q45: 0 | R45: 10000 | S45: 460 | T45: 100 | U45: 125 | V45: 18000 | W45: 1 | X45: 1 | Y45: 0 | Z45: 0 | AA45: 0 | AB45: 0 | AC45: 0 | AE45: chbattle | AF45: {"carrier": ["cannon-turret", "autoloader-turret"], "drive": ["diesel", "diesel-large", "nuclear"]} | AG45: ["pdl"] | AJ45: Type 59 Chassis | AK45: 0 | AL45: 0 | AM45: 0 | AN45: 0 | AO45: 0 | AP45: 0 | AQ45: 0 | AR45: 0 | AS45: 0 | AT45: tracks-standard | AU45: ["tracks-standard"] | AV45: 0 | AW45: 0 | AX45: 0 | AY45: 48
A46: mass-production | B46: manufacturing | C46: ["china"] | D46: 0 | E46: 1 | F46: 1 | G46: 0 | H46: 0 | I46: 0 | J46: 0 | K46: 0 | L46: 0 | M46: 0 | O46: 0 | P46: 0 | Q46: 0 | R46: 0 | S46: 0 | T46: 0 | U46: 0 | V46: 0 | W46: 0 | X46: 0 | Y46: 0 | Z46: 0 | AA46: 0 | AB46: 0 | AC46: 0 | AD46: Separate manufacturing selection, not chassis or physical equipment. Provisional 5% reduction of all hardware before global CP deduction; not the joint-fit optimum. No special per-design rebate. | AJ46: Massenproduktion | AK46: 95 | AL46: 0 | AM46: 0 | AN46: 0 | AO46: 0 | AP46: 0 | AQ46: 0 | AR46: 0 | AS46: 0 | AT46: 0 | AU46: 0 | AV46: 0 | AW46: 0 | AX46: 0 | AY46: 0
A47: dragon-chassis | B47: chassis | C47: ["china"] | D47: 1 | E47: 0 | F47: 1 | G47: 150 | H47: 5000 | I47: 10 | J47: 0 | K47: 0 | L47: 0 | M47: 28000 | O47: 0 | P47: 0 | Q47: 0 | R47: 8000 | S47: 460 | T47: 103 | U47: 125 | V47: 14000 | W47: 1 | X47: 1 | Y47: 0 | Z47: 0 | AA47: 0 | AB47: 0 | AC47: 0 | AD47: Base price/HP/speed fitted. Firewall deploy behavior and Black Napalm remain source references, not implemented. | AE47: chdragon | AF47: {"carrier": ["flame-turret"], "drive": ["diesel", "diesel-large"]} | AG47: ["pdl"] | AJ47: 0 | AK47: 0 | AL47: 0 | AM47: 0 | AN47: 0 | AO47: 0 | AP47: 0 | AQ47: 0 | AR47: 0 | AS47: 0 | AT47: tracks-standard | AU47: ["tracks-standard"] | AV47: 0 | AW47: 0 | AX47: 0 | AY47: 48
A48: gatling-chassis | B48: chassis | C48: ["china"] | D48: 1 | E48: 0 | F48: 1 | G48: 250 | H48: 5500 | I48: 10 | J48: 0 | K48: 0 | L48: 0 | M48: 30000 | O48: 0 | P48: 0 | Q48: 0 | R48: 9000 | S48: 460 | T48: 108 | U48: 130 | V48: 16000 | W48: 1 | X48: 1 | Y48: 0 | Z48: 0 | AA48: 0 | AB48: 0 | AC48: 0 | AD48: Legacy sight override 6c0; preserve as audit metadata, not a claim of standard sight equivalence. AA/ground spool-up not simulated. | AE48: chgtnk | AF48: {"carrier": ["gatling-turret"], "drive": ["diesel", "diesel-large"]} | AG48: ["pdl"] | AJ48: 0 | AK48: 0 | AL48: 0 | AM48: 0 | AN48: 0 | AO48: 0 | AP48: 0 | AQ48: 0 | AR48: 0 | AS48: 0 | AT48: tracks-standard | AU48: ["tracks-standard"] | AV48: 0 | AW48: 0 | AX48: 0 | AY48: 48
A49: flame-turret | B49: carrier | C49: ["china"] | D49: 0 | E49: 0 | F49: 1 | G49: 75 | H49: 400 | I49: 0 | J49: 0 | K49: 0 | L49: 0 | M49: 0 | O49: 0 | P49: 0 | Q49: 0 | R49: 0 | S49: 0 | T49: 0 | U49: 0 | V49: 0 | W49: 0 | X49: 0 | Y49: 8 | Z49: 4 | AA49: 45 | AB49: 0 | AC49: 0 | AD49: Normal attack only; deployed Firewall has additional armaments and state changes. | AE49: CHDragonFlamer | AH49: ["dragon-flamer"] | AJ49: 0 | AK49: 0 | AL49: 0 | AM49: 0 | AN49: 0 | AO49: 0 | AP49: 0 | AQ49: 0 | AR49: 0 | AS49: 0 | AT49: 0 | AU49: 0 | AV49: 0 | AW49: 0 | AX49: 0 | AY49: 0
A50: dragon-flamer | B50: weapon | C50: ["china"] | D50: 0 | E50: 0 | F50: 1 | G50: 125 | H50: 400 | I50: 0 | J50: 0 | K50: 0 | L50: 0 | M50: 0 | O50: 0 | P50: 0 | Q50: 0 | R50: 0 | S50: 0 | T50: 0 | U50: 0 | V50: 0 | W50: 0 | X50: 0 | Y50: 0 | Z50: 0 | AA50: 0 | AB50: 5 | AC50: 0 | AE50: CHDragonFlamer | AI50: ["flame-fuel"] | AJ50: 0 | AK50: 0 | AL50: 0 | AM50: 0 | AN50: 0 | AO50: 0 | AP50: 0 | AQ50: 0 | AR50: 0 | AS50: 0 | AT50: 0 | AU50: 0 | AV50: 0 | AW50: 0 | AX50: 0 | AY50: 0
A51: flame-fuel | B51: ammunition | C51: ["china"] | D51: 0 | E51: 0 | F51: 1 | G51: 50 | H51: 100 | I51: 0 | J51: 0 | K51: 0 | L51: 0 | M51: 0 | O51: 0 | P51: 0 | Q51: 0 | R51: 0 | S51: 0 | T51: 0 | U51: 0 | V51: 0 | W51: 0 | X51: 0 | Y51: 0 | Z51: 0 | AA51: 0 | AB51: 0 | AC51: 2500 | AD51: Raw primary warhead only; fire clusters, heat and garrison damage omitted from calculator. | AJ51: 0 | AK51: 0 | AL51: 0 | AM51: 0 | AN51: 0 | AO51: 0 | AP51: 0 | AQ51: 0 | AR51: 0 | AS51: 0 | AT51: 0 | AU51: 0 | AV51: 0 | AW51: 0 | AX51: 0 | AY51: 0
A52: gatling-turret | B52: carrier | C52: ["china"] | D52: 0 | E52: 0 | F52: 1 | G52: 100 | H52: 500 | I52: 0 | J52: 0 | K52: 0 | L52: 0 | M52: 0 | O52: 0 | P52: 0 | Q52: 0 | R52: 0 | S52: 0 | T52: 0 | U52: 0 | V52: 0 | W52: 0 | X52: 0 | Y52: 1 | Z52: 0 | AA52: 12 | AB52: 0 | AC52: 0 | AD52: Ground cold-state representative only. Reload stages 12/8/4/2 ticks, separate air/ground charge, thresholds 1/3/5, reset delay 40. Full attack-state behavior not modeled. | AE52: ^ChinaGatling | AH52: ["gatling-gun"] | AJ52: 0 | AK52: 0 | AL52: 0 | AM52: 0 | AN52: 0 | AO52: 0 | AP52: 0 | AQ52: 0 | AR52: 0 | AS52: 0 | AT52: 0 | AU52: 0 | AV52: 0 | AW52: 0 | AX52: 0 | AY52: 0
A53: gatling-gun | B53: weapon | C53: ["china"] | D53: 0 | E53: 0 | F53: 1 | G53: 150 | H53: 500 | I53: 0 | J53: 0 | K53: 0 | L53: 0 | M53: 0 | O53: 0 | P53: 0 | Q53: 0 | R53: 0 | S53: 0 | T53: 0 | U53: 0 | V53: 0 | W53: 0 | X53: 0 | Y53: 0 | Z53: 0 | AA53: 0 | AB53: 6 | AC53: 0 | AD53: Ground range 6 cells; AA uses ChinaMGatt.0 with range 9.5. Not a single fixed weapon. | AE53: ChinaMGatt.0G | AI53: ["gatling-rounds"] | AJ53: 0 | AK53: 0 | AL53: 0 | AM53: 0 | AN53: 0 | AO53: 0 | AP53: 0 | AQ53: 0 | AR53: 0 | AS53: 0 | AT53: 0 | AU53: 0 | AV53: 0 | AW53: 0 | AX53: 0 | AY53: 0
A54: gatling-rounds | B54: ammunition | C54: ["china"] | D54: 0 | E54: 0 | F54: 1 | G54: 100 | H54: 400 | I54: 0 | J54: 0 | K54: 0 | L54: 0 | M54: 0 | O54: 0 | P54: 0 | Q54: 0 | R54: 0 | S54: 0 | T54: 0 | U54: 0 | V54: 0 | W54: 0 | X54: 0 | Y54: 0 | Z54: 0 | AA54: 0 | AB54: 0 | AC54: 350 | AD54: Raw ground damage 350; AA raw damage 660. Values are not DPS. | AJ54: 0 | AK54: 0 | AL54: 0 | AM54: 0 | AN54: 0 | AO54: 0 | AP54: 0 | AQ54: 0 | AR54: 0 | AS54: 0 | AT54: 0 | AU54: 0 | AV54: 0 | AW54: 0 | AX54: 0 | AY54: 0
A55: juggernaut | B55: chassis | C55: ["gdi"] | D55: 3 | E55: 0 | F55: 3 | G55: 800 | H55: 12500 | I55: 10 | J55: 0 | K55: 0 | L55: 0 | M55: 60000 | O55: 0 | P55: 0 | Q55: 0 | R55: 20000 | S55: 460 | T55: 50 | U55: 50 | V55: 30000 | W55: 1 | X55: 3 | Y55: 0 | Z55: 0 | AA55: 0 | AB55: 0 | AC55: 0 | AE55: Juggernaut | AF55: {"carrier": ["fixed-triple"], "drive": ["diesel"]} | AG55: [] | AJ55: 0 | AK55: 0 | AL55: 0 | AM55: 0 | AN55: 0 | AO55: 0 | AP55: 0 | AQ55: 0 | AR55: 0 | AS55: 0 | AT55: walker-heavy | AU55: ["walker-heavy"] | AV55: 0 | AW55: 0 | AX55: 0 | AY55: 16
A56: heavy-tesla | B56: chassis | C56: ["soviet"] | D56: 2 | E56: 0 | F56: 2 | G56: 500 | H56: 6500 | I56: 10 | J56: 0 | K56: 0 | L56: 0 | M56: 48000 | O56: 0 | P56: 0 | Q56: 0 | R56: 10000 | S56: 260 | T56: 100 | U56: 110 | V56: 18000 | W56: 1 | X56: 2 | Y56: 0 | Z56: 0 | AA56: 0 | AB56: 0 | AC56: 0 | AE56: TTNK.RA2 | AF56: {"carrier": ["twin-coil"], "drive": ["diesel", "nuclear"]} | AG56: [] | AJ56: 0 | AK56: 0 | AL56: 0 | AM56: 0 | AN56: 0 | AO56: 0 | AP56: 0 | AQ56: 0 | AR56: 0 | AS56: 0 | AT56: tracks-standard | AU56: ["tracks-standard"] | AV56: 0 | AW56: 0 | AX56: 0 | AY56: 48
A57: diesel | B57: drive | C57: ["china", "gdi", "soviet", "nod", "allies"] | D57: 0 | E57: 0 | F57: 1 | G57: 100 | H57: 600 | I57: 0 | J57: 500 | K57: 0 | L57: 0 | M57: 0 | O57: 0 | P57: 0 | Q57: 0 | R57: 0 | S57: 0 | T57: 0 | U57: 0 | V57: 0 | W57: 0 | X57: 0 | Y57: 0 | Z57: 0 | AA57: 0 | AB57: 0 | AC57: 0 | AJ57: 0 | AK57: 0 | AL57: 0 | AM57: 0 | AN57: 0 | AO57: 0 | AP57: 0 | AQ57: 0 | AR57: 0 | AS57: 0 | AT57: 0 | AU57: 0 | AV57: 0 | AW57: 0 | AX57: 0 | AY57: 0
A58: diesel-large | B58: drive | C58: ["china", "gdi", "soviet"] | D58: 1 | E58: 0 | F58: 2 | G58: 200 | H58: 600 | I58: 0 | J58: 550 | K58: 0 | L58: 0 | M58: 0 | O58: 0 | P58: 0 | Q58: 0 | R58: 0 | S58: 0 | T58: 0 | U58: 0 | V58: 0 | W58: 0 | X58: 0 | Y58: 0 | Z58: 0 | AA58: 0 | AB58: 0 | AC58: 0 | AJ58: 0 | AK58: 0 | AL58: 0 | AM58: 0 | AN58: 0 | AO58: 0 | AP58: 0 | AQ58: 0 | AR58: 0 | AS58: 0 | AT58: 0 | AU58: 0 | AV58: 0 | AW58: 0 | AX58: 0 | AY58: 0
A59: nuclear | B59: drive | C59: ["china", "soviet"] | D59: 1 | E59: 1 | F59: 2 | G59: 400 | H59: 600 | I59: 0 | J59: 758.75 | K59: 0 | L59: 0 | M59: 0 | O59: 0 | P59: 0 | Q59: 0 | R59: 0 | S59: 0 | T59: 0 | U59: 0 | V59: 0 | W59: 0 | X59: 0 | Y59: 0 | Z59: 0 | AA59: 0 | AB59: 0 | AC59: 0 | AJ59: 0 | AK59: 0 | AL59: 0 | AM59: 0 | AN59: 0 | AO59: 0 | AP59: 0 | AQ59: 0 | AR59: 0 | AS59: 0 | AT59: 0 | AU59: 0 | AV59: 0 | AW59: 0 | AX59: 0 | AY59: 0
A60: baseline-generator | B60: generator | C60: ["china", "gdi", "soviet", "nod", "allies"] | D60: 0 | E60: 0 | F60: 1 | G60: 0 | H60: 0 | I60: 0 | J60: 0 | K60: 0.25 | L60: 100 | M60: 0 | O60: 0 | P60: 0 | Q60: 0 | R60: 0 | S60: 0 | T60: 0 | U60: 0 | V60: 0 | W60: 0 | X60: 0 | Y60: 0 | Z60: 0 | AA60: 0 | AB60: 0 | AC60: 0 | AJ60: 0 | AK60: 0 | AL60: 0 | AM60: 0 | AN60: 0 | AO60: 0 | AP60: 0 | AQ60: 0 | AR60: 0 | AS60: 0 | AT60: 0 | AU60: 0 | AV60: 0 | AW60: 0 | AX60: 0 | AY60: 0
A61: efficient-generator | B61: generator | C61: ["china", "gdi", "soviet"] | D61: 1 | E61: 0 | F61: 2 | G61: 200 | H61: 0 | I61: 0 | J61: 0 | K61: 0.75 | L61: 120 | M61: 0 | O61: 0 | P61: 0 | Q61: 0 | R61: 0 | S61: 0 | T61: 0 | U61: 0 | V61: 0 | W61: 0 | X61: 0 | Y61: 0 | Z61: 0 | AA61: 0 | AB61: 0 | AC61: 0 | AJ61: 0 | AK61: 0 | AL61: 0 | AM61: 0 | AN61: 0 | AO61: 0 | AP61: 0 | AQ61: 0 | AR61: 0 | AS61: 0 | AT61: 0 | AU61: 0 | AV61: 0 | AW61: 0 | AX61: 0 | AY61: 0
A62: heavy | B62: armor | C62: ["china", "gdi", "soviet", "nod", "allies"] | D62: 0 | E62: 0 | F62: 1 | G62: 0 | H62: 0 | I62: 0 | J62: 0 | K62: 0 | L62: 0 | M62: 0 | N62: Heavy | O62: 100 | P62: 100 | Q62: 100 | R62: 0 | S62: 0 | T62: 0 | U62: 0 | V62: 0 | W62: 0 | X62: 0 | Y62: 0 | Z62: 0 | AA62: 0 | AB62: 0 | AC62: 0 | AJ62: 0 | AK62: 0 | AL62: 0 | AM62: 0 | AN62: 0 | AO62: 0 | AP62: 0 | AQ62: 0 | AR62: 0 | AS62: 0 | AT62: 0 | AU62: 0 | AV62: 0 | AW62: 0 | AX62: 0 | AY62: 0
A63: reflector | B63: armor | C63: ["china", "gdi", "soviet"] | D63: 1 | E63: 1 | F63: 3 | G63: 0 | H63: 0 | I63: 57.5 | J63: 0 | K63: 0 | L63: 0 | M63: 0 | N63: Reflector | O63: 100 | P63: 100 | Q63: 100 | R63: 0 | S63: 0 | T63: 0 | U63: 0 | V63: 0 | W63: 0 | X63: 0 | Y63: 0 | Z63: 0 | AA63: 0 | AB63: 0 | AC63: 0 | AJ63: 0 | AK63: 0 | AL63: 0 | AM63: 0 | AN63: 0 | AO63: 0 | AP63: 0 | AQ63: 0 | AR63: 0 | AS63: 0 | AT63: 0 | AU63: 0 | AV63: 0 | AW63: 0 | AX63: 0 | AY63: 0
A64: cannon-turret | B64: carrier | C64: ["china"] | D64: 0 | E64: 0 | F64: 1 | G64: 100 | H64: 500 | I64: 0 | J64: 0 | K64: 0 | L64: 0 | M64: 0 | O64: 0 | P64: 0 | Q64: 0 | R64: 0 | S64: 0 | T64: 0 | U64: 0 | V64: 0 | W64: 0 | X64: 0 | Y64: 1 | Z64: 0 | AA64: 50 | AB64: 0 | AC64: 0 | AH64: ["cannon"] | AJ64: 0 | AK64: 0 | AL64: 0 | AM64: 0 | AN64: 0 | AO64: 0 | AP64: 0 | AQ64: 0 | AR64: 0 | AS64: 0 | AT64: 0 | AU64: 0 | AV64: 0 | AW64: 0 | AX64: 0 | AY64: 0
A65: autoloader-turret | B65: carrier | C65: ["china"] | D65: 1 | E65: 1 | F65: 1 | G65: 400 | H65: 500 | I65: 0 | J65: 0 | K65: 0 | L65: 0 | M65: 0 | O65: 0 | P65: 0 | Q65: 0 | R65: 0 | S65: 0 | T65: 0 | U65: 0 | V65: 0 | W65: 0 | X65: 0 | Y65: 3 | Z65: 5 | AA65: 50 | AB65: 0 | AC65: 0 | AD65: Same visible single barrel. Autoloading mechanism changes firing cycle, not barrel count. Baseline mount mass retained; hardware price includes autoloader. Global CP credit value applies. | AE65: CHBattlemasterCannon.Autoloader | AH65: ["cannon"] | AJ65: 0 | AK65: 0 | AL65: 0 | AM65: 0 | AN65: 0 | AO65: 0 | AP65: 0 | AQ65: 0 | AR65: 0 | AS65: 0 | AT65: 0 | AU65: 0 | AV65: 0 | AW65: 0 | AX65: 0 | AY65: 0
A66: fixed-triple | B66: carrier | C66: ["gdi"] | D66: 0 | E66: 0 | F66: 3 | G66: 300 | H66: 1500 | I66: 0 | J66: 0 | K66: 0 | L66: 0 | M66: 0 | O66: 0 | P66: 0 | Q66: 0 | R66: 0 | S66: 0 | T66: 0 | U66: 0 | V66: 0 | W66: 0 | X66: 0 | Y66: 3 | Z66: 1 | AA66: 100 | AB66: 0 | AC66: 0 | AH66: ["artillery"] | AJ66: 0 | AK66: 0 | AL66: 0 | AM66: 0 | AN66: 0 | AO66: 0 | AP66: 0 | AQ66: 0 | AR66: 0 | AS66: 33 | AT66: 0 | AU66: 0 | AV66: 0 | AW66: 0 | AX66: 0 | AY66: 0
A67: twin-coil | B67: carrier | C67: ["soviet"] | D67: 0 | E67: 0 | F67: 2 | G67: 200 | H67: 500 | I67: 0 | J67: 0 | K67: 0 | L67: 0 | M67: 0 | O67: 0 | P67: 0 | Q67: 0 | R67: 0 | S67: 0 | T67: 0 | U67: 0 | V67: 0 | W67: 0 | X67: 0 | Y67: 2 | Z67: 1 | AA67: 100 | AB67: 0 | AC67: 0 | AH67: ["tesla"] | AJ67: 0 | AK67: 0 | AL67: 0 | AM67: 0 | AN67: 0 | AO67: 0 | AP67: 0 | AQ67: 0 | AR67: 0 | AS67: 13 | AT67: 0 | AU67: 0 | AV67: 0 | AW67: 0 | AX67: 0 | AY67: 0
A68: cannon | B68: weapon | C68: ["china"] | D68: 0 | E68: 0 | F68: 1 | G68: 200 | H68: 500 | I68: 0 | J68: 0 | K68: 0 | L68: 0 | M68: 0 | O68: 0 | P68: 0 | Q68: 0 | R68: 0 | S68: 0 | T68: 0 | U68: 0 | V68: 0 | W68: 0 | X68: 0 | Y68: 0 | Z68: 0 | AA68: 0 | AB68: 4 | AC68: 0 | AE68: CHBattlemasterCannon | AI68: ["shell", "nuclear-shell"] | AJ68: 0 | AK68: 0 | AL68: 0 | AM68: 0 | AN68: 0 | AO68: 0 | AP68: 0 | AQ68: 0 | AR68: 0 | AS68: 0 | AT68: 0 | AU68: 0 | AV68: 0 | AW68: 0 | AX68: 0 | AY68: 0
A69: artillery | B69: weapon | C69: ["gdi"] | D69: 0 | E69: 0 | F69: 3 | G69: 300 | H69: 900 | I69: 0 | J69: 0 | K69: 0 | L69: 0 | M69: 0 | O69: 0 | P69: 0 | Q69: 0 | R69: 0 | S69: 0 | T69: 0 | U69: 0 | V69: 0 | W69: 0 | X69: 0 | Y69: 0 | Z69: 0 | AA69: 0 | AB69: 0 | AC69: 0 | AE69: JuggernautGun | AI69: ["artillery-shell", "emp-shell"] | AJ69: 0 | AK69: 0 | AL69: 0 | AM69: 0 | AN69: 0 | AO69: 0 | AP69: 0 | AQ69: 0 | AR69: 0 | AS69: 0 | AT69: 0 | AU69: 0 | AV69: 0 | AW69: 0 | AX69: 0 | AY69: 0
A70: tesla | B70: weapon | C70: ["soviet"] | D70: 1 | E70: 0 | F70: 2 | G70: 350 | H70: 700 | I70: 50 | J70: 0 | K70: 0 | L70: 0 | M70: 0 | O70: 0 | P70: 0 | Q70: 0 | R70: 0 | S70: 0 | T70: 0 | U70: 0 | V70: 0 | W70: 0 | X70: 0 | Y70: 0 | Z70: 0 | AA70: 0 | AB70: 0 | AC70: 0 | AE70: TTankZapMK2 | AI70: ["discharge"] | AJ70: 0 | AK70: 0 | AL70: 0 | AM70: 0 | AN70: 0 | AO70: 0 | AP70: 0 | AQ70: 0 | AR70: 0 | AS70: 0 | AT70: 0 | AU70: 0 | AV70: 0 | AW70: 0 | AX70: 0 | AY70: 0
A71: shell | B71: ammunition | C71: ["china"] | D71: 0 | E71: 0 | F71: 1 | G71: 50 | H71: 400 | I71: 0 | J71: 0 | K71: 0 | L71: 0 | M71: 0 | O71: 0 | P71: 0 | Q71: 0 | R71: 0 | S71: 0 | T71: 0 | U71: 0 | V71: 0 | W71: 0 | X71: 0 | Y71: 0 | Z71: 0 | AA71: 0 | AB71: 0 | AC71: 5000 | AJ71: 0 | AK71: 0 | AL71: 0 | AM71: 0 | AN71: 0 | AO71: 0 | AP71: 0 | AQ71: 0 | AR71: 0 | AS71: 0 | AT71: 0 | AU71: 0 | AV71: 0 | AW71: 0 | AX71: 0 | AY71: 0
A72: nuclear-shell | B72: ammunition | C72: ["china"] | D72: 1 | E72: 1 | F72: 1 | G72: 350 | H72: 400 | I72: 0 | J72: 0 | K72: 0 | L72: 0 | M72: 0 | O72: 0 | P72: 0 | Q72: 0 | R72: 0 | S72: 0 | T72: 0 | U72: 0 | V72: 0 | W72: 0 | X72: 0 | Y72: 0 | Z72: 0 | AA72: 0 | AB72: 0 | AC72: 10000 | AD72: First fit: same mass, no additional electric load; +300 hardware offsets 1 CP. Radiation, falloff and recoil need engine composition, not just damage copying. | AE72: CHBattlemasterCannon.Nuclear_Shells | AJ72: 0 | AK72: 0 | AL72: 0 | AM72: 0 | AN72: 0 | AO72: 0 | AP72: 0 | AQ72: 0 | AR72: 0 | AS72: 0 | AT72: 0 | AU72: 0 | AV72: 0 | AW72: 0 | AX72: 0 | AY72: 0
A73: artillery-shell | B73: ammunition | C73: ["gdi"] | D73: 0 | E73: 0 | F73: 3 | G73: 200 | H73: 1000 | I73: 0 | J73: 0 | K73: 0 | L73: 0 | M73: 0 | O73: 0 | P73: 0 | Q73: 0 | R73: 0 | S73: 0 | T73: 0 | U73: 0 | V73: 0 | W73: 0 | X73: 0 | Y73: 0 | Z73: 0 | AA73: 0 | AB73: 0 | AC73: 0 | AJ73: 0 | AK73: 0 | AL73: 0 | AM73: 0 | AN73: 0 | AO73: 0 | AP73: 0 | AQ73: 0 | AR73: 0 | AS73: 0 | AT73: 0 | AU73: 0 | AV73: 0 | AW73: 0 | AX73: 0 | AY73: 0
A74: emp-shell | B74: ammunition | C74: ["gdi"] | D74: 1 | E74: 1 | F74: 3 | G74: 300 | H74: 1000 | I74: 20 | J74: 0 | K74: 0 | L74: 0 | M74: 0 | O74: 0 | P74: 0 | Q74: 0 | R74: 0 | S74: 0 | T74: 0 | U74: 0 | V74: 0 | W74: 0 | X74: 0 | Y74: 0 | Z74: 0 | AA74: 0 | AB74: 0 | AC74: 0 | AE74: JuggernautGun.Emp | AJ74: 0 | AK74: 0 | AL74: 0 | AM74: 0 | AN74: 0 | AO74: 0 | AP74: 0 | AQ74: 0 | AR74: 0 | AS74: 0 | AT74: 0 | AU74: 0 | AV74: 0 | AW74: 0 | AX74: 0 | AY74: 0
A75: discharge | B75: ammunition | C75: ["soviet"] | D75: 0 | E75: 0 | F75: 2 | G75: 100 | H75: 200 | I75: 0 | J75: 0 | K75: 0 | L75: 0 | M75: 0 | O75: 0 | P75: 0 | Q75: 0 | R75: 0 | S75: 0 | T75: 0 | U75: 0 | V75: 0 | W75: 0 | X75: 0 | Y75: 0 | Z75: 0 | AA75: 0 | AB75: 0 | AC75: 0 | AD75: Fixed payload-package mass, not physical shells; no duplicate Tesla electrical charge. | AJ75: 0 | AK75: 0 | AL75: 0 | AM75: 0 | AN75: 0 | AO75: 0 | AP75: 0 | AQ75: 0 | AR75: 0 | AS75: 0 | AT75: 0 | AU75: 0 | AV75: 0 | AW75: 0 | AX75: 0 | AY75: 0
A76: pdl | B76: equipment | C76: ["china"] | D76: 1 | E76: 1 | F76: 3 | G76: 650 | H76: 300 | I76: 47 | J76: 0 | K76: 0 | L76: 0 | M76: 0 | O76: 0 | P76: 0 | Q76: 0 | R76: 0 | S76: 0 | T76: 0 | U76: 0 | V76: 0 | W76: 0 | X76: 0 | Y76: 0 | Z76: 0 | AA76: 0 | AB76: 0 | AC76: 0 | AE76: ^PointLaserDefenseSystem | AJ76: 0 | AK76: 0 | AL76: 0 | AM76: 0 | AN76: 0 | AO76: 0 | AP76: 0 | AQ76: 0 | AR76: 0 | AS76: 0 | AT76: 0 | AU76: 0 | AV76: 0 | AW76: 0 | AX76: 0 | AY76: 0

Sheet Infanterie
A1: ID | B1: Name | C1: Fraktionen | D1: Preis | E1: Masse kg | F1: Transportgewicht | G1: Tech
A2: che3 | B2: Tank Hunter | C2: china | D2: 300 | E2: 100 | F2: 1 | G2: 1
A3: che1 | B3: Red Guard | C3: china | D3: 80 | E3: 100 | F3: 1 | G3: 1
A4: minigunner | B4: Minigunner | C4: china | D4: 200 | E4: 100 | F4: 1 | G4: 1

Sheet Startbesatzung
A1: Design | B1: Infanterie | C1: Anzahl | D1: Preis | E1: Masse kg | F1: Transportgewicht | G1: Tech
A2: Overlord Bunker / mixed crew | B2: che3 | C2: 2 | D2: =C2*VLOOKUP(B2,Infanterie!$A$2:$G$4,4,FALSE) | E2: =C2*VLOOKUP(B2,Infanterie!$A$2:$G$4,5,FALSE) | F2: =C2*VLOOKUP(B2,Infanterie!$A$2:$G$4,6,FALSE) | G2: =IF(C2>0,VLOOKUP(B2,Infanterie!$A$2:$G$4,7,FALSE),0)
A3: Overlord Bunker / mixed crew | B3: che1 | C3: 2 | D3: =C3*VLOOKUP(B3,Infanterie!$A$2:$G$4,4,FALSE) | E3: =C3*VLOOKUP(B3,Infanterie!$A$2:$G$4,5,FALSE) | F3: =C3*VLOOKUP(B3,Infanterie!$A$2:$G$4,6,FALSE) | G3: =IF(C3>0,VLOOKUP(B3,Infanterie!$A$2:$G$4,7,FALSE),0)
A4: Overlord Bunker / partial crew | B4: minigunner | C4: 2 | D4: =C4*VLOOKUP(B4,Infanterie!$A$2:$G$4,4,FALSE) | E4: =C4*VLOOKUP(B4,Infanterie!$A$2:$G$4,5,FALSE) | F4: =C4*VLOOKUP(B4,Infanterie!$A$2:$G$4,6,FALSE) | G4: =IF(C4>0,VLOOKUP(B4,Infanterie!$A$2:$G$4,7,FALSE),0)
A5: Overlord Bunker | B5: che3 | C5: 4 | D5: =C5*VLOOKUP(B5,Infanterie!$A$2:$G$4,4,FALSE) | E5: =C5*VLOOKUP(B5,Infanterie!$A$2:$G$4,5,FALSE) | F5: =C5*VLOOKUP(B5,Infanterie!$A$2:$G$4,6,FALSE) | G5: =IF(C5>0,VLOOKUP(B5,Infanterie!$A$2:$G$4,7,FALSE),0)
A6: Overlord Bunker PDL | B6: che3 | C6: 4 | D6: =C6*VLOOKUP(B6,Infanterie!$A$2:$G$4,4,FALSE) | E6: =C6*VLOOKUP(B6,Infanterie!$A$2:$G$4,5,FALSE) | F6: =C6*VLOOKUP(B6,Infanterie!$A$2:$G$4,6,FALSE) | G6: =IF(C6>0,VLOOKUP(B6,Infanterie!$A$2:$G$4,7,FALSE),0)
A7: Overlord Bunker Reflector | B7: che3 | C7: 4 | D7: =C7*VLOOKUP(B7,Infanterie!$A$2:$G$4,4,FALSE) | E7: =C7*VLOOKUP(B7,Infanterie!$A$2:$G$4,5,FALSE) | F7: =C7*VLOOKUP(B7,Infanterie!$A$2:$G$4,6,FALSE) | G7: =IF(C7>0,VLOOKUP(B7,Infanterie!$A$2:$G$4,7,FALSE),0)

Sheet Entwuerfe
A1: Design | B1: Fraktion | C1: Chassis | D1: Motor | E1: Generator | F1: Panzerung | G1: Traeger | H1: Waffe | I1: Munition | J1: Zusatz 1 | K1: Zusatz 2 | L1: Zusatz 3 | M1: Katalog | N1: CP | O1: Tech | P1: Hardware | Q1: CP-Abzug | R1: Preis | S1: HP | T1: Masse kg | U1: Last kWe | V1: Rest kWm | W1: Tempo | X1: Armor | Y1: Grenzen | Z1: Python Preis | AA1: Python Tempo | AB1: Referenzhinweis | AC1: Fertigungsmodul | AD1: Fertigungsfaktor | AE1: Hardware nach Fertigung | AF1: Aufsatztraeger | AG1: Aufsatzwaffe | AH1: Aufsatzmunition | AI1: Besatzungspreis | AJ1: Besatzungsmasse | AK1: Besatzungstech | AL1: Aufsatz Reichweite | AM1: Aufsatz Mindestreichweite | AN1: Aufsatz Reload Ticks | AO1: Aufsatz Salve | AP1: Aufsatz Rohschaden | AQ1: Fahrwerk | AR1: Locomotor | AS1: Wenderate
A2: Hum-Vee baseline | B2: gdi | C2: humvee-hull | D2: diesel-light | E2: baseline-generator | F2: light | G2: scout-mg-mount | H2: scout-mg | I2: scout-mg-rounds | J2: scout-sensors | M2: =IF(C2="",0,VLOOKUP(C2,Bausteine!$A$2:$AY$76,4,FALSE))+IF(D2="",0,VLOOKUP(D2,Bausteine!$A$2:$AY$76,4,FALSE))+IF(E2="",0,VLOOKUP(E2,Bausteine!$A$2:$AY$76,4,FALSE))+IF(F2="",0,VLOOKUP(F2,Bausteine!$A$2:$AY$76,4,FALSE))+IF(G2="",0,VLOOKUP(G2,Bausteine!$A$2:$AY$76,4,FALSE))+IF(H2="",0,VLOOKUP(H2,Bausteine!$A$2:$AY$76,4,FALSE))+IF(I2="",0,VLOOKUP(I2,Bausteine!$A$2:$AY$76,4,FALSE))+IF(J2="",0,VLOOKUP(J2,Bausteine!$A$2:$AY$76,4,FALSE))+IF(K2="",0,VLOOKUP(K2,Bausteine!$A$2:$AY$76,4,FALSE))+IF(L2="",0,VLOOKUP(L2,Bausteine!$A$2:$AY$76,4,FALSE))+IF(AC2="",0,VLOOKUP(AC2,Bausteine!$A$2:$AY$76,4,FALSE))+IF(AF2="",0,VLOOKUP(AF2,Bausteine!$A$2:$AY$76,4,FALSE))+IF(AG2="",0,VLOOKUP(AG2,Bausteine!$A$2:$AY$76,4,FALSE))+IF(AH2="",0,VLOOKUP(AH2,Bausteine!$A$2:$AY$76,4,FALSE))+IF(AQ2="",0,VLOOKUP(AQ2,Bausteine!$A$2:$AY$76,4,FALSE)) | N2: =IF(C2="",0,VLOOKUP(C2,Bausteine!$A$2:$AY$76,5,FALSE))+IF(D2="",0,VLOOKUP(D2,Bausteine!$A$2:$AY$76,5,FALSE))+IF(E2="",0,VLOOKUP(E2,Bausteine!$A$2:$AY$76,5,FALSE))+IF(F2="",0,VLOOKUP(F2,Bausteine!$A$2:$AY$76,5,FALSE))+IF(G2="",0,VLOOKUP(G2,Bausteine!$A$2:$AY$76,5,FALSE))+IF(H2="",0,VLOOKUP(H2,Bausteine!$A$2:$AY$76,5,FALSE))+IF(I2="",0,VLOOKUP(I2,Bausteine!$A$2:$AY$76,5,FALSE))+IF(J2="",0,VLOOKUP(J2,Bausteine!$A$2:$AY$76,5,FALSE))+IF(K2="",0,VLOOKUP(K2,Bausteine!$A$2:$AY$76,5,FALSE))+IF(L2="",0,VLOOKUP(L2,Bausteine!$A$2:$AY$76,5,FALSE))+IF(AC2="",0,VLOOKUP(AC2,Bausteine!$A$2:$AY$76,5,FALSE))+IF(AF2="",0,VLOOKUP(AF2,Bausteine!$A$2:$AY$76,5,FALSE))+IF(AG2="",0,VLOOKUP(AG2,Bausteine!$A$2:$AY$76,5,FALSE))+IF(AH2="",0,VLOOKUP(AH2,Bausteine!$A$2:$AY$76,5,FALSE))+IF(AQ2="",0,VLOOKUP(AQ2,Bausteine!$A$2:$AY$76,5,FALSE)) | O2: =MAX(IF(C2="",0,VLOOKUP(C2,Bausteine!$A$2:$AY$76,6,FALSE)),IF(D2="",0,VLOOKUP(D2,Bausteine!$A$2:$AY$76,6,FALSE)),IF(E2="",0,VLOOKUP(E2,Bausteine!$A$2:$AY$76,6,FALSE)),IF(F2="",0,VLOOKUP(F2,Bausteine!$A$2:$AY$76,6,FALSE)),IF(G2="",0,VLOOKUP(G2,Bausteine!$A$2:$AY$76,6,FALSE)),IF(H2="",0,VLOOKUP(H2,Bausteine!$A$2:$AY$76,6,FALSE)),IF(I2="",0,VLOOKUP(I2,Bausteine!$A$2:$AY$76,6,FALSE)),IF(J2="",0,VLOOKUP(J2,Bausteine!$A$2:$AY$76,6,FALSE)),IF(K2="",0,VLOOKUP(K2,Bausteine!$A$2:$AY$76,6,FALSE)),IF(L2="",0,VLOOKUP(L2,Bausteine!$A$2:$AY$76,6,FALSE)),IF(AC2="",0,VLOOKUP(AC2,Bausteine!$A$2:$AY$76,6,FALSE)),IF(AF2="",0,VLOOKUP(AF2,Bausteine!$A$2:$AY$76,6,FALSE)),IF(AG2="",0,VLOOKUP(AG2,Bausteine!$A$2:$AY$76,6,FALSE)),IF(AH2="",0,VLOOKUP(AH2,Bausteine!$A$2:$AY$76,6,FALSE)),IF(AQ2="",0,VLOOKUP(AQ2,Bausteine!$A$2:$AY$76,6,FALSE)),AK2) | P2: =IF(C2="",0,VLOOKUP(C2,Bausteine!$A$2:$AY$76,7,FALSE))*IF(F2="",0,VLOOKUP(F2,Bausteine!$A$2:$AY$76,17,FALSE))/100+IF(D2="",0,VLOOKUP(D2,Bausteine!$A$2:$AY$76,7,FALSE))+IF(E2="",0,VLOOKUP(E2,Bausteine!$A$2:$AY$76,7,FALSE))+IF(G2="",0,VLOOKUP(G2,Bausteine!$A$2:$AY$76,7,FALSE))+IF(H2="",0,VLOOKUP(H2,Bausteine!$A$2:$AY$76,7,FALSE))+IF(I2="",0,VLOOKUP(I2,Bausteine!$A$2:$AY$76,7,FALSE))+IF(J2="",0,VLOOKUP(J2,Bausteine!$A$2:$AY$76,7,FALSE))+IF(K2="",0,VLOOKUP(K2,Bausteine!$A$2:$AY$76,7,FALSE))+IF(L2="",0,VLOOKUP(L2,Bausteine!$A$2:$AY$76,7,FALSE))+IF(AC2="",0,VLOOKUP(AC2,Bausteine!$A$2:$AY$76,7,FALSE))+IF(AF2="",0,VLOOKUP(AF2,Bausteine!$A$2:$AY$76,7,FALSE))+IF(AG2="",0,VLOOKUP(AG2,Bausteine!$A$2:$AY$76,7,FALSE))+IF(AH2="",0,VLOOKUP(AH2,Bausteine!$A$2:$AY$76,7,FALSE))+IF(AQ2="",0,VLOOKUP(AQ2,Bausteine!$A$2:$AY$76,7,FALSE))+AI2 | Q2: =N2*Parameter!$B$2 | R2: =AE2-Q2 | S2: =IF(C2="",0,VLOOKUP(C2,Bausteine!$A$2:$AY$76,13,FALSE))*IF(F2="",0,VLOOKUP(F2,Bausteine!$A$2:$AY$76,16,FALSE))/100 | T2: =IF(C2="",0,VLOOKUP(C2,Bausteine!$A$2:$AY$76,8,FALSE))*IF(F2="",0,VLOOKUP(F2,Bausteine!$A$2:$AY$76,15,FALSE))/100+IF(D2="",0,VLOOKUP(D2,Bausteine!$A$2:$AY$76,8,FALSE))+IF(E2="",0,VLOOKUP(E2,Bausteine!$A$2:$AY$76,8,FALSE))+IF(G2="",0,VLOOKUP(G2,Bausteine!$A$2:$AY$76,8,FALSE))+IF(H2="",0,VLOOKUP(H2,Bausteine!$A$2:$AY$76,8,FALSE))+IF(I2="",0,VLOOKUP(I2,Bausteine!$A$2:$AY$76,8,FALSE))+IF(J2="",0,VLOOKUP(J2,Bausteine!$A$2:$AY$76,8,FALSE))+IF(K2="",0,VLOOKUP(K2,Bausteine!$A$2:$AY$76,8,FALSE))+IF(L2="",0,VLOOKUP(L2,Bausteine!$A$2:$AY$76,8,FALSE))+IF(AC2="",0,VLOOKUP(AC2,Bausteine!$A$2:$AY$76,8,FALSE))+IF(AF2="",0,VLOOKUP(AF2,Bausteine!$A$2:$AY$76,8,FALSE))+IF(AG2="",0,VLOOKUP(AG2,Bausteine!$A$2:$AY$76,8,FALSE))+IF(AH2="",0,VLOOKUP(AH2,Bausteine!$A$2:$AY$76,8,FALSE))+IF(AQ2="",0,VLOOKUP(AQ2,Bausteine!$A$2:$AY$76,8,FALSE))+AJ2 | U2: =IF(C2="",0,VLOOKUP(C2,Bausteine!$A$2:$AY$76,9,FALSE))+IF(D2="",0,VLOOKUP(D2,Bausteine!$A$2:$AY$76,9,FALSE))+IF(E2="",0,VLOOKUP(E2,Bausteine!$A$2:$AY$76,9,FALSE))+IF(F2="",0,VLOOKUP(F2,Bausteine!$A$2:$AY$76,9,FALSE))+IF(G2="",0,VLOOKUP(G2,Bausteine!$A$2:$AY$76,9,FALSE))+IF(H2="",0,VLOOKUP(H2,Bausteine!$A$2:$AY$76,9,FALSE))+IF(I2="",0,VLOOKUP(I2,Bausteine!$A$2:$AY$76,9,FALSE))+IF(J2="",0,VLOOKUP(J2,Bausteine!$A$2:$AY$76,9,FALSE))+IF(K2="",0,VLOOKUP(K2,Bausteine!$A$2:$AY$76,9,FALSE))+IF(L2="",0,VLOOKUP(L2,Bausteine!$A$2:$AY$76,9,FALSE))+IF(AC2="",0,VLOOKUP(AC2,Bausteine!$A$2:$AY$76,9,FALSE))+IF(AF2="",0,VLOOKUP(AF2,Bausteine!$A$2:$AY$76,9,FALSE))+IF(AG2="",0,VLOOKUP(AG2,Bausteine!$A$2:$AY$76,9,FALSE))+IF(AH2="",0,VLOOKUP(AH2,Bausteine!$A$2:$AY$76,9,FALSE))+IF(AQ2="",0,VLOOKUP(AQ2,Bausteine!$A$2:$AY$76,9,FALSE)) | V2: =IF(D2="",0,VLOOKUP(D2,Bausteine!$A$2:$AY$76,10,FALSE))-U2/IF(E2="",0,VLOOKUP(E2,Bausteine!$A$2:$AY$76,11,FALSE)) | W2: =IF(Y2<>"OK","",ROUND(MIN(IF(C2="",0,VLOOKUP(C2,Bausteine!$A$2:$AY$76,21,FALSE)),IF(AQ2="",0,VLOOKUP(AQ2,Bausteine!$A$2:$AY$76,21,FALSE)),IF(C2="",0,VLOOKUP(C2,Bausteine!$A$2:$AY$76,20,FALSE))*(V2/T2/(IF(C2="",0,VLOOKUP(C2,Bausteine!$A$2:$AY$76,19,FALSE))/IF(C2="",0,VLOOKUP(C2,Bausteine!$A$2:$AY$76,18,FALSE))))^Parameter!$B$3),0)) | X2: =IF(F2="",0,VLOOKUP(F2,Bausteine!$A$2:$AY$76,14,FALSE)) | Y2: =IFERROR(IF(OR(AD2<=0,AD2>1,R2<=0,T2<=0,V2<=0,U2>IF(E2="",0,VLOOKUP(E2,Bausteine!$A$2:$AY$76,12,FALSE)),T2>MIN(IF(C2="",0,VLOOKUP(C2,Bausteine!$A$2:$AY$76,22,FALSE)),IF(AQ2="",0,VLOOKUP(AQ2,Bausteine!$A$2:$AY$76,22,FALSE))),IF(E2="",0,VLOOKUP(E2,Bausteine!$A$2:$AY$76,11,FALSE))<=0,IF(E2="",0,VLOOKUP(E2,Bausteine!$A$2:$AY$76,11,FALSE))>1),"UNGUELTIG","OK"),"FEHLER") | Z2: 400 | AA2: 157 | AB2: Shared MG/sensors/wheels. Scalar baseline only; sensor and biological-driver traits not compiled. Hull price is an explicit initial baseline fit. | AD2: =IF(AC2="",1,IF(AC2="",0,VLOOKUP(AC2,Bausteine!$A$2:$AY$76,37,FALSE))/100) | AE2: =P2*AD2 | AI2: =SUMIF(Startbesatzung!$A$2:$A$7,A2,Startbesatzung!$D$2:$D$7) | AJ2: =SUMIF(Startbesatzung!$A$2:$A$7,A2,Startbesatzung!$E$2:$E$7) | AK2: =MAX(0,IF(Startbesatzung!A2=A2,Startbesatzung!G2,0),IF(Startbesatzung!A3=A2,Startbesatzung!G3,0),IF(Startbesatzung!A4=A2,Startbesatzung!G4,0),IF(Startbesatzung!A5=A2,Startbesatzung!G5,0),IF(Startbesatzung!A6=A2,Startbesatzung!G6,0),IF(Startbesatzung!A7=A2,Startbesatzung!G7,0)) | AL2: =IF(AF2="","",IF(IF(AH2="",0,VLOOKUP(AH2,Bausteine!$A$2:$AY$76,38,FALSE))>0,IF(AH2="",0,VLOOKUP(AH2,Bausteine!$A$2:$AY$76,38,FALSE)),IF(AG2="",0,VLOOKUP(AG2,Bausteine!$A$2:$AY$76,28,FALSE)))) | AM2: =IF(AF2="","",IF(AG2="",0,VLOOKUP(AG2,Bausteine!$A$2:$AY$76,44,FALSE))) | AN2: =IF(AF2="","",IF(AF2="",0,VLOOKUP(AF2,Bausteine!$A$2:$AY$76,27,FALSE))) | AO2: =IF(AF2="","",IF(AF2="",0,VLOOKUP(AF2,Bausteine!$A$2:$AY$76,25,FALSE))) | AP2: =IF(AF2="","",IF(AH2="",0,VLOOKUP(AH2,Bausteine!$A$2:$AY$76,29,FALSE))) | AQ2: wheels-light | AR2: =IF(AQ2="",0,VLOOKUP(AQ2,Bausteine!$A$2:$AY$76,48,FALSE)) | AS2: =MIN(IF(AQ2="",0,VLOOKUP(AQ2,Bausteine!$A$2:$AY$76,50,FALSE)),IF(C2="",0,VLOOKUP(C2,Bausteine!$A$2:$AY$76,51,FALSE)))
A3: Buggy baseline | B3: nod | C3: buggy-hull | D3: diesel-light | E3: baseline-generator | F3: light | G3: scout-mg-mount | H3: scout-mg | I3: scout-mg-rounds | J3: scout-sensors | M3: =IF(C3="",0,VLOOKUP(C3,Bausteine!$A$2:$AY$76,4,FALSE))+IF(D3="",0,VLOOKUP(D3,Bausteine!$A$2:$AY$76,4,FALSE))+IF(E3="",0,VLOOKUP(E3,Bausteine!$A$2:$AY$76,4,FALSE))+IF(F3="",0,VLOOKUP(F3,Bausteine!$A$2:$AY$76,4,FALSE))+IF(G3="",0,VLOOKUP(G3,Bausteine!$A$2:$AY$76,4,FALSE))+IF(H3="",0,VLOOKUP(H3,Bausteine!$A$2:$AY$76,4,FALSE))+IF(I3="",0,VLOOKUP(I3,Bausteine!$A$2:$AY$76,4,FALSE))+IF(J3="",0,VLOOKUP(J3,Bausteine!$A$2:$AY$76,4,FALSE))+IF(K3="",0,VLOOKUP(K3,Bausteine!$A$2:$AY$76,4,FALSE))+IF(L3="",0,VLOOKUP(L3,Bausteine!$A$2:$AY$76,4,FALSE))+IF(AC3="",0,VLOOKUP(AC3,Bausteine!$A$2:$AY$76,4,FALSE))+IF(AF3="",0,VLOOKUP(AF3,Bausteine!$A$2:$AY$76,4,FALSE))+IF(AG3="",0,VLOOKUP(AG3,Bausteine!$A$2:$AY$76,4,FALSE))+IF(AH3="",0,VLOOKUP(AH3,Bausteine!$A$2:$AY$76,4,FALSE))+IF(AQ3="",0,VLOOKUP(AQ3,Bausteine!$A$2:$AY$76,4,FALSE)) | N3: =IF(C3="",0,VLOOKUP(C3,Bausteine!$A$2:$AY$76,5,FALSE))+IF(D3="",0,VLOOKUP(D3,Bausteine!$A$2:$AY$76,5,FALSE))+IF(E3="",0,VLOOKUP(E3,Bausteine!$A$2:$AY$76,5,FALSE))+IF(F3="",0,VLOOKUP(F3,Bausteine!$A$2:$AY$76,5,FALSE))+IF(G3="",0,VLOOKUP(G3,Bausteine!$A$2:$AY$76,5,FALSE))+IF(H3="",0,VLOOKUP(H3,Bausteine!$A$2:$AY$76,5,FALSE))+IF(I3="",0,VLOOKUP(I3,Bausteine!$A$2:$AY$76,5,FALSE))+IF(J3="",0,VLOOKUP(J3,Bausteine!$A$2:$AY$76,5,FALSE))+IF(K3="",0,VLOOKUP(K3,Bausteine!$A$2:$AY$76,5,FALSE))+IF(L3="",0,VLOOKUP(L3,Bausteine!$A$2:$AY$76,5,FALSE))+IF(AC3="",0,VLOOKUP(AC3,Bausteine!$A$2:$AY$76,5,FALSE))+IF(AF3="",0,VLOOKUP(AF3,Bausteine!$A$2:$AY$76,5,FALSE))+IF(AG3="",0,VLOOKUP(AG3,Bausteine!$A$2:$AY$76,5,FALSE))+IF(AH3="",0,VLOOKUP(AH3,Bausteine!$A$2:$AY$76,5,FALSE))+IF(AQ3="",0,VLOOKUP(AQ3,Bausteine!$A$2:$AY$76,5,FALSE)) | O3: =MAX(IF(C3="",0,VLOOKUP(C3,Bausteine!$A$2:$AY$76,6,FALSE)),IF(D3="",0,VLOOKUP(D3,Bausteine!$A$2:$AY$76,6,FALSE)),IF(E3="",0,VLOOKUP(E3,Bausteine!$A$2:$AY$76,6,FALSE)),IF(F3="",0,VLOOKUP(F3,Bausteine!$A$2:$AY$76,6,FALSE)),IF(G3="",0,VLOOKUP(G3,Bausteine!$A$2:$AY$76,6,FALSE)),IF(H3="",0,VLOOKUP(H3,Bausteine!$A$2:$AY$76,6,FALSE)),IF(I3="",0,VLOOKUP(I3,Bausteine!$A$2:$AY$76,6,FALSE)),IF(J3="",0,VLOOKUP(J3,Bausteine!$A$2:$AY$76,6,FALSE)),IF(K3="",0,VLOOKUP(K3,Bausteine!$A$2:$AY$76,6,FALSE)),IF(L3="",0,VLOOKUP(L3,Bausteine!$A$2:$AY$76,6,FALSE)),IF(AC3="",0,VLOOKUP(AC3,Bausteine!$A$2:$AY$76,6,FALSE)),IF(AF3="",0,VLOOKUP(AF3,Bausteine!$A$2:$AY$76,6,FALSE)),IF(AG3="",0,VLOOKUP(AG3,Bausteine!$A$2:$AY$76,6,FALSE)),IF(AH3="",0,VLOOKUP(AH3,Bausteine!$A$2:$AY$76,6,FALSE)),IF(AQ3="",0,VLOOKUP(AQ3,Bausteine!$A$2:$AY$76,6,FALSE)),AK3) | P3: =IF(C3="",0,VLOOKUP(C3,Bausteine!$A$2:$AY$76,7,FALSE))*IF(F3="",0,VLOOKUP(F3,Bausteine!$A$2:$AY$76,17,FALSE))/100+IF(D3="",0,VLOOKUP(D3,Bausteine!$A$2:$AY$76,7,FALSE))+IF(E3="",0,VLOOKUP(E3,Bausteine!$A$2:$AY$76,7,FALSE))+IF(G3="",0,VLOOKUP(G3,Bausteine!$A$2:$AY$76,7,FALSE))+IF(H3="",0,VLOOKUP(H3,Bausteine!$A$2:$AY$76,7,FALSE))+IF(I3="",0,VLOOKUP(I3,Bausteine!$A$2:$AY$76,7,FALSE))+IF(J3="",0,VLOOKUP(J3,Bausteine!$A$2:$AY$76,7,FALSE))+IF(K3="",0,VLOOKUP(K3,Bausteine!$A$2:$AY$76,7,FALSE))+IF(L3="",0,VLOOKUP(L3,Bausteine!$A$2:$AY$76,7,FALSE))+IF(AC3="",0,VLOOKUP(AC3,Bausteine!$A$2:$AY$76,7,FALSE))+IF(AF3="",0,VLOOKUP(AF3,Bausteine!$A$2:$AY$76,7,FALSE))+IF(AG3="",0,VLOOKUP(AG3,Bausteine!$A$2:$AY$76,7,FALSE))+IF(AH3="",0,VLOOKUP(AH3,Bausteine!$A$2:$AY$76,7,FALSE))+IF(AQ3="",0,VLOOKUP(AQ3,Bausteine!$A$2:$AY$76,7,FALSE))+AI3 | Q3: =N3*Parameter!$B$2 | R3: =AE3-Q3 | S3: =IF(C3="",0,VLOOKUP(C3,Bausteine!$A$2:$AY$76,13,FALSE))*IF(F3="",0,VLOOKUP(F3,Bausteine!$A$2:$AY$76,16,FALSE))/100 | T3: =IF(C3="",0,VLOOKUP(C3,Bausteine!$A$2:$AY$76,8,FALSE))*IF(F3="",0,VLOOKUP(F3,Bausteine!$A$2:$AY$76,15,FALSE))/100+IF(D3="",0,VLOOKUP(D3,Bausteine!$A$2:$AY$76,8,FALSE))+IF(E3="",0,VLOOKUP(E3,Bausteine!$A$2:$AY$76,8,FALSE))+IF(G3="",0,VLOOKUP(G3,Bausteine!$A$2:$AY$76,8,FALSE))+IF(H3="",0,VLOOKUP(H3,Bausteine!$A$2:$AY$76,8,FALSE))+IF(I3="",0,VLOOKUP(I3,Bausteine!$A$2:$AY$76,8,FALSE))+IF(J3="",0,VLOOKUP(J3,Bausteine!$A$2:$AY$76,8,FALSE))+IF(K3="",0,VLOOKUP(K3,Bausteine!$A$2:$AY$76,8,FALSE))+IF(L3="",0,VLOOKUP(L3,Bausteine!$A$2:$AY$76,8,FALSE))+IF(AC3="",0,VLOOKUP(AC3,Bausteine!$A$2:$AY$76,8,FALSE))+IF(AF3="",0,VLOOKUP(AF3,Bausteine!$A$2:$AY$76,8,FALSE))+IF(AG3="",0,VLOOKUP(AG3,Bausteine!$A$2:$AY$76,8,FALSE))+IF(AH3="",0,VLOOKUP(AH3,Bausteine!$A$2:$AY$76,8,FALSE))+IF(AQ3="",0,VLOOKUP(AQ3,Bausteine!$A$2:$AY$76,8,FALSE))+AJ3 | U3: =IF(C3="",0,VLOOKUP(C3,Bausteine!$A$2:$AY$76,9,FALSE))+IF(D3="",0,VLOOKUP(D3,Bausteine!$A$2:$AY$76,9,FALSE))+IF(E3="",0,VLOOKUP(E3,Bausteine!$A$2:$AY$76,9,FALSE))+IF(F3="",0,VLOOKUP(F3,Bausteine!$A$2:$AY$76,9,FALSE))+IF(G3="",0,VLOOKUP(G3,Bausteine!$A$2:$AY$76,9,FALSE))+IF(H3="",0,VLOOKUP(H3,Bausteine!$A$2:$AY$76,9,FALSE))+IF(I3="",0,VLOOKUP(I3,Bausteine!$A$2:$AY$76,9,FALSE))+IF(J3="",0,VLOOKUP(J3,Bausteine!$A$2:$AY$76,9,FALSE))+IF(K3="",0,VLOOKUP(K3,Bausteine!$A$2:$AY$76,9,FALSE))+IF(L3="",0,VLOOKUP(L3,Bausteine!$A$2:$AY$76,9,FALSE))+IF(AC3="",0,VLOOKUP(AC3,Bausteine!$A$2:$AY$76,9,FALSE))+IF(AF3="",0,VLOOKUP(AF3,Bausteine!$A$2:$AY$76,9,FALSE))+IF(AG3="",0,VLOOKUP(AG3,Bausteine!$A$2:$AY$76,9,FALSE))+IF(AH3="",0,VLOOKUP(AH3,Bausteine!$A$2:$AY$76,9,FALSE))+IF(AQ3="",0,VLOOKUP(AQ3,Bausteine!$A$2:$AY$76,9,FALSE)) | V3: =IF(D3="",0,VLOOKUP(D3,Bausteine!$A$2:$AY$76,10,FALSE))-U3/IF(E3="",0,VLOOKUP(E3,Bausteine!$A$2:$AY$76,11,FALSE)) | W3: =IF(Y3<>"OK","",ROUND(MIN(IF(C3="",0,VLOOKUP(C3,Bausteine!$A$2:$AY$76,21,FALSE)),IF(AQ3="",0,VLOOKUP(AQ3,Bausteine!$A$2:$AY$76,21,FALSE)),IF(C3="",0,VLOOKUP(C3,Bausteine!$A$2:$AY$76,20,FALSE))*(V3/T3/(IF(C3="",0,VLOOKUP(C3,Bausteine!$A$2:$AY$76,19,FALSE))/IF(C3="",0,VLOOKUP(C3,Bausteine!$A$2:$AY$76,18,FALSE))))^Parameter!$B$3),0)) | X3: =IF(F3="",0,VLOOKUP(F3,Bausteine!$A$2:$AY$76,14,FALSE)) | Y3: =IFERROR(IF(OR(AD3<=0,AD3>1,R3<=0,T3<=0,V3<=0,U3>IF(E3="",0,VLOOKUP(E3,Bausteine!$A$2:$AY$76,12,FALSE)),T3>MIN(IF(C3="",0,VLOOKUP(C3,Bausteine!$A$2:$AY$76,22,FALSE)),IF(AQ3="",0,VLOOKUP(AQ3,Bausteine!$A$2:$AY$76,22,FALSE))),IF(E3="",0,VLOOKUP(E3,Bausteine!$A$2:$AY$76,11,FALSE))<=0,IF(E3="",0,VLOOKUP(E3,Bausteine!$A$2:$AY$76,11,FALSE))>1),"UNGUELTIG","OK"),"FEHLER") | Z3: 350 | AA3: 157 | AB3: Same MG, wheels, motor and sensors as Hum-Vee. Different hull HP/mass/price; no per-design rebate. | AD3: =IF(AC3="",1,IF(AC3="",0,VLOOKUP(AC3,Bausteine!$A$2:$AY$76,37,FALSE))/100) | AE3: =P3*AD3 | AI3: =SUMIF(Startbesatzung!$A$2:$A$7,A3,Startbesatzung!$D$2:$D$7) | AJ3: =SUMIF(Startbesatzung!$A$2:$A$7,A3,Startbesatzung!$E$2:$E$7) | AK3: =MAX(0,IF(Startbesatzung!A2=A3,Startbesatzung!G2,0),IF(Startbesatzung!A3=A3,Startbesatzung!G3,0),IF(Startbesatzung!A4=A3,Startbesatzung!G4,0),IF(Startbesatzung!A5=A3,Startbesatzung!G5,0),IF(Startbesatzung!A6=A3,Startbesatzung!G6,0),IF(Startbesatzung!A7=A3,Startbesatzung!G7,0)) | AL3: =IF(AF3="","",IF(IF(AH3="",0,VLOOKUP(AH3,Bausteine!$A$2:$AY$76,38,FALSE))>0,IF(AH3="",0,VLOOKUP(AH3,Bausteine!$A$2:$AY$76,38,FALSE)),IF(AG3="",0,VLOOKUP(AG3,Bausteine!$A$2:$AY$76,28,FALSE)))) | AM3: =IF(AF3="","",IF(AG3="",0,VLOOKUP(AG3,Bausteine!$A$2:$AY$76,44,FALSE))) | AN3: =IF(AF3="","",IF(AF3="",0,VLOOKUP(AF3,Bausteine!$A$2:$AY$76,27,FALSE))) | AO3: =IF(AF3="","",IF(AF3="",0,VLOOKUP(AF3,Bausteine!$A$2:$AY$76,25,FALSE))) | AP3: =IF(AF3="","",IF(AH3="",0,VLOOKUP(AH3,Bausteine!$A$2:$AY$76,29,FALSE))) | AQ3: wheels-light | AR3: =IF(AQ3="",0,VLOOKUP(AQ3,Bausteine!$A$2:$AY$76,48,FALSE)) | AS3: =MIN(IF(AQ3="",0,VLOOKUP(AQ3,Bausteine!$A$2:$AY$76,50,FALSE)),IF(C3="",0,VLOOKUP(C3,Bausteine!$A$2:$AY$76,51,FALSE)))
A4: Nod Light Tank baseline | B4: nod | C4: nod-light-hull | D4: diesel | E4: baseline-generator | F4: heavy | G4: light-cannon-mount | H4: light-cannon | I4: light-tank-shell | M4: =IF(C4="",0,VLOOKUP(C4,Bausteine!$A$2:$AY$76,4,FALSE))+IF(D4="",0,VLOOKUP(D4,Bausteine!$A$2:$AY$76,4,FALSE))+IF(E4="",0,VLOOKUP(E4,Bausteine!$A$2:$AY$76,4,FALSE))+IF(F4="",0,VLOOKUP(F4,Bausteine!$A$2:$AY$76,4,FALSE))+IF(G4="",0,VLOOKUP(G4,Bausteine!$A$2:$AY$76,4,FALSE))+IF(H4="",0,VLOOKUP(H4,Bausteine!$A$2:$AY$76,4,FALSE))+IF(I4="",0,VLOOKUP(I4,Bausteine!$A$2:$AY$76,4,FALSE))+IF(J4="",0,VLOOKUP(J4,Bausteine!$A$2:$AY$76,4,FALSE))+IF(K4="",0,VLOOKUP(K4,Bausteine!$A$2:$AY$76,4,FALSE))+IF(L4="",0,VLOOKUP(L4,Bausteine!$A$2:$AY$76,4,FALSE))+IF(AC4="",0,VLOOKUP(AC4,Bausteine!$A$2:$AY$76,4,FALSE))+IF(AF4="",0,VLOOKUP(AF4,Bausteine!$A$2:$AY$76,4,FALSE))+IF(AG4="",0,VLOOKUP(AG4,Bausteine!$A$2:$AY$76,4,FALSE))+IF(AH4="",0,VLOOKUP(AH4,Bausteine!$A$2:$AY$76,4,FALSE))+IF(AQ4="",0,VLOOKUP(AQ4,Bausteine!$A$2:$AY$76,4,FALSE)) | N4: =IF(C4="",0,VLOOKUP(C4,Bausteine!$A$2:$AY$76,5,FALSE))+IF(D4="",0,VLOOKUP(D4,Bausteine!$A$2:$AY$76,5,FALSE))+IF(E4="",0,VLOOKUP(E4,Bausteine!$A$2:$AY$76,5,FALSE))+IF(F4="",0,VLOOKUP(F4,Bausteine!$A$2:$AY$76,5,FALSE))+IF(G4="",0,VLOOKUP(G4,Bausteine!$A$2:$AY$76,5,FALSE))+IF(H4="",0,VLOOKUP(H4,Bausteine!$A$2:$AY$76,5,FALSE))+IF(I4="",0,VLOOKUP(I4,Bausteine!$A$2:$AY$76,5,FALSE))+IF(J4="",0,VLOOKUP(J4,Bausteine!$A$2:$AY$76,5,FALSE))+IF(K4="",0,VLOOKUP(K4,Bausteine!$A$2:$AY$76,5,FALSE))+IF(L4="",0,VLOOKUP(L4,Bausteine!$A$2:$AY$76,5,FALSE))+IF(AC4="",0,VLOOKUP(AC4,Bausteine!$A$2:$AY$76,5,FALSE))+IF(AF4="",0,VLOOKUP(AF4,Bausteine!$A$2:$AY$76,5,FALSE))+IF(AG4="",0,VLOOKUP(AG4,Bausteine!$A$2:$AY$76,5,FALSE))+IF(AH4="",0,VLOOKUP(AH4,Bausteine!$A$2:$AY$76,5,FALSE))+IF(AQ4="",0,VLOOKUP(AQ4,Bausteine!$A$2:$AY$76,5,FALSE)) | O4: =MAX(IF(C4="",0,VLOOKUP(C4,Bausteine!$A$2:$AY$76,6,FALSE)),IF(D4="",0,VLOOKUP(D4,Bausteine!$A$2:$AY$76,6,FALSE)),IF(E4="",0,VLOOKUP(E4,Bausteine!$A$2:$AY$76,6,FALSE)),IF(F4="",0,VLOOKUP(F4,Bausteine!$A$2:$AY$76,6,FALSE)),IF(G4="",0,VLOOKUP(G4,Bausteine!$A$2:$AY$76,6,FALSE)),IF(H4="",0,VLOOKUP(H4,Bausteine!$A$2:$AY$76,6,FALSE)),IF(I4="",0,VLOOKUP(I4,Bausteine!$A$2:$AY$76,6,FALSE)),IF(J4="",0,VLOOKUP(J4,Bausteine!$A$2:$AY$76,6,FALSE)),IF(K4="",0,VLOOKUP(K4,Bausteine!$A$2:$AY$76,6,FALSE)),IF(L4="",0,VLOOKUP(L4,Bausteine!$A$2:$AY$76,6,FALSE)),IF(AC4="",0,VLOOKUP(AC4,Bausteine!$A$2:$AY$76,6,FALSE)),IF(AF4="",0,VLOOKUP(AF4,Bausteine!$A$2:$AY$76,6,FALSE)),IF(AG4="",0,VLOOKUP(AG4,Bausteine!$A$2:$AY$76,6,FALSE)),IF(AH4="",0,VLOOKUP(AH4,Bausteine!$A$2:$AY$76,6,FALSE)),IF(AQ4="",0,VLOOKUP(AQ4,Bausteine!$A$2:$AY$76,6,FALSE)),AK4) | P4: =IF(C4="",0,VLOOKUP(C4,Bausteine!$A$2:$AY$76,7,FALSE))*IF(F4="",0,VLOOKUP(F4,Bausteine!$A$2:$AY$76,17,FALSE))/100+IF(D4="",0,VLOOKUP(D4,Bausteine!$A$2:$AY$76,7,FALSE))+IF(E4="",0,VLOOKUP(E4,Bausteine!$A$2:$AY$76,7,FALSE))+IF(G4="",0,VLOOKUP(G4,Bausteine!$A$2:$AY$76,7,FALSE))+IF(H4="",0,VLOOKUP(H4,Bausteine!$A$2:$AY$76,7,FALSE))+IF(I4="",0,VLOOKUP(I4,Bausteine!$A$2:$AY$76,7,FALSE))+IF(J4="",0,VLOOKUP(J4,Bausteine!$A$2:$AY$76,7,FALSE))+IF(K4="",0,VLOOKUP(K4,Bausteine!$A$2:$AY$76,7,FALSE))+IF(L4="",0,VLOOKUP(L4,Bausteine!$A$2:$AY$76,7,FALSE))+IF(AC4="",0,VLOOKUP(AC4,Bausteine!$A$2:$AY$76,7,FALSE))+IF(AF4="",0,VLOOKUP(AF4,Bausteine!$A$2:$AY$76,7,FALSE))+IF(AG4="",0,VLOOKUP(AG4,Bausteine!$A$2:$AY$76,7,FALSE))+IF(AH4="",0,VLOOKUP(AH4,Bausteine!$A$2:$AY$76,7,FALSE))+IF(AQ4="",0,VLOOKUP(AQ4,Bausteine!$A$2:$AY$76,7,FALSE))+AI4 | Q4: =N4*Parameter!$B$2 | R4: =AE4-Q4 | S4: =IF(C4="",0,VLOOKUP(C4,Bausteine!$A$2:$AY$76,13,FALSE))*IF(F4="",0,VLOOKUP(F4,Bausteine!$A$2:$AY$76,16,FALSE))/100 | T4: =IF(C4="",0,VLOOKUP(C4,Bausteine!$A$2:$AY$76,8,FALSE))*IF(F4="",0,VLOOKUP(F4,Bausteine!$A$2:$AY$76,15,FALSE))/100+IF(D4="",0,VLOOKUP(D4,Bausteine!$A$2:$AY$76,8,FALSE))+IF(E4="",0,VLOOKUP(E4,Bausteine!$A$2:$AY$76,8,FALSE))+IF(G4="",0,VLOOKUP(G4,Bausteine!$A$2:$AY$76,8,FALSE))+IF(H4="",0,VLOOKUP(H4,Bausteine!$A$2:$AY$76,8,FALSE))+IF(I4="",0,VLOOKUP(I4,Bausteine!$A$2:$AY$76,8,FALSE))+IF(J4="",0,VLOOKUP(J4,Bausteine!$A$2:$AY$76,8,FALSE))+IF(K4="",0,VLOOKUP(K4,Bausteine!$A$2:$AY$76,8,FALSE))+IF(L4="",0,VLOOKUP(L4,Bausteine!$A$2:$AY$76,8,FALSE))+IF(AC4="",0,VLOOKUP(AC4,Bausteine!$A$2:$AY$76,8,FALSE))+IF(AF4="",0,VLOOKUP(AF4,Bausteine!$A$2:$AY$76,8,FALSE))+IF(AG4="",0,VLOOKUP(AG4,Bausteine!$A$2:$AY$76,8,FALSE))+IF(AH4="",0,VLOOKUP(AH4,Bausteine!$A$2:$AY$76,8,FALSE))+IF(AQ4="",0,VLOOKUP(AQ4,Bausteine!$A$2:$AY$76,8,FALSE))+AJ4 | U4: =IF(C4="",0,VLOOKUP(C4,Bausteine!$A$2:$AY$76,9,FALSE))+IF(D4="",0,VLOOKUP(D4,Bausteine!$A$2:$AY$76,9,FALSE))+IF(E4="",0,VLOOKUP(E4,Bausteine!$A$2:$AY$76,9,FALSE))+IF(F4="",0,VLOOKUP(F4,Bausteine!$A$2:$AY$76,9,FALSE))+IF(G4="",0,VLOOKUP(G4,Bausteine!$A$2:$AY$76,9,FALSE))+IF(H4="",0,VLOOKUP(H4,Bausteine!$A$2:$AY$76,9,FALSE))+IF(I4="",0,VLOOKUP(I4,Bausteine!$A$2:$AY$76,9,FALSE))+IF(J4="",0,VLOOKUP(J4,Bausteine!$A$2:$AY$76,9,FALSE))+IF(K4="",0,VLOOKUP(K4,Bausteine!$A$2:$AY$76,9,FALSE))+IF(L4="",0,VLOOKUP(L4,Bausteine!$A$2:$AY$76,9,FALSE))+IF(AC4="",0,VLOOKUP(AC4,Bausteine!$A$2:$AY$76,9,FALSE))+IF(AF4="",0,VLOOKUP(AF4,Bausteine!$A$2:$AY$76,9,FALSE))+IF(AG4="",0,VLOOKUP(AG4,Bausteine!$A$2:$AY$76,9,FALSE))+IF(AH4="",0,VLOOKUP(AH4,Bausteine!$A$2:$AY$76,9,FALSE))+IF(AQ4="",0,VLOOKUP(AQ4,Bausteine!$A$2:$AY$76,9,FALSE)) | V4: =IF(D4="",0,VLOOKUP(D4,Bausteine!$A$2:$AY$76,10,FALSE))-U4/IF(E4="",0,VLOOKUP(E4,Bausteine!$A$2:$AY$76,11,FALSE)) | W4: =IF(Y4<>"OK","",ROUND(MIN(IF(C4="",0,VLOOKUP(C4,Bausteine!$A$2:$AY$76,21,FALSE)),IF(AQ4="",0,VLOOKUP(AQ4,Bausteine!$A$2:$AY$76,21,FALSE)),IF(C4="",0,VLOOKUP(C4,Bausteine!$A$2:$AY$76,20,FALSE))*(V4/T4/(IF(C4="",0,VLOOKUP(C4,Bausteine!$A$2:$AY$76,19,FALSE))/IF(C4="",0,VLOOKUP(C4,Bausteine!$A$2:$AY$76,18,FALSE))))^Parameter!$B$3),0)) | X4: =IF(F4="",0,VLOOKUP(F4,Bausteine!$A$2:$AY$76,14,FALSE)) | Y4: =IFERROR(IF(OR(AD4<=0,AD4>1,R4<=0,T4<=0,V4<=0,U4>IF(E4="",0,VLOOKUP(E4,Bausteine!$A$2:$AY$76,12,FALSE)),T4>MIN(IF(C4="",0,VLOOKUP(C4,Bausteine!$A$2:$AY$76,22,FALSE)),IF(AQ4="",0,VLOOKUP(AQ4,Bausteine!$A$2:$AY$76,22,FALSE))),IF(E4="",0,VLOOKUP(E4,Bausteine!$A$2:$AY$76,11,FALSE))<=0,IF(E4="",0,VLOOKUP(E4,Bausteine!$A$2:$AY$76,11,FALSE))>1),"UNGUELTIG","OK"),"FEHLER") | Z4: 625 | AA4: 100 | AB4: Shared 30mm assembly with Devil/T-34. No laser upgrades or drone/driver behavior compiled. | AD4: =IF(AC4="",1,IF(AC4="",0,VLOOKUP(AC4,Bausteine!$A$2:$AY$76,37,FALSE))/100) | AE4: =P4*AD4 | AI4: =SUMIF(Startbesatzung!$A$2:$A$7,A4,Startbesatzung!$D$2:$D$7) | AJ4: =SUMIF(Startbesatzung!$A$2:$A$7,A4,Startbesatzung!$E$2:$E$7) | AK4: =MAX(0,IF(Startbesatzung!A2=A4,Startbesatzung!G2,0),IF(Startbesatzung!A3=A4,Startbesatzung!G3,0),IF(Startbesatzung!A4=A4,Startbesatzung!G4,0),IF(Startbesatzung!A5=A4,Startbesatzung!G5,0),IF(Startbesatzung!A6=A4,Startbesatzung!G6,0),IF(Startbesatzung!A7=A4,Startbesatzung!G7,0)) | AL4: =IF(AF4="","",IF(IF(AH4="",0,VLOOKUP(AH4,Bausteine!$A$2:$AY$76,38,FALSE))>0,IF(AH4="",0,VLOOKUP(AH4,Bausteine!$A$2:$AY$76,38,FALSE)),IF(AG4="",0,VLOOKUP(AG4,Bausteine!$A$2:$AY$76,28,FALSE)))) | AM4: =IF(AF4="","",IF(AG4="",0,VLOOKUP(AG4,Bausteine!$A$2:$AY$76,44,FALSE))) | AN4: =IF(AF4="","",IF(AF4="",0,VLOOKUP(AF4,Bausteine!$A$2:$AY$76,27,FALSE))) | AO4: =IF(AF4="","",IF(AF4="",0,VLOOKUP(AF4,Bausteine!$A$2:$AY$76,25,FALSE))) | AP4: =IF(AF4="","",IF(AH4="",0,VLOOKUP(AH4,Bausteine!$A$2:$AY$76,29,FALSE))) | AQ4: tracks-standard | AR4: =IF(AQ4="",0,VLOOKUP(AQ4,Bausteine!$A$2:$AY$76,48,FALSE)) | AS4: =MIN(IF(AQ4="",0,VLOOKUP(AQ4,Bausteine!$A$2:$AY$76,50,FALSE)),IF(C4="",0,VLOOKUP(C4,Bausteine!$A$2:$AY$76,51,FALSE)))
A5: T-34 baseline | B5: soviet | C5: t34-hull | D5: diesel | E5: baseline-generator | F5: heavy | G5: light-cannon-mount | H5: light-cannon | I5: light-tank-shell | M5: =IF(C5="",0,VLOOKUP(C5,Bausteine!$A$2:$AY$76,4,FALSE))+IF(D5="",0,VLOOKUP(D5,Bausteine!$A$2:$AY$76,4,FALSE))+IF(E5="",0,VLOOKUP(E5,Bausteine!$A$2:$AY$76,4,FALSE))+IF(F5="",0,VLOOKUP(F5,Bausteine!$A$2:$AY$76,4,FALSE))+IF(G5="",0,VLOOKUP(G5,Bausteine!$A$2:$AY$76,4,FALSE))+IF(H5="",0,VLOOKUP(H5,Bausteine!$A$2:$AY$76,4,FALSE))+IF(I5="",0,VLOOKUP(I5,Bausteine!$A$2:$AY$76,4,FALSE))+IF(J5="",0,VLOOKUP(J5,Bausteine!$A$2:$AY$76,4,FALSE))+IF(K5="",0,VLOOKUP(K5,Bausteine!$A$2:$AY$76,4,FALSE))+IF(L5="",0,VLOOKUP(L5,Bausteine!$A$2:$AY$76,4,FALSE))+IF(AC5="",0,VLOOKUP(AC5,Bausteine!$A$2:$AY$76,4,FALSE))+IF(AF5="",0,VLOOKUP(AF5,Bausteine!$A$2:$AY$76,4,FALSE))+IF(AG5="",0,VLOOKUP(AG5,Bausteine!$A$2:$AY$76,4,FALSE))+IF(AH5="",0,VLOOKUP(AH5,Bausteine!$A$2:$AY$76,4,FALSE))+IF(AQ5="",0,VLOOKUP(AQ5,Bausteine!$A$2:$AY$76,4,FALSE)) | N5: =IF(C5="",0,VLOOKUP(C5,Bausteine!$A$2:$AY$76,5,FALSE))+IF(D5="",0,VLOOKUP(D5,Bausteine!$A$2:$AY$76,5,FALSE))+IF(E5="",0,VLOOKUP(E5,Bausteine!$A$2:$AY$76,5,FALSE))+IF(F5="",0,VLOOKUP(F5,Bausteine!$A$2:$AY$76,5,FALSE))+IF(G5="",0,VLOOKUP(G5,Bausteine!$A$2:$AY$76,5,FALSE))+IF(H5="",0,VLOOKUP(H5,Bausteine!$A$2:$AY$76,5,FALSE))+IF(I5="",0,VLOOKUP(I5,Bausteine!$A$2:$AY$76,5,FALSE))+IF(J5="",0,VLOOKUP(J5,Bausteine!$A$2:$AY$76,5,FALSE))+IF(K5="",0,VLOOKUP(K5,Bausteine!$A$2:$AY$76,5,FALSE))+IF(L5="",0,VLOOKUP(L5,Bausteine!$A$2:$AY$76,5,FALSE))+IF(AC5="",0,VLOOKUP(AC5,Bausteine!$A$2:$AY$76,5,FALSE))+IF(AF5="",0,VLOOKUP(AF5,Bausteine!$A$2:$AY$76,5,FALSE))+IF(AG5="",0,VLOOKUP(AG5,Bausteine!$A$2:$AY$76,5,FALSE))+IF(AH5="",0,VLOOKUP(AH5,Bausteine!$A$2:$AY$76,5,FALSE))+IF(AQ5="",0,VLOOKUP(AQ5,Bausteine!$A$2:$AY$76,5,FALSE)) | O5: =MAX(IF(C5="",0,VLOOKUP(C5,Bausteine!$A$2:$AY$76,6,FALSE)),IF(D5="",0,VLOOKUP(D5,Bausteine!$A$2:$AY$76,6,FALSE)),IF(E5="",0,VLOOKUP(E5,Bausteine!$A$2:$AY$76,6,FALSE)),IF(F5="",0,VLOOKUP(F5,Bausteine!$A$2:$AY$76,6,FALSE)),IF(G5="",0,VLOOKUP(G5,Bausteine!$A$2:$AY$76,6,FALSE)),IF(H5="",0,VLOOKUP(H5,Bausteine!$A$2:$AY$76,6,FALSE)),IF(I5="",0,VLOOKUP(I5,Bausteine!$A$2:$AY$76,6,FALSE)),IF(J5="",0,VLOOKUP(J5,Bausteine!$A$2:$AY$76,6,FALSE)),IF(K5="",0,VLOOKUP(K5,Bausteine!$A$2:$AY$76,6,FALSE)),IF(L5="",0,VLOOKUP(L5,Bausteine!$A$2:$AY$76,6,FALSE)),IF(AC5="",0,VLOOKUP(AC5,Bausteine!$A$2:$AY$76,6,FALSE)),IF(AF5="",0,VLOOKUP(AF5,Bausteine!$A$2:$AY$76,6,FALSE)),IF(AG5="",0,VLOOKUP(AG5,Bausteine!$A$2:$AY$76,6,FALSE)),IF(AH5="",0,VLOOKUP(AH5,Bausteine!$A$2:$AY$76,6,FALSE)),IF(AQ5="",0,VLOOKUP(AQ5,Bausteine!$A$2:$AY$76,6,FALSE)),AK5) | P5: =IF(C5="",0,VLOOKUP(C5,Bausteine!$A$2:$AY$76,7,FALSE))*IF(F5="",0,VLOOKUP(F5,Bausteine!$A$2:$AY$76,17,FALSE))/100+IF(D5="",0,VLOOKUP(D5,Bausteine!$A$2:$AY$76,7,FALSE))+IF(E5="",0,VLOOKUP(E5,Bausteine!$A$2:$AY$76,7,FALSE))+IF(G5="",0,VLOOKUP(G5,Bausteine!$A$2:$AY$76,7,FALSE))+IF(H5="",0,VLOOKUP(H5,Bausteine!$A$2:$AY$76,7,FALSE))+IF(I5="",0,VLOOKUP(I5,Bausteine!$A$2:$AY$76,7,FALSE))+IF(J5="",0,VLOOKUP(J5,Bausteine!$A$2:$AY$76,7,FALSE))+IF(K5="",0,VLOOKUP(K5,Bausteine!$A$2:$AY$76,7,FALSE))+IF(L5="",0,VLOOKUP(L5,Bausteine!$A$2:$AY$76,7,FALSE))+IF(AC5="",0,VLOOKUP(AC5,Bausteine!$A$2:$AY$76,7,FALSE))+IF(AF5="",0,VLOOKUP(AF5,Bausteine!$A$2:$AY$76,7,FALSE))+IF(AG5="",0,VLOOKUP(AG5,Bausteine!$A$2:$AY$76,7,FALSE))+IF(AH5="",0,VLOOKUP(AH5,Bausteine!$A$2:$AY$76,7,FALSE))+IF(AQ5="",0,VLOOKUP(AQ5,Bausteine!$A$2:$AY$76,7,FALSE))+AI5 | Q5: =N5*Parameter!$B$2 | R5: =AE5-Q5 | S5: =IF(C5="",0,VLOOKUP(C5,Bausteine!$A$2:$AY$76,13,FALSE))*IF(F5="",0,VLOOKUP(F5,Bausteine!$A$2:$AY$76,16,FALSE))/100 | T5: =IF(C5="",0,VLOOKUP(C5,Bausteine!$A$2:$AY$76,8,FALSE))*IF(F5="",0,VLOOKUP(F5,Bausteine!$A$2:$AY$76,15,FALSE))/100+IF(D5="",0,VLOOKUP(D5,Bausteine!$A$2:$AY$76,8,FALSE))+IF(E5="",0,VLOOKUP(E5,Bausteine!$A$2:$AY$76,8,FALSE))+IF(G5="",0,VLOOKUP(G5,Bausteine!$A$2:$AY$76,8,FALSE))+IF(H5="",0,VLOOKUP(H5,Bausteine!$A$2:$AY$76,8,FALSE))+IF(I5="",0,VLOOKUP(I5,Bausteine!$A$2:$AY$76,8,FALSE))+IF(J5="",0,VLOOKUP(J5,Bausteine!$A$2:$AY$76,8,FALSE))+IF(K5="",0,VLOOKUP(K5,Bausteine!$A$2:$AY$76,8,FALSE))+IF(L5="",0,VLOOKUP(L5,Bausteine!$A$2:$AY$76,8,FALSE))+IF(AC5="",0,VLOOKUP(AC5,Bausteine!$A$2:$AY$76,8,FALSE))+IF(AF5="",0,VLOOKUP(AF5,Bausteine!$A$2:$AY$76,8,FALSE))+IF(AG5="",0,VLOOKUP(AG5,Bausteine!$A$2:$AY$76,8,FALSE))+IF(AH5="",0,VLOOKUP(AH5,Bausteine!$A$2:$AY$76,8,FALSE))+IF(AQ5="",0,VLOOKUP(AQ5,Bausteine!$A$2:$AY$76,8,FALSE))+AJ5 | U5: =IF(C5="",0,VLOOKUP(C5,Bausteine!$A$2:$AY$76,9,FALSE))+IF(D5="",0,VLOOKUP(D5,Bausteine!$A$2:$AY$76,9,FALSE))+IF(E5="",0,VLOOKUP(E5,Bausteine!$A$2:$AY$76,9,FALSE))+IF(F5="",0,VLOOKUP(F5,Bausteine!$A$2:$AY$76,9,FALSE))+IF(G5="",0,VLOOKUP(G5,Bausteine!$A$2:$AY$76,9,FALSE))+IF(H5="",0,VLOOKUP(H5,Bausteine!$A$2:$AY$76,9,FALSE))+IF(I5="",0,VLOOKUP(I5,Bausteine!$A$2:$AY$76,9,FALSE))+IF(J5="",0,VLOOKUP(J5,Bausteine!$A$2:$AY$76,9,FALSE))+IF(K5="",0,VLOOKUP(K5,Bausteine!$A$2:$AY$76,9,FALSE))+IF(L5="",0,VLOOKUP(L5,Bausteine!$A$2:$AY$76,9,FALSE))+IF(AC5="",0,VLOOKUP(AC5,Bausteine!$A$2:$AY$76,9,FALSE))+IF(AF5="",0,VLOOKUP(AF5,Bausteine!$A$2:$AY$76,9,FALSE))+IF(AG5="",0,VLOOKUP(AG5,Bausteine!$A$2:$AY$76,9,FALSE))+IF(AH5="",0,VLOOKUP(AH5,Bausteine!$A$2:$AY$76,9,FALSE))+IF(AQ5="",0,VLOOKUP(AQ5,Bausteine!$A$2:$AY$76,9,FALSE)) | V5: =IF(D5="",0,VLOOKUP(D5,Bausteine!$A$2:$AY$76,10,FALSE))-U5/IF(E5="",0,VLOOKUP(E5,Bausteine!$A$2:$AY$76,11,FALSE)) | W5: =IF(Y5<>"OK","",ROUND(MIN(IF(C5="",0,VLOOKUP(C5,Bausteine!$A$2:$AY$76,21,FALSE)),IF(AQ5="",0,VLOOKUP(AQ5,Bausteine!$A$2:$AY$76,21,FALSE)),IF(C5="",0,VLOOKUP(C5,Bausteine!$A$2:$AY$76,20,FALSE))*(V5/T5/(IF(C5="",0,VLOOKUP(C5,Bausteine!$A$2:$AY$76,19,FALSE))/IF(C5="",0,VLOOKUP(C5,Bausteine!$A$2:$AY$76,18,FALSE))))^Parameter!$B$3),0)) | X5: =IF(F5="",0,VLOOKUP(F5,Bausteine!$A$2:$AY$76,14,FALSE)) | Y5: =IFERROR(IF(OR(AD5<=0,AD5>1,R5<=0,T5<=0,V5<=0,U5>IF(E5="",0,VLOOKUP(E5,Bausteine!$A$2:$AY$76,12,FALSE)),T5>MIN(IF(C5="",0,VLOOKUP(C5,Bausteine!$A$2:$AY$76,22,FALSE)),IF(AQ5="",0,VLOOKUP(AQ5,Bausteine!$A$2:$AY$76,22,FALSE))),IF(E5="",0,VLOOKUP(E5,Bausteine!$A$2:$AY$76,11,FALSE))<=0,IF(E5="",0,VLOOKUP(E5,Bausteine!$A$2:$AY$76,11,FALSE))>1),"UNGUELTIG","OK"),"FEHLER") | Z5: 600 | AA5: 100 | AB5: Cluster upgrade excluded; Soviet base-faction availability is proposed, legacy unit is North Korea. Initial hull price fit, not independent balance validation. | AD5: =IF(AC5="",1,IF(AC5="",0,VLOOKUP(AC5,Bausteine!$A$2:$AY$76,37,FALSE))/100) | AE5: =P5*AD5 | AI5: =SUMIF(Startbesatzung!$A$2:$A$7,A5,Startbesatzung!$D$2:$D$7) | AJ5: =SUMIF(Startbesatzung!$A$2:$A$7,A5,Startbesatzung!$E$2:$E$7) | AK5: =MAX(0,IF(Startbesatzung!A2=A5,Startbesatzung!G2,0),IF(Startbesatzung!A3=A5,Startbesatzung!G3,0),IF(Startbesatzung!A4=A5,Startbesatzung!G4,0),IF(Startbesatzung!A5=A5,Startbesatzung!G5,0),IF(Startbesatzung!A6=A5,Startbesatzung!G6,0),IF(Startbesatzung!A7=A5,Startbesatzung!G7,0)) | AL5: =IF(AF5="","",IF(IF(AH5="",0,VLOOKUP(AH5,Bausteine!$A$2:$AY$76,38,FALSE))>0,IF(AH5="",0,VLOOKUP(AH5,Bausteine!$A$2:$AY$76,38,FALSE)),IF(AG5="",0,VLOOKUP(AG5,Bausteine!$A$2:$AY$76,28,FALSE)))) | AM5: =IF(AF5="","",IF(AG5="",0,VLOOKUP(AG5,Bausteine!$A$2:$AY$76,44,FALSE))) | AN5: =IF(AF5="","",IF(AF5="",0,VLOOKUP(AF5,Bausteine!$A$2:$AY$76,27,FALSE))) | AO5: =IF(AF5="","",IF(AF5="",0,VLOOKUP(AF5,Bausteine!$A$2:$AY$76,25,FALSE))) | AP5: =IF(AF5="","",IF(AH5="",0,VLOOKUP(AH5,Bausteine!$A$2:$AY$76,29,FALSE))) | AQ5: tracks-standard | AR5: =IF(AQ5="",0,VLOOKUP(AQ5,Bausteine!$A$2:$AY$76,48,FALSE)) | AS5: =MIN(IF(AQ5="",0,VLOOKUP(AQ5,Bausteine!$A$2:$AY$76,50,FALSE)),IF(C5="",0,VLOOKUP(C5,Bausteine!$A$2:$AY$76,51,FALSE)))
A6: Devil Tank baseline | B6: soviet | C6: devil-hull | D6: diesel | E6: baseline-generator | F6: heavy | G6: light-cannon-mount | H6: light-cannon | I6: light-tank-shell | M6: =IF(C6="",0,VLOOKUP(C6,Bausteine!$A$2:$AY$76,4,FALSE))+IF(D6="",0,VLOOKUP(D6,Bausteine!$A$2:$AY$76,4,FALSE))+IF(E6="",0,VLOOKUP(E6,Bausteine!$A$2:$AY$76,4,FALSE))+IF(F6="",0,VLOOKUP(F6,Bausteine!$A$2:$AY$76,4,FALSE))+IF(G6="",0,VLOOKUP(G6,Bausteine!$A$2:$AY$76,4,FALSE))+IF(H6="",0,VLOOKUP(H6,Bausteine!$A$2:$AY$76,4,FALSE))+IF(I6="",0,VLOOKUP(I6,Bausteine!$A$2:$AY$76,4,FALSE))+IF(J6="",0,VLOOKUP(J6,Bausteine!$A$2:$AY$76,4,FALSE))+IF(K6="",0,VLOOKUP(K6,Bausteine!$A$2:$AY$76,4,FALSE))+IF(L6="",0,VLOOKUP(L6,Bausteine!$A$2:$AY$76,4,FALSE))+IF(AC6="",0,VLOOKUP(AC6,Bausteine!$A$2:$AY$76,4,FALSE))+IF(AF6="",0,VLOOKUP(AF6,Bausteine!$A$2:$AY$76,4,FALSE))+IF(AG6="",0,VLOOKUP(AG6,Bausteine!$A$2:$AY$76,4,FALSE))+IF(AH6="",0,VLOOKUP(AH6,Bausteine!$A$2:$AY$76,4,FALSE))+IF(AQ6="",0,VLOOKUP(AQ6,Bausteine!$A$2:$AY$76,4,FALSE)) | N6: =IF(C6="",0,VLOOKUP(C6,Bausteine!$A$2:$AY$76,5,FALSE))+IF(D6="",0,VLOOKUP(D6,Bausteine!$A$2:$AY$76,5,FALSE))+IF(E6="",0,VLOOKUP(E6,Bausteine!$A$2:$AY$76,5,FALSE))+IF(F6="",0,VLOOKUP(F6,Bausteine!$A$2:$AY$76,5,FALSE))+IF(G6="",0,VLOOKUP(G6,Bausteine!$A$2:$AY$76,5,FALSE))+IF(H6="",0,VLOOKUP(H6,Bausteine!$A$2:$AY$76,5,FALSE))+IF(I6="",0,VLOOKUP(I6,Bausteine!$A$2:$AY$76,5,FALSE))+IF(J6="",0,VLOOKUP(J6,Bausteine!$A$2:$AY$76,5,FALSE))+IF(K6="",0,VLOOKUP(K6,Bausteine!$A$2:$AY$76,5,FALSE))+IF(L6="",0,VLOOKUP(L6,Bausteine!$A$2:$AY$76,5,FALSE))+IF(AC6="",0,VLOOKUP(AC6,Bausteine!$A$2:$AY$76,5,FALSE))+IF(AF6="",0,VLOOKUP(AF6,Bausteine!$A$2:$AY$76,5,FALSE))+IF(AG6="",0,VLOOKUP(AG6,Bausteine!$A$2:$AY$76,5,FALSE))+IF(AH6="",0,VLOOKUP(AH6,Bausteine!$A$2:$AY$76,5,FALSE))+IF(AQ6="",0,VLOOKUP(AQ6,Bausteine!$A$2:$AY$76,5,FALSE)) | O6: =MAX(IF(C6="",0,VLOOKUP(C6,Bausteine!$A$2:$AY$76,6,FALSE)),IF(D6="",0,VLOOKUP(D6,Bausteine!$A$2:$AY$76,6,FALSE)),IF(E6="",0,VLOOKUP(E6,Bausteine!$A$2:$AY$76,6,FALSE)),IF(F6="",0,VLOOKUP(F6,Bausteine!$A$2:$AY$76,6,FALSE)),IF(G6="",0,VLOOKUP(G6,Bausteine!$A$2:$AY$76,6,FALSE)),IF(H6="",0,VLOOKUP(H6,Bausteine!$A$2:$AY$76,6,FALSE)),IF(I6="",0,VLOOKUP(I6,Bausteine!$A$2:$AY$76,6,FALSE)),IF(J6="",0,VLOOKUP(J6,Bausteine!$A$2:$AY$76,6,FALSE)),IF(K6="",0,VLOOKUP(K6,Bausteine!$A$2:$AY$76,6,FALSE)),IF(L6="",0,VLOOKUP(L6,Bausteine!$A$2:$AY$76,6,FALSE)),IF(AC6="",0,VLOOKUP(AC6,Bausteine!$A$2:$AY$76,6,FALSE)),IF(AF6="",0,VLOOKUP(AF6,Bausteine!$A$2:$AY$76,6,FALSE)),IF(AG6="",0,VLOOKUP(AG6,Bausteine!$A$2:$AY$76,6,FALSE)),IF(AH6="",0,VLOOKUP(AH6,Bausteine!$A$2:$AY$76,6,FALSE)),IF(AQ6="",0,VLOOKUP(AQ6,Bausteine!$A$2:$AY$76,6,FALSE)),AK6) | P6: =IF(C6="",0,VLOOKUP(C6,Bausteine!$A$2:$AY$76,7,FALSE))*IF(F6="",0,VLOOKUP(F6,Bausteine!$A$2:$AY$76,17,FALSE))/100+IF(D6="",0,VLOOKUP(D6,Bausteine!$A$2:$AY$76,7,FALSE))+IF(E6="",0,VLOOKUP(E6,Bausteine!$A$2:$AY$76,7,FALSE))+IF(G6="",0,VLOOKUP(G6,Bausteine!$A$2:$AY$76,7,FALSE))+IF(H6="",0,VLOOKUP(H6,Bausteine!$A$2:$AY$76,7,FALSE))+IF(I6="",0,VLOOKUP(I6,Bausteine!$A$2:$AY$76,7,FALSE))+IF(J6="",0,VLOOKUP(J6,Bausteine!$A$2:$AY$76,7,FALSE))+IF(K6="",0,VLOOKUP(K6,Bausteine!$A$2:$AY$76,7,FALSE))+IF(L6="",0,VLOOKUP(L6,Bausteine!$A$2:$AY$76,7,FALSE))+IF(AC6="",0,VLOOKUP(AC6,Bausteine!$A$2:$AY$76,7,FALSE))+IF(AF6="",0,VLOOKUP(AF6,Bausteine!$A$2:$AY$76,7,FALSE))+IF(AG6="",0,VLOOKUP(AG6,Bausteine!$A$2:$AY$76,7,FALSE))+IF(AH6="",0,VLOOKUP(AH6,Bausteine!$A$2:$AY$76,7,FALSE))+IF(AQ6="",0,VLOOKUP(AQ6,Bausteine!$A$2:$AY$76,7,FALSE))+AI6 | Q6: =N6*Parameter!$B$2 | R6: =AE6-Q6 | S6: =IF(C6="",0,VLOOKUP(C6,Bausteine!$A$2:$AY$76,13,FALSE))*IF(F6="",0,VLOOKUP(F6,Bausteine!$A$2:$AY$76,16,FALSE))/100 | T6: =IF(C6="",0,VLOOKUP(C6,Bausteine!$A$2:$AY$76,8,FALSE))*IF(F6="",0,VLOOKUP(F6,Bausteine!$A$2:$AY$76,15,FALSE))/100+IF(D6="",0,VLOOKUP(D6,Bausteine!$A$2:$AY$76,8,FALSE))+IF(E6="",0,VLOOKUP(E6,Bausteine!$A$2:$AY$76,8,FALSE))+IF(G6="",0,VLOOKUP(G6,Bausteine!$A$2:$AY$76,8,FALSE))+IF(H6="",0,VLOOKUP(H6,Bausteine!$A$2:$AY$76,8,FALSE))+IF(I6="",0,VLOOKUP(I6,Bausteine!$A$2:$AY$76,8,FALSE))+IF(J6="",0,VLOOKUP(J6,Bausteine!$A$2:$AY$76,8,FALSE))+IF(K6="",0,VLOOKUP(K6,Bausteine!$A$2:$AY$76,8,FALSE))+IF(L6="",0,VLOOKUP(L6,Bausteine!$A$2:$AY$76,8,FALSE))+IF(AC6="",0,VLOOKUP(AC6,Bausteine!$A$2:$AY$76,8,FALSE))+IF(AF6="",0,VLOOKUP(AF6,Bausteine!$A$2:$AY$76,8,FALSE))+IF(AG6="",0,VLOOKUP(AG6,Bausteine!$A$2:$AY$76,8,FALSE))+IF(AH6="",0,VLOOKUP(AH6,Bausteine!$A$2:$AY$76,8,FALSE))+IF(AQ6="",0,VLOOKUP(AQ6,Bausteine!$A$2:$AY$76,8,FALSE))+AJ6 | U6: =IF(C6="",0,VLOOKUP(C6,Bausteine!$A$2:$AY$76,9,FALSE))+IF(D6="",0,VLOOKUP(D6,Bausteine!$A$2:$AY$76,9,FALSE))+IF(E6="",0,VLOOKUP(E6,Bausteine!$A$2:$AY$76,9,FALSE))+IF(F6="",0,VLOOKUP(F6,Bausteine!$A$2:$AY$76,9,FALSE))+IF(G6="",0,VLOOKUP(G6,Bausteine!$A$2:$AY$76,9,FALSE))+IF(H6="",0,VLOOKUP(H6,Bausteine!$A$2:$AY$76,9,FALSE))+IF(I6="",0,VLOOKUP(I6,Bausteine!$A$2:$AY$76,9,FALSE))+IF(J6="",0,VLOOKUP(J6,Bausteine!$A$2:$AY$76,9,FALSE))+IF(K6="",0,VLOOKUP(K6,Bausteine!$A$2:$AY$76,9,FALSE))+IF(L6="",0,VLOOKUP(L6,Bausteine!$A$2:$AY$76,9,FALSE))+IF(AC6="",0,VLOOKUP(AC6,Bausteine!$A$2:$AY$76,9,FALSE))+IF(AF6="",0,VLOOKUP(AF6,Bausteine!$A$2:$AY$76,9,FALSE))+IF(AG6="",0,VLOOKUP(AG6,Bausteine!$A$2:$AY$76,9,FALSE))+IF(AH6="",0,VLOOKUP(AH6,Bausteine!$A$2:$AY$76,9,FALSE))+IF(AQ6="",0,VLOOKUP(AQ6,Bausteine!$A$2:$AY$76,9,FALSE)) | V6: =IF(D6="",0,VLOOKUP(D6,Bausteine!$A$2:$AY$76,10,FALSE))-U6/IF(E6="",0,VLOOKUP(E6,Bausteine!$A$2:$AY$76,11,FALSE)) | W6: =IF(Y6<>"OK","",ROUND(MIN(IF(C6="",0,VLOOKUP(C6,Bausteine!$A$2:$AY$76,21,FALSE)),IF(AQ6="",0,VLOOKUP(AQ6,Bausteine!$A$2:$AY$76,21,FALSE)),IF(C6="",0,VLOOKUP(C6,Bausteine!$A$2:$AY$76,20,FALSE))*(V6/T6/(IF(C6="",0,VLOOKUP(C6,Bausteine!$A$2:$AY$76,19,FALSE))/IF(C6="",0,VLOOKUP(C6,Bausteine!$A$2:$AY$76,18,FALSE))))^Parameter!$B$3),0)) | X6: =IF(F6="",0,VLOOKUP(F6,Bausteine!$A$2:$AY$76,14,FALSE)) | Y6: =IFERROR(IF(OR(AD6<=0,AD6>1,R6<=0,T6<=0,V6<=0,U6>IF(E6="",0,VLOOKUP(E6,Bausteine!$A$2:$AY$76,12,FALSE)),T6>MIN(IF(C6="",0,VLOOKUP(C6,Bausteine!$A$2:$AY$76,22,FALSE)),IF(AQ6="",0,VLOOKUP(AQ6,Bausteine!$A$2:$AY$76,22,FALSE))),IF(E6="",0,VLOOKUP(E6,Bausteine!$A$2:$AY$76,11,FALSE))<=0,IF(E6="",0,VLOOKUP(E6,Bausteine!$A$2:$AY$76,11,FALSE))>1),"UNGUELTIG","OK"),"FEHLER") | Z6: 700 | AA6: 90 | AB6: Iraq reference, mapped to Soviet base catalog. Existing live PDL/Reflector balancing not changed; not modeled on this new hull yet. | AD6: =IF(AC6="",1,IF(AC6="",0,VLOOKUP(AC6,Bausteine!$A$2:$AY$76,37,FALSE))/100) | AE6: =P6*AD6 | AI6: =SUMIF(Startbesatzung!$A$2:$A$7,A6,Startbesatzung!$D$2:$D$7) | AJ6: =SUMIF(Startbesatzung!$A$2:$A$7,A6,Startbesatzung!$E$2:$E$7) | AK6: =MAX(0,IF(Startbesatzung!A2=A6,Startbesatzung!G2,0),IF(Startbesatzung!A3=A6,Startbesatzung!G3,0),IF(Startbesatzung!A4=A6,Startbesatzung!G4,0),IF(Startbesatzung!A5=A6,Startbesatzung!G5,0),IF(Startbesatzung!A6=A6,Startbesatzung!G6,0),IF(Startbesatzung!A7=A6,Startbesatzung!G7,0)) | AL6: =IF(AF6="","",IF(IF(AH6="",0,VLOOKUP(AH6,Bausteine!$A$2:$AY$76,38,FALSE))>0,IF(AH6="",0,VLOOKUP(AH6,Bausteine!$A$2:$AY$76,38,FALSE)),IF(AG6="",0,VLOOKUP(AG6,Bausteine!$A$2:$AY$76,28,FALSE)))) | AM6: =IF(AF6="","",IF(AG6="",0,VLOOKUP(AG6,Bausteine!$A$2:$AY$76,44,FALSE))) | AN6: =IF(AF6="","",IF(AF6="",0,VLOOKUP(AF6,Bausteine!$A$2:$AY$76,27,FALSE))) | AO6: =IF(AF6="","",IF(AF6="",0,VLOOKUP(AF6,Bausteine!$A$2:$AY$76,25,FALSE))) | AP6: =IF(AF6="","",IF(AH6="",0,VLOOKUP(AH6,Bausteine!$A$2:$AY$76,29,FALSE))) | AQ6: tracks-standard | AR6: =IF(AQ6="",0,VLOOKUP(AQ6,Bausteine!$A$2:$AY$76,48,FALSE)) | AS6: =MIN(IF(AQ6="",0,VLOOKUP(AQ6,Bausteine!$A$2:$AY$76,50,FALSE)),IF(C6="",0,VLOOKUP(C6,Bausteine!$A$2:$AY$76,51,FALSE)))
A7: GDI Battle Tank baseline | B7: gdi | C7: gdi-battle-hull | D7: diesel | E7: baseline-generator | F7: heavy | G7: medium-cannon-mount | H7: medium-cannon | I7: medium-tank-shell | M7: =IF(C7="",0,VLOOKUP(C7,Bausteine!$A$2:$AY$76,4,FALSE))+IF(D7="",0,VLOOKUP(D7,Bausteine!$A$2:$AY$76,4,FALSE))+IF(E7="",0,VLOOKUP(E7,Bausteine!$A$2:$AY$76,4,FALSE))+IF(F7="",0,VLOOKUP(F7,Bausteine!$A$2:$AY$76,4,FALSE))+IF(G7="",0,VLOOKUP(G7,Bausteine!$A$2:$AY$76,4,FALSE))+IF(H7="",0,VLOOKUP(H7,Bausteine!$A$2:$AY$76,4,FALSE))+IF(I7="",0,VLOOKUP(I7,Bausteine!$A$2:$AY$76,4,FALSE))+IF(J7="",0,VLOOKUP(J7,Bausteine!$A$2:$AY$76,4,FALSE))+IF(K7="",0,VLOOKUP(K7,Bausteine!$A$2:$AY$76,4,FALSE))+IF(L7="",0,VLOOKUP(L7,Bausteine!$A$2:$AY$76,4,FALSE))+IF(AC7="",0,VLOOKUP(AC7,Bausteine!$A$2:$AY$76,4,FALSE))+IF(AF7="",0,VLOOKUP(AF7,Bausteine!$A$2:$AY$76,4,FALSE))+IF(AG7="",0,VLOOKUP(AG7,Bausteine!$A$2:$AY$76,4,FALSE))+IF(AH7="",0,VLOOKUP(AH7,Bausteine!$A$2:$AY$76,4,FALSE))+IF(AQ7="",0,VLOOKUP(AQ7,Bausteine!$A$2:$AY$76,4,FALSE)) | N7: =IF(C7="",0,VLOOKUP(C7,Bausteine!$A$2:$AY$76,5,FALSE))+IF(D7="",0,VLOOKUP(D7,Bausteine!$A$2:$AY$76,5,FALSE))+IF(E7="",0,VLOOKUP(E7,Bausteine!$A$2:$AY$76,5,FALSE))+IF(F7="",0,VLOOKUP(F7,Bausteine!$A$2:$AY$76,5,FALSE))+IF(G7="",0,VLOOKUP(G7,Bausteine!$A$2:$AY$76,5,FALSE))+IF(H7="",0,VLOOKUP(H7,Bausteine!$A$2:$AY$76,5,FALSE))+IF(I7="",0,VLOOKUP(I7,Bausteine!$A$2:$AY$76,5,FALSE))+IF(J7="",0,VLOOKUP(J7,Bausteine!$A$2:$AY$76,5,FALSE))+IF(K7="",0,VLOOKUP(K7,Bausteine!$A$2:$AY$76,5,FALSE))+IF(L7="",0,VLOOKUP(L7,Bausteine!$A$2:$AY$76,5,FALSE))+IF(AC7="",0,VLOOKUP(AC7,Bausteine!$A$2:$AY$76,5,FALSE))+IF(AF7="",0,VLOOKUP(AF7,Bausteine!$A$2:$AY$76,5,FALSE))+IF(AG7="",0,VLOOKUP(AG7,Bausteine!$A$2:$AY$76,5,FALSE))+IF(AH7="",0,VLOOKUP(AH7,Bausteine!$A$2:$AY$76,5,FALSE))+IF(AQ7="",0,VLOOKUP(AQ7,Bausteine!$A$2:$AY$76,5,FALSE)) | O7: =MAX(IF(C7="",0,VLOOKUP(C7,Bausteine!$A$2:$AY$76,6,FALSE)),IF(D7="",0,VLOOKUP(D7,Bausteine!$A$2:$AY$76,6,FALSE)),IF(E7="",0,VLOOKUP(E7,Bausteine!$A$2:$AY$76,6,FALSE)),IF(F7="",0,VLOOKUP(F7,Bausteine!$A$2:$AY$76,6,FALSE)),IF(G7="",0,VLOOKUP(G7,Bausteine!$A$2:$AY$76,6,FALSE)),IF(H7="",0,VLOOKUP(H7,Bausteine!$A$2:$AY$76,6,FALSE)),IF(I7="",0,VLOOKUP(I7,Bausteine!$A$2:$AY$76,6,FALSE)),IF(J7="",0,VLOOKUP(J7,Bausteine!$A$2:$AY$76,6,FALSE)),IF(K7="",0,VLOOKUP(K7,Bausteine!$A$2:$AY$76,6,FALSE)),IF(L7="",0,VLOOKUP(L7,Bausteine!$A$2:$AY$76,6,FALSE)),IF(AC7="",0,VLOOKUP(AC7,Bausteine!$A$2:$AY$76,6,FALSE)),IF(AF7="",0,VLOOKUP(AF7,Bausteine!$A$2:$AY$76,6,FALSE)),IF(AG7="",0,VLOOKUP(AG7,Bausteine!$A$2:$AY$76,6,FALSE)),IF(AH7="",0,VLOOKUP(AH7,Bausteine!$A$2:$AY$76,6,FALSE)),IF(AQ7="",0,VLOOKUP(AQ7,Bausteine!$A$2:$AY$76,6,FALSE)),AK7) | P7: =IF(C7="",0,VLOOKUP(C7,Bausteine!$A$2:$AY$76,7,FALSE))*IF(F7="",0,VLOOKUP(F7,Bausteine!$A$2:$AY$76,17,FALSE))/100+IF(D7="",0,VLOOKUP(D7,Bausteine!$A$2:$AY$76,7,FALSE))+IF(E7="",0,VLOOKUP(E7,Bausteine!$A$2:$AY$76,7,FALSE))+IF(G7="",0,VLOOKUP(G7,Bausteine!$A$2:$AY$76,7,FALSE))+IF(H7="",0,VLOOKUP(H7,Bausteine!$A$2:$AY$76,7,FALSE))+IF(I7="",0,VLOOKUP(I7,Bausteine!$A$2:$AY$76,7,FALSE))+IF(J7="",0,VLOOKUP(J7,Bausteine!$A$2:$AY$76,7,FALSE))+IF(K7="",0,VLOOKUP(K7,Bausteine!$A$2:$AY$76,7,FALSE))+IF(L7="",0,VLOOKUP(L7,Bausteine!$A$2:$AY$76,7,FALSE))+IF(AC7="",0,VLOOKUP(AC7,Bausteine!$A$2:$AY$76,7,FALSE))+IF(AF7="",0,VLOOKUP(AF7,Bausteine!$A$2:$AY$76,7,FALSE))+IF(AG7="",0,VLOOKUP(AG7,Bausteine!$A$2:$AY$76,7,FALSE))+IF(AH7="",0,VLOOKUP(AH7,Bausteine!$A$2:$AY$76,7,FALSE))+IF(AQ7="",0,VLOOKUP(AQ7,Bausteine!$A$2:$AY$76,7,FALSE))+AI7 | Q7: =N7*Parameter!$B$2 | R7: =AE7-Q7 | S7: =IF(C7="",0,VLOOKUP(C7,Bausteine!$A$2:$AY$76,13,FALSE))*IF(F7="",0,VLOOKUP(F7,Bausteine!$A$2:$AY$76,16,FALSE))/100 | T7: =IF(C7="",0,VLOOKUP(C7,Bausteine!$A$2:$AY$76,8,FALSE))*IF(F7="",0,VLOOKUP(F7,Bausteine!$A$2:$AY$76,15,FALSE))/100+IF(D7="",0,VLOOKUP(D7,Bausteine!$A$2:$AY$76,8,FALSE))+IF(E7="",0,VLOOKUP(E7,Bausteine!$A$2:$AY$76,8,FALSE))+IF(G7="",0,VLOOKUP(G7,Bausteine!$A$2:$AY$76,8,FALSE))+IF(H7="",0,VLOOKUP(H7,Bausteine!$A$2:$AY$76,8,FALSE))+IF(I7="",0,VLOOKUP(I7,Bausteine!$A$2:$AY$76,8,FALSE))+IF(J7="",0,VLOOKUP(J7,Bausteine!$A$2:$AY$76,8,FALSE))+IF(K7="",0,VLOOKUP(K7,Bausteine!$A$2:$AY$76,8,FALSE))+IF(L7="",0,VLOOKUP(L7,Bausteine!$A$2:$AY$76,8,FALSE))+IF(AC7="",0,VLOOKUP(AC7,Bausteine!$A$2:$AY$76,8,FALSE))+IF(AF7="",0,VLOOKUP(AF7,Bausteine!$A$2:$AY$76,8,FALSE))+IF(AG7="",0,VLOOKUP(AG7,Bausteine!$A$2:$AY$76,8,FALSE))+IF(AH7="",0,VLOOKUP(AH7,Bausteine!$A$2:$AY$76,8,FALSE))+IF(AQ7="",0,VLOOKUP(AQ7,Bausteine!$A$2:$AY$76,8,FALSE))+AJ7 | U7: =IF(C7="",0,VLOOKUP(C7,Bausteine!$A$2:$AY$76,9,FALSE))+IF(D7="",0,VLOOKUP(D7,Bausteine!$A$2:$AY$76,9,FALSE))+IF(E7="",0,VLOOKUP(E7,Bausteine!$A$2:$AY$76,9,FALSE))+IF(F7="",0,VLOOKUP(F7,Bausteine!$A$2:$AY$76,9,FALSE))+IF(G7="",0,VLOOKUP(G7,Bausteine!$A$2:$AY$76,9,FALSE))+IF(H7="",0,VLOOKUP(H7,Bausteine!$A$2:$AY$76,9,FALSE))+IF(I7="",0,VLOOKUP(I7,Bausteine!$A$2:$AY$76,9,FALSE))+IF(J7="",0,VLOOKUP(J7,Bausteine!$A$2:$AY$76,9,FALSE))+IF(K7="",0,VLOOKUP(K7,Bausteine!$A$2:$AY$76,9,FALSE))+IF(L7="",0,VLOOKUP(L7,Bausteine!$A$2:$AY$76,9,FALSE))+IF(AC7="",0,VLOOKUP(AC7,Bausteine!$A$2:$AY$76,9,FALSE))+IF(AF7="",0,VLOOKUP(AF7,Bausteine!$A$2:$AY$76,9,FALSE))+IF(AG7="",0,VLOOKUP(AG7,Bausteine!$A$2:$AY$76,9,FALSE))+IF(AH7="",0,VLOOKUP(AH7,Bausteine!$A$2:$AY$76,9,FALSE))+IF(AQ7="",0,VLOOKUP(AQ7,Bausteine!$A$2:$AY$76,9,FALSE)) | V7: =IF(D7="",0,VLOOKUP(D7,Bausteine!$A$2:$AY$76,10,FALSE))-U7/IF(E7="",0,VLOOKUP(E7,Bausteine!$A$2:$AY$76,11,FALSE)) | W7: =IF(Y7<>"OK","",ROUND(MIN(IF(C7="",0,VLOOKUP(C7,Bausteine!$A$2:$AY$76,21,FALSE)),IF(AQ7="",0,VLOOKUP(AQ7,Bausteine!$A$2:$AY$76,21,FALSE)),IF(C7="",0,VLOOKUP(C7,Bausteine!$A$2:$AY$76,20,FALSE))*(V7/T7/(IF(C7="",0,VLOOKUP(C7,Bausteine!$A$2:$AY$76,19,FALSE))/IF(C7="",0,VLOOKUP(C7,Bausteine!$A$2:$AY$76,18,FALSE))))^Parameter!$B$3),0)) | X7: =IF(F7="",0,VLOOKUP(F7,Bausteine!$A$2:$AY$76,14,FALSE)) | Y7: =IFERROR(IF(OR(AD7<=0,AD7>1,R7<=0,T7<=0,V7<=0,U7>IF(E7="",0,VLOOKUP(E7,Bausteine!$A$2:$AY$76,12,FALSE)),T7>MIN(IF(C7="",0,VLOOKUP(C7,Bausteine!$A$2:$AY$76,22,FALSE)),IF(AQ7="",0,VLOOKUP(AQ7,Bausteine!$A$2:$AY$76,22,FALSE))),IF(E7="",0,VLOOKUP(E7,Bausteine!$A$2:$AY$76,11,FALSE))<=0,IF(E7="",0,VLOOKUP(E7,Bausteine!$A$2:$AY$76,11,FALSE))>1),"UNGUELTIG","OK"),"FEHLER") | Z7: 900 | AA7: 82 | AB7: 120mm legacy binding; shared scalar family with 90mm, but distinct report/muzzle kept for future compiler. Vehicle armor bonus/drone pairing excluded. | AD7: =IF(AC7="",1,IF(AC7="",0,VLOOKUP(AC7,Bausteine!$A$2:$AY$76,37,FALSE))/100) | AE7: =P7*AD7 | AI7: =SUMIF(Startbesatzung!$A$2:$A$7,A7,Startbesatzung!$D$2:$D$7) | AJ7: =SUMIF(Startbesatzung!$A$2:$A$7,A7,Startbesatzung!$E$2:$E$7) | AK7: =MAX(0,IF(Startbesatzung!A2=A7,Startbesatzung!G2,0),IF(Startbesatzung!A3=A7,Startbesatzung!G3,0),IF(Startbesatzung!A4=A7,Startbesatzung!G4,0),IF(Startbesatzung!A5=A7,Startbesatzung!G5,0),IF(Startbesatzung!A6=A7,Startbesatzung!G6,0),IF(Startbesatzung!A7=A7,Startbesatzung!G7,0)) | AL7: =IF(AF7="","",IF(IF(AH7="",0,VLOOKUP(AH7,Bausteine!$A$2:$AY$76,38,FALSE))>0,IF(AH7="",0,VLOOKUP(AH7,Bausteine!$A$2:$AY$76,38,FALSE)),IF(AG7="",0,VLOOKUP(AG7,Bausteine!$A$2:$AY$76,28,FALSE)))) | AM7: =IF(AF7="","",IF(AG7="",0,VLOOKUP(AG7,Bausteine!$A$2:$AY$76,44,FALSE))) | AN7: =IF(AF7="","",IF(AF7="",0,VLOOKUP(AF7,Bausteine!$A$2:$AY$76,27,FALSE))) | AO7: =IF(AF7="","",IF(AF7="",0,VLOOKUP(AF7,Bausteine!$A$2:$AY$76,25,FALSE))) | AP7: =IF(AF7="","",IF(AH7="",0,VLOOKUP(AH7,Bausteine!$A$2:$AY$76,29,FALSE))) | AQ7: tracks-standard | AR7: =IF(AQ7="",0,VLOOKUP(AQ7,Bausteine!$A$2:$AY$76,48,FALSE)) | AS7: =MIN(IF(AQ7="",0,VLOOKUP(AQ7,Bausteine!$A$2:$AY$76,50,FALSE)),IF(C7="",0,VLOOKUP(C7,Bausteine!$A$2:$AY$76,51,FALSE)))
A8: Allied Medium Tank prototype | B8: allies | C8: allied-medium-hull | D8: diesel | E8: baseline-generator | F8: heavy | G8: medium-cannon-mount | H8: medium-cannon | I8: medium-tank-shell | M8: =IF(C8="",0,VLOOKUP(C8,Bausteine!$A$2:$AY$76,4,FALSE))+IF(D8="",0,VLOOKUP(D8,Bausteine!$A$2:$AY$76,4,FALSE))+IF(E8="",0,VLOOKUP(E8,Bausteine!$A$2:$AY$76,4,FALSE))+IF(F8="",0,VLOOKUP(F8,Bausteine!$A$2:$AY$76,4,FALSE))+IF(G8="",0,VLOOKUP(G8,Bausteine!$A$2:$AY$76,4,FALSE))+IF(H8="",0,VLOOKUP(H8,Bausteine!$A$2:$AY$76,4,FALSE))+IF(I8="",0,VLOOKUP(I8,Bausteine!$A$2:$AY$76,4,FALSE))+IF(J8="",0,VLOOKUP(J8,Bausteine!$A$2:$AY$76,4,FALSE))+IF(K8="",0,VLOOKUP(K8,Bausteine!$A$2:$AY$76,4,FALSE))+IF(L8="",0,VLOOKUP(L8,Bausteine!$A$2:$AY$76,4,FALSE))+IF(AC8="",0,VLOOKUP(AC8,Bausteine!$A$2:$AY$76,4,FALSE))+IF(AF8="",0,VLOOKUP(AF8,Bausteine!$A$2:$AY$76,4,FALSE))+IF(AG8="",0,VLOOKUP(AG8,Bausteine!$A$2:$AY$76,4,FALSE))+IF(AH8="",0,VLOOKUP(AH8,Bausteine!$A$2:$AY$76,4,FALSE))+IF(AQ8="",0,VLOOKUP(AQ8,Bausteine!$A$2:$AY$76,4,FALSE)) | N8: =IF(C8="",0,VLOOKUP(C8,Bausteine!$A$2:$AY$76,5,FALSE))+IF(D8="",0,VLOOKUP(D8,Bausteine!$A$2:$AY$76,5,FALSE))+IF(E8="",0,VLOOKUP(E8,Bausteine!$A$2:$AY$76,5,FALSE))+IF(F8="",0,VLOOKUP(F8,Bausteine!$A$2:$AY$76,5,FALSE))+IF(G8="",0,VLOOKUP(G8,Bausteine!$A$2:$AY$76,5,FALSE))+IF(H8="",0,VLOOKUP(H8,Bausteine!$A$2:$AY$76,5,FALSE))+IF(I8="",0,VLOOKUP(I8,Bausteine!$A$2:$AY$76,5,FALSE))+IF(J8="",0,VLOOKUP(J8,Bausteine!$A$2:$AY$76,5,FALSE))+IF(K8="",0,VLOOKUP(K8,Bausteine!$A$2:$AY$76,5,FALSE))+IF(L8="",0,VLOOKUP(L8,Bausteine!$A$2:$AY$76,5,FALSE))+IF(AC8="",0,VLOOKUP(AC8,Bausteine!$A$2:$AY$76,5,FALSE))+IF(AF8="",0,VLOOKUP(AF8,Bausteine!$A$2:$AY$76,5,FALSE))+IF(AG8="",0,VLOOKUP(AG8,Bausteine!$A$2:$AY$76,5,FALSE))+IF(AH8="",0,VLOOKUP(AH8,Bausteine!$A$2:$AY$76,5,FALSE))+IF(AQ8="",0,VLOOKUP(AQ8,Bausteine!$A$2:$AY$76,5,FALSE)) | O8: =MAX(IF(C8="",0,VLOOKUP(C8,Bausteine!$A$2:$AY$76,6,FALSE)),IF(D8="",0,VLOOKUP(D8,Bausteine!$A$2:$AY$76,6,FALSE)),IF(E8="",0,VLOOKUP(E8,Bausteine!$A$2:$AY$76,6,FALSE)),IF(F8="",0,VLOOKUP(F8,Bausteine!$A$2:$AY$76,6,FALSE)),IF(G8="",0,VLOOKUP(G8,Bausteine!$A$2:$AY$76,6,FALSE)),IF(H8="",0,VLOOKUP(H8,Bausteine!$A$2:$AY$76,6,FALSE)),IF(I8="",0,VLOOKUP(I8,Bausteine!$A$2:$AY$76,6,FALSE)),IF(J8="",0,VLOOKUP(J8,Bausteine!$A$2:$AY$76,6,FALSE)),IF(K8="",0,VLOOKUP(K8,Bausteine!$A$2:$AY$76,6,FALSE)),IF(L8="",0,VLOOKUP(L8,Bausteine!$A$2:$AY$76,6,FALSE)),IF(AC8="",0,VLOOKUP(AC8,Bausteine!$A$2:$AY$76,6,FALSE)),IF(AF8="",0,VLOOKUP(AF8,Bausteine!$A$2:$AY$76,6,FALSE)),IF(AG8="",0,VLOOKUP(AG8,Bausteine!$A$2:$AY$76,6,FALSE)),IF(AH8="",0,VLOOKUP(AH8,Bausteine!$A$2:$AY$76,6,FALSE)),IF(AQ8="",0,VLOOKUP(AQ8,Bausteine!$A$2:$AY$76,6,FALSE)),AK8) | P8: =IF(C8="",0,VLOOKUP(C8,Bausteine!$A$2:$AY$76,7,FALSE))*IF(F8="",0,VLOOKUP(F8,Bausteine!$A$2:$AY$76,17,FALSE))/100+IF(D8="",0,VLOOKUP(D8,Bausteine!$A$2:$AY$76,7,FALSE))+IF(E8="",0,VLOOKUP(E8,Bausteine!$A$2:$AY$76,7,FALSE))+IF(G8="",0,VLOOKUP(G8,Bausteine!$A$2:$AY$76,7,FALSE))+IF(H8="",0,VLOOKUP(H8,Bausteine!$A$2:$AY$76,7,FALSE))+IF(I8="",0,VLOOKUP(I8,Bausteine!$A$2:$AY$76,7,FALSE))+IF(J8="",0,VLOOKUP(J8,Bausteine!$A$2:$AY$76,7,FALSE))+IF(K8="",0,VLOOKUP(K8,Bausteine!$A$2:$AY$76,7,FALSE))+IF(L8="",0,VLOOKUP(L8,Bausteine!$A$2:$AY$76,7,FALSE))+IF(AC8="",0,VLOOKUP(AC8,Bausteine!$A$2:$AY$76,7,FALSE))+IF(AF8="",0,VLOOKUP(AF8,Bausteine!$A$2:$AY$76,7,FALSE))+IF(AG8="",0,VLOOKUP(AG8,Bausteine!$A$2:$AY$76,7,FALSE))+IF(AH8="",0,VLOOKUP(AH8,Bausteine!$A$2:$AY$76,7,FALSE))+IF(AQ8="",0,VLOOKUP(AQ8,Bausteine!$A$2:$AY$76,7,FALSE))+AI8 | Q8: =N8*Parameter!$B$2 | R8: =AE8-Q8 | S8: =IF(C8="",0,VLOOKUP(C8,Bausteine!$A$2:$AY$76,13,FALSE))*IF(F8="",0,VLOOKUP(F8,Bausteine!$A$2:$AY$76,16,FALSE))/100 | T8: =IF(C8="",0,VLOOKUP(C8,Bausteine!$A$2:$AY$76,8,FALSE))*IF(F8="",0,VLOOKUP(F8,Bausteine!$A$2:$AY$76,15,FALSE))/100+IF(D8="",0,VLOOKUP(D8,Bausteine!$A$2:$AY$76,8,FALSE))+IF(E8="",0,VLOOKUP(E8,Bausteine!$A$2:$AY$76,8,FALSE))+IF(G8="",0,VLOOKUP(G8,Bausteine!$A$2:$AY$76,8,FALSE))+IF(H8="",0,VLOOKUP(H8,Bausteine!$A$2:$AY$76,8,FALSE))+IF(I8="",0,VLOOKUP(I8,Bausteine!$A$2:$AY$76,8,FALSE))+IF(J8="",0,VLOOKUP(J8,Bausteine!$A$2:$AY$76,8,FALSE))+IF(K8="",0,VLOOKUP(K8,Bausteine!$A$2:$AY$76,8,FALSE))+IF(L8="",0,VLOOKUP(L8,Bausteine!$A$2:$AY$76,8,FALSE))+IF(AC8="",0,VLOOKUP(AC8,Bausteine!$A$2:$AY$76,8,FALSE))+IF(AF8="",0,VLOOKUP(AF8,Bausteine!$A$2:$AY$76,8,FALSE))+IF(AG8="",0,VLOOKUP(AG8,Bausteine!$A$2:$AY$76,8,FALSE))+IF(AH8="",0,VLOOKUP(AH8,Bausteine!$A$2:$AY$76,8,FALSE))+IF(AQ8="",0,VLOOKUP(AQ8,Bausteine!$A$2:$AY$76,8,FALSE))+AJ8 | U8: =IF(C8="",0,VLOOKUP(C8,Bausteine!$A$2:$AY$76,9,FALSE))+IF(D8="",0,VLOOKUP(D8,Bausteine!$A$2:$AY$76,9,FALSE))+IF(E8="",0,VLOOKUP(E8,Bausteine!$A$2:$AY$76,9,FALSE))+IF(F8="",0,VLOOKUP(F8,Bausteine!$A$2:$AY$76,9,FALSE))+IF(G8="",0,VLOOKUP(G8,Bausteine!$A$2:$AY$76,9,FALSE))+IF(H8="",0,VLOOKUP(H8,Bausteine!$A$2:$AY$76,9,FALSE))+IF(I8="",0,VLOOKUP(I8,Bausteine!$A$2:$AY$76,9,FALSE))+IF(J8="",0,VLOOKUP(J8,Bausteine!$A$2:$AY$76,9,FALSE))+IF(K8="",0,VLOOKUP(K8,Bausteine!$A$2:$AY$76,9,FALSE))+IF(L8="",0,VLOOKUP(L8,Bausteine!$A$2:$AY$76,9,FALSE))+IF(AC8="",0,VLOOKUP(AC8,Bausteine!$A$2:$AY$76,9,FALSE))+IF(AF8="",0,VLOOKUP(AF8,Bausteine!$A$2:$AY$76,9,FALSE))+IF(AG8="",0,VLOOKUP(AG8,Bausteine!$A$2:$AY$76,9,FALSE))+IF(AH8="",0,VLOOKUP(AH8,Bausteine!$A$2:$AY$76,9,FALSE))+IF(AQ8="",0,VLOOKUP(AQ8,Bausteine!$A$2:$AY$76,9,FALSE)) | V8: =IF(D8="",0,VLOOKUP(D8,Bausteine!$A$2:$AY$76,10,FALSE))-U8/IF(E8="",0,VLOOKUP(E8,Bausteine!$A$2:$AY$76,11,FALSE)) | W8: =IF(Y8<>"OK","",ROUND(MIN(IF(C8="",0,VLOOKUP(C8,Bausteine!$A$2:$AY$76,21,FALSE)),IF(AQ8="",0,VLOOKUP(AQ8,Bausteine!$A$2:$AY$76,21,FALSE)),IF(C8="",0,VLOOKUP(C8,Bausteine!$A$2:$AY$76,20,FALSE))*(V8/T8/(IF(C8="",0,VLOOKUP(C8,Bausteine!$A$2:$AY$76,19,FALSE))/IF(C8="",0,VLOOKUP(C8,Bausteine!$A$2:$AY$76,18,FALSE))))^Parameter!$B$3),0)) | X8: =IF(F8="",0,VLOOKUP(F8,Bausteine!$A$2:$AY$76,14,FALSE)) | Y8: =IFERROR(IF(OR(AD8<=0,AD8>1,R8<=0,T8<=0,V8<=0,U8>IF(E8="",0,VLOOKUP(E8,Bausteine!$A$2:$AY$76,12,FALSE)),T8>MIN(IF(C8="",0,VLOOKUP(C8,Bausteine!$A$2:$AY$76,22,FALSE)),IF(AQ8="",0,VLOOKUP(AQ8,Bausteine!$A$2:$AY$76,22,FALSE))),IF(E8="",0,VLOOKUP(E8,Bausteine!$A$2:$AY$76,11,FALSE))<=0,IF(E8="",0,VLOOKUP(E8,Bausteine!$A$2:$AY$76,11,FALSE))>1),"UNGUELTIG","OK"),"FEHLER") | Z8: 800 | AA8: 82 | AB8: 2TNK is a disabled parent, NOT a currently buildable actor. Basis for three national art variants. Armored Doctrine price multiplier excluded. | AD8: =IF(AC8="",1,IF(AC8="",0,VLOOKUP(AC8,Bausteine!$A$2:$AY$76,37,FALSE))/100) | AE8: =P8*AD8 | AI8: =SUMIF(Startbesatzung!$A$2:$A$7,A8,Startbesatzung!$D$2:$D$7) | AJ8: =SUMIF(Startbesatzung!$A$2:$A$7,A8,Startbesatzung!$E$2:$E$7) | AK8: =MAX(0,IF(Startbesatzung!A2=A8,Startbesatzung!G2,0),IF(Startbesatzung!A3=A8,Startbesatzung!G3,0),IF(Startbesatzung!A4=A8,Startbesatzung!G4,0),IF(Startbesatzung!A5=A8,Startbesatzung!G5,0),IF(Startbesatzung!A6=A8,Startbesatzung!G6,0),IF(Startbesatzung!A7=A8,Startbesatzung!G7,0)) | AL8: =IF(AF8="","",IF(IF(AH8="",0,VLOOKUP(AH8,Bausteine!$A$2:$AY$76,38,FALSE))>0,IF(AH8="",0,VLOOKUP(AH8,Bausteine!$A$2:$AY$76,38,FALSE)),IF(AG8="",0,VLOOKUP(AG8,Bausteine!$A$2:$AY$76,28,FALSE)))) | AM8: =IF(AF8="","",IF(AG8="",0,VLOOKUP(AG8,Bausteine!$A$2:$AY$76,44,FALSE))) | AN8: =IF(AF8="","",IF(AF8="",0,VLOOKUP(AF8,Bausteine!$A$2:$AY$76,27,FALSE))) | AO8: =IF(AF8="","",IF(AF8="",0,VLOOKUP(AF8,Bausteine!$A$2:$AY$76,25,FALSE))) | AP8: =IF(AF8="","",IF(AH8="",0,VLOOKUP(AH8,Bausteine!$A$2:$AY$76,29,FALSE))) | AQ8: tracks-standard | AR8: =IF(AQ8="",0,VLOOKUP(AQ8,Bausteine!$A$2:$AY$76,48,FALSE)) | AS8: =MIN(IF(AQ8="",0,VLOOKUP(AQ8,Bausteine!$A$2:$AY$76,50,FALSE)),IF(C8="",0,VLOOKUP(C8,Bausteine!$A$2:$AY$76,51,FALSE)))
A9: Challenger baseline | B9: allies | C9: allied-medium-hull | D9: diesel | E9: baseline-generator | F9: heavy | G9: medium-cannon-mount | H9: medium-cannon | I9: medium-tank-shell | M9: =IF(C9="",0,VLOOKUP(C9,Bausteine!$A$2:$AY$76,4,FALSE))+IF(D9="",0,VLOOKUP(D9,Bausteine!$A$2:$AY$76,4,FALSE))+IF(E9="",0,VLOOKUP(E9,Bausteine!$A$2:$AY$76,4,FALSE))+IF(F9="",0,VLOOKUP(F9,Bausteine!$A$2:$AY$76,4,FALSE))+IF(G9="",0,VLOOKUP(G9,Bausteine!$A$2:$AY$76,4,FALSE))+IF(H9="",0,VLOOKUP(H9,Bausteine!$A$2:$AY$76,4,FALSE))+IF(I9="",0,VLOOKUP(I9,Bausteine!$A$2:$AY$76,4,FALSE))+IF(J9="",0,VLOOKUP(J9,Bausteine!$A$2:$AY$76,4,FALSE))+IF(K9="",0,VLOOKUP(K9,Bausteine!$A$2:$AY$76,4,FALSE))+IF(L9="",0,VLOOKUP(L9,Bausteine!$A$2:$AY$76,4,FALSE))+IF(AC9="",0,VLOOKUP(AC9,Bausteine!$A$2:$AY$76,4,FALSE))+IF(AF9="",0,VLOOKUP(AF9,Bausteine!$A$2:$AY$76,4,FALSE))+IF(AG9="",0,VLOOKUP(AG9,Bausteine!$A$2:$AY$76,4,FALSE))+IF(AH9="",0,VLOOKUP(AH9,Bausteine!$A$2:$AY$76,4,FALSE))+IF(AQ9="",0,VLOOKUP(AQ9,Bausteine!$A$2:$AY$76,4,FALSE)) | N9: =IF(C9="",0,VLOOKUP(C9,Bausteine!$A$2:$AY$76,5,FALSE))+IF(D9="",0,VLOOKUP(D9,Bausteine!$A$2:$AY$76,5,FALSE))+IF(E9="",0,VLOOKUP(E9,Bausteine!$A$2:$AY$76,5,FALSE))+IF(F9="",0,VLOOKUP(F9,Bausteine!$A$2:$AY$76,5,FALSE))+IF(G9="",0,VLOOKUP(G9,Bausteine!$A$2:$AY$76,5,FALSE))+IF(H9="",0,VLOOKUP(H9,Bausteine!$A$2:$AY$76,5,FALSE))+IF(I9="",0,VLOOKUP(I9,Bausteine!$A$2:$AY$76,5,FALSE))+IF(J9="",0,VLOOKUP(J9,Bausteine!$A$2:$AY$76,5,FALSE))+IF(K9="",0,VLOOKUP(K9,Bausteine!$A$2:$AY$76,5,FALSE))+IF(L9="",0,VLOOKUP(L9,Bausteine!$A$2:$AY$76,5,FALSE))+IF(AC9="",0,VLOOKUP(AC9,Bausteine!$A$2:$AY$76,5,FALSE))+IF(AF9="",0,VLOOKUP(AF9,Bausteine!$A$2:$AY$76,5,FALSE))+IF(AG9="",0,VLOOKUP(AG9,Bausteine!$A$2:$AY$76,5,FALSE))+IF(AH9="",0,VLOOKUP(AH9,Bausteine!$A$2:$AY$76,5,FALSE))+IF(AQ9="",0,VLOOKUP(AQ9,Bausteine!$A$2:$AY$76,5,FALSE)) | O9: =MAX(IF(C9="",0,VLOOKUP(C9,Bausteine!$A$2:$AY$76,6,FALSE)),IF(D9="",0,VLOOKUP(D9,Bausteine!$A$2:$AY$76,6,FALSE)),IF(E9="",0,VLOOKUP(E9,Bausteine!$A$2:$AY$76,6,FALSE)),IF(F9="",0,VLOOKUP(F9,Bausteine!$A$2:$AY$76,6,FALSE)),IF(G9="",0,VLOOKUP(G9,Bausteine!$A$2:$AY$76,6,FALSE)),IF(H9="",0,VLOOKUP(H9,Bausteine!$A$2:$AY$76,6,FALSE)),IF(I9="",0,VLOOKUP(I9,Bausteine!$A$2:$AY$76,6,FALSE)),IF(J9="",0,VLOOKUP(J9,Bausteine!$A$2:$AY$76,6,FALSE)),IF(K9="",0,VLOOKUP(K9,Bausteine!$A$2:$AY$76,6,FALSE)),IF(L9="",0,VLOOKUP(L9,Bausteine!$A$2:$AY$76,6,FALSE)),IF(AC9="",0,VLOOKUP(AC9,Bausteine!$A$2:$AY$76,6,FALSE)),IF(AF9="",0,VLOOKUP(AF9,Bausteine!$A$2:$AY$76,6,FALSE)),IF(AG9="",0,VLOOKUP(AG9,Bausteine!$A$2:$AY$76,6,FALSE)),IF(AH9="",0,VLOOKUP(AH9,Bausteine!$A$2:$AY$76,6,FALSE)),IF(AQ9="",0,VLOOKUP(AQ9,Bausteine!$A$2:$AY$76,6,FALSE)),AK9) | P9: =IF(C9="",0,VLOOKUP(C9,Bausteine!$A$2:$AY$76,7,FALSE))*IF(F9="",0,VLOOKUP(F9,Bausteine!$A$2:$AY$76,17,FALSE))/100+IF(D9="",0,VLOOKUP(D9,Bausteine!$A$2:$AY$76,7,FALSE))+IF(E9="",0,VLOOKUP(E9,Bausteine!$A$2:$AY$76,7,FALSE))+IF(G9="",0,VLOOKUP(G9,Bausteine!$A$2:$AY$76,7,FALSE))+IF(H9="",0,VLOOKUP(H9,Bausteine!$A$2:$AY$76,7,FALSE))+IF(I9="",0,VLOOKUP(I9,Bausteine!$A$2:$AY$76,7,FALSE))+IF(J9="",0,VLOOKUP(J9,Bausteine!$A$2:$AY$76,7,FALSE))+IF(K9="",0,VLOOKUP(K9,Bausteine!$A$2:$AY$76,7,FALSE))+IF(L9="",0,VLOOKUP(L9,Bausteine!$A$2:$AY$76,7,FALSE))+IF(AC9="",0,VLOOKUP(AC9,Bausteine!$A$2:$AY$76,7,FALSE))+IF(AF9="",0,VLOOKUP(AF9,Bausteine!$A$2:$AY$76,7,FALSE))+IF(AG9="",0,VLOOKUP(AG9,Bausteine!$A$2:$AY$76,7,FALSE))+IF(AH9="",0,VLOOKUP(AH9,Bausteine!$A$2:$AY$76,7,FALSE))+IF(AQ9="",0,VLOOKUP(AQ9,Bausteine!$A$2:$AY$76,7,FALSE))+AI9 | Q9: =N9*Parameter!$B$2 | R9: =AE9-Q9 | S9: =IF(C9="",0,VLOOKUP(C9,Bausteine!$A$2:$AY$76,13,FALSE))*IF(F9="",0,VLOOKUP(F9,Bausteine!$A$2:$AY$76,16,FALSE))/100 | T9: =IF(C9="",0,VLOOKUP(C9,Bausteine!$A$2:$AY$76,8,FALSE))*IF(F9="",0,VLOOKUP(F9,Bausteine!$A$2:$AY$76,15,FALSE))/100+IF(D9="",0,VLOOKUP(D9,Bausteine!$A$2:$AY$76,8,FALSE))+IF(E9="",0,VLOOKUP(E9,Bausteine!$A$2:$AY$76,8,FALSE))+IF(G9="",0,VLOOKUP(G9,Bausteine!$A$2:$AY$76,8,FALSE))+IF(H9="",0,VLOOKUP(H9,Bausteine!$A$2:$AY$76,8,FALSE))+IF(I9="",0,VLOOKUP(I9,Bausteine!$A$2:$AY$76,8,FALSE))+IF(J9="",0,VLOOKUP(J9,Bausteine!$A$2:$AY$76,8,FALSE))+IF(K9="",0,VLOOKUP(K9,Bausteine!$A$2:$AY$76,8,FALSE))+IF(L9="",0,VLOOKUP(L9,Bausteine!$A$2:$AY$76,8,FALSE))+IF(AC9="",0,VLOOKUP(AC9,Bausteine!$A$2:$AY$76,8,FALSE))+IF(AF9="",0,VLOOKUP(AF9,Bausteine!$A$2:$AY$76,8,FALSE))+IF(AG9="",0,VLOOKUP(AG9,Bausteine!$A$2:$AY$76,8,FALSE))+IF(AH9="",0,VLOOKUP(AH9,Bausteine!$A$2:$AY$76,8,FALSE))+IF(AQ9="",0,VLOOKUP(AQ9,Bausteine!$A$2:$AY$76,8,FALSE))+AJ9 | U9: =IF(C9="",0,VLOOKUP(C9,Bausteine!$A$2:$AY$76,9,FALSE))+IF(D9="",0,VLOOKUP(D9,Bausteine!$A$2:$AY$76,9,FALSE))+IF(E9="",0,VLOOKUP(E9,Bausteine!$A$2:$AY$76,9,FALSE))+IF(F9="",0,VLOOKUP(F9,Bausteine!$A$2:$AY$76,9,FALSE))+IF(G9="",0,VLOOKUP(G9,Bausteine!$A$2:$AY$76,9,FALSE))+IF(H9="",0,VLOOKUP(H9,Bausteine!$A$2:$AY$76,9,FALSE))+IF(I9="",0,VLOOKUP(I9,Bausteine!$A$2:$AY$76,9,FALSE))+IF(J9="",0,VLOOKUP(J9,Bausteine!$A$2:$AY$76,9,FALSE))+IF(K9="",0,VLOOKUP(K9,Bausteine!$A$2:$AY$76,9,FALSE))+IF(L9="",0,VLOOKUP(L9,Bausteine!$A$2:$AY$76,9,FALSE))+IF(AC9="",0,VLOOKUP(AC9,Bausteine!$A$2:$AY$76,9,FALSE))+IF(AF9="",0,VLOOKUP(AF9,Bausteine!$A$2:$AY$76,9,FALSE))+IF(AG9="",0,VLOOKUP(AG9,Bausteine!$A$2:$AY$76,9,FALSE))+IF(AH9="",0,VLOOKUP(AH9,Bausteine!$A$2:$AY$76,9,FALSE))+IF(AQ9="",0,VLOOKUP(AQ9,Bausteine!$A$2:$AY$76,9,FALSE)) | V9: =IF(D9="",0,VLOOKUP(D9,Bausteine!$A$2:$AY$76,10,FALSE))-U9/IF(E9="",0,VLOOKUP(E9,Bausteine!$A$2:$AY$76,11,FALSE)) | W9: =IF(Y9<>"OK","",ROUND(MIN(IF(C9="",0,VLOOKUP(C9,Bausteine!$A$2:$AY$76,21,FALSE)),IF(AQ9="",0,VLOOKUP(AQ9,Bausteine!$A$2:$AY$76,21,FALSE)),IF(C9="",0,VLOOKUP(C9,Bausteine!$A$2:$AY$76,20,FALSE))*(V9/T9/(IF(C9="",0,VLOOKUP(C9,Bausteine!$A$2:$AY$76,19,FALSE))/IF(C9="",0,VLOOKUP(C9,Bausteine!$A$2:$AY$76,18,FALSE))))^Parameter!$B$3),0)) | X9: =IF(F9="",0,VLOOKUP(F9,Bausteine!$A$2:$AY$76,14,FALSE)) | Y9: =IFERROR(IF(OR(AD9<=0,AD9>1,R9<=0,T9<=0,V9<=0,U9>IF(E9="",0,VLOOKUP(E9,Bausteine!$A$2:$AY$76,12,FALSE)),T9>MIN(IF(C9="",0,VLOOKUP(C9,Bausteine!$A$2:$AY$76,22,FALSE)),IF(AQ9="",0,VLOOKUP(AQ9,Bausteine!$A$2:$AY$76,22,FALSE))),IF(E9="",0,VLOOKUP(E9,Bausteine!$A$2:$AY$76,11,FALSE))<=0,IF(E9="",0,VLOOKUP(E9,Bausteine!$A$2:$AY$76,11,FALSE))>1),"UNGUELTIG","OK"),"FEHLER") | Z9: 800 | AA9: 82 | AB9: Scalar values inherited from 2TNK; full Challenger artwork binding retained. No claim of mixable national hull/turret sprites. | AD9: =IF(AC9="",1,IF(AC9="",0,VLOOKUP(AC9,Bausteine!$A$2:$AY$76,37,FALSE))/100) | AE9: =P9*AD9 | AI9: =SUMIF(Startbesatzung!$A$2:$A$7,A9,Startbesatzung!$D$2:$D$7) | AJ9: =SUMIF(Startbesatzung!$A$2:$A$7,A9,Startbesatzung!$E$2:$E$7) | AK9: =MAX(0,IF(Startbesatzung!A2=A9,Startbesatzung!G2,0),IF(Startbesatzung!A3=A9,Startbesatzung!G3,0),IF(Startbesatzung!A4=A9,Startbesatzung!G4,0),IF(Startbesatzung!A5=A9,Startbesatzung!G5,0),IF(Startbesatzung!A6=A9,Startbesatzung!G6,0),IF(Startbesatzung!A7=A9,Startbesatzung!G7,0)) | AL9: =IF(AF9="","",IF(IF(AH9="",0,VLOOKUP(AH9,Bausteine!$A$2:$AY$76,38,FALSE))>0,IF(AH9="",0,VLOOKUP(AH9,Bausteine!$A$2:$AY$76,38,FALSE)),IF(AG9="",0,VLOOKUP(AG9,Bausteine!$A$2:$AY$76,28,FALSE)))) | AM9: =IF(AF9="","",IF(AG9="",0,VLOOKUP(AG9,Bausteine!$A$2:$AY$76,44,FALSE))) | AN9: =IF(AF9="","",IF(AF9="",0,VLOOKUP(AF9,Bausteine!$A$2:$AY$76,27,FALSE))) | AO9: =IF(AF9="","",IF(AF9="",0,VLOOKUP(AF9,Bausteine!$A$2:$AY$76,25,FALSE))) | AP9: =IF(AF9="","",IF(AH9="",0,VLOOKUP(AH9,Bausteine!$A$2:$AY$76,29,FALSE))) | AQ9: tracks-standard | AR9: =IF(AQ9="",0,VLOOKUP(AQ9,Bausteine!$A$2:$AY$76,48,FALSE)) | AS9: =MIN(IF(AQ9="",0,VLOOKUP(AQ9,Bausteine!$A$2:$AY$76,50,FALSE)),IF(C9="",0,VLOOKUP(C9,Bausteine!$A$2:$AY$76,51,FALSE)))
A10: Leclerc baseline | B10: allies | C10: allied-medium-hull | D10: diesel | E10: baseline-generator | F10: heavy | G10: medium-cannon-mount | H10: medium-cannon | I10: medium-tank-shell | M10: =IF(C10="",0,VLOOKUP(C10,Bausteine!$A$2:$AY$76,4,FALSE))+IF(D10="",0,VLOOKUP(D10,Bausteine!$A$2:$AY$76,4,FALSE))+IF(E10="",0,VLOOKUP(E10,Bausteine!$A$2:$AY$76,4,FALSE))+IF(F10="",0,VLOOKUP(F10,Bausteine!$A$2:$AY$76,4,FALSE))+IF(G10="",0,VLOOKUP(G10,Bausteine!$A$2:$AY$76,4,FALSE))+IF(H10="",0,VLOOKUP(H10,Bausteine!$A$2:$AY$76,4,FALSE))+IF(I10="",0,VLOOKUP(I10,Bausteine!$A$2:$AY$76,4,FALSE))+IF(J10="",0,VLOOKUP(J10,Bausteine!$A$2:$AY$76,4,FALSE))+IF(K10="",0,VLOOKUP(K10,Bausteine!$A$2:$AY$76,4,FALSE))+IF(L10="",0,VLOOKUP(L10,Bausteine!$A$2:$AY$76,4,FALSE))+IF(AC10="",0,VLOOKUP(AC10,Bausteine!$A$2:$AY$76,4,FALSE))+IF(AF10="",0,VLOOKUP(AF10,Bausteine!$A$2:$AY$76,4,FALSE))+IF(AG10="",0,VLOOKUP(AG10,Bausteine!$A$2:$AY$76,4,FALSE))+IF(AH10="",0,VLOOKUP(AH10,Bausteine!$A$2:$AY$76,4,FALSE))+IF(AQ10="",0,VLOOKUP(AQ10,Bausteine!$A$2:$AY$76,4,FALSE)) | N10: =IF(C10="",0,VLOOKUP(C10,Bausteine!$A$2:$AY$76,5,FALSE))+IF(D10="",0,VLOOKUP(D10,Bausteine!$A$2:$AY$76,5,FALSE))+IF(E10="",0,VLOOKUP(E10,Bausteine!$A$2:$AY$76,5,FALSE))+IF(F10="",0,VLOOKUP(F10,Bausteine!$A$2:$AY$76,5,FALSE))+IF(G10="",0,VLOOKUP(G10,Bausteine!$A$2:$AY$76,5,FALSE))+IF(H10="",0,VLOOKUP(H10,Bausteine!$A$2:$AY$76,5,FALSE))+IF(I10="",0,VLOOKUP(I10,Bausteine!$A$2:$AY$76,5,FALSE))+IF(J10="",0,VLOOKUP(J10,Bausteine!$A$2:$AY$76,5,FALSE))+IF(K10="",0,VLOOKUP(K10,Bausteine!$A$2:$AY$76,5,FALSE))+IF(L10="",0,VLOOKUP(L10,Bausteine!$A$2:$AY$76,5,FALSE))+IF(AC10="",0,VLOOKUP(AC10,Bausteine!$A$2:$AY$76,5,FALSE))+IF(AF10="",0,VLOOKUP(AF10,Bausteine!$A$2:$AY$76,5,FALSE))+IF(AG10="",0,VLOOKUP(AG10,Bausteine!$A$2:$AY$76,5,FALSE))+IF(AH10="",0,VLOOKUP(AH10,Bausteine!$A$2:$AY$76,5,FALSE))+IF(AQ10="",0,VLOOKUP(AQ10,Bausteine!$A$2:$AY$76,5,FALSE)) | O10: =MAX(IF(C10="",0,VLOOKUP(C10,Bausteine!$A$2:$AY$76,6,FALSE)),IF(D10="",0,VLOOKUP(D10,Bausteine!$A$2:$AY$76,6,FALSE)),IF(E10="",0,VLOOKUP(E10,Bausteine!$A$2:$AY$76,6,FALSE)),IF(F10="",0,VLOOKUP(F10,Bausteine!$A$2:$AY$76,6,FALSE)),IF(G10="",0,VLOOKUP(G10,Bausteine!$A$2:$AY$76,6,FALSE)),IF(H10="",0,VLOOKUP(H10,Bausteine!$A$2:$AY$76,6,FALSE)),IF(I10="",0,VLOOKUP(I10,Bausteine!$A$2:$AY$76,6,FALSE)),IF(J10="",0,VLOOKUP(J10,Bausteine!$A$2:$AY$76,6,FALSE)),IF(K10="",0,VLOOKUP(K10,Bausteine!$A$2:$AY$76,6,FALSE)),IF(L10="",0,VLOOKUP(L10,Bausteine!$A$2:$AY$76,6,FALSE)),IF(AC10="",0,VLOOKUP(AC10,Bausteine!$A$2:$AY$76,6,FALSE)),IF(AF10="",0,VLOOKUP(AF10,Bausteine!$A$2:$AY$76,6,FALSE)),IF(AG10="",0,VLOOKUP(AG10,Bausteine!$A$2:$AY$76,6,FALSE)),IF(AH10="",0,VLOOKUP(AH10,Bausteine!$A$2:$AY$76,6,FALSE)),IF(AQ10="",0,VLOOKUP(AQ10,Bausteine!$A$2:$AY$76,6,FALSE)),AK10) | P10: =IF(C10="",0,VLOOKUP(C10,Bausteine!$A$2:$AY$76,7,FALSE))*IF(F10="",0,VLOOKUP(F10,Bausteine!$A$2:$AY$76,17,FALSE))/100+IF(D10="",0,VLOOKUP(D10,Bausteine!$A$2:$AY$76,7,FALSE))+IF(E10="",0,VLOOKUP(E10,Bausteine!$A$2:$AY$76,7,FALSE))+IF(G10="",0,VLOOKUP(G10,Bausteine!$A$2:$AY$76,7,FALSE))+IF(H10="",0,VLOOKUP(H10,Bausteine!$A$2:$AY$76,7,FALSE))+IF(I10="",0,VLOOKUP(I10,Bausteine!$A$2:$AY$76,7,FALSE))+IF(J10="",0,VLOOKUP(J10,Bausteine!$A$2:$AY$76,7,FALSE))+IF(K10="",0,VLOOKUP(K10,Bausteine!$A$2:$AY$76,7,FALSE))+IF(L10="",0,VLOOKUP(L10,Bausteine!$A$2:$AY$76,7,FALSE))+IF(AC10="",0,VLOOKUP(AC10,Bausteine!$A$2:$AY$76,7,FALSE))+IF(AF10="",0,VLOOKUP(AF10,Bausteine!$A$2:$AY$76,7,FALSE))+IF(AG10="",0,VLOOKUP(AG10,Bausteine!$A$2:$AY$76,7,FALSE))+IF(AH10="",0,VLOOKUP(AH10,Bausteine!$A$2:$AY$76,7,FALSE))+IF(AQ10="",0,VLOOKUP(AQ10,Bausteine!$A$2:$AY$76,7,FALSE))+AI10 | Q10: =N10*Parameter!$B$2 | R10: =AE10-Q10 | S10: =IF(C10="",0,VLOOKUP(C10,Bausteine!$A$2:$AY$76,13,FALSE))*IF(F10="",0,VLOOKUP(F10,Bausteine!$A$2:$AY$76,16,FALSE))/100 | T10: =IF(C10="",0,VLOOKUP(C10,Bausteine!$A$2:$AY$76,8,FALSE))*IF(F10="",0,VLOOKUP(F10,Bausteine!$A$2:$AY$76,15,FALSE))/100+IF(D10="",0,VLOOKUP(D10,Bausteine!$A$2:$AY$76,8,FALSE))+IF(E10="",0,VLOOKUP(E10,Bausteine!$A$2:$AY$76,8,FALSE))+IF(G10="",0,VLOOKUP(G10,Bausteine!$A$2:$AY$76,8,FALSE))+IF(H10="",0,VLOOKUP(H10,Bausteine!$A$2:$AY$76,8,FALSE))+IF(I10="",0,VLOOKUP(I10,Bausteine!$A$2:$AY$76,8,FALSE))+IF(J10="",0,VLOOKUP(J10,Bausteine!$A$2:$AY$76,8,FALSE))+IF(K10="",0,VLOOKUP(K10,Bausteine!$A$2:$AY$76,8,FALSE))+IF(L10="",0,VLOOKUP(L10,Bausteine!$A$2:$AY$76,8,FALSE))+IF(AC10="",0,VLOOKUP(AC10,Bausteine!$A$2:$AY$76,8,FALSE))+IF(AF10="",0,VLOOKUP(AF10,Bausteine!$A$2:$AY$76,8,FALSE))+IF(AG10="",0,VLOOKUP(AG10,Bausteine!$A$2:$AY$76,8,FALSE))+IF(AH10="",0,VLOOKUP(AH10,Bausteine!$A$2:$AY$76,8,FALSE))+IF(AQ10="",0,VLOOKUP(AQ10,Bausteine!$A$2:$AY$76,8,FALSE))+AJ10 | U10: =IF(C10="",0,VLOOKUP(C10,Bausteine!$A$2:$AY$76,9,FALSE))+IF(D10="",0,VLOOKUP(D10,Bausteine!$A$2:$AY$76,9,FALSE))+IF(E10="",0,VLOOKUP(E10,Bausteine!$A$2:$AY$76,9,FALSE))+IF(F10="",0,VLOOKUP(F10,Bausteine!$A$2:$AY$76,9,FALSE))+IF(G10="",0,VLOOKUP(G10,Bausteine!$A$2:$AY$76,9,FALSE))+IF(H10="",0,VLOOKUP(H10,Bausteine!$A$2:$AY$76,9,FALSE))+IF(I10="",0,VLOOKUP(I10,Bausteine!$A$2:$AY$76,9,FALSE))+IF(J10="",0,VLOOKUP(J10,Bausteine!$A$2:$AY$76,9,FALSE))+IF(K10="",0,VLOOKUP(K10,Bausteine!$A$2:$AY$76,9,FALSE))+IF(L10="",0,VLOOKUP(L10,Bausteine!$A$2:$AY$76,9,FALSE))+IF(AC10="",0,VLOOKUP(AC10,Bausteine!$A$2:$AY$76,9,FALSE))+IF(AF10="",0,VLOOKUP(AF10,Bausteine!$A$2:$AY$76,9,FALSE))+IF(AG10="",0,VLOOKUP(AG10,Bausteine!$A$2:$AY$76,9,FALSE))+IF(AH10="",0,VLOOKUP(AH10,Bausteine!$A$2:$AY$76,9,FALSE))+IF(AQ10="",0,VLOOKUP(AQ10,Bausteine!$A$2:$AY$76,9,FALSE)) | V10: =IF(D10="",0,VLOOKUP(D10,Bausteine!$A$2:$AY$76,10,FALSE))-U10/IF(E10="",0,VLOOKUP(E10,Bausteine!$A$2:$AY$76,11,FALSE)) | W10: =IF(Y10<>"OK","",ROUND(MIN(IF(C10="",0,VLOOKUP(C10,Bausteine!$A$2:$AY$76,21,FALSE)),IF(AQ10="",0,VLOOKUP(AQ10,Bausteine!$A$2:$AY$76,21,FALSE)),IF(C10="",0,VLOOKUP(C10,Bausteine!$A$2:$AY$76,20,FALSE))*(V10/T10/(IF(C10="",0,VLOOKUP(C10,Bausteine!$A$2:$AY$76,19,FALSE))/IF(C10="",0,VLOOKUP(C10,Bausteine!$A$2:$AY$76,18,FALSE))))^Parameter!$B$3),0)) | X10: =IF(F10="",0,VLOOKUP(F10,Bausteine!$A$2:$AY$76,14,FALSE)) | Y10: =IFERROR(IF(OR(AD10<=0,AD10>1,R10<=0,T10<=0,V10<=0,U10>IF(E10="",0,VLOOKUP(E10,Bausteine!$A$2:$AY$76,12,FALSE)),T10>MIN(IF(C10="",0,VLOOKUP(C10,Bausteine!$A$2:$AY$76,22,FALSE)),IF(AQ10="",0,VLOOKUP(AQ10,Bausteine!$A$2:$AY$76,22,FALSE))),IF(E10="",0,VLOOKUP(E10,Bausteine!$A$2:$AY$76,11,FALSE))<=0,IF(E10="",0,VLOOKUP(E10,Bausteine!$A$2:$AY$76,11,FALSE))>1),"UNGUELTIG","OK"),"FEHLER") | Z10: 800 | AA10: 82 | AB10: Scalar values inherited from 2TNK; preserve Leclerc artwork, not an additional independent component fit. | AD10: =IF(AC10="",1,IF(AC10="",0,VLOOKUP(AC10,Bausteine!$A$2:$AY$76,37,FALSE))/100) | AE10: =P10*AD10 | AI10: =SUMIF(Startbesatzung!$A$2:$A$7,A10,Startbesatzung!$D$2:$D$7) | AJ10: =SUMIF(Startbesatzung!$A$2:$A$7,A10,Startbesatzung!$E$2:$E$7) | AK10: =MAX(0,IF(Startbesatzung!A2=A10,Startbesatzung!G2,0),IF(Startbesatzung!A3=A10,Startbesatzung!G3,0),IF(Startbesatzung!A4=A10,Startbesatzung!G4,0),IF(Startbesatzung!A5=A10,Startbesatzung!G5,0),IF(Startbesatzung!A6=A10,Startbesatzung!G6,0),IF(Startbesatzung!A7=A10,Startbesatzung!G7,0)) | AL10: =IF(AF10="","",IF(IF(AH10="",0,VLOOKUP(AH10,Bausteine!$A$2:$AY$76,38,FALSE))>0,IF(AH10="",0,VLOOKUP(AH10,Bausteine!$A$2:$AY$76,38,FALSE)),IF(AG10="",0,VLOOKUP(AG10,Bausteine!$A$2:$AY$76,28,FALSE)))) | AM10: =IF(AF10="","",IF(AG10="",0,VLOOKUP(AG10,Bausteine!$A$2:$AY$76,44,FALSE))) | AN10: =IF(AF10="","",IF(AF10="",0,VLOOKUP(AF10,Bausteine!$A$2:$AY$76,27,FALSE))) | AO10: =IF(AF10="","",IF(AF10="",0,VLOOKUP(AF10,Bausteine!$A$2:$AY$76,25,FALSE))) | AP10: =IF(AF10="","",IF(AH10="",0,VLOOKUP(AH10,Bausteine!$A$2:$AY$76,29,FALSE))) | AQ10: tracks-standard | AR10: =IF(AQ10="",0,VLOOKUP(AQ10,Bausteine!$A$2:$AY$76,48,FALSE)) | AS10: =MIN(IF(AQ10="",0,VLOOKUP(AQ10,Bausteine!$A$2:$AY$76,50,FALSE)),IF(C10="",0,VLOOKUP(C10,Bausteine!$A$2:$AY$76,51,FALSE)))
A11: Leopard baseline | B11: allies | C11: allied-medium-hull | D11: diesel | E11: baseline-generator | F11: heavy | G11: medium-cannon-mount | H11: medium-cannon | I11: medium-tank-shell | M11: =IF(C11="",0,VLOOKUP(C11,Bausteine!$A$2:$AY$76,4,FALSE))+IF(D11="",0,VLOOKUP(D11,Bausteine!$A$2:$AY$76,4,FALSE))+IF(E11="",0,VLOOKUP(E11,Bausteine!$A$2:$AY$76,4,FALSE))+IF(F11="",0,VLOOKUP(F11,Bausteine!$A$2:$AY$76,4,FALSE))+IF(G11="",0,VLOOKUP(G11,Bausteine!$A$2:$AY$76,4,FALSE))+IF(H11="",0,VLOOKUP(H11,Bausteine!$A$2:$AY$76,4,FALSE))+IF(I11="",0,VLOOKUP(I11,Bausteine!$A$2:$AY$76,4,FALSE))+IF(J11="",0,VLOOKUP(J11,Bausteine!$A$2:$AY$76,4,FALSE))+IF(K11="",0,VLOOKUP(K11,Bausteine!$A$2:$AY$76,4,FALSE))+IF(L11="",0,VLOOKUP(L11,Bausteine!$A$2:$AY$76,4,FALSE))+IF(AC11="",0,VLOOKUP(AC11,Bausteine!$A$2:$AY$76,4,FALSE))+IF(AF11="",0,VLOOKUP(AF11,Bausteine!$A$2:$AY$76,4,FALSE))+IF(AG11="",0,VLOOKUP(AG11,Bausteine!$A$2:$AY$76,4,FALSE))+IF(AH11="",0,VLOOKUP(AH11,Bausteine!$A$2:$AY$76,4,FALSE))+IF(AQ11="",0,VLOOKUP(AQ11,Bausteine!$A$2:$AY$76,4,FALSE)) | N11: =IF(C11="",0,VLOOKUP(C11,Bausteine!$A$2:$AY$76,5,FALSE))+IF(D11="",0,VLOOKUP(D11,Bausteine!$A$2:$AY$76,5,FALSE))+IF(E11="",0,VLOOKUP(E11,Bausteine!$A$2:$AY$76,5,FALSE))+IF(F11="",0,VLOOKUP(F11,Bausteine!$A$2:$AY$76,5,FALSE))+IF(G11="",0,VLOOKUP(G11,Bausteine!$A$2:$AY$76,5,FALSE))+IF(H11="",0,VLOOKUP(H11,Bausteine!$A$2:$AY$76,5,FALSE))+IF(I11="",0,VLOOKUP(I11,Bausteine!$A$2:$AY$76,5,FALSE))+IF(J11="",0,VLOOKUP(J11,Bausteine!$A$2:$AY$76,5,FALSE))+IF(K11="",0,VLOOKUP(K11,Bausteine!$A$2:$AY$76,5,FALSE))+IF(L11="",0,VLOOKUP(L11,Bausteine!$A$2:$AY$76,5,FALSE))+IF(AC11="",0,VLOOKUP(AC11,Bausteine!$A$2:$AY$76,5,FALSE))+IF(AF11="",0,VLOOKUP(AF11,Bausteine!$A$2:$AY$76,5,FALSE))+IF(AG11="",0,VLOOKUP(AG11,Bausteine!$A$2:$AY$76,5,FALSE))+IF(AH11="",0,VLOOKUP(AH11,Bausteine!$A$2:$AY$76,5,FALSE))+IF(AQ11="",0,VLOOKUP(AQ11,Bausteine!$A$2:$AY$76,5,FALSE)) | O11: =MAX(IF(C11="",0,VLOOKUP(C11,Bausteine!$A$2:$AY$76,6,FALSE)),IF(D11="",0,VLOOKUP(D11,Bausteine!$A$2:$AY$76,6,FALSE)),IF(E11="",0,VLOOKUP(E11,Bausteine!$A$2:$AY$76,6,FALSE)),IF(F11="",0,VLOOKUP(F11,Bausteine!$A$2:$AY$76,6,FALSE)),IF(G11="",0,VLOOKUP(G11,Bausteine!$A$2:$AY$76,6,FALSE)),IF(H11="",0,VLOOKUP(H11,Bausteine!$A$2:$AY$76,6,FALSE)),IF(I11="",0,VLOOKUP(I11,Bausteine!$A$2:$AY$76,6,FALSE)),IF(J11="",0,VLOOKUP(J11,Bausteine!$A$2:$AY$76,6,FALSE)),IF(K11="",0,VLOOKUP(K11,Bausteine!$A$2:$AY$76,6,FALSE)),IF(L11="",0,VLOOKUP(L11,Bausteine!$A$2:$AY$76,6,FALSE)),IF(AC11="",0,VLOOKUP(AC11,Bausteine!$A$2:$AY$76,6,FALSE)),IF(AF11="",0,VLOOKUP(AF11,Bausteine!$A$2:$AY$76,6,FALSE)),IF(AG11="",0,VLOOKUP(AG11,Bausteine!$A$2:$AY$76,6,FALSE)),IF(AH11="",0,VLOOKUP(AH11,Bausteine!$A$2:$AY$76,6,FALSE)),IF(AQ11="",0,VLOOKUP(AQ11,Bausteine!$A$2:$AY$76,6,FALSE)),AK11) | P11: =IF(C11="",0,VLOOKUP(C11,Bausteine!$A$2:$AY$76,7,FALSE))*IF(F11="",0,VLOOKUP(F11,Bausteine!$A$2:$AY$76,17,FALSE))/100+IF(D11="",0,VLOOKUP(D11,Bausteine!$A$2:$AY$76,7,FALSE))+IF(E11="",0,VLOOKUP(E11,Bausteine!$A$2:$AY$76,7,FALSE))+IF(G11="",0,VLOOKUP(G11,Bausteine!$A$2:$AY$76,7,FALSE))+IF(H11="",0,VLOOKUP(H11,Bausteine!$A$2:$AY$76,7,FALSE))+IF(I11="",0,VLOOKUP(I11,Bausteine!$A$2:$AY$76,7,FALSE))+IF(J11="",0,VLOOKUP(J11,Bausteine!$A$2:$AY$76,7,FALSE))+IF(K11="",0,VLOOKUP(K11,Bausteine!$A$2:$AY$76,7,FALSE))+IF(L11="",0,VLOOKUP(L11,Bausteine!$A$2:$AY$76,7,FALSE))+IF(AC11="",0,VLOOKUP(AC11,Bausteine!$A$2:$AY$76,7,FALSE))+IF(AF11="",0,VLOOKUP(AF11,Bausteine!$A$2:$AY$76,7,FALSE))+IF(AG11="",0,VLOOKUP(AG11,Bausteine!$A$2:$AY$76,7,FALSE))+IF(AH11="",0,VLOOKUP(AH11,Bausteine!$A$2:$AY$76,7,FALSE))+IF(AQ11="",0,VLOOKUP(AQ11,Bausteine!$A$2:$AY$76,7,FALSE))+AI11 | Q11: =N11*Parameter!$B$2 | R11: =AE11-Q11 | S11: =IF(C11="",0,VLOOKUP(C11,Bausteine!$A$2:$AY$76,13,FALSE))*IF(F11="",0,VLOOKUP(F11,Bausteine!$A$2:$AY$76,16,FALSE))/100 | T11: =IF(C11="",0,VLOOKUP(C11,Bausteine!$A$2:$AY$76,8,FALSE))*IF(F11="",0,VLOOKUP(F11,Bausteine!$A$2:$AY$76,15,FALSE))/100+IF(D11="",0,VLOOKUP(D11,Bausteine!$A$2:$AY$76,8,FALSE))+IF(E11="",0,VLOOKUP(E11,Bausteine!$A$2:$AY$76,8,FALSE))+IF(G11="",0,VLOOKUP(G11,Bausteine!$A$2:$AY$76,8,FALSE))+IF(H11="",0,VLOOKUP(H11,Bausteine!$A$2:$AY$76,8,FALSE))+IF(I11="",0,VLOOKUP(I11,Bausteine!$A$2:$AY$76,8,FALSE))+IF(J11="",0,VLOOKUP(J11,Bausteine!$A$2:$AY$76,8,FALSE))+IF(K11="",0,VLOOKUP(K11,Bausteine!$A$2:$AY$76,8,FALSE))+IF(L11="",0,VLOOKUP(L11,Bausteine!$A$2:$AY$76,8,FALSE))+IF(AC11="",0,VLOOKUP(AC11,Bausteine!$A$2:$AY$76,8,FALSE))+IF(AF11="",0,VLOOKUP(AF11,Bausteine!$A$2:$AY$76,8,FALSE))+IF(AG11="",0,VLOOKUP(AG11,Bausteine!$A$2:$AY$76,8,FALSE))+IF(AH11="",0,VLOOKUP(AH11,Bausteine!$A$2:$AY$76,8,FALSE))+IF(AQ11="",0,VLOOKUP(AQ11,Bausteine!$A$2:$AY$76,8,FALSE))+AJ11 | U11: =IF(C11="",0,VLOOKUP(C11,Bausteine!$A$2:$AY$76,9,FALSE))+IF(D11="",0,VLOOKUP(D11,Bausteine!$A$2:$AY$76,9,FALSE))+IF(E11="",0,VLOOKUP(E11,Bausteine!$A$2:$AY$76,9,FALSE))+IF(F11="",0,VLOOKUP(F11,Bausteine!$A$2:$AY$76,9,FALSE))+IF(G11="",0,VLOOKUP(G11,Bausteine!$A$2:$AY$76,9,FALSE))+IF(H11="",0,VLOOKUP(H11,Bausteine!$A$2:$AY$76,9,FALSE))+IF(I11="",0,VLOOKUP(I11,Bausteine!$A$2:$AY$76,9,FALSE))+IF(J11="",0,VLOOKUP(J11,Bausteine!$A$2:$AY$76,9,FALSE))+IF(K11="",0,VLOOKUP(K11,Bausteine!$A$2:$AY$76,9,FALSE))+IF(L11="",0,VLOOKUP(L11,Bausteine!$A$2:$AY$76,9,FALSE))+IF(AC11="",0,VLOOKUP(AC11,Bausteine!$A$2:$AY$76,9,FALSE))+IF(AF11="",0,VLOOKUP(AF11,Bausteine!$A$2:$AY$76,9,FALSE))+IF(AG11="",0,VLOOKUP(AG11,Bausteine!$A$2:$AY$76,9,FALSE))+IF(AH11="",0,VLOOKUP(AH11,Bausteine!$A$2:$AY$76,9,FALSE))+IF(AQ11="",0,VLOOKUP(AQ11,Bausteine!$A$2:$AY$76,9,FALSE)) | V11: =IF(D11="",0,VLOOKUP(D11,Bausteine!$A$2:$AY$76,10,FALSE))-U11/IF(E11="",0,VLOOKUP(E11,Bausteine!$A$2:$AY$76,11,FALSE)) | W11: =IF(Y11<>"OK","",ROUND(MIN(IF(C11="",0,VLOOKUP(C11,Bausteine!$A$2:$AY$76,21,FALSE)),IF(AQ11="",0,VLOOKUP(AQ11,Bausteine!$A$2:$AY$76,21,FALSE)),IF(C11="",0,VLOOKUP(C11,Bausteine!$A$2:$AY$76,20,FALSE))*(V11/T11/(IF(C11="",0,VLOOKUP(C11,Bausteine!$A$2:$AY$76,19,FALSE))/IF(C11="",0,VLOOKUP(C11,Bausteine!$A$2:$AY$76,18,FALSE))))^Parameter!$B$3),0)) | X11: =IF(F11="",0,VLOOKUP(F11,Bausteine!$A$2:$AY$76,14,FALSE)) | Y11: =IFERROR(IF(OR(AD11<=0,AD11>1,R11<=0,T11<=0,V11<=0,U11>IF(E11="",0,VLOOKUP(E11,Bausteine!$A$2:$AY$76,12,FALSE)),T11>MIN(IF(C11="",0,VLOOKUP(C11,Bausteine!$A$2:$AY$76,22,FALSE)),IF(AQ11="",0,VLOOKUP(AQ11,Bausteine!$A$2:$AY$76,22,FALSE))),IF(E11="",0,VLOOKUP(E11,Bausteine!$A$2:$AY$76,11,FALSE))<=0,IF(E11="",0,VLOOKUP(E11,Bausteine!$A$2:$AY$76,11,FALSE))>1),"UNGUELTIG","OK"),"FEHLER") | Z11: 800 | AA11: 82 | AB11: Scalar values inherited from 2TNK; preserve Leopard artwork, not an additional independent component fit. | AD11: =IF(AC11="",1,IF(AC11="",0,VLOOKUP(AC11,Bausteine!$A$2:$AY$76,37,FALSE))/100) | AE11: =P11*AD11 | AI11: =SUMIF(Startbesatzung!$A$2:$A$7,A11,Startbesatzung!$D$2:$D$7) | AJ11: =SUMIF(Startbesatzung!$A$2:$A$7,A11,Startbesatzung!$E$2:$E$7) | AK11: =MAX(0,IF(Startbesatzung!A2=A11,Startbesatzung!G2,0),IF(Startbesatzung!A3=A11,Startbesatzung!G3,0),IF(Startbesatzung!A4=A11,Startbesatzung!G4,0),IF(Startbesatzung!A5=A11,Startbesatzung!G5,0),IF(Startbesatzung!A6=A11,Startbesatzung!G6,0),IF(Startbesatzung!A7=A11,Startbesatzung!G7,0)) | AL11: =IF(AF11="","",IF(IF(AH11="",0,VLOOKUP(AH11,Bausteine!$A$2:$AY$76,38,FALSE))>0,IF(AH11="",0,VLOOKUP(AH11,Bausteine!$A$2:$AY$76,38,FALSE)),IF(AG11="",0,VLOOKUP(AG11,Bausteine!$A$2:$AY$76,28,FALSE)))) | AM11: =IF(AF11="","",IF(AG11="",0,VLOOKUP(AG11,Bausteine!$A$2:$AY$76,44,FALSE))) | AN11: =IF(AF11="","",IF(AF11="",0,VLOOKUP(AF11,Bausteine!$A$2:$AY$76,27,FALSE))) | AO11: =IF(AF11="","",IF(AF11="",0,VLOOKUP(AF11,Bausteine!$A$2:$AY$76,25,FALSE))) | AP11: =IF(AF11="","",IF(AH11="",0,VLOOKUP(AH11,Bausteine!$A$2:$AY$76,29,FALSE))) | AQ11: tracks-standard | AR11: =IF(AQ11="",0,VLOOKUP(AQ11,Bausteine!$A$2:$AY$76,48,FALSE)) | AS11: =MIN(IF(AQ11="",0,VLOOKUP(AQ11,Bausteine!$A$2:$AY$76,50,FALSE)),IF(C11="",0,VLOOKUP(C11,Bausteine!$A$2:$AY$76,51,FALSE)))
A12: Soviet Heavy Tank baseline | B12: soviet | C12: soviet-heavy-hull | D12: diesel | E12: baseline-generator | F12: heavy | G12: soviet-twin-mount | H12: medium-cannon | I12: medium-tank-shell | M12: =IF(C12="",0,VLOOKUP(C12,Bausteine!$A$2:$AY$76,4,FALSE))+IF(D12="",0,VLOOKUP(D12,Bausteine!$A$2:$AY$76,4,FALSE))+IF(E12="",0,VLOOKUP(E12,Bausteine!$A$2:$AY$76,4,FALSE))+IF(F12="",0,VLOOKUP(F12,Bausteine!$A$2:$AY$76,4,FALSE))+IF(G12="",0,VLOOKUP(G12,Bausteine!$A$2:$AY$76,4,FALSE))+IF(H12="",0,VLOOKUP(H12,Bausteine!$A$2:$AY$76,4,FALSE))+IF(I12="",0,VLOOKUP(I12,Bausteine!$A$2:$AY$76,4,FALSE))+IF(J12="",0,VLOOKUP(J12,Bausteine!$A$2:$AY$76,4,FALSE))+IF(K12="",0,VLOOKUP(K12,Bausteine!$A$2:$AY$76,4,FALSE))+IF(L12="",0,VLOOKUP(L12,Bausteine!$A$2:$AY$76,4,FALSE))+IF(AC12="",0,VLOOKUP(AC12,Bausteine!$A$2:$AY$76,4,FALSE))+IF(AF12="",0,VLOOKUP(AF12,Bausteine!$A$2:$AY$76,4,FALSE))+IF(AG12="",0,VLOOKUP(AG12,Bausteine!$A$2:$AY$76,4,FALSE))+IF(AH12="",0,VLOOKUP(AH12,Bausteine!$A$2:$AY$76,4,FALSE))+IF(AQ12="",0,VLOOKUP(AQ12,Bausteine!$A$2:$AY$76,4,FALSE)) | N12: =IF(C12="",0,VLOOKUP(C12,Bausteine!$A$2:$AY$76,5,FALSE))+IF(D12="",0,VLOOKUP(D12,Bausteine!$A$2:$AY$76,5,FALSE))+IF(E12="",0,VLOOKUP(E12,Bausteine!$A$2:$AY$76,5,FALSE))+IF(F12="",0,VLOOKUP(F12,Bausteine!$A$2:$AY$76,5,FALSE))+IF(G12="",0,VLOOKUP(G12,Bausteine!$A$2:$AY$76,5,FALSE))+IF(H12="",0,VLOOKUP(H12,Bausteine!$A$2:$AY$76,5,FALSE))+IF(I12="",0,VLOOKUP(I12,Bausteine!$A$2:$AY$76,5,FALSE))+IF(J12="",0,VLOOKUP(J12,Bausteine!$A$2:$AY$76,5,FALSE))+IF(K12="",0,VLOOKUP(K12,Bausteine!$A$2:$AY$76,5,FALSE))+IF(L12="",0,VLOOKUP(L12,Bausteine!$A$2:$AY$76,5,FALSE))+IF(AC12="",0,VLOOKUP(AC12,Bausteine!$A$2:$AY$76,5,FALSE))+IF(AF12="",0,VLOOKUP(AF12,Bausteine!$A$2:$AY$76,5,FALSE))+IF(AG12="",0,VLOOKUP(AG12,Bausteine!$A$2:$AY$76,5,FALSE))+IF(AH12="",0,VLOOKUP(AH12,Bausteine!$A$2:$AY$76,5,FALSE))+IF(AQ12="",0,VLOOKUP(AQ12,Bausteine!$A$2:$AY$76,5,FALSE)) | O12: =MAX(IF(C12="",0,VLOOKUP(C12,Bausteine!$A$2:$AY$76,6,FALSE)),IF(D12="",0,VLOOKUP(D12,Bausteine!$A$2:$AY$76,6,FALSE)),IF(E12="",0,VLOOKUP(E12,Bausteine!$A$2:$AY$76,6,FALSE)),IF(F12="",0,VLOOKUP(F12,Bausteine!$A$2:$AY$76,6,FALSE)),IF(G12="",0,VLOOKUP(G12,Bausteine!$A$2:$AY$76,6,FALSE)),IF(H12="",0,VLOOKUP(H12,Bausteine!$A$2:$AY$76,6,FALSE)),IF(I12="",0,VLOOKUP(I12,Bausteine!$A$2:$AY$76,6,FALSE)),IF(J12="",0,VLOOKUP(J12,Bausteine!$A$2:$AY$76,6,FALSE)),IF(K12="",0,VLOOKUP(K12,Bausteine!$A$2:$AY$76,6,FALSE)),IF(L12="",0,VLOOKUP(L12,Bausteine!$A$2:$AY$76,6,FALSE)),IF(AC12="",0,VLOOKUP(AC12,Bausteine!$A$2:$AY$76,6,FALSE)),IF(AF12="",0,VLOOKUP(AF12,Bausteine!$A$2:$AY$76,6,FALSE)),IF(AG12="",0,VLOOKUP(AG12,Bausteine!$A$2:$AY$76,6,FALSE)),IF(AH12="",0,VLOOKUP(AH12,Bausteine!$A$2:$AY$76,6,FALSE)),IF(AQ12="",0,VLOOKUP(AQ12,Bausteine!$A$2:$AY$76,6,FALSE)),AK12) | P12: =IF(C12="",0,VLOOKUP(C12,Bausteine!$A$2:$AY$76,7,FALSE))*IF(F12="",0,VLOOKUP(F12,Bausteine!$A$2:$AY$76,17,FALSE))/100+IF(D12="",0,VLOOKUP(D12,Bausteine!$A$2:$AY$76,7,FALSE))+IF(E12="",0,VLOOKUP(E12,Bausteine!$A$2:$AY$76,7,FALSE))+IF(G12="",0,VLOOKUP(G12,Bausteine!$A$2:$AY$76,7,FALSE))+IF(H12="",0,VLOOKUP(H12,Bausteine!$A$2:$AY$76,7,FALSE))+IF(I12="",0,VLOOKUP(I12,Bausteine!$A$2:$AY$76,7,FALSE))+IF(J12="",0,VLOOKUP(J12,Bausteine!$A$2:$AY$76,7,FALSE))+IF(K12="",0,VLOOKUP(K12,Bausteine!$A$2:$AY$76,7,FALSE))+IF(L12="",0,VLOOKUP(L12,Bausteine!$A$2:$AY$76,7,FALSE))+IF(AC12="",0,VLOOKUP(AC12,Bausteine!$A$2:$AY$76,7,FALSE))+IF(AF12="",0,VLOOKUP(AF12,Bausteine!$A$2:$AY$76,7,FALSE))+IF(AG12="",0,VLOOKUP(AG12,Bausteine!$A$2:$AY$76,7,FALSE))+IF(AH12="",0,VLOOKUP(AH12,Bausteine!$A$2:$AY$76,7,FALSE))+IF(AQ12="",0,VLOOKUP(AQ12,Bausteine!$A$2:$AY$76,7,FALSE))+AI12 | Q12: =N12*Parameter!$B$2 | R12: =AE12-Q12 | S12: =IF(C12="",0,VLOOKUP(C12,Bausteine!$A$2:$AY$76,13,FALSE))*IF(F12="",0,VLOOKUP(F12,Bausteine!$A$2:$AY$76,16,FALSE))/100 | T12: =IF(C12="",0,VLOOKUP(C12,Bausteine!$A$2:$AY$76,8,FALSE))*IF(F12="",0,VLOOKUP(F12,Bausteine!$A$2:$AY$76,15,FALSE))/100+IF(D12="",0,VLOOKUP(D12,Bausteine!$A$2:$AY$76,8,FALSE))+IF(E12="",0,VLOOKUP(E12,Bausteine!$A$2:$AY$76,8,FALSE))+IF(G12="",0,VLOOKUP(G12,Bausteine!$A$2:$AY$76,8,FALSE))+IF(H12="",0,VLOOKUP(H12,Bausteine!$A$2:$AY$76,8,FALSE))+IF(I12="",0,VLOOKUP(I12,Bausteine!$A$2:$AY$76,8,FALSE))+IF(J12="",0,VLOOKUP(J12,Bausteine!$A$2:$AY$76,8,FALSE))+IF(K12="",0,VLOOKUP(K12,Bausteine!$A$2:$AY$76,8,FALSE))+IF(L12="",0,VLOOKUP(L12,Bausteine!$A$2:$AY$76,8,FALSE))+IF(AC12="",0,VLOOKUP(AC12,Bausteine!$A$2:$AY$76,8,FALSE))+IF(AF12="",0,VLOOKUP(AF12,Bausteine!$A$2:$AY$76,8,FALSE))+IF(AG12="",0,VLOOKUP(AG12,Bausteine!$A$2:$AY$76,8,FALSE))+IF(AH12="",0,VLOOKUP(AH12,Bausteine!$A$2:$AY$76,8,FALSE))+IF(AQ12="",0,VLOOKUP(AQ12,Bausteine!$A$2:$AY$76,8,FALSE))+AJ12 | U12: =IF(C12="",0,VLOOKUP(C12,Bausteine!$A$2:$AY$76,9,FALSE))+IF(D12="",0,VLOOKUP(D12,Bausteine!$A$2:$AY$76,9,FALSE))+IF(E12="",0,VLOOKUP(E12,Bausteine!$A$2:$AY$76,9,FALSE))+IF(F12="",0,VLOOKUP(F12,Bausteine!$A$2:$AY$76,9,FALSE))+IF(G12="",0,VLOOKUP(G12,Bausteine!$A$2:$AY$76,9,FALSE))+IF(H12="",0,VLOOKUP(H12,Bausteine!$A$2:$AY$76,9,FALSE))+IF(I12="",0,VLOOKUP(I12,Bausteine!$A$2:$AY$76,9,FALSE))+IF(J12="",0,VLOOKUP(J12,Bausteine!$A$2:$AY$76,9,FALSE))+IF(K12="",0,VLOOKUP(K12,Bausteine!$A$2:$AY$76,9,FALSE))+IF(L12="",0,VLOOKUP(L12,Bausteine!$A$2:$AY$76,9,FALSE))+IF(AC12="",0,VLOOKUP(AC12,Bausteine!$A$2:$AY$76,9,FALSE))+IF(AF12="",0,VLOOKUP(AF12,Bausteine!$A$2:$AY$76,9,FALSE))+IF(AG12="",0,VLOOKUP(AG12,Bausteine!$A$2:$AY$76,9,FALSE))+IF(AH12="",0,VLOOKUP(AH12,Bausteine!$A$2:$AY$76,9,FALSE))+IF(AQ12="",0,VLOOKUP(AQ12,Bausteine!$A$2:$AY$76,9,FALSE)) | V12: =IF(D12="",0,VLOOKUP(D12,Bausteine!$A$2:$AY$76,10,FALSE))-U12/IF(E12="",0,VLOOKUP(E12,Bausteine!$A$2:$AY$76,11,FALSE)) | W12: =IF(Y12<>"OK","",ROUND(MIN(IF(C12="",0,VLOOKUP(C12,Bausteine!$A$2:$AY$76,21,FALSE)),IF(AQ12="",0,VLOOKUP(AQ12,Bausteine!$A$2:$AY$76,21,FALSE)),IF(C12="",0,VLOOKUP(C12,Bausteine!$A$2:$AY$76,20,FALSE))*(V12/T12/(IF(C12="",0,VLOOKUP(C12,Bausteine!$A$2:$AY$76,19,FALSE))/IF(C12="",0,VLOOKUP(C12,Bausteine!$A$2:$AY$76,18,FALSE))))^Parameter!$B$3),0)) | X12: =IF(F12="",0,VLOOKUP(F12,Bausteine!$A$2:$AY$76,14,FALSE)) | Y12: =IFERROR(IF(OR(AD12<=0,AD12>1,R12<=0,T12<=0,V12<=0,U12>IF(E12="",0,VLOOKUP(E12,Bausteine!$A$2:$AY$76,12,FALSE)),T12>MIN(IF(C12="",0,VLOOKUP(C12,Bausteine!$A$2:$AY$76,22,FALSE)),IF(AQ12="",0,VLOOKUP(AQ12,Bausteine!$A$2:$AY$76,22,FALSE))),IF(E12="",0,VLOOKUP(E12,Bausteine!$A$2:$AY$76,11,FALSE))<=0,IF(E12="",0,VLOOKUP(E12,Bausteine!$A$2:$AY$76,11,FALSE))>1),"UNGUELTIG","OK"),"FEHLER") | Z12: 1100 | AA12: 68 | AB12: 125mm legacy binding: twin carrier changes cadence while shared medium payload keeps original versus. AP variants excluded. | AD12: =IF(AC12="",1,IF(AC12="",0,VLOOKUP(AC12,Bausteine!$A$2:$AY$76,37,FALSE))/100) | AE12: =P12*AD12 | AI12: =SUMIF(Startbesatzung!$A$2:$A$7,A12,Startbesatzung!$D$2:$D$7) | AJ12: =SUMIF(Startbesatzung!$A$2:$A$7,A12,Startbesatzung!$E$2:$E$7) | AK12: =MAX(0,IF(Startbesatzung!A2=A12,Startbesatzung!G2,0),IF(Startbesatzung!A3=A12,Startbesatzung!G3,0),IF(Startbesatzung!A4=A12,Startbesatzung!G4,0),IF(Startbesatzung!A5=A12,Startbesatzung!G5,0),IF(Startbesatzung!A6=A12,Startbesatzung!G6,0),IF(Startbesatzung!A7=A12,Startbesatzung!G7,0)) | AL12: =IF(AF12="","",IF(IF(AH12="",0,VLOOKUP(AH12,Bausteine!$A$2:$AY$76,38,FALSE))>0,IF(AH12="",0,VLOOKUP(AH12,Bausteine!$A$2:$AY$76,38,FALSE)),IF(AG12="",0,VLOOKUP(AG12,Bausteine!$A$2:$AY$76,28,FALSE)))) | AM12: =IF(AF12="","",IF(AG12="",0,VLOOKUP(AG12,Bausteine!$A$2:$AY$76,44,FALSE))) | AN12: =IF(AF12="","",IF(AF12="",0,VLOOKUP(AF12,Bausteine!$A$2:$AY$76,27,FALSE))) | AO12: =IF(AF12="","",IF(AF12="",0,VLOOKUP(AF12,Bausteine!$A$2:$AY$76,25,FALSE))) | AP12: =IF(AF12="","",IF(AH12="",0,VLOOKUP(AH12,Bausteine!$A$2:$AY$76,29,FALSE))) | AQ12: tracks-standard | AR12: =IF(AQ12="",0,VLOOKUP(AQ12,Bausteine!$A$2:$AY$76,48,FALSE)) | AS12: =MIN(IF(AQ12="",0,VLOOKUP(AQ12,Bausteine!$A$2:$AY$76,50,FALSE)),IF(C12="",0,VLOOKUP(C12,Bausteine!$A$2:$AY$76,51,FALSE)))
A13: Allied Artillery baseline | B13: allies | C13: field-artillery-hull | D13: diesel | E13: baseline-generator | F13: light | G13: field-artillery-mount | H13: field-artillery | I13: field-artillery-he | M13: =IF(C13="",0,VLOOKUP(C13,Bausteine!$A$2:$AY$76,4,FALSE))+IF(D13="",0,VLOOKUP(D13,Bausteine!$A$2:$AY$76,4,FALSE))+IF(E13="",0,VLOOKUP(E13,Bausteine!$A$2:$AY$76,4,FALSE))+IF(F13="",0,VLOOKUP(F13,Bausteine!$A$2:$AY$76,4,FALSE))+IF(G13="",0,VLOOKUP(G13,Bausteine!$A$2:$AY$76,4,FALSE))+IF(H13="",0,VLOOKUP(H13,Bausteine!$A$2:$AY$76,4,FALSE))+IF(I13="",0,VLOOKUP(I13,Bausteine!$A$2:$AY$76,4,FALSE))+IF(J13="",0,VLOOKUP(J13,Bausteine!$A$2:$AY$76,4,FALSE))+IF(K13="",0,VLOOKUP(K13,Bausteine!$A$2:$AY$76,4,FALSE))+IF(L13="",0,VLOOKUP(L13,Bausteine!$A$2:$AY$76,4,FALSE))+IF(AC13="",0,VLOOKUP(AC13,Bausteine!$A$2:$AY$76,4,FALSE))+IF(AF13="",0,VLOOKUP(AF13,Bausteine!$A$2:$AY$76,4,FALSE))+IF(AG13="",0,VLOOKUP(AG13,Bausteine!$A$2:$AY$76,4,FALSE))+IF(AH13="",0,VLOOKUP(AH13,Bausteine!$A$2:$AY$76,4,FALSE))+IF(AQ13="",0,VLOOKUP(AQ13,Bausteine!$A$2:$AY$76,4,FALSE)) | N13: =IF(C13="",0,VLOOKUP(C13,Bausteine!$A$2:$AY$76,5,FALSE))+IF(D13="",0,VLOOKUP(D13,Bausteine!$A$2:$AY$76,5,FALSE))+IF(E13="",0,VLOOKUP(E13,Bausteine!$A$2:$AY$76,5,FALSE))+IF(F13="",0,VLOOKUP(F13,Bausteine!$A$2:$AY$76,5,FALSE))+IF(G13="",0,VLOOKUP(G13,Bausteine!$A$2:$AY$76,5,FALSE))+IF(H13="",0,VLOOKUP(H13,Bausteine!$A$2:$AY$76,5,FALSE))+IF(I13="",0,VLOOKUP(I13,Bausteine!$A$2:$AY$76,5,FALSE))+IF(J13="",0,VLOOKUP(J13,Bausteine!$A$2:$AY$76,5,FALSE))+IF(K13="",0,VLOOKUP(K13,Bausteine!$A$2:$AY$76,5,FALSE))+IF(L13="",0,VLOOKUP(L13,Bausteine!$A$2:$AY$76,5,FALSE))+IF(AC13="",0,VLOOKUP(AC13,Bausteine!$A$2:$AY$76,5,FALSE))+IF(AF13="",0,VLOOKUP(AF13,Bausteine!$A$2:$AY$76,5,FALSE))+IF(AG13="",0,VLOOKUP(AG13,Bausteine!$A$2:$AY$76,5,FALSE))+IF(AH13="",0,VLOOKUP(AH13,Bausteine!$A$2:$AY$76,5,FALSE))+IF(AQ13="",0,VLOOKUP(AQ13,Bausteine!$A$2:$AY$76,5,FALSE)) | O13: =MAX(IF(C13="",0,VLOOKUP(C13,Bausteine!$A$2:$AY$76,6,FALSE)),IF(D13="",0,VLOOKUP(D13,Bausteine!$A$2:$AY$76,6,FALSE)),IF(E13="",0,VLOOKUP(E13,Bausteine!$A$2:$AY$76,6,FALSE)),IF(F13="",0,VLOOKUP(F13,Bausteine!$A$2:$AY$76,6,FALSE)),IF(G13="",0,VLOOKUP(G13,Bausteine!$A$2:$AY$76,6,FALSE)),IF(H13="",0,VLOOKUP(H13,Bausteine!$A$2:$AY$76,6,FALSE)),IF(I13="",0,VLOOKUP(I13,Bausteine!$A$2:$AY$76,6,FALSE)),IF(J13="",0,VLOOKUP(J13,Bausteine!$A$2:$AY$76,6,FALSE)),IF(K13="",0,VLOOKUP(K13,Bausteine!$A$2:$AY$76,6,FALSE)),IF(L13="",0,VLOOKUP(L13,Bausteine!$A$2:$AY$76,6,FALSE)),IF(AC13="",0,VLOOKUP(AC13,Bausteine!$A$2:$AY$76,6,FALSE)),IF(AF13="",0,VLOOKUP(AF13,Bausteine!$A$2:$AY$76,6,FALSE)),IF(AG13="",0,VLOOKUP(AG13,Bausteine!$A$2:$AY$76,6,FALSE)),IF(AH13="",0,VLOOKUP(AH13,Bausteine!$A$2:$AY$76,6,FALSE)),IF(AQ13="",0,VLOOKUP(AQ13,Bausteine!$A$2:$AY$76,6,FALSE)),AK13) | P13: =IF(C13="",0,VLOOKUP(C13,Bausteine!$A$2:$AY$76,7,FALSE))*IF(F13="",0,VLOOKUP(F13,Bausteine!$A$2:$AY$76,17,FALSE))/100+IF(D13="",0,VLOOKUP(D13,Bausteine!$A$2:$AY$76,7,FALSE))+IF(E13="",0,VLOOKUP(E13,Bausteine!$A$2:$AY$76,7,FALSE))+IF(G13="",0,VLOOKUP(G13,Bausteine!$A$2:$AY$76,7,FALSE))+IF(H13="",0,VLOOKUP(H13,Bausteine!$A$2:$AY$76,7,FALSE))+IF(I13="",0,VLOOKUP(I13,Bausteine!$A$2:$AY$76,7,FALSE))+IF(J13="",0,VLOOKUP(J13,Bausteine!$A$2:$AY$76,7,FALSE))+IF(K13="",0,VLOOKUP(K13,Bausteine!$A$2:$AY$76,7,FALSE))+IF(L13="",0,VLOOKUP(L13,Bausteine!$A$2:$AY$76,7,FALSE))+IF(AC13="",0,VLOOKUP(AC13,Bausteine!$A$2:$AY$76,7,FALSE))+IF(AF13="",0,VLOOKUP(AF13,Bausteine!$A$2:$AY$76,7,FALSE))+IF(AG13="",0,VLOOKUP(AG13,Bausteine!$A$2:$AY$76,7,FALSE))+IF(AH13="",0,VLOOKUP(AH13,Bausteine!$A$2:$AY$76,7,FALSE))+IF(AQ13="",0,VLOOKUP(AQ13,Bausteine!$A$2:$AY$76,7,FALSE))+AI13 | Q13: =N13*Parameter!$B$2 | R13: =AE13-Q13 | S13: =IF(C13="",0,VLOOKUP(C13,Bausteine!$A$2:$AY$76,13,FALSE))*IF(F13="",0,VLOOKUP(F13,Bausteine!$A$2:$AY$76,16,FALSE))/100 | T13: =IF(C13="",0,VLOOKUP(C13,Bausteine!$A$2:$AY$76,8,FALSE))*IF(F13="",0,VLOOKUP(F13,Bausteine!$A$2:$AY$76,15,FALSE))/100+IF(D13="",0,VLOOKUP(D13,Bausteine!$A$2:$AY$76,8,FALSE))+IF(E13="",0,VLOOKUP(E13,Bausteine!$A$2:$AY$76,8,FALSE))+IF(G13="",0,VLOOKUP(G13,Bausteine!$A$2:$AY$76,8,FALSE))+IF(H13="",0,VLOOKUP(H13,Bausteine!$A$2:$AY$76,8,FALSE))+IF(I13="",0,VLOOKUP(I13,Bausteine!$A$2:$AY$76,8,FALSE))+IF(J13="",0,VLOOKUP(J13,Bausteine!$A$2:$AY$76,8,FALSE))+IF(K13="",0,VLOOKUP(K13,Bausteine!$A$2:$AY$76,8,FALSE))+IF(L13="",0,VLOOKUP(L13,Bausteine!$A$2:$AY$76,8,FALSE))+IF(AC13="",0,VLOOKUP(AC13,Bausteine!$A$2:$AY$76,8,FALSE))+IF(AF13="",0,VLOOKUP(AF13,Bausteine!$A$2:$AY$76,8,FALSE))+IF(AG13="",0,VLOOKUP(AG13,Bausteine!$A$2:$AY$76,8,FALSE))+IF(AH13="",0,VLOOKUP(AH13,Bausteine!$A$2:$AY$76,8,FALSE))+IF(AQ13="",0,VLOOKUP(AQ13,Bausteine!$A$2:$AY$76,8,FALSE))+AJ13 | U13: =IF(C13="",0,VLOOKUP(C13,Bausteine!$A$2:$AY$76,9,FALSE))+IF(D13="",0,VLOOKUP(D13,Bausteine!$A$2:$AY$76,9,FALSE))+IF(E13="",0,VLOOKUP(E13,Bausteine!$A$2:$AY$76,9,FALSE))+IF(F13="",0,VLOOKUP(F13,Bausteine!$A$2:$AY$76,9,FALSE))+IF(G13="",0,VLOOKUP(G13,Bausteine!$A$2:$AY$76,9,FALSE))+IF(H13="",0,VLOOKUP(H13,Bausteine!$A$2:$AY$76,9,FALSE))+IF(I13="",0,VLOOKUP(I13,Bausteine!$A$2:$AY$76,9,FALSE))+IF(J13="",0,VLOOKUP(J13,Bausteine!$A$2:$AY$76,9,FALSE))+IF(K13="",0,VLOOKUP(K13,Bausteine!$A$2:$AY$76,9,FALSE))+IF(L13="",0,VLOOKUP(L13,Bausteine!$A$2:$AY$76,9,FALSE))+IF(AC13="",0,VLOOKUP(AC13,Bausteine!$A$2:$AY$76,9,FALSE))+IF(AF13="",0,VLOOKUP(AF13,Bausteine!$A$2:$AY$76,9,FALSE))+IF(AG13="",0,VLOOKUP(AG13,Bausteine!$A$2:$AY$76,9,FALSE))+IF(AH13="",0,VLOOKUP(AH13,Bausteine!$A$2:$AY$76,9,FALSE))+IF(AQ13="",0,VLOOKUP(AQ13,Bausteine!$A$2:$AY$76,9,FALSE)) | V13: =IF(D13="",0,VLOOKUP(D13,Bausteine!$A$2:$AY$76,10,FALSE))-U13/IF(E13="",0,VLOOKUP(E13,Bausteine!$A$2:$AY$76,11,FALSE)) | W13: =IF(Y13<>"OK","",ROUND(MIN(IF(C13="",0,VLOOKUP(C13,Bausteine!$A$2:$AY$76,21,FALSE)),IF(AQ13="",0,VLOOKUP(AQ13,Bausteine!$A$2:$AY$76,21,FALSE)),IF(C13="",0,VLOOKUP(C13,Bausteine!$A$2:$AY$76,20,FALSE))*(V13/T13/(IF(C13="",0,VLOOKUP(C13,Bausteine!$A$2:$AY$76,19,FALSE))/IF(C13="",0,VLOOKUP(C13,Bausteine!$A$2:$AY$76,18,FALSE))))^Parameter!$B$3),0)) | X13: =IF(F13="",0,VLOOKUP(F13,Bausteine!$A$2:$AY$76,14,FALSE)) | Y13: =IFERROR(IF(OR(AD13<=0,AD13>1,R13<=0,T13<=0,V13<=0,U13>IF(E13="",0,VLOOKUP(E13,Bausteine!$A$2:$AY$76,12,FALSE)),T13>MIN(IF(C13="",0,VLOOKUP(C13,Bausteine!$A$2:$AY$76,22,FALSE)),IF(AQ13="",0,VLOOKUP(AQ13,Bausteine!$A$2:$AY$76,22,FALSE))),IF(E13="",0,VLOOKUP(E13,Bausteine!$A$2:$AY$76,11,FALSE))<=0,IF(E13="",0,VLOOKUP(E13,Bausteine!$A$2:$AY$76,11,FALSE))>1),"UNGUELTIG","OK"),"FEHLER") | Z13: 550 | AA13: 56 | AB13: Fixed AttackFrontal, lighttracked and Light armor. ArtilleryExplode death behavior and doctrine modifiers remain template integration work. | AD13: =IF(AC13="",1,IF(AC13="",0,VLOOKUP(AC13,Bausteine!$A$2:$AY$76,37,FALSE))/100) | AE13: =P13*AD13 | AI13: =SUMIF(Startbesatzung!$A$2:$A$7,A13,Startbesatzung!$D$2:$D$7) | AJ13: =SUMIF(Startbesatzung!$A$2:$A$7,A13,Startbesatzung!$E$2:$E$7) | AK13: =MAX(0,IF(Startbesatzung!A2=A13,Startbesatzung!G2,0),IF(Startbesatzung!A3=A13,Startbesatzung!G3,0),IF(Startbesatzung!A4=A13,Startbesatzung!G4,0),IF(Startbesatzung!A5=A13,Startbesatzung!G5,0),IF(Startbesatzung!A6=A13,Startbesatzung!G6,0),IF(Startbesatzung!A7=A13,Startbesatzung!G7,0)) | AL13: =IF(AF13="","",IF(IF(AH13="",0,VLOOKUP(AH13,Bausteine!$A$2:$AY$76,38,FALSE))>0,IF(AH13="",0,VLOOKUP(AH13,Bausteine!$A$2:$AY$76,38,FALSE)),IF(AG13="",0,VLOOKUP(AG13,Bausteine!$A$2:$AY$76,28,FALSE)))) | AM13: =IF(AF13="","",IF(AG13="",0,VLOOKUP(AG13,Bausteine!$A$2:$AY$76,44,FALSE))) | AN13: =IF(AF13="","",IF(AF13="",0,VLOOKUP(AF13,Bausteine!$A$2:$AY$76,27,FALSE))) | AO13: =IF(AF13="","",IF(AF13="",0,VLOOKUP(AF13,Bausteine!$A$2:$AY$76,25,FALSE))) | AP13: =IF(AF13="","",IF(AH13="",0,VLOOKUP(AH13,Bausteine!$A$2:$AY$76,29,FALSE))) | AQ13: tracks-light-artillery | AR13: =IF(AQ13="",0,VLOOKUP(AQ13,Bausteine!$A$2:$AY$76,48,FALSE)) | AS13: =MIN(IF(AQ13="",0,VLOOKUP(AQ13,Bausteine!$A$2:$AY$76,50,FALSE)),IF(C13="",0,VLOOKUP(C13,Bausteine!$A$2:$AY$76,51,FALSE)))
A14: Overlord Mortar Roof / draft | B14: china | C14: overlord-chassis | D14: diesel-heavy | E14: baseline-generator | F14: heavy | G14: heavy-twin-turret | H14: overlord-cannon | I14: heavy-shell | M14: =IF(C14="",0,VLOOKUP(C14,Bausteine!$A$2:$AY$76,4,FALSE))+IF(D14="",0,VLOOKUP(D14,Bausteine!$A$2:$AY$76,4,FALSE))+IF(E14="",0,VLOOKUP(E14,Bausteine!$A$2:$AY$76,4,FALSE))+IF(F14="",0,VLOOKUP(F14,Bausteine!$A$2:$AY$76,4,FALSE))+IF(G14="",0,VLOOKUP(G14,Bausteine!$A$2:$AY$76,4,FALSE))+IF(H14="",0,VLOOKUP(H14,Bausteine!$A$2:$AY$76,4,FALSE))+IF(I14="",0,VLOOKUP(I14,Bausteine!$A$2:$AY$76,4,FALSE))+IF(J14="",0,VLOOKUP(J14,Bausteine!$A$2:$AY$76,4,FALSE))+IF(K14="",0,VLOOKUP(K14,Bausteine!$A$2:$AY$76,4,FALSE))+IF(L14="",0,VLOOKUP(L14,Bausteine!$A$2:$AY$76,4,FALSE))+IF(AC14="",0,VLOOKUP(AC14,Bausteine!$A$2:$AY$76,4,FALSE))+IF(AF14="",0,VLOOKUP(AF14,Bausteine!$A$2:$AY$76,4,FALSE))+IF(AG14="",0,VLOOKUP(AG14,Bausteine!$A$2:$AY$76,4,FALSE))+IF(AH14="",0,VLOOKUP(AH14,Bausteine!$A$2:$AY$76,4,FALSE))+IF(AQ14="",0,VLOOKUP(AQ14,Bausteine!$A$2:$AY$76,4,FALSE)) | N14: =IF(C14="",0,VLOOKUP(C14,Bausteine!$A$2:$AY$76,5,FALSE))+IF(D14="",0,VLOOKUP(D14,Bausteine!$A$2:$AY$76,5,FALSE))+IF(E14="",0,VLOOKUP(E14,Bausteine!$A$2:$AY$76,5,FALSE))+IF(F14="",0,VLOOKUP(F14,Bausteine!$A$2:$AY$76,5,FALSE))+IF(G14="",0,VLOOKUP(G14,Bausteine!$A$2:$AY$76,5,FALSE))+IF(H14="",0,VLOOKUP(H14,Bausteine!$A$2:$AY$76,5,FALSE))+IF(I14="",0,VLOOKUP(I14,Bausteine!$A$2:$AY$76,5,FALSE))+IF(J14="",0,VLOOKUP(J14,Bausteine!$A$2:$AY$76,5,FALSE))+IF(K14="",0,VLOOKUP(K14,Bausteine!$A$2:$AY$76,5,FALSE))+IF(L14="",0,VLOOKUP(L14,Bausteine!$A$2:$AY$76,5,FALSE))+IF(AC14="",0,VLOOKUP(AC14,Bausteine!$A$2:$AY$76,5,FALSE))+IF(AF14="",0,VLOOKUP(AF14,Bausteine!$A$2:$AY$76,5,FALSE))+IF(AG14="",0,VLOOKUP(AG14,Bausteine!$A$2:$AY$76,5,FALSE))+IF(AH14="",0,VLOOKUP(AH14,Bausteine!$A$2:$AY$76,5,FALSE))+IF(AQ14="",0,VLOOKUP(AQ14,Bausteine!$A$2:$AY$76,5,FALSE)) | O14: =MAX(IF(C14="",0,VLOOKUP(C14,Bausteine!$A$2:$AY$76,6,FALSE)),IF(D14="",0,VLOOKUP(D14,Bausteine!$A$2:$AY$76,6,FALSE)),IF(E14="",0,VLOOKUP(E14,Bausteine!$A$2:$AY$76,6,FALSE)),IF(F14="",0,VLOOKUP(F14,Bausteine!$A$2:$AY$76,6,FALSE)),IF(G14="",0,VLOOKUP(G14,Bausteine!$A$2:$AY$76,6,FALSE)),IF(H14="",0,VLOOKUP(H14,Bausteine!$A$2:$AY$76,6,FALSE)),IF(I14="",0,VLOOKUP(I14,Bausteine!$A$2:$AY$76,6,FALSE)),IF(J14="",0,VLOOKUP(J14,Bausteine!$A$2:$AY$76,6,FALSE)),IF(K14="",0,VLOOKUP(K14,Bausteine!$A$2:$AY$76,6,FALSE)),IF(L14="",0,VLOOKUP(L14,Bausteine!$A$2:$AY$76,6,FALSE)),IF(AC14="",0,VLOOKUP(AC14,Bausteine!$A$2:$AY$76,6,FALSE)),IF(AF14="",0,VLOOKUP(AF14,Bausteine!$A$2:$AY$76,6,FALSE)),IF(AG14="",0,VLOOKUP(AG14,Bausteine!$A$2:$AY$76,6,FALSE)),IF(AH14="",0,VLOOKUP(AH14,Bausteine!$A$2:$AY$76,6,FALSE)),IF(AQ14="",0,VLOOKUP(AQ14,Bausteine!$A$2:$AY$76,6,FALSE)),AK14) | P14: =IF(C14="",0,VLOOKUP(C14,Bausteine!$A$2:$AY$76,7,FALSE))*IF(F14="",0,VLOOKUP(F14,Bausteine!$A$2:$AY$76,17,FALSE))/100+IF(D14="",0,VLOOKUP(D14,Bausteine!$A$2:$AY$76,7,FALSE))+IF(E14="",0,VLOOKUP(E14,Bausteine!$A$2:$AY$76,7,FALSE))+IF(G14="",0,VLOOKUP(G14,Bausteine!$A$2:$AY$76,7,FALSE))+IF(H14="",0,VLOOKUP(H14,Bausteine!$A$2:$AY$76,7,FALSE))+IF(I14="",0,VLOOKUP(I14,Bausteine!$A$2:$AY$76,7,FALSE))+IF(J14="",0,VLOOKUP(J14,Bausteine!$A$2:$AY$76,7,FALSE))+IF(K14="",0,VLOOKUP(K14,Bausteine!$A$2:$AY$76,7,FALSE))+IF(L14="",0,VLOOKUP(L14,Bausteine!$A$2:$AY$76,7,FALSE))+IF(AC14="",0,VLOOKUP(AC14,Bausteine!$A$2:$AY$76,7,FALSE))+IF(AF14="",0,VLOOKUP(AF14,Bausteine!$A$2:$AY$76,7,FALSE))+IF(AG14="",0,VLOOKUP(AG14,Bausteine!$A$2:$AY$76,7,FALSE))+IF(AH14="",0,VLOOKUP(AH14,Bausteine!$A$2:$AY$76,7,FALSE))+IF(AQ14="",0,VLOOKUP(AQ14,Bausteine!$A$2:$AY$76,7,FALSE))+AI14 | Q14: =N14*Parameter!$B$2 | R14: =AE14-Q14 | S14: =IF(C14="",0,VLOOKUP(C14,Bausteine!$A$2:$AY$76,13,FALSE))*IF(F14="",0,VLOOKUP(F14,Bausteine!$A$2:$AY$76,16,FALSE))/100 | T14: =IF(C14="",0,VLOOKUP(C14,Bausteine!$A$2:$AY$76,8,FALSE))*IF(F14="",0,VLOOKUP(F14,Bausteine!$A$2:$AY$76,15,FALSE))/100+IF(D14="",0,VLOOKUP(D14,Bausteine!$A$2:$AY$76,8,FALSE))+IF(E14="",0,VLOOKUP(E14,Bausteine!$A$2:$AY$76,8,FALSE))+IF(G14="",0,VLOOKUP(G14,Bausteine!$A$2:$AY$76,8,FALSE))+IF(H14="",0,VLOOKUP(H14,Bausteine!$A$2:$AY$76,8,FALSE))+IF(I14="",0,VLOOKUP(I14,Bausteine!$A$2:$AY$76,8,FALSE))+IF(J14="",0,VLOOKUP(J14,Bausteine!$A$2:$AY$76,8,FALSE))+IF(K14="",0,VLOOKUP(K14,Bausteine!$A$2:$AY$76,8,FALSE))+IF(L14="",0,VLOOKUP(L14,Bausteine!$A$2:$AY$76,8,FALSE))+IF(AC14="",0,VLOOKUP(AC14,Bausteine!$A$2:$AY$76,8,FALSE))+IF(AF14="",0,VLOOKUP(AF14,Bausteine!$A$2:$AY$76,8,FALSE))+IF(AG14="",0,VLOOKUP(AG14,Bausteine!$A$2:$AY$76,8,FALSE))+IF(AH14="",0,VLOOKUP(AH14,Bausteine!$A$2:$AY$76,8,FALSE))+IF(AQ14="",0,VLOOKUP(AQ14,Bausteine!$A$2:$AY$76,8,FALSE))+AJ14 | U14: =IF(C14="",0,VLOOKUP(C14,Bausteine!$A$2:$AY$76,9,FALSE))+IF(D14="",0,VLOOKUP(D14,Bausteine!$A$2:$AY$76,9,FALSE))+IF(E14="",0,VLOOKUP(E14,Bausteine!$A$2:$AY$76,9,FALSE))+IF(F14="",0,VLOOKUP(F14,Bausteine!$A$2:$AY$76,9,FALSE))+IF(G14="",0,VLOOKUP(G14,Bausteine!$A$2:$AY$76,9,FALSE))+IF(H14="",0,VLOOKUP(H14,Bausteine!$A$2:$AY$76,9,FALSE))+IF(I14="",0,VLOOKUP(I14,Bausteine!$A$2:$AY$76,9,FALSE))+IF(J14="",0,VLOOKUP(J14,Bausteine!$A$2:$AY$76,9,FALSE))+IF(K14="",0,VLOOKUP(K14,Bausteine!$A$2:$AY$76,9,FALSE))+IF(L14="",0,VLOOKUP(L14,Bausteine!$A$2:$AY$76,9,FALSE))+IF(AC14="",0,VLOOKUP(AC14,Bausteine!$A$2:$AY$76,9,FALSE))+IF(AF14="",0,VLOOKUP(AF14,Bausteine!$A$2:$AY$76,9,FALSE))+IF(AG14="",0,VLOOKUP(AG14,Bausteine!$A$2:$AY$76,9,FALSE))+IF(AH14="",0,VLOOKUP(AH14,Bausteine!$A$2:$AY$76,9,FALSE))+IF(AQ14="",0,VLOOKUP(AQ14,Bausteine!$A$2:$AY$76,9,FALSE)) | V14: =IF(D14="",0,VLOOKUP(D14,Bausteine!$A$2:$AY$76,10,FALSE))-U14/IF(E14="",0,VLOOKUP(E14,Bausteine!$A$2:$AY$76,11,FALSE)) | W14: =IF(Y14<>"OK","",ROUND(MIN(IF(C14="",0,VLOOKUP(C14,Bausteine!$A$2:$AY$76,21,FALSE)),IF(AQ14="",0,VLOOKUP(AQ14,Bausteine!$A$2:$AY$76,21,FALSE)),IF(C14="",0,VLOOKUP(C14,Bausteine!$A$2:$AY$76,20,FALSE))*(V14/T14/(IF(C14="",0,VLOOKUP(C14,Bausteine!$A$2:$AY$76,19,FALSE))/IF(C14="",0,VLOOKUP(C14,Bausteine!$A$2:$AY$76,18,FALSE))))^Parameter!$B$3),0)) | X14: =IF(F14="",0,VLOOKUP(F14,Bausteine!$A$2:$AY$76,14,FALSE)) | Y14: =IFERROR(IF(OR(AD14<=0,AD14>1,R14<=0,T14<=0,V14<=0,U14>IF(E14="",0,VLOOKUP(E14,Bausteine!$A$2:$AY$76,12,FALSE)),T14>MIN(IF(C14="",0,VLOOKUP(C14,Bausteine!$A$2:$AY$76,22,FALSE)),IF(AQ14="",0,VLOOKUP(AQ14,Bausteine!$A$2:$AY$76,22,FALSE))),IF(E14="",0,VLOOKUP(E14,Bausteine!$A$2:$AY$76,11,FALSE))<=0,IF(E14="",0,VLOOKUP(E14,Bausteine!$A$2:$AY$76,11,FALSE))>1),"UNGUELTIG","OK"),"FEHLER") | Z14: 2650 | AA14: 54 | AB14: OFFLINE DRAFT: existing artytur.shp, mount on Overlord not live-tested. Proposed 650-credit additional assembly, no CP. Main cannon retained. No legacy reference target. | AD14: =IF(AC14="",1,IF(AC14="",0,VLOOKUP(AC14,Bausteine!$A$2:$AY$76,37,FALSE))/100) | AE14: =P14*AD14 | AF14: mortar-roof-carrier | AG14: roof-mortar | AH14: mortar-he | AI14: =SUMIF(Startbesatzung!$A$2:$A$7,A14,Startbesatzung!$D$2:$D$7) | AJ14: =SUMIF(Startbesatzung!$A$2:$A$7,A14,Startbesatzung!$E$2:$E$7) | AK14: =MAX(0,IF(Startbesatzung!A2=A14,Startbesatzung!G2,0),IF(Startbesatzung!A3=A14,Startbesatzung!G3,0),IF(Startbesatzung!A4=A14,Startbesatzung!G4,0),IF(Startbesatzung!A5=A14,Startbesatzung!G5,0),IF(Startbesatzung!A6=A14,Startbesatzung!G6,0),IF(Startbesatzung!A7=A14,Startbesatzung!G7,0)) | AL14: =IF(AF14="","",IF(IF(AH14="",0,VLOOKUP(AH14,Bausteine!$A$2:$AY$76,38,FALSE))>0,IF(AH14="",0,VLOOKUP(AH14,Bausteine!$A$2:$AY$76,38,FALSE)),IF(AG14="",0,VLOOKUP(AG14,Bausteine!$A$2:$AY$76,28,FALSE)))) | AM14: =IF(AF14="","",IF(AG14="",0,VLOOKUP(AG14,Bausteine!$A$2:$AY$76,44,FALSE))) | AN14: =IF(AF14="","",IF(AF14="",0,VLOOKUP(AF14,Bausteine!$A$2:$AY$76,27,FALSE))) | AO14: =IF(AF14="","",IF(AF14="",0,VLOOKUP(AF14,Bausteine!$A$2:$AY$76,25,FALSE))) | AP14: =IF(AF14="","",IF(AH14="",0,VLOOKUP(AH14,Bausteine!$A$2:$AY$76,29,FALSE))) | AQ14: tracks-superheavy | AR14: =IF(AQ14="",0,VLOOKUP(AQ14,Bausteine!$A$2:$AY$76,48,FALSE)) | AS14: =MIN(IF(AQ14="",0,VLOOKUP(AQ14,Bausteine!$A$2:$AY$76,50,FALSE)),IF(C14="",0,VLOOKUP(C14,Bausteine!$A$2:$AY$76,51,FALSE)))
A15: Overlord Mortar Roof PDL / draft | B15: china | C15: overlord-chassis | D15: diesel-heavy-boost | E15: efficient-generator | F15: heavy | G15: heavy-twin-turret | H15: overlord-cannon | I15: heavy-shell | J15: pdl | M15: =IF(C15="",0,VLOOKUP(C15,Bausteine!$A$2:$AY$76,4,FALSE))+IF(D15="",0,VLOOKUP(D15,Bausteine!$A$2:$AY$76,4,FALSE))+IF(E15="",0,VLOOKUP(E15,Bausteine!$A$2:$AY$76,4,FALSE))+IF(F15="",0,VLOOKUP(F15,Bausteine!$A$2:$AY$76,4,FALSE))+IF(G15="",0,VLOOKUP(G15,Bausteine!$A$2:$AY$76,4,FALSE))+IF(H15="",0,VLOOKUP(H15,Bausteine!$A$2:$AY$76,4,FALSE))+IF(I15="",0,VLOOKUP(I15,Bausteine!$A$2:$AY$76,4,FALSE))+IF(J15="",0,VLOOKUP(J15,Bausteine!$A$2:$AY$76,4,FALSE))+IF(K15="",0,VLOOKUP(K15,Bausteine!$A$2:$AY$76,4,FALSE))+IF(L15="",0,VLOOKUP(L15,Bausteine!$A$2:$AY$76,4,FALSE))+IF(AC15="",0,VLOOKUP(AC15,Bausteine!$A$2:$AY$76,4,FALSE))+IF(AF15="",0,VLOOKUP(AF15,Bausteine!$A$2:$AY$76,4,FALSE))+IF(AG15="",0,VLOOKUP(AG15,Bausteine!$A$2:$AY$76,4,FALSE))+IF(AH15="",0,VLOOKUP(AH15,Bausteine!$A$2:$AY$76,4,FALSE))+IF(AQ15="",0,VLOOKUP(AQ15,Bausteine!$A$2:$AY$76,4,FALSE)) | N15: =IF(C15="",0,VLOOKUP(C15,Bausteine!$A$2:$AY$76,5,FALSE))+IF(D15="",0,VLOOKUP(D15,Bausteine!$A$2:$AY$76,5,FALSE))+IF(E15="",0,VLOOKUP(E15,Bausteine!$A$2:$AY$76,5,FALSE))+IF(F15="",0,VLOOKUP(F15,Bausteine!$A$2:$AY$76,5,FALSE))+IF(G15="",0,VLOOKUP(G15,Bausteine!$A$2:$AY$76,5,FALSE))+IF(H15="",0,VLOOKUP(H15,Bausteine!$A$2:$AY$76,5,FALSE))+IF(I15="",0,VLOOKUP(I15,Bausteine!$A$2:$AY$76,5,FALSE))+IF(J15="",0,VLOOKUP(J15,Bausteine!$A$2:$AY$76,5,FALSE))+IF(K15="",0,VLOOKUP(K15,Bausteine!$A$2:$AY$76,5,FALSE))+IF(L15="",0,VLOOKUP(L15,Bausteine!$A$2:$AY$76,5,FALSE))+IF(AC15="",0,VLOOKUP(AC15,Bausteine!$A$2:$AY$76,5,FALSE))+IF(AF15="",0,VLOOKUP(AF15,Bausteine!$A$2:$AY$76,5,FALSE))+IF(AG15="",0,VLOOKUP(AG15,Bausteine!$A$2:$AY$76,5,FALSE))+IF(AH15="",0,VLOOKUP(AH15,Bausteine!$A$2:$AY$76,5,FALSE))+IF(AQ15="",0,VLOOKUP(AQ15,Bausteine!$A$2:$AY$76,5,FALSE)) | O15: =MAX(IF(C15="",0,VLOOKUP(C15,Bausteine!$A$2:$AY$76,6,FALSE)),IF(D15="",0,VLOOKUP(D15,Bausteine!$A$2:$AY$76,6,FALSE)),IF(E15="",0,VLOOKUP(E15,Bausteine!$A$2:$AY$76,6,FALSE)),IF(F15="",0,VLOOKUP(F15,Bausteine!$A$2:$AY$76,6,FALSE)),IF(G15="",0,VLOOKUP(G15,Bausteine!$A$2:$AY$76,6,FALSE)),IF(H15="",0,VLOOKUP(H15,Bausteine!$A$2:$AY$76,6,FALSE)),IF(I15="",0,VLOOKUP(I15,Bausteine!$A$2:$AY$76,6,FALSE)),IF(J15="",0,VLOOKUP(J15,Bausteine!$A$2:$AY$76,6,FALSE)),IF(K15="",0,VLOOKUP(K15,Bausteine!$A$2:$AY$76,6,FALSE)),IF(L15="",0,VLOOKUP(L15,Bausteine!$A$2:$AY$76,6,FALSE)),IF(AC15="",0,VLOOKUP(AC15,Bausteine!$A$2:$AY$76,6,FALSE)),IF(AF15="",0,VLOOKUP(AF15,Bausteine!$A$2:$AY$76,6,FALSE)),IF(AG15="",0,VLOOKUP(AG15,Bausteine!$A$2:$AY$76,6,FALSE)),IF(AH15="",0,VLOOKUP(AH15,Bausteine!$A$2:$AY$76,6,FALSE)),IF(AQ15="",0,VLOOKUP(AQ15,Bausteine!$A$2:$AY$76,6,FALSE)),AK15) | P15: =IF(C15="",0,VLOOKUP(C15,Bausteine!$A$2:$AY$76,7,FALSE))*IF(F15="",0,VLOOKUP(F15,Bausteine!$A$2:$AY$76,17,FALSE))/100+IF(D15="",0,VLOOKUP(D15,Bausteine!$A$2:$AY$76,7,FALSE))+IF(E15="",0,VLOOKUP(E15,Bausteine!$A$2:$AY$76,7,FALSE))+IF(G15="",0,VLOOKUP(G15,Bausteine!$A$2:$AY$76,7,FALSE))+IF(H15="",0,VLOOKUP(H15,Bausteine!$A$2:$AY$76,7,FALSE))+IF(I15="",0,VLOOKUP(I15,Bausteine!$A$2:$AY$76,7,FALSE))+IF(J15="",0,VLOOKUP(J15,Bausteine!$A$2:$AY$76,7,FALSE))+IF(K15="",0,VLOOKUP(K15,Bausteine!$A$2:$AY$76,7,FALSE))+IF(L15="",0,VLOOKUP(L15,Bausteine!$A$2:$AY$76,7,FALSE))+IF(AC15="",0,VLOOKUP(AC15,Bausteine!$A$2:$AY$76,7,FALSE))+IF(AF15="",0,VLOOKUP(AF15,Bausteine!$A$2:$AY$76,7,FALSE))+IF(AG15="",0,VLOOKUP(AG15,Bausteine!$A$2:$AY$76,7,FALSE))+IF(AH15="",0,VLOOKUP(AH15,Bausteine!$A$2:$AY$76,7,FALSE))+IF(AQ15="",0,VLOOKUP(AQ15,Bausteine!$A$2:$AY$76,7,FALSE))+AI15 | Q15: =N15*Parameter!$B$2 | R15: =AE15-Q15 | S15: =IF(C15="",0,VLOOKUP(C15,Bausteine!$A$2:$AY$76,13,FALSE))*IF(F15="",0,VLOOKUP(F15,Bausteine!$A$2:$AY$76,16,FALSE))/100 | T15: =IF(C15="",0,VLOOKUP(C15,Bausteine!$A$2:$AY$76,8,FALSE))*IF(F15="",0,VLOOKUP(F15,Bausteine!$A$2:$AY$76,15,FALSE))/100+IF(D15="",0,VLOOKUP(D15,Bausteine!$A$2:$AY$76,8,FALSE))+IF(E15="",0,VLOOKUP(E15,Bausteine!$A$2:$AY$76,8,FALSE))+IF(G15="",0,VLOOKUP(G15,Bausteine!$A$2:$AY$76,8,FALSE))+IF(H15="",0,VLOOKUP(H15,Bausteine!$A$2:$AY$76,8,FALSE))+IF(I15="",0,VLOOKUP(I15,Bausteine!$A$2:$AY$76,8,FALSE))+IF(J15="",0,VLOOKUP(J15,Bausteine!$A$2:$AY$76,8,FALSE))+IF(K15="",0,VLOOKUP(K15,Bausteine!$A$2:$AY$76,8,FALSE))+IF(L15="",0,VLOOKUP(L15,Bausteine!$A$2:$AY$76,8,FALSE))+IF(AC15="",0,VLOOKUP(AC15,Bausteine!$A$2:$AY$76,8,FALSE))+IF(AF15="",0,VLOOKUP(AF15,Bausteine!$A$2:$AY$76,8,FALSE))+IF(AG15="",0,VLOOKUP(AG15,Bausteine!$A$2:$AY$76,8,FALSE))+IF(AH15="",0,VLOOKUP(AH15,Bausteine!$A$2:$AY$76,8,FALSE))+IF(AQ15="",0,VLOOKUP(AQ15,Bausteine!$A$2:$AY$76,8,FALSE))+AJ15 | U15: =IF(C15="",0,VLOOKUP(C15,Bausteine!$A$2:$AY$76,9,FALSE))+IF(D15="",0,VLOOKUP(D15,Bausteine!$A$2:$AY$76,9,FALSE))+IF(E15="",0,VLOOKUP(E15,Bausteine!$A$2:$AY$76,9,FALSE))+IF(F15="",0,VLOOKUP(F15,Bausteine!$A$2:$AY$76,9,FALSE))+IF(G15="",0,VLOOKUP(G15,Bausteine!$A$2:$AY$76,9,FALSE))+IF(H15="",0,VLOOKUP(H15,Bausteine!$A$2:$AY$76,9,FALSE))+IF(I15="",0,VLOOKUP(I15,Bausteine!$A$2:$AY$76,9,FALSE))+IF(J15="",0,VLOOKUP(J15,Bausteine!$A$2:$AY$76,9,FALSE))+IF(K15="",0,VLOOKUP(K15,Bausteine!$A$2:$AY$76,9,FALSE))+IF(L15="",0,VLOOKUP(L15,Bausteine!$A$2:$AY$76,9,FALSE))+IF(AC15="",0,VLOOKUP(AC15,Bausteine!$A$2:$AY$76,9,FALSE))+IF(AF15="",0,VLOOKUP(AF15,Bausteine!$A$2:$AY$76,9,FALSE))+IF(AG15="",0,VLOOKUP(AG15,Bausteine!$A$2:$AY$76,9,FALSE))+IF(AH15="",0,VLOOKUP(AH15,Bausteine!$A$2:$AY$76,9,FALSE))+IF(AQ15="",0,VLOOKUP(AQ15,Bausteine!$A$2:$AY$76,9,FALSE)) | V15: =IF(D15="",0,VLOOKUP(D15,Bausteine!$A$2:$AY$76,10,FALSE))-U15/IF(E15="",0,VLOOKUP(E15,Bausteine!$A$2:$AY$76,11,FALSE)) | W15: =IF(Y15<>"OK","",ROUND(MIN(IF(C15="",0,VLOOKUP(C15,Bausteine!$A$2:$AY$76,21,FALSE)),IF(AQ15="",0,VLOOKUP(AQ15,Bausteine!$A$2:$AY$76,21,FALSE)),IF(C15="",0,VLOOKUP(C15,Bausteine!$A$2:$AY$76,20,FALSE))*(V15/T15/(IF(C15="",0,VLOOKUP(C15,Bausteine!$A$2:$AY$76,19,FALSE))/IF(C15="",0,VLOOKUP(C15,Bausteine!$A$2:$AY$76,18,FALSE))))^Parameter!$B$3),0)) | X15: =IF(F15="",0,VLOOKUP(F15,Bausteine!$A$2:$AY$76,14,FALSE)) | Y15: =IFERROR(IF(OR(AD15<=0,AD15>1,R15<=0,T15<=0,V15<=0,U15>IF(E15="",0,VLOOKUP(E15,Bausteine!$A$2:$AY$76,12,FALSE)),T15>MIN(IF(C15="",0,VLOOKUP(C15,Bausteine!$A$2:$AY$76,22,FALSE)),IF(AQ15="",0,VLOOKUP(AQ15,Bausteine!$A$2:$AY$76,22,FALSE))),IF(E15="",0,VLOOKUP(E15,Bausteine!$A$2:$AY$76,11,FALSE))<=0,IF(E15="",0,VLOOKUP(E15,Bausteine!$A$2:$AY$76,11,FALSE))>1),"UNGUELTIG","OK"),"FEHLER") | Z15: 3300 | AA15: 55 | AB15: OFFLINE DRAFT: unverified mounting; shared standard PDL and heavy-drive upgrade unchanged. | AD15: =IF(AC15="",1,IF(AC15="",0,VLOOKUP(AC15,Bausteine!$A$2:$AY$76,37,FALSE))/100) | AE15: =P15*AD15 | AF15: mortar-roof-carrier | AG15: roof-mortar | AH15: mortar-he | AI15: =SUMIF(Startbesatzung!$A$2:$A$7,A15,Startbesatzung!$D$2:$D$7) | AJ15: =SUMIF(Startbesatzung!$A$2:$A$7,A15,Startbesatzung!$E$2:$E$7) | AK15: =MAX(0,IF(Startbesatzung!A2=A15,Startbesatzung!G2,0),IF(Startbesatzung!A3=A15,Startbesatzung!G3,0),IF(Startbesatzung!A4=A15,Startbesatzung!G4,0),IF(Startbesatzung!A5=A15,Startbesatzung!G5,0),IF(Startbesatzung!A6=A15,Startbesatzung!G6,0),IF(Startbesatzung!A7=A15,Startbesatzung!G7,0)) | AL15: =IF(AF15="","",IF(IF(AH15="",0,VLOOKUP(AH15,Bausteine!$A$2:$AY$76,38,FALSE))>0,IF(AH15="",0,VLOOKUP(AH15,Bausteine!$A$2:$AY$76,38,FALSE)),IF(AG15="",0,VLOOKUP(AG15,Bausteine!$A$2:$AY$76,28,FALSE)))) | AM15: =IF(AF15="","",IF(AG15="",0,VLOOKUP(AG15,Bausteine!$A$2:$AY$76,44,FALSE))) | AN15: =IF(AF15="","",IF(AF15="",0,VLOOKUP(AF15,Bausteine!$A$2:$AY$76,27,FALSE))) | AO15: =IF(AF15="","",IF(AF15="",0,VLOOKUP(AF15,Bausteine!$A$2:$AY$76,25,FALSE))) | AP15: =IF(AF15="","",IF(AH15="",0,VLOOKUP(AH15,Bausteine!$A$2:$AY$76,29,FALSE))) | AQ15: tracks-superheavy | AR15: =IF(AQ15="",0,VLOOKUP(AQ15,Bausteine!$A$2:$AY$76,48,FALSE)) | AS15: =MIN(IF(AQ15="",0,VLOOKUP(AQ15,Bausteine!$A$2:$AY$76,50,FALSE)),IF(C15="",0,VLOOKUP(C15,Bausteine!$A$2:$AY$76,51,FALSE)))
A16: Overlord Mortar Roof Reflector / draft | B16: china | C16: overlord-chassis | D16: diesel-heavy-boost | E16: efficient-generator | F16: reflector | G16: heavy-twin-turret | H16: overlord-cannon | I16: heavy-shell | M16: =IF(C16="",0,VLOOKUP(C16,Bausteine!$A$2:$AY$76,4,FALSE))+IF(D16="",0,VLOOKUP(D16,Bausteine!$A$2:$AY$76,4,FALSE))+IF(E16="",0,VLOOKUP(E16,Bausteine!$A$2:$AY$76,4,FALSE))+IF(F16="",0,VLOOKUP(F16,Bausteine!$A$2:$AY$76,4,FALSE))+IF(G16="",0,VLOOKUP(G16,Bausteine!$A$2:$AY$76,4,FALSE))+IF(H16="",0,VLOOKUP(H16,Bausteine!$A$2:$AY$76,4,FALSE))+IF(I16="",0,VLOOKUP(I16,Bausteine!$A$2:$AY$76,4,FALSE))+IF(J16="",0,VLOOKUP(J16,Bausteine!$A$2:$AY$76,4,FALSE))+IF(K16="",0,VLOOKUP(K16,Bausteine!$A$2:$AY$76,4,FALSE))+IF(L16="",0,VLOOKUP(L16,Bausteine!$A$2:$AY$76,4,FALSE))+IF(AC16="",0,VLOOKUP(AC16,Bausteine!$A$2:$AY$76,4,FALSE))+IF(AF16="",0,VLOOKUP(AF16,Bausteine!$A$2:$AY$76,4,FALSE))+IF(AG16="",0,VLOOKUP(AG16,Bausteine!$A$2:$AY$76,4,FALSE))+IF(AH16="",0,VLOOKUP(AH16,Bausteine!$A$2:$AY$76,4,FALSE))+IF(AQ16="",0,VLOOKUP(AQ16,Bausteine!$A$2:$AY$76,4,FALSE)) | N16: =IF(C16="",0,VLOOKUP(C16,Bausteine!$A$2:$AY$76,5,FALSE))+IF(D16="",0,VLOOKUP(D16,Bausteine!$A$2:$AY$76,5,FALSE))+IF(E16="",0,VLOOKUP(E16,Bausteine!$A$2:$AY$76,5,FALSE))+IF(F16="",0,VLOOKUP(F16,Bausteine!$A$2:$AY$76,5,FALSE))+IF(G16="",0,VLOOKUP(G16,Bausteine!$A$2:$AY$76,5,FALSE))+IF(H16="",0,VLOOKUP(H16,Bausteine!$A$2:$AY$76,5,FALSE))+IF(I16="",0,VLOOKUP(I16,Bausteine!$A$2:$AY$76,5,FALSE))+IF(J16="",0,VLOOKUP(J16,Bausteine!$A$2:$AY$76,5,FALSE))+IF(K16="",0,VLOOKUP(K16,Bausteine!$A$2:$AY$76,5,FALSE))+IF(L16="",0,VLOOKUP(L16,Bausteine!$A$2:$AY$76,5,FALSE))+IF(AC16="",0,VLOOKUP(AC16,Bausteine!$A$2:$AY$76,5,FALSE))+IF(AF16="",0,VLOOKUP(AF16,Bausteine!$A$2:$AY$76,5,FALSE))+IF(AG16="",0,VLOOKUP(AG16,Bausteine!$A$2:$AY$76,5,FALSE))+IF(AH16="",0,VLOOKUP(AH16,Bausteine!$A$2:$AY$76,5,FALSE))+IF(AQ16="",0,VLOOKUP(AQ16,Bausteine!$A$2:$AY$76,5,FALSE)) | O16: =MAX(IF(C16="",0,VLOOKUP(C16,Bausteine!$A$2:$AY$76,6,FALSE)),IF(D16="",0,VLOOKUP(D16,Bausteine!$A$2:$AY$76,6,FALSE)),IF(E16="",0,VLOOKUP(E16,Bausteine!$A$2:$AY$76,6,FALSE)),IF(F16="",0,VLOOKUP(F16,Bausteine!$A$2:$AY$76,6,FALSE)),IF(G16="",0,VLOOKUP(G16,Bausteine!$A$2:$AY$76,6,FALSE)),IF(H16="",0,VLOOKUP(H16,Bausteine!$A$2:$AY$76,6,FALSE)),IF(I16="",0,VLOOKUP(I16,Bausteine!$A$2:$AY$76,6,FALSE)),IF(J16="",0,VLOOKUP(J16,Bausteine!$A$2:$AY$76,6,FALSE)),IF(K16="",0,VLOOKUP(K16,Bausteine!$A$2:$AY$76,6,FALSE)),IF(L16="",0,VLOOKUP(L16,Bausteine!$A$2:$AY$76,6,FALSE)),IF(AC16="",0,VLOOKUP(AC16,Bausteine!$A$2:$AY$76,6,FALSE)),IF(AF16="",0,VLOOKUP(AF16,Bausteine!$A$2:$AY$76,6,FALSE)),IF(AG16="",0,VLOOKUP(AG16,Bausteine!$A$2:$AY$76,6,FALSE)),IF(AH16="",0,VLOOKUP(AH16,Bausteine!$A$2:$AY$76,6,FALSE)),IF(AQ16="",0,VLOOKUP(AQ16,Bausteine!$A$2:$AY$76,6,FALSE)),AK16) | P16: =IF(C16="",0,VLOOKUP(C16,Bausteine!$A$2:$AY$76,7,FALSE))*IF(F16="",0,VLOOKUP(F16,Bausteine!$A$2:$AY$76,17,FALSE))/100+IF(D16="",0,VLOOKUP(D16,Bausteine!$A$2:$AY$76,7,FALSE))+IF(E16="",0,VLOOKUP(E16,Bausteine!$A$2:$AY$76,7,FALSE))+IF(G16="",0,VLOOKUP(G16,Bausteine!$A$2:$AY$76,7,FALSE))+IF(H16="",0,VLOOKUP(H16,Bausteine!$A$2:$AY$76,7,FALSE))+IF(I16="",0,VLOOKUP(I16,Bausteine!$A$2:$AY$76,7,FALSE))+IF(J16="",0,VLOOKUP(J16,Bausteine!$A$2:$AY$76,7,FALSE))+IF(K16="",0,VLOOKUP(K16,Bausteine!$A$2:$AY$76,7,FALSE))+IF(L16="",0,VLOOKUP(L16,Bausteine!$A$2:$AY$76,7,FALSE))+IF(AC16="",0,VLOOKUP(AC16,Bausteine!$A$2:$AY$76,7,FALSE))+IF(AF16="",0,VLOOKUP(AF16,Bausteine!$A$2:$AY$76,7,FALSE))+IF(AG16="",0,VLOOKUP(AG16,Bausteine!$A$2:$AY$76,7,FALSE))+IF(AH16="",0,VLOOKUP(AH16,Bausteine!$A$2:$AY$76,7,FALSE))+IF(AQ16="",0,VLOOKUP(AQ16,Bausteine!$A$2:$AY$76,7,FALSE))+AI16 | Q16: =N16*Parameter!$B$2 | R16: =AE16-Q16 | S16: =IF(C16="",0,VLOOKUP(C16,Bausteine!$A$2:$AY$76,13,FALSE))*IF(F16="",0,VLOOKUP(F16,Bausteine!$A$2:$AY$76,16,FALSE))/100 | T16: =IF(C16="",0,VLOOKUP(C16,Bausteine!$A$2:$AY$76,8,FALSE))*IF(F16="",0,VLOOKUP(F16,Bausteine!$A$2:$AY$76,15,FALSE))/100+IF(D16="",0,VLOOKUP(D16,Bausteine!$A$2:$AY$76,8,FALSE))+IF(E16="",0,VLOOKUP(E16,Bausteine!$A$2:$AY$76,8,FALSE))+IF(G16="",0,VLOOKUP(G16,Bausteine!$A$2:$AY$76,8,FALSE))+IF(H16="",0,VLOOKUP(H16,Bausteine!$A$2:$AY$76,8,FALSE))+IF(I16="",0,VLOOKUP(I16,Bausteine!$A$2:$AY$76,8,FALSE))+IF(J16="",0,VLOOKUP(J16,Bausteine!$A$2:$AY$76,8,FALSE))+IF(K16="",0,VLOOKUP(K16,Bausteine!$A$2:$AY$76,8,FALSE))+IF(L16="",0,VLOOKUP(L16,Bausteine!$A$2:$AY$76,8,FALSE))+IF(AC16="",0,VLOOKUP(AC16,Bausteine!$A$2:$AY$76,8,FALSE))+IF(AF16="",0,VLOOKUP(AF16,Bausteine!$A$2:$AY$76,8,FALSE))+IF(AG16="",0,VLOOKUP(AG16,Bausteine!$A$2:$AY$76,8,FALSE))+IF(AH16="",0,VLOOKUP(AH16,Bausteine!$A$2:$AY$76,8,FALSE))+IF(AQ16="",0,VLOOKUP(AQ16,Bausteine!$A$2:$AY$76,8,FALSE))+AJ16 | U16: =IF(C16="",0,VLOOKUP(C16,Bausteine!$A$2:$AY$76,9,FALSE))+IF(D16="",0,VLOOKUP(D16,Bausteine!$A$2:$AY$76,9,FALSE))+IF(E16="",0,VLOOKUP(E16,Bausteine!$A$2:$AY$76,9,FALSE))+IF(F16="",0,VLOOKUP(F16,Bausteine!$A$2:$AY$76,9,FALSE))+IF(G16="",0,VLOOKUP(G16,Bausteine!$A$2:$AY$76,9,FALSE))+IF(H16="",0,VLOOKUP(H16,Bausteine!$A$2:$AY$76,9,FALSE))+IF(I16="",0,VLOOKUP(I16,Bausteine!$A$2:$AY$76,9,FALSE))+IF(J16="",0,VLOOKUP(J16,Bausteine!$A$2:$AY$76,9,FALSE))+IF(K16="",0,VLOOKUP(K16,Bausteine!$A$2:$AY$76,9,FALSE))+IF(L16="",0,VLOOKUP(L16,Bausteine!$A$2:$AY$76,9,FALSE))+IF(AC16="",0,VLOOKUP(AC16,Bausteine!$A$2:$AY$76,9,FALSE))+IF(AF16="",0,VLOOKUP(AF16,Bausteine!$A$2:$AY$76,9,FALSE))+IF(AG16="",0,VLOOKUP(AG16,Bausteine!$A$2:$AY$76,9,FALSE))+IF(AH16="",0,VLOOKUP(AH16,Bausteine!$A$2:$AY$76,9,FALSE))+IF(AQ16="",0,VLOOKUP(AQ16,Bausteine!$A$2:$AY$76,9,FALSE)) | V16: =IF(D16="",0,VLOOKUP(D16,Bausteine!$A$2:$AY$76,10,FALSE))-U16/IF(E16="",0,VLOOKUP(E16,Bausteine!$A$2:$AY$76,11,FALSE)) | W16: =IF(Y16<>"OK","",ROUND(MIN(IF(C16="",0,VLOOKUP(C16,Bausteine!$A$2:$AY$76,21,FALSE)),IF(AQ16="",0,VLOOKUP(AQ16,Bausteine!$A$2:$AY$76,21,FALSE)),IF(C16="",0,VLOOKUP(C16,Bausteine!$A$2:$AY$76,20,FALSE))*(V16/T16/(IF(C16="",0,VLOOKUP(C16,Bausteine!$A$2:$AY$76,19,FALSE))/IF(C16="",0,VLOOKUP(C16,Bausteine!$A$2:$AY$76,18,FALSE))))^Parameter!$B$3),0)) | X16: =IF(F16="",0,VLOOKUP(F16,Bausteine!$A$2:$AY$76,14,FALSE)) | Y16: =IFERROR(IF(OR(AD16<=0,AD16>1,R16<=0,T16<=0,V16<=0,U16>IF(E16="",0,VLOOKUP(E16,Bausteine!$A$2:$AY$76,12,FALSE)),T16>MIN(IF(C16="",0,VLOOKUP(C16,Bausteine!$A$2:$AY$76,22,FALSE)),IF(AQ16="",0,VLOOKUP(AQ16,Bausteine!$A$2:$AY$76,22,FALSE))),IF(E16="",0,VLOOKUP(E16,Bausteine!$A$2:$AY$76,11,FALSE))<=0,IF(E16="",0,VLOOKUP(E16,Bausteine!$A$2:$AY$76,11,FALSE))>1),"UNGUELTIG","OK"),"FEHLER") | Z16: 2650 | AA16: 55 | AB16: OFFLINE DRAFT: unverified mounting; reflector power budget and global CP credit unchanged. | AD16: =IF(AC16="",1,IF(AC16="",0,VLOOKUP(AC16,Bausteine!$A$2:$AY$76,37,FALSE))/100) | AE16: =P16*AD16 | AF16: mortar-roof-carrier | AG16: roof-mortar | AH16: mortar-he | AI16: =SUMIF(Startbesatzung!$A$2:$A$7,A16,Startbesatzung!$D$2:$D$7) | AJ16: =SUMIF(Startbesatzung!$A$2:$A$7,A16,Startbesatzung!$E$2:$E$7) | AK16: =MAX(0,IF(Startbesatzung!A2=A16,Startbesatzung!G2,0),IF(Startbesatzung!A3=A16,Startbesatzung!G3,0),IF(Startbesatzung!A4=A16,Startbesatzung!G4,0),IF(Startbesatzung!A5=A16,Startbesatzung!G5,0),IF(Startbesatzung!A6=A16,Startbesatzung!G6,0),IF(Startbesatzung!A7=A16,Startbesatzung!G7,0)) | AL16: =IF(AF16="","",IF(IF(AH16="",0,VLOOKUP(AH16,Bausteine!$A$2:$AY$76,38,FALSE))>0,IF(AH16="",0,VLOOKUP(AH16,Bausteine!$A$2:$AY$76,38,FALSE)),IF(AG16="",0,VLOOKUP(AG16,Bausteine!$A$2:$AY$76,28,FALSE)))) | AM16: =IF(AF16="","",IF(AG16="",0,VLOOKUP(AG16,Bausteine!$A$2:$AY$76,44,FALSE))) | AN16: =IF(AF16="","",IF(AF16="",0,VLOOKUP(AF16,Bausteine!$A$2:$AY$76,27,FALSE))) | AO16: =IF(AF16="","",IF(AF16="",0,VLOOKUP(AF16,Bausteine!$A$2:$AY$76,25,FALSE))) | AP16: =IF(AF16="","",IF(AH16="",0,VLOOKUP(AH16,Bausteine!$A$2:$AY$76,29,FALSE))) | AQ16: tracks-superheavy | AR16: =IF(AQ16="",0,VLOOKUP(AQ16,Bausteine!$A$2:$AY$76,48,FALSE)) | AS16: =MIN(IF(AQ16="",0,VLOOKUP(AQ16,Bausteine!$A$2:$AY$76,50,FALSE)),IF(C16="",0,VLOOKUP(C16,Bausteine!$A$2:$AY$76,51,FALSE)))
A17: Overlord Flame Roof / draft | B17: china | C17: overlord-chassis | D17: diesel-heavy | E17: baseline-generator | F17: heavy | G17: heavy-twin-turret | H17: overlord-cannon | I17: heavy-shell | M17: =IF(C17="",0,VLOOKUP(C17,Bausteine!$A$2:$AY$76,4,FALSE))+IF(D17="",0,VLOOKUP(D17,Bausteine!$A$2:$AY$76,4,FALSE))+IF(E17="",0,VLOOKUP(E17,Bausteine!$A$2:$AY$76,4,FALSE))+IF(F17="",0,VLOOKUP(F17,Bausteine!$A$2:$AY$76,4,FALSE))+IF(G17="",0,VLOOKUP(G17,Bausteine!$A$2:$AY$76,4,FALSE))+IF(H17="",0,VLOOKUP(H17,Bausteine!$A$2:$AY$76,4,FALSE))+IF(I17="",0,VLOOKUP(I17,Bausteine!$A$2:$AY$76,4,FALSE))+IF(J17="",0,VLOOKUP(J17,Bausteine!$A$2:$AY$76,4,FALSE))+IF(K17="",0,VLOOKUP(K17,Bausteine!$A$2:$AY$76,4,FALSE))+IF(L17="",0,VLOOKUP(L17,Bausteine!$A$2:$AY$76,4,FALSE))+IF(AC17="",0,VLOOKUP(AC17,Bausteine!$A$2:$AY$76,4,FALSE))+IF(AF17="",0,VLOOKUP(AF17,Bausteine!$A$2:$AY$76,4,FALSE))+IF(AG17="",0,VLOOKUP(AG17,Bausteine!$A$2:$AY$76,4,FALSE))+IF(AH17="",0,VLOOKUP(AH17,Bausteine!$A$2:$AY$76,4,FALSE))+IF(AQ17="",0,VLOOKUP(AQ17,Bausteine!$A$2:$AY$76,4,FALSE)) | N17: =IF(C17="",0,VLOOKUP(C17,Bausteine!$A$2:$AY$76,5,FALSE))+IF(D17="",0,VLOOKUP(D17,Bausteine!$A$2:$AY$76,5,FALSE))+IF(E17="",0,VLOOKUP(E17,Bausteine!$A$2:$AY$76,5,FALSE))+IF(F17="",0,VLOOKUP(F17,Bausteine!$A$2:$AY$76,5,FALSE))+IF(G17="",0,VLOOKUP(G17,Bausteine!$A$2:$AY$76,5,FALSE))+IF(H17="",0,VLOOKUP(H17,Bausteine!$A$2:$AY$76,5,FALSE))+IF(I17="",0,VLOOKUP(I17,Bausteine!$A$2:$AY$76,5,FALSE))+IF(J17="",0,VLOOKUP(J17,Bausteine!$A$2:$AY$76,5,FALSE))+IF(K17="",0,VLOOKUP(K17,Bausteine!$A$2:$AY$76,5,FALSE))+IF(L17="",0,VLOOKUP(L17,Bausteine!$A$2:$AY$76,5,FALSE))+IF(AC17="",0,VLOOKUP(AC17,Bausteine!$A$2:$AY$76,5,FALSE))+IF(AF17="",0,VLOOKUP(AF17,Bausteine!$A$2:$AY$76,5,FALSE))+IF(AG17="",0,VLOOKUP(AG17,Bausteine!$A$2:$AY$76,5,FALSE))+IF(AH17="",0,VLOOKUP(AH17,Bausteine!$A$2:$AY$76,5,FALSE))+IF(AQ17="",0,VLOOKUP(AQ17,Bausteine!$A$2:$AY$76,5,FALSE)) | O17: =MAX(IF(C17="",0,VLOOKUP(C17,Bausteine!$A$2:$AY$76,6,FALSE)),IF(D17="",0,VLOOKUP(D17,Bausteine!$A$2:$AY$76,6,FALSE)),IF(E17="",0,VLOOKUP(E17,Bausteine!$A$2:$AY$76,6,FALSE)),IF(F17="",0,VLOOKUP(F17,Bausteine!$A$2:$AY$76,6,FALSE)),IF(G17="",0,VLOOKUP(G17,Bausteine!$A$2:$AY$76,6,FALSE)),IF(H17="",0,VLOOKUP(H17,Bausteine!$A$2:$AY$76,6,FALSE)),IF(I17="",0,VLOOKUP(I17,Bausteine!$A$2:$AY$76,6,FALSE)),IF(J17="",0,VLOOKUP(J17,Bausteine!$A$2:$AY$76,6,FALSE)),IF(K17="",0,VLOOKUP(K17,Bausteine!$A$2:$AY$76,6,FALSE)),IF(L17="",0,VLOOKUP(L17,Bausteine!$A$2:$AY$76,6,FALSE)),IF(AC17="",0,VLOOKUP(AC17,Bausteine!$A$2:$AY$76,6,FALSE)),IF(AF17="",0,VLOOKUP(AF17,Bausteine!$A$2:$AY$76,6,FALSE)),IF(AG17="",0,VLOOKUP(AG17,Bausteine!$A$2:$AY$76,6,FALSE)),IF(AH17="",0,VLOOKUP(AH17,Bausteine!$A$2:$AY$76,6,FALSE)),IF(AQ17="",0,VLOOKUP(AQ17,Bausteine!$A$2:$AY$76,6,FALSE)),AK17) | P17: =IF(C17="",0,VLOOKUP(C17,Bausteine!$A$2:$AY$76,7,FALSE))*IF(F17="",0,VLOOKUP(F17,Bausteine!$A$2:$AY$76,17,FALSE))/100+IF(D17="",0,VLOOKUP(D17,Bausteine!$A$2:$AY$76,7,FALSE))+IF(E17="",0,VLOOKUP(E17,Bausteine!$A$2:$AY$76,7,FALSE))+IF(G17="",0,VLOOKUP(G17,Bausteine!$A$2:$AY$76,7,FALSE))+IF(H17="",0,VLOOKUP(H17,Bausteine!$A$2:$AY$76,7,FALSE))+IF(I17="",0,VLOOKUP(I17,Bausteine!$A$2:$AY$76,7,FALSE))+IF(J17="",0,VLOOKUP(J17,Bausteine!$A$2:$AY$76,7,FALSE))+IF(K17="",0,VLOOKUP(K17,Bausteine!$A$2:$AY$76,7,FALSE))+IF(L17="",0,VLOOKUP(L17,Bausteine!$A$2:$AY$76,7,FALSE))+IF(AC17="",0,VLOOKUP(AC17,Bausteine!$A$2:$AY$76,7,FALSE))+IF(AF17="",0,VLOOKUP(AF17,Bausteine!$A$2:$AY$76,7,FALSE))+IF(AG17="",0,VLOOKUP(AG17,Bausteine!$A$2:$AY$76,7,FALSE))+IF(AH17="",0,VLOOKUP(AH17,Bausteine!$A$2:$AY$76,7,FALSE))+IF(AQ17="",0,VLOOKUP(AQ17,Bausteine!$A$2:$AY$76,7,FALSE))+AI17 | Q17: =N17*Parameter!$B$2 | R17: =AE17-Q17 | S17: =IF(C17="",0,VLOOKUP(C17,Bausteine!$A$2:$AY$76,13,FALSE))*IF(F17="",0,VLOOKUP(F17,Bausteine!$A$2:$AY$76,16,FALSE))/100 | T17: =IF(C17="",0,VLOOKUP(C17,Bausteine!$A$2:$AY$76,8,FALSE))*IF(F17="",0,VLOOKUP(F17,Bausteine!$A$2:$AY$76,15,FALSE))/100+IF(D17="",0,VLOOKUP(D17,Bausteine!$A$2:$AY$76,8,FALSE))+IF(E17="",0,VLOOKUP(E17,Bausteine!$A$2:$AY$76,8,FALSE))+IF(G17="",0,VLOOKUP(G17,Bausteine!$A$2:$AY$76,8,FALSE))+IF(H17="",0,VLOOKUP(H17,Bausteine!$A$2:$AY$76,8,FALSE))+IF(I17="",0,VLOOKUP(I17,Bausteine!$A$2:$AY$76,8,FALSE))+IF(J17="",0,VLOOKUP(J17,Bausteine!$A$2:$AY$76,8,FALSE))+IF(K17="",0,VLOOKUP(K17,Bausteine!$A$2:$AY$76,8,FALSE))+IF(L17="",0,VLOOKUP(L17,Bausteine!$A$2:$AY$76,8,FALSE))+IF(AC17="",0,VLOOKUP(AC17,Bausteine!$A$2:$AY$76,8,FALSE))+IF(AF17="",0,VLOOKUP(AF17,Bausteine!$A$2:$AY$76,8,FALSE))+IF(AG17="",0,VLOOKUP(AG17,Bausteine!$A$2:$AY$76,8,FALSE))+IF(AH17="",0,VLOOKUP(AH17,Bausteine!$A$2:$AY$76,8,FALSE))+IF(AQ17="",0,VLOOKUP(AQ17,Bausteine!$A$2:$AY$76,8,FALSE))+AJ17 | U17: =IF(C17="",0,VLOOKUP(C17,Bausteine!$A$2:$AY$76,9,FALSE))+IF(D17="",0,VLOOKUP(D17,Bausteine!$A$2:$AY$76,9,FALSE))+IF(E17="",0,VLOOKUP(E17,Bausteine!$A$2:$AY$76,9,FALSE))+IF(F17="",0,VLOOKUP(F17,Bausteine!$A$2:$AY$76,9,FALSE))+IF(G17="",0,VLOOKUP(G17,Bausteine!$A$2:$AY$76,9,FALSE))+IF(H17="",0,VLOOKUP(H17,Bausteine!$A$2:$AY$76,9,FALSE))+IF(I17="",0,VLOOKUP(I17,Bausteine!$A$2:$AY$76,9,FALSE))+IF(J17="",0,VLOOKUP(J17,Bausteine!$A$2:$AY$76,9,FALSE))+IF(K17="",0,VLOOKUP(K17,Bausteine!$A$2:$AY$76,9,FALSE))+IF(L17="",0,VLOOKUP(L17,Bausteine!$A$2:$AY$76,9,FALSE))+IF(AC17="",0,VLOOKUP(AC17,Bausteine!$A$2:$AY$76,9,FALSE))+IF(AF17="",0,VLOOKUP(AF17,Bausteine!$A$2:$AY$76,9,FALSE))+IF(AG17="",0,VLOOKUP(AG17,Bausteine!$A$2:$AY$76,9,FALSE))+IF(AH17="",0,VLOOKUP(AH17,Bausteine!$A$2:$AY$76,9,FALSE))+IF(AQ17="",0,VLOOKUP(AQ17,Bausteine!$A$2:$AY$76,9,FALSE)) | V17: =IF(D17="",0,VLOOKUP(D17,Bausteine!$A$2:$AY$76,10,FALSE))-U17/IF(E17="",0,VLOOKUP(E17,Bausteine!$A$2:$AY$76,11,FALSE)) | W17: =IF(Y17<>"OK","",ROUND(MIN(IF(C17="",0,VLOOKUP(C17,Bausteine!$A$2:$AY$76,21,FALSE)),IF(AQ17="",0,VLOOKUP(AQ17,Bausteine!$A$2:$AY$76,21,FALSE)),IF(C17="",0,VLOOKUP(C17,Bausteine!$A$2:$AY$76,20,FALSE))*(V17/T17/(IF(C17="",0,VLOOKUP(C17,Bausteine!$A$2:$AY$76,19,FALSE))/IF(C17="",0,VLOOKUP(C17,Bausteine!$A$2:$AY$76,18,FALSE))))^Parameter!$B$3),0)) | X17: =IF(F17="",0,VLOOKUP(F17,Bausteine!$A$2:$AY$76,14,FALSE)) | Y17: =IFERROR(IF(OR(AD17<=0,AD17>1,R17<=0,T17<=0,V17<=0,U17>IF(E17="",0,VLOOKUP(E17,Bausteine!$A$2:$AY$76,12,FALSE)),T17>MIN(IF(C17="",0,VLOOKUP(C17,Bausteine!$A$2:$AY$76,22,FALSE)),IF(AQ17="",0,VLOOKUP(AQ17,Bausteine!$A$2:$AY$76,22,FALSE))),IF(E17="",0,VLOOKUP(E17,Bausteine!$A$2:$AY$76,11,FALSE))<=0,IF(E17="",0,VLOOKUP(E17,Bausteine!$A$2:$AY$76,11,FALSE))>1),"UNGUELTIG","OK"),"FEHLER") | Z17: 2250 | AA17: 55 | AB17: OFFLINE DRAFT: chdragontur.shp has 32 separate facings; Overlord offsets, palette, scale, muzzle and animations NOT live-tested. Reuses existing flame parts without price changes; no original vehicle target. | AD17: =IF(AC17="",1,IF(AC17="",0,VLOOKUP(AC17,Bausteine!$A$2:$AY$76,37,FALSE))/100) | AE17: =P17*AD17 | AF17: flame-turret | AG17: dragon-flamer | AH17: flame-fuel | AI17: =SUMIF(Startbesatzung!$A$2:$A$7,A17,Startbesatzung!$D$2:$D$7) | AJ17: =SUMIF(Startbesatzung!$A$2:$A$7,A17,Startbesatzung!$E$2:$E$7) | AK17: =MAX(0,IF(Startbesatzung!A2=A17,Startbesatzung!G2,0),IF(Startbesatzung!A3=A17,Startbesatzung!G3,0),IF(Startbesatzung!A4=A17,Startbesatzung!G4,0),IF(Startbesatzung!A5=A17,Startbesatzung!G5,0),IF(Startbesatzung!A6=A17,Startbesatzung!G6,0),IF(Startbesatzung!A7=A17,Startbesatzung!G7,0)) | AL17: =IF(AF17="","",IF(IF(AH17="",0,VLOOKUP(AH17,Bausteine!$A$2:$AY$76,38,FALSE))>0,IF(AH17="",0,VLOOKUP(AH17,Bausteine!$A$2:$AY$76,38,FALSE)),IF(AG17="",0,VLOOKUP(AG17,Bausteine!$A$2:$AY$76,28,FALSE)))) | AM17: =IF(AF17="","",IF(AG17="",0,VLOOKUP(AG17,Bausteine!$A$2:$AY$76,44,FALSE))) | AN17: =IF(AF17="","",IF(AF17="",0,VLOOKUP(AF17,Bausteine!$A$2:$AY$76,27,FALSE))) | AO17: =IF(AF17="","",IF(AF17="",0,VLOOKUP(AF17,Bausteine!$A$2:$AY$76,25,FALSE))) | AP17: =IF(AF17="","",IF(AH17="",0,VLOOKUP(AH17,Bausteine!$A$2:$AY$76,29,FALSE))) | AQ17: tracks-superheavy | AR17: =IF(AQ17="",0,VLOOKUP(AQ17,Bausteine!$A$2:$AY$76,48,FALSE)) | AS17: =MIN(IF(AQ17="",0,VLOOKUP(AQ17,Bausteine!$A$2:$AY$76,50,FALSE)),IF(C17="",0,VLOOKUP(C17,Bausteine!$A$2:$AY$76,51,FALSE)))
A18: Overlord Flame Roof PDL / draft | B18: china | C18: overlord-chassis | D18: diesel-heavy-boost | E18: efficient-generator | F18: heavy | G18: heavy-twin-turret | H18: overlord-cannon | I18: heavy-shell | J18: pdl | M18: =IF(C18="",0,VLOOKUP(C18,Bausteine!$A$2:$AY$76,4,FALSE))+IF(D18="",0,VLOOKUP(D18,Bausteine!$A$2:$AY$76,4,FALSE))+IF(E18="",0,VLOOKUP(E18,Bausteine!$A$2:$AY$76,4,FALSE))+IF(F18="",0,VLOOKUP(F18,Bausteine!$A$2:$AY$76,4,FALSE))+IF(G18="",0,VLOOKUP(G18,Bausteine!$A$2:$AY$76,4,FALSE))+IF(H18="",0,VLOOKUP(H18,Bausteine!$A$2:$AY$76,4,FALSE))+IF(I18="",0,VLOOKUP(I18,Bausteine!$A$2:$AY$76,4,FALSE))+IF(J18="",0,VLOOKUP(J18,Bausteine!$A$2:$AY$76,4,FALSE))+IF(K18="",0,VLOOKUP(K18,Bausteine!$A$2:$AY$76,4,FALSE))+IF(L18="",0,VLOOKUP(L18,Bausteine!$A$2:$AY$76,4,FALSE))+IF(AC18="",0,VLOOKUP(AC18,Bausteine!$A$2:$AY$76,4,FALSE))+IF(AF18="",0,VLOOKUP(AF18,Bausteine!$A$2:$AY$76,4,FALSE))+IF(AG18="",0,VLOOKUP(AG18,Bausteine!$A$2:$AY$76,4,FALSE))+IF(AH18="",0,VLOOKUP(AH18,Bausteine!$A$2:$AY$76,4,FALSE))+IF(AQ18="",0,VLOOKUP(AQ18,Bausteine!$A$2:$AY$76,4,FALSE)) | N18: =IF(C18="",0,VLOOKUP(C18,Bausteine!$A$2:$AY$76,5,FALSE))+IF(D18="",0,VLOOKUP(D18,Bausteine!$A$2:$AY$76,5,FALSE))+IF(E18="",0,VLOOKUP(E18,Bausteine!$A$2:$AY$76,5,FALSE))+IF(F18="",0,VLOOKUP(F18,Bausteine!$A$2:$AY$76,5,FALSE))+IF(G18="",0,VLOOKUP(G18,Bausteine!$A$2:$AY$76,5,FALSE))+IF(H18="",0,VLOOKUP(H18,Bausteine!$A$2:$AY$76,5,FALSE))+IF(I18="",0,VLOOKUP(I18,Bausteine!$A$2:$AY$76,5,FALSE))+IF(J18="",0,VLOOKUP(J18,Bausteine!$A$2:$AY$76,5,FALSE))+IF(K18="",0,VLOOKUP(K18,Bausteine!$A$2:$AY$76,5,FALSE))+IF(L18="",0,VLOOKUP(L18,Bausteine!$A$2:$AY$76,5,FALSE))+IF(AC18="",0,VLOOKUP(AC18,Bausteine!$A$2:$AY$76,5,FALSE))+IF(AF18="",0,VLOOKUP(AF18,Bausteine!$A$2:$AY$76,5,FALSE))+IF(AG18="",0,VLOOKUP(AG18,Bausteine!$A$2:$AY$76,5,FALSE))+IF(AH18="",0,VLOOKUP(AH18,Bausteine!$A$2:$AY$76,5,FALSE))+IF(AQ18="",0,VLOOKUP(AQ18,Bausteine!$A$2:$AY$76,5,FALSE)) | O18: =MAX(IF(C18="",0,VLOOKUP(C18,Bausteine!$A$2:$AY$76,6,FALSE)),IF(D18="",0,VLOOKUP(D18,Bausteine!$A$2:$AY$76,6,FALSE)),IF(E18="",0,VLOOKUP(E18,Bausteine!$A$2:$AY$76,6,FALSE)),IF(F18="",0,VLOOKUP(F18,Bausteine!$A$2:$AY$76,6,FALSE)),IF(G18="",0,VLOOKUP(G18,Bausteine!$A$2:$AY$76,6,FALSE)),IF(H18="",0,VLOOKUP(H18,Bausteine!$A$2:$AY$76,6,FALSE)),IF(I18="",0,VLOOKUP(I18,Bausteine!$A$2:$AY$76,6,FALSE)),IF(J18="",0,VLOOKUP(J18,Bausteine!$A$2:$AY$76,6,FALSE)),IF(K18="",0,VLOOKUP(K18,Bausteine!$A$2:$AY$76,6,FALSE)),IF(L18="",0,VLOOKUP(L18,Bausteine!$A$2:$AY$76,6,FALSE)),IF(AC18="",0,VLOOKUP(AC18,Bausteine!$A$2:$AY$76,6,FALSE)),IF(AF18="",0,VLOOKUP(AF18,Bausteine!$A$2:$AY$76,6,FALSE)),IF(AG18="",0,VLOOKUP(AG18,Bausteine!$A$2:$AY$76,6,FALSE)),IF(AH18="",0,VLOOKUP(AH18,Bausteine!$A$2:$AY$76,6,FALSE)),IF(AQ18="",0,VLOOKUP(AQ18,Bausteine!$A$2:$AY$76,6,FALSE)),AK18) | P18: =IF(C18="",0,VLOOKUP(C18,Bausteine!$A$2:$AY$76,7,FALSE))*IF(F18="",0,VLOOKUP(F18,Bausteine!$A$2:$AY$76,17,FALSE))/100+IF(D18="",0,VLOOKUP(D18,Bausteine!$A$2:$AY$76,7,FALSE))+IF(E18="",0,VLOOKUP(E18,Bausteine!$A$2:$AY$76,7,FALSE))+IF(G18="",0,VLOOKUP(G18,Bausteine!$A$2:$AY$76,7,FALSE))+IF(H18="",0,VLOOKUP(H18,Bausteine!$A$2:$AY$76,7,FALSE))+IF(I18="",0,VLOOKUP(I18,Bausteine!$A$2:$AY$76,7,FALSE))+IF(J18="",0,VLOOKUP(J18,Bausteine!$A$2:$AY$76,7,FALSE))+IF(K18="",0,VLOOKUP(K18,Bausteine!$A$2:$AY$76,7,FALSE))+IF(L18="",0,VLOOKUP(L18,Bausteine!$A$2:$AY$76,7,FALSE))+IF(AC18="",0,VLOOKUP(AC18,Bausteine!$A$2:$AY$76,7,FALSE))+IF(AF18="",0,VLOOKUP(AF18,Bausteine!$A$2:$AY$76,7,FALSE))+IF(AG18="",0,VLOOKUP(AG18,Bausteine!$A$2:$AY$76,7,FALSE))+IF(AH18="",0,VLOOKUP(AH18,Bausteine!$A$2:$AY$76,7,FALSE))+IF(AQ18="",0,VLOOKUP(AQ18,Bausteine!$A$2:$AY$76,7,FALSE))+AI18 | Q18: =N18*Parameter!$B$2 | R18: =AE18-Q18 | S18: =IF(C18="",0,VLOOKUP(C18,Bausteine!$A$2:$AY$76,13,FALSE))*IF(F18="",0,VLOOKUP(F18,Bausteine!$A$2:$AY$76,16,FALSE))/100 | T18: =IF(C18="",0,VLOOKUP(C18,Bausteine!$A$2:$AY$76,8,FALSE))*IF(F18="",0,VLOOKUP(F18,Bausteine!$A$2:$AY$76,15,FALSE))/100+IF(D18="",0,VLOOKUP(D18,Bausteine!$A$2:$AY$76,8,FALSE))+IF(E18="",0,VLOOKUP(E18,Bausteine!$A$2:$AY$76,8,FALSE))+IF(G18="",0,VLOOKUP(G18,Bausteine!$A$2:$AY$76,8,FALSE))+IF(H18="",0,VLOOKUP(H18,Bausteine!$A$2:$AY$76,8,FALSE))+IF(I18="",0,VLOOKUP(I18,Bausteine!$A$2:$AY$76,8,FALSE))+IF(J18="",0,VLOOKUP(J18,Bausteine!$A$2:$AY$76,8,FALSE))+IF(K18="",0,VLOOKUP(K18,Bausteine!$A$2:$AY$76,8,FALSE))+IF(L18="",0,VLOOKUP(L18,Bausteine!$A$2:$AY$76,8,FALSE))+IF(AC18="",0,VLOOKUP(AC18,Bausteine!$A$2:$AY$76,8,FALSE))+IF(AF18="",0,VLOOKUP(AF18,Bausteine!$A$2:$AY$76,8,FALSE))+IF(AG18="",0,VLOOKUP(AG18,Bausteine!$A$2:$AY$76,8,FALSE))+IF(AH18="",0,VLOOKUP(AH18,Bausteine!$A$2:$AY$76,8,FALSE))+IF(AQ18="",0,VLOOKUP(AQ18,Bausteine!$A$2:$AY$76,8,FALSE))+AJ18 | U18: =IF(C18="",0,VLOOKUP(C18,Bausteine!$A$2:$AY$76,9,FALSE))+IF(D18="",0,VLOOKUP(D18,Bausteine!$A$2:$AY$76,9,FALSE))+IF(E18="",0,VLOOKUP(E18,Bausteine!$A$2:$AY$76,9,FALSE))+IF(F18="",0,VLOOKUP(F18,Bausteine!$A$2:$AY$76,9,FALSE))+IF(G18="",0,VLOOKUP(G18,Bausteine!$A$2:$AY$76,9,FALSE))+IF(H18="",0,VLOOKUP(H18,Bausteine!$A$2:$AY$76,9,FALSE))+IF(I18="",0,VLOOKUP(I18,Bausteine!$A$2:$AY$76,9,FALSE))+IF(J18="",0,VLOOKUP(J18,Bausteine!$A$2:$AY$76,9,FALSE))+IF(K18="",0,VLOOKUP(K18,Bausteine!$A$2:$AY$76,9,FALSE))+IF(L18="",0,VLOOKUP(L18,Bausteine!$A$2:$AY$76,9,FALSE))+IF(AC18="",0,VLOOKUP(AC18,Bausteine!$A$2:$AY$76,9,FALSE))+IF(AF18="",0,VLOOKUP(AF18,Bausteine!$A$2:$AY$76,9,FALSE))+IF(AG18="",0,VLOOKUP(AG18,Bausteine!$A$2:$AY$76,9,FALSE))+IF(AH18="",0,VLOOKUP(AH18,Bausteine!$A$2:$AY$76,9,FALSE))+IF(AQ18="",0,VLOOKUP(AQ18,Bausteine!$A$2:$AY$76,9,FALSE)) | V18: =IF(D18="",0,VLOOKUP(D18,Bausteine!$A$2:$AY$76,10,FALSE))-U18/IF(E18="",0,VLOOKUP(E18,Bausteine!$A$2:$AY$76,11,FALSE)) | W18: =IF(Y18<>"OK","",ROUND(MIN(IF(C18="",0,VLOOKUP(C18,Bausteine!$A$2:$AY$76,21,FALSE)),IF(AQ18="",0,VLOOKUP(AQ18,Bausteine!$A$2:$AY$76,21,FALSE)),IF(C18="",0,VLOOKUP(C18,Bausteine!$A$2:$AY$76,20,FALSE))*(V18/T18/(IF(C18="",0,VLOOKUP(C18,Bausteine!$A$2:$AY$76,19,FALSE))/IF(C18="",0,VLOOKUP(C18,Bausteine!$A$2:$AY$76,18,FALSE))))^Parameter!$B$3),0)) | X18: =IF(F18="",0,VLOOKUP(F18,Bausteine!$A$2:$AY$76,14,FALSE)) | Y18: =IFERROR(IF(OR(AD18<=0,AD18>1,R18<=0,T18<=0,V18<=0,U18>IF(E18="",0,VLOOKUP(E18,Bausteine!$A$2:$AY$76,12,FALSE)),T18>MIN(IF(C18="",0,VLOOKUP(C18,Bausteine!$A$2:$AY$76,22,FALSE)),IF(AQ18="",0,VLOOKUP(AQ18,Bausteine!$A$2:$AY$76,22,FALSE))),IF(E18="",0,VLOOKUP(E18,Bausteine!$A$2:$AY$76,11,FALSE))<=0,IF(E18="",0,VLOOKUP(E18,Bausteine!$A$2:$AY$76,11,FALSE))>1),"UNGUELTIG","OK"),"FEHLER") | Z18: 2900 | AA18: 55 | AB18: OFFLINE DRAFT: unverified roof artwork. Existing PDL and flame parts, no special rebate. Main gun and auxiliary fire names must be composed safely. | AD18: =IF(AC18="",1,IF(AC18="",0,VLOOKUP(AC18,Bausteine!$A$2:$AY$76,37,FALSE))/100) | AE18: =P18*AD18 | AF18: flame-turret | AG18: dragon-flamer | AH18: flame-fuel | AI18: =SUMIF(Startbesatzung!$A$2:$A$7,A18,Startbesatzung!$D$2:$D$7) | AJ18: =SUMIF(Startbesatzung!$A$2:$A$7,A18,Startbesatzung!$E$2:$E$7) | AK18: =MAX(0,IF(Startbesatzung!A2=A18,Startbesatzung!G2,0),IF(Startbesatzung!A3=A18,Startbesatzung!G3,0),IF(Startbesatzung!A4=A18,Startbesatzung!G4,0),IF(Startbesatzung!A5=A18,Startbesatzung!G5,0),IF(Startbesatzung!A6=A18,Startbesatzung!G6,0),IF(Startbesatzung!A7=A18,Startbesatzung!G7,0)) | AL18: =IF(AF18="","",IF(IF(AH18="",0,VLOOKUP(AH18,Bausteine!$A$2:$AY$76,38,FALSE))>0,IF(AH18="",0,VLOOKUP(AH18,Bausteine!$A$2:$AY$76,38,FALSE)),IF(AG18="",0,VLOOKUP(AG18,Bausteine!$A$2:$AY$76,28,FALSE)))) | AM18: =IF(AF18="","",IF(AG18="",0,VLOOKUP(AG18,Bausteine!$A$2:$AY$76,44,FALSE))) | AN18: =IF(AF18="","",IF(AF18="",0,VLOOKUP(AF18,Bausteine!$A$2:$AY$76,27,FALSE))) | AO18: =IF(AF18="","",IF(AF18="",0,VLOOKUP(AF18,Bausteine!$A$2:$AY$76,25,FALSE))) | AP18: =IF(AF18="","",IF(AH18="",0,VLOOKUP(AH18,Bausteine!$A$2:$AY$76,29,FALSE))) | AQ18: tracks-superheavy | AR18: =IF(AQ18="",0,VLOOKUP(AQ18,Bausteine!$A$2:$AY$76,48,FALSE)) | AS18: =MIN(IF(AQ18="",0,VLOOKUP(AQ18,Bausteine!$A$2:$AY$76,50,FALSE)),IF(C18="",0,VLOOKUP(C18,Bausteine!$A$2:$AY$76,51,FALSE)))
A19: Overlord Flame Roof Reflector / draft | B19: china | C19: overlord-chassis | D19: diesel-heavy-boost | E19: efficient-generator | F19: reflector | G19: heavy-twin-turret | H19: overlord-cannon | I19: heavy-shell | M19: =IF(C19="",0,VLOOKUP(C19,Bausteine!$A$2:$AY$76,4,FALSE))+IF(D19="",0,VLOOKUP(D19,Bausteine!$A$2:$AY$76,4,FALSE))+IF(E19="",0,VLOOKUP(E19,Bausteine!$A$2:$AY$76,4,FALSE))+IF(F19="",0,VLOOKUP(F19,Bausteine!$A$2:$AY$76,4,FALSE))+IF(G19="",0,VLOOKUP(G19,Bausteine!$A$2:$AY$76,4,FALSE))+IF(H19="",0,VLOOKUP(H19,Bausteine!$A$2:$AY$76,4,FALSE))+IF(I19="",0,VLOOKUP(I19,Bausteine!$A$2:$AY$76,4,FALSE))+IF(J19="",0,VLOOKUP(J19,Bausteine!$A$2:$AY$76,4,FALSE))+IF(K19="",0,VLOOKUP(K19,Bausteine!$A$2:$AY$76,4,FALSE))+IF(L19="",0,VLOOKUP(L19,Bausteine!$A$2:$AY$76,4,FALSE))+IF(AC19="",0,VLOOKUP(AC19,Bausteine!$A$2:$AY$76,4,FALSE))+IF(AF19="",0,VLOOKUP(AF19,Bausteine!$A$2:$AY$76,4,FALSE))+IF(AG19="",0,VLOOKUP(AG19,Bausteine!$A$2:$AY$76,4,FALSE))+IF(AH19="",0,VLOOKUP(AH19,Bausteine!$A$2:$AY$76,4,FALSE))+IF(AQ19="",0,VLOOKUP(AQ19,Bausteine!$A$2:$AY$76,4,FALSE)) | N19: =IF(C19="",0,VLOOKUP(C19,Bausteine!$A$2:$AY$76,5,FALSE))+IF(D19="",0,VLOOKUP(D19,Bausteine!$A$2:$AY$76,5,FALSE))+IF(E19="",0,VLOOKUP(E19,Bausteine!$A$2:$AY$76,5,FALSE))+IF(F19="",0,VLOOKUP(F19,Bausteine!$A$2:$AY$76,5,FALSE))+IF(G19="",0,VLOOKUP(G19,Bausteine!$A$2:$AY$76,5,FALSE))+IF(H19="",0,VLOOKUP(H19,Bausteine!$A$2:$AY$76,5,FALSE))+IF(I19="",0,VLOOKUP(I19,Bausteine!$A$2:$AY$76,5,FALSE))+IF(J19="",0,VLOOKUP(J19,Bausteine!$A$2:$AY$76,5,FALSE))+IF(K19="",0,VLOOKUP(K19,Bausteine!$A$2:$AY$76,5,FALSE))+IF(L19="",0,VLOOKUP(L19,Bausteine!$A$2:$AY$76,5,FALSE))+IF(AC19="",0,VLOOKUP(AC19,Bausteine!$A$2:$AY$76,5,FALSE))+IF(AF19="",0,VLOOKUP(AF19,Bausteine!$A$2:$AY$76,5,FALSE))+IF(AG19="",0,VLOOKUP(AG19,Bausteine!$A$2:$AY$76,5,FALSE))+IF(AH19="",0,VLOOKUP(AH19,Bausteine!$A$2:$AY$76,5,FALSE))+IF(AQ19="",0,VLOOKUP(AQ19,Bausteine!$A$2:$AY$76,5,FALSE)) | O19: =MAX(IF(C19="",0,VLOOKUP(C19,Bausteine!$A$2:$AY$76,6,FALSE)),IF(D19="",0,VLOOKUP(D19,Bausteine!$A$2:$AY$76,6,FALSE)),IF(E19="",0,VLOOKUP(E19,Bausteine!$A$2:$AY$76,6,FALSE)),IF(F19="",0,VLOOKUP(F19,Bausteine!$A$2:$AY$76,6,FALSE)),IF(G19="",0,VLOOKUP(G19,Bausteine!$A$2:$AY$76,6,FALSE)),IF(H19="",0,VLOOKUP(H19,Bausteine!$A$2:$AY$76,6,FALSE)),IF(I19="",0,VLOOKUP(I19,Bausteine!$A$2:$AY$76,6,FALSE)),IF(J19="",0,VLOOKUP(J19,Bausteine!$A$2:$AY$76,6,FALSE)),IF(K19="",0,VLOOKUP(K19,Bausteine!$A$2:$AY$76,6,FALSE)),IF(L19="",0,VLOOKUP(L19,Bausteine!$A$2:$AY$76,6,FALSE)),IF(AC19="",0,VLOOKUP(AC19,Bausteine!$A$2:$AY$76,6,FALSE)),IF(AF19="",0,VLOOKUP(AF19,Bausteine!$A$2:$AY$76,6,FALSE)),IF(AG19="",0,VLOOKUP(AG19,Bausteine!$A$2:$AY$76,6,FALSE)),IF(AH19="",0,VLOOKUP(AH19,Bausteine!$A$2:$AY$76,6,FALSE)),IF(AQ19="",0,VLOOKUP(AQ19,Bausteine!$A$2:$AY$76,6,FALSE)),AK19) | P19: =IF(C19="",0,VLOOKUP(C19,Bausteine!$A$2:$AY$76,7,FALSE))*IF(F19="",0,VLOOKUP(F19,Bausteine!$A$2:$AY$76,17,FALSE))/100+IF(D19="",0,VLOOKUP(D19,Bausteine!$A$2:$AY$76,7,FALSE))+IF(E19="",0,VLOOKUP(E19,Bausteine!$A$2:$AY$76,7,FALSE))+IF(G19="",0,VLOOKUP(G19,Bausteine!$A$2:$AY$76,7,FALSE))+IF(H19="",0,VLOOKUP(H19,Bausteine!$A$2:$AY$76,7,FALSE))+IF(I19="",0,VLOOKUP(I19,Bausteine!$A$2:$AY$76,7,FALSE))+IF(J19="",0,VLOOKUP(J19,Bausteine!$A$2:$AY$76,7,FALSE))+IF(K19="",0,VLOOKUP(K19,Bausteine!$A$2:$AY$76,7,FALSE))+IF(L19="",0,VLOOKUP(L19,Bausteine!$A$2:$AY$76,7,FALSE))+IF(AC19="",0,VLOOKUP(AC19,Bausteine!$A$2:$AY$76,7,FALSE))+IF(AF19="",0,VLOOKUP(AF19,Bausteine!$A$2:$AY$76,7,FALSE))+IF(AG19="",0,VLOOKUP(AG19,Bausteine!$A$2:$AY$76,7,FALSE))+IF(AH19="",0,VLOOKUP(AH19,Bausteine!$A$2:$AY$76,7,FALSE))+IF(AQ19="",0,VLOOKUP(AQ19,Bausteine!$A$2:$AY$76,7,FALSE))+AI19 | Q19: =N19*Parameter!$B$2 | R19: =AE19-Q19 | S19: =IF(C19="",0,VLOOKUP(C19,Bausteine!$A$2:$AY$76,13,FALSE))*IF(F19="",0,VLOOKUP(F19,Bausteine!$A$2:$AY$76,16,FALSE))/100 | T19: =IF(C19="",0,VLOOKUP(C19,Bausteine!$A$2:$AY$76,8,FALSE))*IF(F19="",0,VLOOKUP(F19,Bausteine!$A$2:$AY$76,15,FALSE))/100+IF(D19="",0,VLOOKUP(D19,Bausteine!$A$2:$AY$76,8,FALSE))+IF(E19="",0,VLOOKUP(E19,Bausteine!$A$2:$AY$76,8,FALSE))+IF(G19="",0,VLOOKUP(G19,Bausteine!$A$2:$AY$76,8,FALSE))+IF(H19="",0,VLOOKUP(H19,Bausteine!$A$2:$AY$76,8,FALSE))+IF(I19="",0,VLOOKUP(I19,Bausteine!$A$2:$AY$76,8,FALSE))+IF(J19="",0,VLOOKUP(J19,Bausteine!$A$2:$AY$76,8,FALSE))+IF(K19="",0,VLOOKUP(K19,Bausteine!$A$2:$AY$76,8,FALSE))+IF(L19="",0,VLOOKUP(L19,Bausteine!$A$2:$AY$76,8,FALSE))+IF(AC19="",0,VLOOKUP(AC19,Bausteine!$A$2:$AY$76,8,FALSE))+IF(AF19="",0,VLOOKUP(AF19,Bausteine!$A$2:$AY$76,8,FALSE))+IF(AG19="",0,VLOOKUP(AG19,Bausteine!$A$2:$AY$76,8,FALSE))+IF(AH19="",0,VLOOKUP(AH19,Bausteine!$A$2:$AY$76,8,FALSE))+IF(AQ19="",0,VLOOKUP(AQ19,Bausteine!$A$2:$AY$76,8,FALSE))+AJ19 | U19: =IF(C19="",0,VLOOKUP(C19,Bausteine!$A$2:$AY$76,9,FALSE))+IF(D19="",0,VLOOKUP(D19,Bausteine!$A$2:$AY$76,9,FALSE))+IF(E19="",0,VLOOKUP(E19,Bausteine!$A$2:$AY$76,9,FALSE))+IF(F19="",0,VLOOKUP(F19,Bausteine!$A$2:$AY$76,9,FALSE))+IF(G19="",0,VLOOKUP(G19,Bausteine!$A$2:$AY$76,9,FALSE))+IF(H19="",0,VLOOKUP(H19,Bausteine!$A$2:$AY$76,9,FALSE))+IF(I19="",0,VLOOKUP(I19,Bausteine!$A$2:$AY$76,9,FALSE))+IF(J19="",0,VLOOKUP(J19,Bausteine!$A$2:$AY$76,9,FALSE))+IF(K19="",0,VLOOKUP(K19,Bausteine!$A$2:$AY$76,9,FALSE))+IF(L19="",0,VLOOKUP(L19,Bausteine!$A$2:$AY$76,9,FALSE))+IF(AC19="",0,VLOOKUP(AC19,Bausteine!$A$2:$AY$76,9,FALSE))+IF(AF19="",0,VLOOKUP(AF19,Bausteine!$A$2:$AY$76,9,FALSE))+IF(AG19="",0,VLOOKUP(AG19,Bausteine!$A$2:$AY$76,9,FALSE))+IF(AH19="",0,VLOOKUP(AH19,Bausteine!$A$2:$AY$76,9,FALSE))+IF(AQ19="",0,VLOOKUP(AQ19,Bausteine!$A$2:$AY$76,9,FALSE)) | V19: =IF(D19="",0,VLOOKUP(D19,Bausteine!$A$2:$AY$76,10,FALSE))-U19/IF(E19="",0,VLOOKUP(E19,Bausteine!$A$2:$AY$76,11,FALSE)) | W19: =IF(Y19<>"OK","",ROUND(MIN(IF(C19="",0,VLOOKUP(C19,Bausteine!$A$2:$AY$76,21,FALSE)),IF(AQ19="",0,VLOOKUP(AQ19,Bausteine!$A$2:$AY$76,21,FALSE)),IF(C19="",0,VLOOKUP(C19,Bausteine!$A$2:$AY$76,20,FALSE))*(V19/T19/(IF(C19="",0,VLOOKUP(C19,Bausteine!$A$2:$AY$76,19,FALSE))/IF(C19="",0,VLOOKUP(C19,Bausteine!$A$2:$AY$76,18,FALSE))))^Parameter!$B$3),0)) | X19: =IF(F19="",0,VLOOKUP(F19,Bausteine!$A$2:$AY$76,14,FALSE)) | Y19: =IFERROR(IF(OR(AD19<=0,AD19>1,R19<=0,T19<=0,V19<=0,U19>IF(E19="",0,VLOOKUP(E19,Bausteine!$A$2:$AY$76,12,FALSE)),T19>MIN(IF(C19="",0,VLOOKUP(C19,Bausteine!$A$2:$AY$76,22,FALSE)),IF(AQ19="",0,VLOOKUP(AQ19,Bausteine!$A$2:$AY$76,22,FALSE))),IF(E19="",0,VLOOKUP(E19,Bausteine!$A$2:$AY$76,11,FALSE))<=0,IF(E19="",0,VLOOKUP(E19,Bausteine!$A$2:$AY$76,11,FALSE))>1),"UNGUELTIG","OK"),"FEHLER") | Z19: 2250 | AA19: 55 | AB19: OFFLINE DRAFT: unverified roof artwork. Ordinary flame loadout already has lingering fire effects; no new ammunition compiler is implemented. | AD19: =IF(AC19="",1,IF(AC19="",0,VLOOKUP(AC19,Bausteine!$A$2:$AY$76,37,FALSE))/100) | AE19: =P19*AD19 | AF19: flame-turret | AG19: dragon-flamer | AH19: flame-fuel | AI19: =SUMIF(Startbesatzung!$A$2:$A$7,A19,Startbesatzung!$D$2:$D$7) | AJ19: =SUMIF(Startbesatzung!$A$2:$A$7,A19,Startbesatzung!$E$2:$E$7) | AK19: =MAX(0,IF(Startbesatzung!A2=A19,Startbesatzung!G2,0),IF(Startbesatzung!A3=A19,Startbesatzung!G3,0),IF(Startbesatzung!A4=A19,Startbesatzung!G4,0),IF(Startbesatzung!A5=A19,Startbesatzung!G5,0),IF(Startbesatzung!A6=A19,Startbesatzung!G6,0),IF(Startbesatzung!A7=A19,Startbesatzung!G7,0)) | AL19: =IF(AF19="","",IF(IF(AH19="",0,VLOOKUP(AH19,Bausteine!$A$2:$AY$76,38,FALSE))>0,IF(AH19="",0,VLOOKUP(AH19,Bausteine!$A$2:$AY$76,38,FALSE)),IF(AG19="",0,VLOOKUP(AG19,Bausteine!$A$2:$AY$76,28,FALSE)))) | AM19: =IF(AF19="","",IF(AG19="",0,VLOOKUP(AG19,Bausteine!$A$2:$AY$76,44,FALSE))) | AN19: =IF(AF19="","",IF(AF19="",0,VLOOKUP(AF19,Bausteine!$A$2:$AY$76,27,FALSE))) | AO19: =IF(AF19="","",IF(AF19="",0,VLOOKUP(AF19,Bausteine!$A$2:$AY$76,25,FALSE))) | AP19: =IF(AF19="","",IF(AH19="",0,VLOOKUP(AH19,Bausteine!$A$2:$AY$76,29,FALSE))) | AQ19: tracks-superheavy | AR19: =IF(AQ19="",0,VLOOKUP(AQ19,Bausteine!$A$2:$AY$76,48,FALSE)) | AS19: =MIN(IF(AQ19="",0,VLOOKUP(AQ19,Bausteine!$A$2:$AY$76,50,FALSE)),IF(C19="",0,VLOOKUP(C19,Bausteine!$A$2:$AY$76,51,FALSE)))
A20: Overlord Gatling | B20: china | C20: overlord-chassis | D20: diesel-heavy | E20: baseline-generator | F20: heavy | G20: heavy-twin-turret | H20: overlord-cannon | I20: heavy-shell | M20: =IF(C20="",0,VLOOKUP(C20,Bausteine!$A$2:$AY$76,4,FALSE))+IF(D20="",0,VLOOKUP(D20,Bausteine!$A$2:$AY$76,4,FALSE))+IF(E20="",0,VLOOKUP(E20,Bausteine!$A$2:$AY$76,4,FALSE))+IF(F20="",0,VLOOKUP(F20,Bausteine!$A$2:$AY$76,4,FALSE))+IF(G20="",0,VLOOKUP(G20,Bausteine!$A$2:$AY$76,4,FALSE))+IF(H20="",0,VLOOKUP(H20,Bausteine!$A$2:$AY$76,4,FALSE))+IF(I20="",0,VLOOKUP(I20,Bausteine!$A$2:$AY$76,4,FALSE))+IF(J20="",0,VLOOKUP(J20,Bausteine!$A$2:$AY$76,4,FALSE))+IF(K20="",0,VLOOKUP(K20,Bausteine!$A$2:$AY$76,4,FALSE))+IF(L20="",0,VLOOKUP(L20,Bausteine!$A$2:$AY$76,4,FALSE))+IF(AC20="",0,VLOOKUP(AC20,Bausteine!$A$2:$AY$76,4,FALSE))+IF(AF20="",0,VLOOKUP(AF20,Bausteine!$A$2:$AY$76,4,FALSE))+IF(AG20="",0,VLOOKUP(AG20,Bausteine!$A$2:$AY$76,4,FALSE))+IF(AH20="",0,VLOOKUP(AH20,Bausteine!$A$2:$AY$76,4,FALSE))+IF(AQ20="",0,VLOOKUP(AQ20,Bausteine!$A$2:$AY$76,4,FALSE)) | N20: =IF(C20="",0,VLOOKUP(C20,Bausteine!$A$2:$AY$76,5,FALSE))+IF(D20="",0,VLOOKUP(D20,Bausteine!$A$2:$AY$76,5,FALSE))+IF(E20="",0,VLOOKUP(E20,Bausteine!$A$2:$AY$76,5,FALSE))+IF(F20="",0,VLOOKUP(F20,Bausteine!$A$2:$AY$76,5,FALSE))+IF(G20="",0,VLOOKUP(G20,Bausteine!$A$2:$AY$76,5,FALSE))+IF(H20="",0,VLOOKUP(H20,Bausteine!$A$2:$AY$76,5,FALSE))+IF(I20="",0,VLOOKUP(I20,Bausteine!$A$2:$AY$76,5,FALSE))+IF(J20="",0,VLOOKUP(J20,Bausteine!$A$2:$AY$76,5,FALSE))+IF(K20="",0,VLOOKUP(K20,Bausteine!$A$2:$AY$76,5,FALSE))+IF(L20="",0,VLOOKUP(L20,Bausteine!$A$2:$AY$76,5,FALSE))+IF(AC20="",0,VLOOKUP(AC20,Bausteine!$A$2:$AY$76,5,FALSE))+IF(AF20="",0,VLOOKUP(AF20,Bausteine!$A$2:$AY$76,5,FALSE))+IF(AG20="",0,VLOOKUP(AG20,Bausteine!$A$2:$AY$76,5,FALSE))+IF(AH20="",0,VLOOKUP(AH20,Bausteine!$A$2:$AY$76,5,FALSE))+IF(AQ20="",0,VLOOKUP(AQ20,Bausteine!$A$2:$AY$76,5,FALSE)) | O20: =MAX(IF(C20="",0,VLOOKUP(C20,Bausteine!$A$2:$AY$76,6,FALSE)),IF(D20="",0,VLOOKUP(D20,Bausteine!$A$2:$AY$76,6,FALSE)),IF(E20="",0,VLOOKUP(E20,Bausteine!$A$2:$AY$76,6,FALSE)),IF(F20="",0,VLOOKUP(F20,Bausteine!$A$2:$AY$76,6,FALSE)),IF(G20="",0,VLOOKUP(G20,Bausteine!$A$2:$AY$76,6,FALSE)),IF(H20="",0,VLOOKUP(H20,Bausteine!$A$2:$AY$76,6,FALSE)),IF(I20="",0,VLOOKUP(I20,Bausteine!$A$2:$AY$76,6,FALSE)),IF(J20="",0,VLOOKUP(J20,Bausteine!$A$2:$AY$76,6,FALSE)),IF(K20="",0,VLOOKUP(K20,Bausteine!$A$2:$AY$76,6,FALSE)),IF(L20="",0,VLOOKUP(L20,Bausteine!$A$2:$AY$76,6,FALSE)),IF(AC20="",0,VLOOKUP(AC20,Bausteine!$A$2:$AY$76,6,FALSE)),IF(AF20="",0,VLOOKUP(AF20,Bausteine!$A$2:$AY$76,6,FALSE)),IF(AG20="",0,VLOOKUP(AG20,Bausteine!$A$2:$AY$76,6,FALSE)),IF(AH20="",0,VLOOKUP(AH20,Bausteine!$A$2:$AY$76,6,FALSE)),IF(AQ20="",0,VLOOKUP(AQ20,Bausteine!$A$2:$AY$76,6,FALSE)),AK20) | P20: =IF(C20="",0,VLOOKUP(C20,Bausteine!$A$2:$AY$76,7,FALSE))*IF(F20="",0,VLOOKUP(F20,Bausteine!$A$2:$AY$76,17,FALSE))/100+IF(D20="",0,VLOOKUP(D20,Bausteine!$A$2:$AY$76,7,FALSE))+IF(E20="",0,VLOOKUP(E20,Bausteine!$A$2:$AY$76,7,FALSE))+IF(G20="",0,VLOOKUP(G20,Bausteine!$A$2:$AY$76,7,FALSE))+IF(H20="",0,VLOOKUP(H20,Bausteine!$A$2:$AY$76,7,FALSE))+IF(I20="",0,VLOOKUP(I20,Bausteine!$A$2:$AY$76,7,FALSE))+IF(J20="",0,VLOOKUP(J20,Bausteine!$A$2:$AY$76,7,FALSE))+IF(K20="",0,VLOOKUP(K20,Bausteine!$A$2:$AY$76,7,FALSE))+IF(L20="",0,VLOOKUP(L20,Bausteine!$A$2:$AY$76,7,FALSE))+IF(AC20="",0,VLOOKUP(AC20,Bausteine!$A$2:$AY$76,7,FALSE))+IF(AF20="",0,VLOOKUP(AF20,Bausteine!$A$2:$AY$76,7,FALSE))+IF(AG20="",0,VLOOKUP(AG20,Bausteine!$A$2:$AY$76,7,FALSE))+IF(AH20="",0,VLOOKUP(AH20,Bausteine!$A$2:$AY$76,7,FALSE))+IF(AQ20="",0,VLOOKUP(AQ20,Bausteine!$A$2:$AY$76,7,FALSE))+AI20 | Q20: =N20*Parameter!$B$2 | R20: =AE20-Q20 | S20: =IF(C20="",0,VLOOKUP(C20,Bausteine!$A$2:$AY$76,13,FALSE))*IF(F20="",0,VLOOKUP(F20,Bausteine!$A$2:$AY$76,16,FALSE))/100 | T20: =IF(C20="",0,VLOOKUP(C20,Bausteine!$A$2:$AY$76,8,FALSE))*IF(F20="",0,VLOOKUP(F20,Bausteine!$A$2:$AY$76,15,FALSE))/100+IF(D20="",0,VLOOKUP(D20,Bausteine!$A$2:$AY$76,8,FALSE))+IF(E20="",0,VLOOKUP(E20,Bausteine!$A$2:$AY$76,8,FALSE))+IF(G20="",0,VLOOKUP(G20,Bausteine!$A$2:$AY$76,8,FALSE))+IF(H20="",0,VLOOKUP(H20,Bausteine!$A$2:$AY$76,8,FALSE))+IF(I20="",0,VLOOKUP(I20,Bausteine!$A$2:$AY$76,8,FALSE))+IF(J20="",0,VLOOKUP(J20,Bausteine!$A$2:$AY$76,8,FALSE))+IF(K20="",0,VLOOKUP(K20,Bausteine!$A$2:$AY$76,8,FALSE))+IF(L20="",0,VLOOKUP(L20,Bausteine!$A$2:$AY$76,8,FALSE))+IF(AC20="",0,VLOOKUP(AC20,Bausteine!$A$2:$AY$76,8,FALSE))+IF(AF20="",0,VLOOKUP(AF20,Bausteine!$A$2:$AY$76,8,FALSE))+IF(AG20="",0,VLOOKUP(AG20,Bausteine!$A$2:$AY$76,8,FALSE))+IF(AH20="",0,VLOOKUP(AH20,Bausteine!$A$2:$AY$76,8,FALSE))+IF(AQ20="",0,VLOOKUP(AQ20,Bausteine!$A$2:$AY$76,8,FALSE))+AJ20 | U20: =IF(C20="",0,VLOOKUP(C20,Bausteine!$A$2:$AY$76,9,FALSE))+IF(D20="",0,VLOOKUP(D20,Bausteine!$A$2:$AY$76,9,FALSE))+IF(E20="",0,VLOOKUP(E20,Bausteine!$A$2:$AY$76,9,FALSE))+IF(F20="",0,VLOOKUP(F20,Bausteine!$A$2:$AY$76,9,FALSE))+IF(G20="",0,VLOOKUP(G20,Bausteine!$A$2:$AY$76,9,FALSE))+IF(H20="",0,VLOOKUP(H20,Bausteine!$A$2:$AY$76,9,FALSE))+IF(I20="",0,VLOOKUP(I20,Bausteine!$A$2:$AY$76,9,FALSE))+IF(J20="",0,VLOOKUP(J20,Bausteine!$A$2:$AY$76,9,FALSE))+IF(K20="",0,VLOOKUP(K20,Bausteine!$A$2:$AY$76,9,FALSE))+IF(L20="",0,VLOOKUP(L20,Bausteine!$A$2:$AY$76,9,FALSE))+IF(AC20="",0,VLOOKUP(AC20,Bausteine!$A$2:$AY$76,9,FALSE))+IF(AF20="",0,VLOOKUP(AF20,Bausteine!$A$2:$AY$76,9,FALSE))+IF(AG20="",0,VLOOKUP(AG20,Bausteine!$A$2:$AY$76,9,FALSE))+IF(AH20="",0,VLOOKUP(AH20,Bausteine!$A$2:$AY$76,9,FALSE))+IF(AQ20="",0,VLOOKUP(AQ20,Bausteine!$A$2:$AY$76,9,FALSE)) | V20: =IF(D20="",0,VLOOKUP(D20,Bausteine!$A$2:$AY$76,10,FALSE))-U20/IF(E20="",0,VLOOKUP(E20,Bausteine!$A$2:$AY$76,11,FALSE)) | W20: =IF(Y20<>"OK","",ROUND(MIN(IF(C20="",0,VLOOKUP(C20,Bausteine!$A$2:$AY$76,21,FALSE)),IF(AQ20="",0,VLOOKUP(AQ20,Bausteine!$A$2:$AY$76,21,FALSE)),IF(C20="",0,VLOOKUP(C20,Bausteine!$A$2:$AY$76,20,FALSE))*(V20/T20/(IF(C20="",0,VLOOKUP(C20,Bausteine!$A$2:$AY$76,19,FALSE))/IF(C20="",0,VLOOKUP(C20,Bausteine!$A$2:$AY$76,18,FALSE))))^Parameter!$B$3),0)) | X20: =IF(F20="",0,VLOOKUP(F20,Bausteine!$A$2:$AY$76,14,FALSE)) | Y20: =IFERROR(IF(OR(AD20<=0,AD20>1,R20<=0,T20<=0,V20<=0,U20>IF(E20="",0,VLOOKUP(E20,Bausteine!$A$2:$AY$76,12,FALSE)),T20>MIN(IF(C20="",0,VLOOKUP(C20,Bausteine!$A$2:$AY$76,22,FALSE)),IF(AQ20="",0,VLOOKUP(AQ20,Bausteine!$A$2:$AY$76,22,FALSE))),IF(E20="",0,VLOOKUP(E20,Bausteine!$A$2:$AY$76,11,FALSE))<=0,IF(E20="",0,VLOOKUP(E20,Bausteine!$A$2:$AY$76,11,FALSE))>1),"UNGUELTIG","OK"),"FEHLER") | Z20: 2000 | AA20: 54 | AB20: Separate roof carrier; retains main cannon. Gatling spin-up and sensors reuse existing templates. | AD20: =IF(AC20="",1,IF(AC20="",0,VLOOKUP(AC20,Bausteine!$A$2:$AY$76,37,FALSE))/100) | AE20: =P20*AD20 | AF20: gatling-roof-carrier | AG20: gatling-gun | AH20: gatling-rounds | AI20: =SUMIF(Startbesatzung!$A$2:$A$7,A20,Startbesatzung!$D$2:$D$7) | AJ20: =SUMIF(Startbesatzung!$A$2:$A$7,A20,Startbesatzung!$E$2:$E$7) | AK20: =MAX(0,IF(Startbesatzung!A2=A20,Startbesatzung!G2,0),IF(Startbesatzung!A3=A20,Startbesatzung!G3,0),IF(Startbesatzung!A4=A20,Startbesatzung!G4,0),IF(Startbesatzung!A5=A20,Startbesatzung!G5,0),IF(Startbesatzung!A6=A20,Startbesatzung!G6,0),IF(Startbesatzung!A7=A20,Startbesatzung!G7,0)) | AL20: =IF(AF20="","",IF(IF(AH20="",0,VLOOKUP(AH20,Bausteine!$A$2:$AY$76,38,FALSE))>0,IF(AH20="",0,VLOOKUP(AH20,Bausteine!$A$2:$AY$76,38,FALSE)),IF(AG20="",0,VLOOKUP(AG20,Bausteine!$A$2:$AY$76,28,FALSE)))) | AM20: =IF(AF20="","",IF(AG20="",0,VLOOKUP(AG20,Bausteine!$A$2:$AY$76,44,FALSE))) | AN20: =IF(AF20="","",IF(AF20="",0,VLOOKUP(AF20,Bausteine!$A$2:$AY$76,27,FALSE))) | AO20: =IF(AF20="","",IF(AF20="",0,VLOOKUP(AF20,Bausteine!$A$2:$AY$76,25,FALSE))) | AP20: =IF(AF20="","",IF(AH20="",0,VLOOKUP(AH20,Bausteine!$A$2:$AY$76,29,FALSE))) | AQ20: tracks-superheavy | AR20: =IF(AQ20="",0,VLOOKUP(AQ20,Bausteine!$A$2:$AY$76,48,FALSE)) | AS20: =MIN(IF(AQ20="",0,VLOOKUP(AQ20,Bausteine!$A$2:$AY$76,50,FALSE)),IF(C20="",0,VLOOKUP(C20,Bausteine!$A$2:$AY$76,51,FALSE)))
