Workbook
Name ComponentIDs: 'Bausteine'!$A$2:$A$46
Name InfantryIDs: 'Infanterie'!$A$2:$A$4

Sheet Hinweise
A1: YMCA Modular – Kalibrierung
A2: Referenz | B2: Quellblock-Abgleich: 9d8a9dec (integrierter Game-Stand), siehe reference-audit.md.
A3: Status | B3: Experimentelle Zahlen; keine Spielregeln oder grafische/volle Verhaltensgleichheit.
A4: Eingaben | B4: Parameter und Bausteinwerte sind editierbar. Formeln berechnen Entwuerfe/Vergleich beim Öffnen neu.
A5: Preise | B5: Hardwarekosten minus CP-Anforderung mal globaler CP-Creditwert. Keine Sonderrabatte.
A6: Massenproduktion | B6: Separates Fertigungsmodul: vorläufig 95% aller Hardwarekosten, danach globaler CP-Abzug. Preisfit ist separate Studie.
A7: Arbeitsfluss | B7: catalog.json ist Quelle. export_excel.py erzeugt eine neue Momentaufnahme, kein Excel-Import.
A8: Schutz | B8: Exporter überschreibt keine bestehende Arbeitsmappe; für neue Daten neuen Dateinamen verwenden.
A9: Erweiterung | B9: Neue Bausteine/Designs in JSON eintragen und neu exportieren. Manuelles Zeilenanfügen wird nicht automatisch verdrahtet.
A10: Validierung | B10: Excel prüft nur elektrische/physische Grenzen; Rolle, Fraktion, Montage und Besatzungskosten-Konsistenz im Python-Rechner prüfen.
A11: Bunkerpreis | B11: Leeres Bunkermodul plus separat gewählte Startbesatzung. Infanteriepreise und Besatzungszeilen sind editierbar; Kosten/Masse werden einmal addiert.
A12: Aufsatzplatz | B12: Gatling, Bunker und Lautsprecher teilen roof. Vollständige Slot-/Fraktions-/Kapazitätsprüfung weiterhin im Python-Rechner.
A13: Grafikentwürfe | B13: Flame/Mortar Roof / draft sind nur Offline-Kalkulation. Sprites geprüft, Montage auf Overlord noch nicht. Kein Originalvergleich oder spielbarer Actor.
... A19: Referenzbedingungen | B19: Base states without isotope stability, horde, uranium or veterancy bonuses. Isotope stability now applies 90% received damage as well as death-explosion suppression; not modeled as extra HP.

Sheet Parameter
A1: Parameter | B1: Wert
A2: Credits pro CP | B2: 300
A3: Geschwindigkeitsexponent | B3: 0.5
A4: Katalogbudget | B4: 50

Sheet Bausteine
A1: ID | B1: Rolle | C1: Fraktionen | D1: Katalog-Tier | E1: CP | F1: Tech | G1: Hardwarepreis | H1: Masse kg | I1: Bedarf kWe | J1: Motor kWm | K1: Generator Wirkungsgrad | L1: Generator max kWe | M1: HP Chassis | N1: Panzerung | O1: Chassis Masse % | P1: Chassis HP % | Q1: Chassis Preis % | R1: Referenzmasse kg | S1: Referenzleistung kWm | T1: Referenztempo | U1: Max Tempo | V1: Max Masse kg | W1: Waffentraegerplaetze | X1: Zusatzplaetze | Y1: Salve | Z1: Schussabstand Ticks | AA1: Nachladen Ticks | AB1: Reichweite Zellen | AC1: Rohschaden | AD1: Hinweis | AE1: Quelle | AF1: Kompatibilitaet | AG1: Ausrüstung erlaubt | AH1: Waffen erlaubt | AI1: Munition erlaubt | AJ1: Anzeigename | AK1: Hardware Fertigung % | AL1: Munition Reichweite Override | AM1: Transportkapazitaet | AN1: Ausschluesse | AO1: Aufsatzplatz | AP1: Zusatztraeger erlaubt | AQ1: Infanterie erlaubt | AR1: Mindestreichweite Zellen | AS1: Feuerverzug Ticks
A2: mortar-roof-carrier | B2: carrier | C2: ["china"] | D2: 1 | E2: 0 | F2: 3 | G2: 200 | H2: 400 | I2: 2 | J2: 0 | K2: 0 | L2: 0 | M2: 0 | O2: 0 | P2: 0 | Q2: 0 | R2: 0 | S2: 0 | T2: 0 | U2: 0 | V2: 0 | W2: 0 | X2: 0 | Y2: 1 | Z2: 0 | AA2: 60 | AB2: 0 | AC2: 0 | AD2: Experimental China gameplay carrier using existing artillery artwork, not Allied weapon access. Proposed 200-credit mount, 12 turn speed. Offset, scale, recoil and muzzle on Overlord not live-tested; infantry Mortar FireDelay 15 retained as a trial. | AE2: batf.artillery.turret / artytur.shp | AH2: ["roof-mortar"] | AJ2: Leichter Artillerie-Aufsatzturm | AK2: 0 | AL2: 0 | AM2: 0 | AN2: 0 | AO2: 0 | AP2: 0 | AQ2: 0 | AR2: 0 | AS2: 15
A3: roof-mortar | B3: weapon | C3: ["china"] | D3: 1 | E3: 0 | F3: 3 | G3: 350 | H3: 600 | I3: 3 | J3: 0 | K3: 0 | L3: 0 | M3: 0 | O3: 0 | P3: 0 | Q3: 0 | R3: 0 | S3: 0 | T3: 0 | U3: 0 | V3: 0 | W3: 0 | X3: 0 | Y3: 0 | Z3: 0 | AA3: 0 | AB3: 11 | AC3: 0 | AD3: Existing BulletCA: speed 166, launch angle 92, inaccuracy 768, BOMB image. New vehicle price, mass and power are proposals, not inferred from 150-credit infantry. | AE3: Mortar / MortarPrototype | AI3: ["mortar-he"] | AJ3: Leichter Fahrzeugmoerser | AK3: 0 | AL3: 0 | AM3: 0 | AN3: 0 | AO3: 0 | AP3: 0 | AQ3: 0 | AR3: 1 | AS3: 0
A4: mortar-he | B4: ammunition | C4: ["china"] | D4: 0 | E4: 0 | F4: 3 | G4: 100 | H4: 300 | I4: 0 | J4: 0 | K4: 0 | L4: 0 | M4: 0 | O4: 0 | P4: 0 | Q4: 0 | R4: 0 | S4: 0 | T4: 0 | U4: 0 | V4: 0 | W4: 0 | X4: 0 | Y4: 0 | Z4: 0 | AA4: 0 | AB4: 0 | AC4: 5500 | AD4: Raw primary damage only, not DPS. Full impact/smudge/water effects belong to existing payload template; no compiler yet. | AE4: MortarPrototype | AJ4: Moerser-Sprenggranaten | AK4: 0 | AL4: 0 | AM4: 0 | AN4: 0 | AO4: 0 | AP4: 0 | AQ4: 0 | AR4: 0 | AS4: 0
A5: overlord-chassis | B5: chassis | C5: ["china"] | D5: 3 | E5: 0 | F5: 2 | G5: 1000 | H5: 25000 | I5: 10 | J5: 0 | K5: 0 | L5: 0 | M5: 95000 | O5: 0 | P5: 0 | Q5: 0 | R5: 32000 | S5: 960 | T5: 56 | U5: 70 | V5: 45000 | W5: 2 | X5: 3 | Y5: 0 | Z5: 0 | AA5: 0 | AB5: 0 | AC5: 0 | AD5: Main heavy carrier plus shared roof slot for an approved auxiliary carrier, bunker or speaker. Emperor 80% received-damage modifier is excluded from base state. | AE5: choverlord | AF5: {"carrier": ["heavy-twin-turret"], "drive": ["diesel-heavy", "diesel-heavy-boost"]} | AG5: ["pdl", "propaganda-speaker", "firing-bunker"] | AJ5: Schweres Kettenfahrgestell (Overlord) | AK5: 0 | AL5: 0 | AM5: 0 | AN5: 0 | AO5: 0 | AP5: {"slot": "roof", "carriers": ["gatling-roof-carrier"], "experimental_carriers": ["flame-turret", "mortar-roof-carrier"]} | AQ5: 0 | AR5: 0 | AS5: 0
A6: diesel-heavy | B6: drive | C6: ["china", "gdi", "soviet"] | D6: 1 | E6: 0 | F6: 2 | G6: 300 | H6: 2000 | I6: 0 | J6: 1000 | K6: 0 | L6: 0 | M6: 0 | O6: 0 | P6: 0 | Q6: 0 | R6: 0 | S6: 0 | T6: 0 | U6: 0 | V6: 0 | W6: 0 | X6: 0 | Y6: 0 | Z6: 0 | AA6: 0 | AB6: 0 | AC6: 0 | AD6: New provisional heavy family, not a formula derived from engine size. | AJ6: Schwerer Dieselmotor | AK6: 0 | AL6: 0 | AM6: 0 | AN6: 0 | AO6: 0 | AP6: 0 | AQ6: 0 | AR6: 0 | AS6: 0
A7: diesel-heavy-boost | B7: drive | C7: ["china", "gdi", "soviet"] | D7: 2 | E7: 0 | F7: 2 | G7: 400 | H7: 2000 | I7: 0 | J7: 1045 | K7: 0 | L7: 0 | M7: 0 | O7: 0 | P7: 0 | Q7: 0 | R7: 0 | S7: 0 | T7: 0 | U7: 0 | V7: 0 | W7: 0 | X7: 0 | Y7: 0 | Z7: 0 | AA7: 0 | AB7: 0 | AC7: 0 | AJ7: Leistungsgesteigerter schwerer Dieselmotor | AK7: 0 | AL7: 0 | AM7: 0 | AN7: 0 | AO7: 0 | AP7: 0 | AQ7: 0 | AR7: 0 | AS7: 0
A8: heavy-twin-turret | B8: carrier | C8: ["china"] | D8: 0 | E8: 0 | F8: 2 | G8: 250 | H8: 2000 | I8: 0 | J8: 0 | K8: 0 | L8: 0 | M8: 0 | O8: 0 | P8: 0 | Q8: 0 | R8: 0 | S8: 0 | T8: 0 | U8: 0 | V8: 0 | W8: 0 | X8: 0 | Y8: 2 | Z8: 6 | AA8: 90 | AB8: 0 | AC8: 0 | AD8: Normal, nuclear and speaker artwork bindings must select appropriate existing turret sequences; no claim of arbitrary visual interchangeability. | AE8: OverlordCannon | AH8: ["overlord-cannon"] | AJ8: Schwerer Zwillingsgeschützturm | AK8: 0 | AL8: 0 | AM8: 0 | AN8: 0 | AO8: 0 | AP8: 0 | AQ8: 0 | AR8: 0 | AS8: 0
A9: overlord-cannon | B9: weapon | C9: ["china"] | D9: 0 | E9: 0 | F9: 2 | G9: 300 | H9: 1500 | I9: 0 | J9: 0 | K9: 0 | L9: 0 | M9: 0 | O9: 0 | P9: 0 | Q9: 0 | R9: 0 | S9: 0 | T9: 0 | U9: 0 | V9: 0 | W9: 0 | X9: 0 | Y9: 0 | Z9: 0 | AA9: 0 | AB9: 5 | AC9: 0 | AE9: OverlordCannon | AI9: ["heavy-shell", "heavy-nuclear-shell"] | AJ9: Schwere Panzerkanone | AK9: 0 | AL9: 0 | AM9: 0 | AN9: 0 | AO9: 0 | AP9: 0 | AQ9: 0 | AR9: 0 | AS9: 0
A10: heavy-shell | B10: ammunition | C10: ["china"] | D10: 0 | E10: 0 | F10: 2 | G10: 150 | H10: 1500 | I10: 0 | J10: 0 | K10: 0 | L10: 0 | M10: 0 | O10: 0 | P10: 0 | Q10: 0 | R10: 0 | S10: 0 | T10: 0 | U10: 0 | V10: 0 | W10: 0 | X10: 0 | Y10: 0 | Z10: 0 | AA10: 0 | AB10: 0 | AC10: 8000 | AE10: OverlordCannon | AJ10: Schwere Panzergranaten | AK10: 0 | AL10: 0 | AM10: 0 | AN10: 0 | AO10: 0 | AP10: 0 | AQ10: 0 | AR10: 0 | AS10: 0
A11: heavy-nuclear-shell | B11: ammunition | C11: ["china"] | D11: 1 | E11: 1 | F11: 3 | G11: 950 | H11: 1500 | I11: 0 | J11: 0 | K11: 0 | L11: 0 | M11: 0 | O11: 0 | P11: 0 | Q11: 0 | R11: 0 | S11: 0 | T11: 0 | U11: 0 | V11: 0 | W11: 0 | X11: 0 | Y11: 0 | Z11: 0 | AA11: 0 | AB11: 0 | AC11: 24000 | AD11: Base nuclear Overlord price fits +800 hardware minus 300/CP. Full radiation/projectile/effect rules reused later; no nuclear motor implied. | AE11: OverlordCannonNuclear | AJ11: Schwere Nukleargranaten | AK11: 0 | AL11: 5.5 | AM11: 0 | AN11: 0 | AO11: 0 | AP11: 0 | AQ11: 0 | AR11: 0 | AS11: 0
A12: firing-bunker | B12: equipment | C12: ["china"] | D12: 1 | E12: 1 | F12: 3 | G12: 100 | H12: 600 | I12: 5 | J12: 0 | K12: 0 | L12: 0 | M12: 0 | O12: 0 | P12: 0 | Q12: 0 | R12: 0 | S12: 0 | T12: 0 | U12: 0 | V12: 0 | W12: 0 | X12: 0 | Y12: 0 | Z12: 0 | AA12: 0 | AB12: 0 | AC12: 0 | AD12: Empty module. Start crew is a separate design selection; price/mass added once. Empty cost/mass experimental. PDL composition uses ^AttackingCargoAndPDL; requires turretbunker artwork. | AE12: ^AttackingCargoAndTurret | AJ12: Besetzbarer Bunker | AK12: 0 | AL12: 0 | AM12: 4 | AN12: 0 | AO12: roof | AP12: 0 | AQ12: ["che1", "che3", "minigunner"] | AR12: 0 | AS12: 0
A13: gatling-roof-carrier | B13: carrier | C13: ["china"] | D13: 1 | E13: 1 | F13: 3 | G13: 50 | H13: 300 | I13: 5 | J13: 0 | K13: 0 | L13: 0 | M13: 0 | O13: 0 | P13: 0 | Q13: 0 | R13: 0 | S13: 0 | T13: 0 | U13: 0 | V13: 0 | W13: 0 | X13: 0 | Y13: 1 | Z13: 0 | AA13: 12 | AB13: 0 | AC13: 0 | AD13: Shares gatling weapon/ammunition. Complete legacy behavior includes sensor equipment, ground/AA spin-up and turretgat sprite; 50-credit carrier allocation is a provisional fit, not intrinsic market value. | AE13: ^ChinaGatlingOverlord + ^SensorEquipment | AH13: ["gatling-gun"] | AJ13: Gatling-Aufsatzturm | AK13: 0 | AL13: 0 | AM13: 0 | AN13: 0 | AO13: 0 | AP13: 0 | AQ13: 0 | AR13: 0 | AS13: 0
A14: propaganda-speaker | B14: equipment | C14: ["china"] | D14: 1 | E14: 1 | F14: 3 | G14: 500 | H14: 500 | I14: 20 | J14: 0 | K14: 0 | L14: 0 | M14: 0 | O14: 0 | P14: 0 | Q14: 0 | R14: 0 | S14: 0 | T14: 0 | U14: 0 | V14: 0 | W14: 0 | X14: 0 | Y14: 0 | Z14: 0 | AA14: 0 | AB14: 0 | AC14: 0 | AD14: Existing aura/upgrade traits to reuse. +500 hardware minus 300/CP fits base price; mass and load deliberately expose speed residuals. | AE14: ^PropagandaSpeaker | AJ14: Propagandalautsprecher | AK14: 0 | AL14: 0 | AM14: 0 | AN14: 0 | AO14: roof | AP14: 0 | AQ14: 0 | AR14: 0 | AS14: 0
A15: battlemaster | B15: chassis | C15: ["china"] | D15: 1 | E15: 0 | F15: 1 | G15: 500 | H15: 8000 | I15: 10 | J15: 0 | K15: 0 | L15: 0 | M15: 40000 | O15: 0 | P15: 0 | Q15: 0 | R15: 10000 | S15: 460 | T15: 100 | U15: 125 | V15: 18000 | W15: 1 | X15: 1 | Y15: 0 | Z15: 0 | AA15: 0 | AB15: 0 | AC15: 0 | AF15: {"carrier": ["cannon-turret", "autoloader-turret"], "drive": ["diesel", "diesel-large", "nuclear"]} | AG15: ["pdl"] | AJ15: Type 59 Chassis | AK15: 0 | AL15: 0 | AM15: 0 | AN15: 0 | AO15: 0 | AP15: 0 | AQ15: 0 | AR15: 0 | AS15: 0
A16: mass-production | B16: manufacturing | C16: ["china"] | D16: 0 | E16: 1 | F16: 1 | G16: 0 | H16: 0 | I16: 0 | J16: 0 | K16: 0 | L16: 0 | M16: 0 | O16: 0 | P16: 0 | Q16: 0 | R16: 0 | S16: 0 | T16: 0 | U16: 0 | V16: 0 | W16: 0 | X16: 0 | Y16: 0 | Z16: 0 | AA16: 0 | AB16: 0 | AC16: 0 | AD16: Separate manufacturing selection, not chassis or physical equipment. Provisional 5% reduction of all hardware before global CP deduction; not the joint-fit optimum. No special per-design rebate. | AJ16: Massenproduktion | AK16: 95 | AL16: 0 | AM16: 0 | AN16: 0 | AO16: 0 | AP16: 0 | AQ16: 0 | AR16: 0 | AS16: 0
A17: dragon-chassis | B17: chassis | C17: ["china"] | D17: 1 | E17: 0 | F17: 1 | G17: 250 | H17: 6500 | I17: 10 | J17: 0 | K17: 0 | L17: 0 | M17: 28000 | O17: 0 | P17: 0 | Q17: 0 | R17: 8000 | S17: 460 | T17: 103 | U17: 125 | V17: 14000 | W17: 1 | X17: 1 | Y17: 0 | Z17: 0 | AA17: 0 | AB17: 0 | AC17: 0 | AD17: Base price/HP/speed fitted. Firewall deploy behavior and Black Napalm remain source references, not implemented. | AE17: chdragon | AF17: {"carrier": ["flame-turret"], "drive": ["diesel", "diesel-large"]} | AG17: ["pdl"] | AJ17: 0 | AK17: 0 | AL17: 0 | AM17: 0 | AN17: 0 | AO17: 0 | AP17: 0 | AQ17: 0 | AR17: 0 | AS17: 0
A18: gatling-chassis | B18: chassis | C18: ["china"] | D18: 1 | E18: 0 | F18: 1 | G18: 350 | H18: 7000 | I18: 10 | J18: 0 | K18: 0 | L18: 0 | M18: 30000 | O18: 0 | P18: 0 | Q18: 0 | R18: 9000 | S18: 460 | T18: 108 | U18: 130 | V18: 16000 | W18: 1 | X18: 1 | Y18: 0 | Z18: 0 | AA18: 0 | AB18: 0 | AC18: 0 | AD18: Legacy sight override 6c0; preserve as audit metadata, not a claim of standard sight equivalence. AA/ground spool-up not simulated. | AE18: chgtnk | AF18: {"carrier": ["gatling-turret"], "drive": ["diesel", "diesel-large"]} | AG18: ["pdl"] | AJ18: 0 | AK18: 0 | AL18: 0 | AM18: 0 | AN18: 0 | AO18: 0 | AP18: 0 | AQ18: 0 | AR18: 0 | AS18: 0
A19: flame-turret | B19: carrier | C19: ["china"] | D19: 0 | E19: 0 | F19: 1 | G19: 75 | H19: 400 | I19: 0 | J19: 0 | K19: 0 | L19: 0 | M19: 0 | O19: 0 | P19: 0 | Q19: 0 | R19: 0 | S19: 0 | T19: 0 | U19: 0 | V19: 0 | W19: 0 | X19: 0 | Y19: 8 | Z19: 4 | AA19: 45 | AB19: 0 | AC19: 0 | AD19: Normal attack only; deployed Firewall has additional armaments and state changes. | AE19: CHDragonFlamer | AH19: ["dragon-flamer"] | AJ19: 0 | AK19: 0 | AL19: 0 | AM19: 0 | AN19: 0 | AO19: 0 | AP19: 0 | AQ19: 0 | AR19: 0 | AS19: 0
A20: dragon-flamer | B20: weapon | C20: ["china"] | D20: 0 | E20: 0 | F20: 1 | G20: 125 | H20: 400 | I20: 0 | J20: 0 | K20: 0 | L20: 0 | M20: 0 | O20: 0 | P20: 0 | Q20: 0 | R20: 0 | S20: 0 | T20: 0 | U20: 0 | V20: 0 | W20: 0 | X20: 0 | Y20: 0 | Z20: 0 | AA20: 0 | AB20: 5 | AC20: 0 | AE20: CHDragonFlamer | AI20: ["flame-fuel"] | AJ20: 0 | AK20: 0 | AL20: 0 | AM20: 0 | AN20: 0 | AO20: 0 | AP20: 0 | AQ20: 0 | AR20: 0 | AS20: 0
A21: flame-fuel | B21: ammunition | C21: ["china"] | D21: 0 | E21: 0 | F21: 1 | G21: 50 | H21: 100 | I21: 0 | J21: 0 | K21: 0 | L21: 0 | M21: 0 | O21: 0 | P21: 0 | Q21: 0 | R21: 0 | S21: 0 | T21: 0 | U21: 0 | V21: 0 | W21: 0 | X21: 0 | Y21: 0 | Z21: 0 | AA21: 0 | AB21: 0 | AC21: 2500 | AD21: Raw primary warhead only; fire clusters, heat and garrison damage omitted from calculator. | AJ21: 0 | AK21: 0 | AL21: 0 | AM21: 0 | AN21: 0 | AO21: 0 | AP21: 0 | AQ21: 0 | AR21: 0 | AS21: 0
A22: gatling-turret | B22: carrier | C22: ["china"] | D22: 0 | E22: 0 | F22: 1 | G22: 100 | H22: 500 | I22: 0 | J22: 0 | K22: 0 | L22: 0 | M22: 0 | O22: 0 | P22: 0 | Q22: 0 | R22: 0 | S22: 0 | T22: 0 | U22: 0 | V22: 0 | W22: 0 | X22: 0 | Y22: 1 | Z22: 0 | AA22: 12 | AB22: 0 | AC22: 0 | AD22: Ground cold-state representative only. Reload stages 12/8/4/2 ticks, separate air/ground charge, thresholds 1/3/5, reset delay 40. Full attack-state behavior not modeled. | AE22: ^ChinaGatling | AH22: ["gatling-gun"] | AJ22: 0 | AK22: 0 | AL22: 0 | AM22: 0 | AN22: 0 | AO22: 0 | AP22: 0 | AQ22: 0 | AR22: 0 | AS22: 0
A23: gatling-gun | B23: weapon | C23: ["china"] | D23: 0 | E23: 0 | F23: 1 | G23: 150 | H23: 500 | I23: 0 | J23: 0 | K23: 0 | L23: 0 | M23: 0 | O23: 0 | P23: 0 | Q23: 0 | R23: 0 | S23: 0 | T23: 0 | U23: 0 | V23: 0 | W23: 0 | X23: 0 | Y23: 0 | Z23: 0 | AA23: 0 | AB23: 6 | AC23: 0 | AD23: Ground range 6 cells; AA uses ChinaMGatt.0 with range 9.5. Not a single fixed weapon. | AE23: ChinaMGatt.0G | AI23: ["gatling-rounds"] | AJ23: 0 | AK23: 0 | AL23: 0 | AM23: 0 | AN23: 0 | AO23: 0 | AP23: 0 | AQ23: 0 | AR23: 0 | AS23: 0
A24: gatling-rounds | B24: ammunition | C24: ["china"] | D24: 0 | E24: 0 | F24: 1 | G24: 100 | H24: 400 | I24: 0 | J24: 0 | K24: 0 | L24: 0 | M24: 0 | O24: 0 | P24: 0 | Q24: 0 | R24: 0 | S24: 0 | T24: 0 | U24: 0 | V24: 0 | W24: 0 | X24: 0 | Y24: 0 | Z24: 0 | AA24: 0 | AB24: 0 | AC24: 350 | AD24: Raw ground damage 350; AA raw damage 660. Values are not DPS. | AJ24: 0 | AK24: 0 | AL24: 0 | AM24: 0 | AN24: 0 | AO24: 0 | AP24: 0 | AQ24: 0 | AR24: 0 | AS24: 0
A25: juggernaut | B25: chassis | C25: ["gdi"] | D25: 3 | E25: 0 | F25: 3 | G25: 1100 | H25: 16000 | I25: 10 | J25: 0 | K25: 0 | L25: 0 | M25: 60000 | O25: 0 | P25: 0 | Q25: 0 | R25: 20000 | S25: 460 | T25: 50 | U25: 50 | V25: 30000 | W25: 1 | X25: 3 | Y25: 0 | Z25: 0 | AA25: 0 | AB25: 0 | AC25: 0 | AF25: {"carrier": ["fixed-triple"], "drive": ["diesel"]} | AG25: [] | AJ25: 0 | AK25: 0 | AL25: 0 | AM25: 0 | AN25: 0 | AO25: 0 | AP25: 0 | AQ25: 0 | AR25: 0 | AS25: 0
A26: heavy-tesla | B26: chassis | C26: ["soviet"] | D26: 2 | E26: 0 | F26: 2 | G26: 600 | H26: 8000 | I26: 10 | J26: 0 | K26: 0 | L26: 0 | M26: 48000 | O26: 0 | P26: 0 | Q26: 0 | R26: 10000 | S26: 260 | T26: 100 | U26: 110 | V26: 18000 | W26: 1 | X26: 2 | Y26: 0 | Z26: 0 | AA26: 0 | AB26: 0 | AC26: 0 | AF26: {"carrier": ["twin-coil"], "drive": ["diesel", "nuclear"]} | AG26: [] | AJ26: 0 | AK26: 0 | AL26: 0 | AM26: 0 | AN26: 0 | AO26: 0 | AP26: 0 | AQ26: 0 | AR26: 0 | AS26: 0
A27: diesel | B27: drive | C27: ["china", "gdi", "soviet"] | D27: 0 | E27: 0 | F27: 1 | G27: 100 | H27: 600 | I27: 0 | J27: 500 | K27: 0 | L27: 0 | M27: 0 | O27: 0 | P27: 0 | Q27: 0 | R27: 0 | S27: 0 | T27: 0 | U27: 0 | V27: 0 | W27: 0 | X27: 0 | Y27: 0 | Z27: 0 | AA27: 0 | AB27: 0 | AC27: 0 | AJ27: 0 | AK27: 0 | AL27: 0 | AM27: 0 | AN27: 0 | AO27: 0 | AP27: 0 | AQ27: 0 | AR27: 0 | AS27: 0
A28: diesel-large | B28: drive | C28: ["china", "gdi", "soviet"] | D28: 1 | E28: 0 | F28: 2 | G28: 200 | H28: 600 | I28: 0 | J28: 550 | K28: 0 | L28: 0 | M28: 0 | O28: 0 | P28: 0 | Q28: 0 | R28: 0 | S28: 0 | T28: 0 | U28: 0 | V28: 0 | W28: 0 | X28: 0 | Y28: 0 | Z28: 0 | AA28: 0 | AB28: 0 | AC28: 0 | AJ28: 0 | AK28: 0 | AL28: 0 | AM28: 0 | AN28: 0 | AO28: 0 | AP28: 0 | AQ28: 0 | AR28: 0 | AS28: 0
A29: nuclear | B29: drive | C29: ["china", "soviet"] | D29: 1 | E29: 1 | F29: 2 | G29: 400 | H29: 600 | I29: 0 | J29: 758.75 | K29: 0 | L29: 0 | M29: 0 | O29: 0 | P29: 0 | Q29: 0 | R29: 0 | S29: 0 | T29: 0 | U29: 0 | V29: 0 | W29: 0 | X29: 0 | Y29: 0 | Z29: 0 | AA29: 0 | AB29: 0 | AC29: 0 | AJ29: 0 | AK29: 0 | AL29: 0 | AM29: 0 | AN29: 0 | AO29: 0 | AP29: 0 | AQ29: 0 | AR29: 0 | AS29: 0
A30: baseline-generator | B30: generator | C30: ["china", "gdi", "soviet"] | D30: 0 | E30: 0 | F30: 1 | G30: 0 | H30: 0 | I30: 0 | J30: 0 | K30: 0.25 | L30: 100 | M30: 0 | O30: 0 | P30: 0 | Q30: 0 | R30: 0 | S30: 0 | T30: 0 | U30: 0 | V30: 0 | W30: 0 | X30: 0 | Y30: 0 | Z30: 0 | AA30: 0 | AB30: 0 | AC30: 0 | AJ30: 0 | AK30: 0 | AL30: 0 | AM30: 0 | AN30: 0 | AO30: 0 | AP30: 0 | AQ30: 0 | AR30: 0 | AS30: 0
A31: efficient-generator | B31: generator | C31: ["china", "gdi", "soviet"] | D31: 1 | E31: 0 | F31: 2 | G31: 200 | H31: 0 | I31: 0 | J31: 0 | K31: 0.75 | L31: 120 | M31: 0 | O31: 0 | P31: 0 | Q31: 0 | R31: 0 | S31: 0 | T31: 0 | U31: 0 | V31: 0 | W31: 0 | X31: 0 | Y31: 0 | Z31: 0 | AA31: 0 | AB31: 0 | AC31: 0 | AJ31: 0 | AK31: 0 | AL31: 0 | AM31: 0 | AN31: 0 | AO31: 0 | AP31: 0 | AQ31: 0 | AR31: 0 | AS31: 0
A32: heavy | B32: armor | C32: ["china", "gdi", "soviet"] | D32: 0 | E32: 0 | F32: 1 | G32: 0 | H32: 0 | I32: 0 | J32: 0 | K32: 0 | L32: 0 | M32: 0 | N32: Heavy | O32: 100 | P32: 100 | Q32: 100 | R32: 0 | S32: 0 | T32: 0 | U32: 0 | V32: 0 | W32: 0 | X32: 0 | Y32: 0 | Z32: 0 | AA32: 0 | AB32: 0 | AC32: 0 | AJ32: 0 | AK32: 0 | AL32: 0 | AM32: 0 | AN32: 0 | AO32: 0 | AP32: 0 | AQ32: 0 | AR32: 0 | AS32: 0
A33: reflector | B33: armor | C33: ["china", "gdi", "soviet"] | D33: 1 | E33: 1 | F33: 3 | G33: 0 | H33: 0 | I33: 57.5 | J33: 0 | K33: 0 | L33: 0 | M33: 0 | N33: Reflector | O33: 100 | P33: 100 | Q33: 100 | R33: 0 | S33: 0 | T33: 0 | U33: 0 | V33: 0 | W33: 0 | X33: 0 | Y33: 0 | Z33: 0 | AA33: 0 | AB33: 0 | AC33: 0 | AJ33: 0 | AK33: 0 | AL33: 0 | AM33: 0 | AN33: 0 | AO33: 0 | AP33: 0 | AQ33: 0 | AR33: 0 | AS33: 0
A34: cannon-turret | B34: carrier | C34: ["china"] | D34: 0 | E34: 0 | F34: 1 | G34: 100 | H34: 500 | I34: 0 | J34: 0 | K34: 0 | L34: 0 | M34: 0 | O34: 0 | P34: 0 | Q34: 0 | R34: 0 | S34: 0 | T34: 0 | U34: 0 | V34: 0 | W34: 0 | X34: 0 | Y34: 1 | Z34: 0 | AA34: 50 | AB34: 0 | AC34: 0 | AH34: ["cannon"] | AJ34: 0 | AK34: 0 | AL34: 0 | AM34: 0 | AN34: 0 | AO34: 0 | AP34: 0 | AQ34: 0 | AR34: 0 | AS34: 0
A35: autoloader-turret | B35: carrier | C35: ["china"] | D35: 1 | E35: 1 | F35: 1 | G35: 400 | H35: 500 | I35: 0 | J35: 0 | K35: 0 | L35: 0 | M35: 0 | O35: 0 | P35: 0 | Q35: 0 | R35: 0 | S35: 0 | T35: 0 | U35: 0 | V35: 0 | W35: 0 | X35: 0 | Y35: 3 | Z35: 5 | AA35: 50 | AB35: 0 | AC35: 0 | AD35: Same visible single barrel. Autoloading mechanism changes firing cycle, not barrel count. Baseline mount mass retained; hardware price includes autoloader. Global CP credit value applies. | AE35: CHBattlemasterCannon.Autoloader | AH35: ["cannon"] | AJ35: 0 | AK35: 0 | AL35: 0 | AM35: 0 | AN35: 0 | AO35: 0 | AP35: 0 | AQ35: 0 | AR35: 0 | AS35: 0
A36: fixed-triple | B36: carrier | C36: ["gdi"] | D36: 0 | E36: 0 | F36: 3 | G36: 300 | H36: 1500 | I36: 0 | J36: 0 | K36: 0 | L36: 0 | M36: 0 | O36: 0 | P36: 0 | Q36: 0 | R36: 0 | S36: 0 | T36: 0 | U36: 0 | V36: 0 | W36: 0 | X36: 0 | Y36: 3 | Z36: 1 | AA36: 100 | AB36: 0 | AC36: 0 | AH36: ["artillery"] | AJ36: 0 | AK36: 0 | AL36: 0 | AM36: 0 | AN36: 0 | AO36: 0 | AP36: 0 | AQ36: 0 | AR36: 0 | AS36: 33
A37: twin-coil | B37: carrier | C37: ["soviet"] | D37: 0 | E37: 0 | F37: 2 | G37: 200 | H37: 500 | I37: 0 | J37: 0 | K37: 0 | L37: 0 | M37: 0 | O37: 0 | P37: 0 | Q37: 0 | R37: 0 | S37: 0 | T37: 0 | U37: 0 | V37: 0 | W37: 0 | X37: 0 | Y37: 2 | Z37: 1 | AA37: 100 | AB37: 0 | AC37: 0 | AH37: ["tesla"] | AJ37: 0 | AK37: 0 | AL37: 0 | AM37: 0 | AN37: 0 | AO37: 0 | AP37: 0 | AQ37: 0 | AR37: 0 | AS37: 13
A38: cannon | B38: weapon | C38: ["china"] | D38: 0 | E38: 0 | F38: 1 | G38: 200 | H38: 500 | I38: 0 | J38: 0 | K38: 0 | L38: 0 | M38: 0 | O38: 0 | P38: 0 | Q38: 0 | R38: 0 | S38: 0 | T38: 0 | U38: 0 | V38: 0 | W38: 0 | X38: 0 | Y38: 0 | Z38: 0 | AA38: 0 | AB38: 4 | AC38: 0 | AE38: CHBattlemasterCannon | AI38: ["shell", "nuclear-shell"] | AJ38: 0 | AK38: 0 | AL38: 0 | AM38: 0 | AN38: 0 | AO38: 0 | AP38: 0 | AQ38: 0 | AR38: 0 | AS38: 0
A39: artillery | B39: weapon | C39: ["gdi"] | D39: 0 | E39: 0 | F39: 3 | G39: 300 | H39: 900 | I39: 0 | J39: 0 | K39: 0 | L39: 0 | M39: 0 | O39: 0 | P39: 0 | Q39: 0 | R39: 0 | S39: 0 | T39: 0 | U39: 0 | V39: 0 | W39: 0 | X39: 0 | Y39: 0 | Z39: 0 | AA39: 0 | AB39: 0 | AC39: 0 | AE39: JuggernautGun | AI39: ["artillery-shell", "emp-shell"] | AJ39: 0 | AK39: 0 | AL39: 0 | AM39: 0 | AN39: 0 | AO39: 0 | AP39: 0 | AQ39: 0 | AR39: 0 | AS39: 0
A40: tesla | B40: weapon | C40: ["soviet"] | D40: 1 | E40: 0 | F40: 2 | G40: 350 | H40: 700 | I40: 50 | J40: 0 | K40: 0 | L40: 0 | M40: 0 | O40: 0 | P40: 0 | Q40: 0 | R40: 0 | S40: 0 | T40: 0 | U40: 0 | V40: 0 | W40: 0 | X40: 0 | Y40: 0 | Z40: 0 | AA40: 0 | AB40: 0 | AC40: 0 | AE40: TTankZapMK2 | AI40: ["discharge"] | AJ40: 0 | AK40: 0 | AL40: 0 | AM40: 0 | AN40: 0 | AO40: 0 | AP40: 0 | AQ40: 0 | AR40: 0 | AS40: 0
A41: shell | B41: ammunition | C41: ["china"] | D41: 0 | E41: 0 | F41: 1 | G41: 50 | H41: 400 | I41: 0 | J41: 0 | K41: 0 | L41: 0 | M41: 0 | O41: 0 | P41: 0 | Q41: 0 | R41: 0 | S41: 0 | T41: 0 | U41: 0 | V41: 0 | W41: 0 | X41: 0 | Y41: 0 | Z41: 0 | AA41: 0 | AB41: 0 | AC41: 5000 | AJ41: 0 | AK41: 0 | AL41: 0 | AM41: 0 | AN41: 0 | AO41: 0 | AP41: 0 | AQ41: 0 | AR41: 0 | AS41: 0
A42: nuclear-shell | B42: ammunition | C42: ["china"] | D42: 1 | E42: 1 | F42: 1 | G42: 350 | H42: 400 | I42: 0 | J42: 0 | K42: 0 | L42: 0 | M42: 0 | O42: 0 | P42: 0 | Q42: 0 | R42: 0 | S42: 0 | T42: 0 | U42: 0 | V42: 0 | W42: 0 | X42: 0 | Y42: 0 | Z42: 0 | AA42: 0 | AB42: 0 | AC42: 10000 | AD42: First fit: same mass, no additional electric load; +300 hardware offsets 1 CP. Radiation, falloff and recoil need engine composition, not just damage copying. | AE42: CHBattlemasterCannon.Nuclear_Shells | AJ42: 0 | AK42: 0 | AL42: 0 | AM42: 0 | AN42: 0 | AO42: 0 | AP42: 0 | AQ42: 0 | AR42: 0 | AS42: 0
A43: artillery-shell | B43: ammunition | C43: ["gdi"] | D43: 0 | E43: 0 | F43: 3 | G43: 200 | H43: 1000 | I43: 0 | J43: 0 | K43: 0 | L43: 0 | M43: 0 | O43: 0 | P43: 0 | Q43: 0 | R43: 0 | S43: 0 | T43: 0 | U43: 0 | V43: 0 | W43: 0 | X43: 0 | Y43: 0 | Z43: 0 | AA43: 0 | AB43: 0 | AC43: 0 | AJ43: 0 | AK43: 0 | AL43: 0 | AM43: 0 | AN43: 0 | AO43: 0 | AP43: 0 | AQ43: 0 | AR43: 0 | AS43: 0
A44: emp-shell | B44: ammunition | C44: ["gdi"] | D44: 1 | E44: 1 | F44: 3 | G44: 300 | H44: 1000 | I44: 20 | J44: 0 | K44: 0 | L44: 0 | M44: 0 | O44: 0 | P44: 0 | Q44: 0 | R44: 0 | S44: 0 | T44: 0 | U44: 0 | V44: 0 | W44: 0 | X44: 0 | Y44: 0 | Z44: 0 | AA44: 0 | AB44: 0 | AC44: 0 | AE44: JuggernautGun.Emp | AJ44: 0 | AK44: 0 | AL44: 0 | AM44: 0 | AN44: 0 | AO44: 0 | AP44: 0 | AQ44: 0 | AR44: 0 | AS44: 0
A45: discharge | B45: ammunition | C45: ["soviet"] | D45: 0 | E45: 0 | F45: 2 | G45: 100 | H45: 200 | I45: 0 | J45: 0 | K45: 0 | L45: 0 | M45: 0 | O45: 0 | P45: 0 | Q45: 0 | R45: 0 | S45: 0 | T45: 0 | U45: 0 | V45: 0 | W45: 0 | X45: 0 | Y45: 0 | Z45: 0 | AA45: 0 | AB45: 0 | AC45: 0 | AD45: Fixed payload-package mass, not physical shells; no duplicate Tesla electrical charge. | AJ45: 0 | AK45: 0 | AL45: 0 | AM45: 0 | AN45: 0 | AO45: 0 | AP45: 0 | AQ45: 0 | AR45: 0 | AS45: 0
A46: pdl | B46: equipment | C46: ["china"] | D46: 1 | E46: 1 | F46: 3 | G46: 650 | H46: 300 | I46: 47 | J46: 0 | K46: 0 | L46: 0 | M46: 0 | O46: 0 | P46: 0 | Q46: 0 | R46: 0 | S46: 0 | T46: 0 | U46: 0 | V46: 0 | W46: 0 | X46: 0 | Y46: 0 | Z46: 0 | AA46: 0 | AB46: 0 | AC46: 0 | AE46: ^PointLaserDefenseSystem | AJ46: 0 | AK46: 0 | AL46: 0 | AM46: 0 | AN46: 0 | AO46: 0 | AP46: 0 | AQ46: 0 | AR46: 0 | AS46: 0

Sheet Infanterie
A1: ID | B1: Name | C1: Fraktionen | D1: Preis | E1: Masse kg | F1: Transportgewicht | G1: Tech
A2: che3 | B2: Tank Hunter | C2: china | D2: 300 | E2: 100 | F2: 1 | G2: 1
A3: che1 | B3: Red Guard | C3: china | D3: 80 | E3: 100 | F3: 1 | G3: 1
A4: minigunner | B4: Minigunner | C4: china | D4: 200 | E4: 100 | F4: 1 | G4: 1

Sheet Startbesatzung
A1: Design | B1: Infanterie | C1: Anzahl | D1: Preis | E1: Masse kg | F1: Transportgewicht | G1: Tech
A2: Overlord Bunker / mixed crew | B2: che3 | C2: 2 | D2: =C2*VLOOKUP(B2,Infanterie!$A$2:$G$4,4,FALSE) | E2: =C2*VLOOKUP(B2,Infanterie!$A$2:$G$4,5,FALSE) | F2: =C2*VLOOKUP(B2,Infanterie!$A$2:$G$4,6,FALSE) | G2: =IF(C2>0,VLOOKUP(B2,Infanterie!$A$2:$G$4,7,FALSE),0)
A3: Overlord Bunker / mixed crew | B3: che1 | C3: 2 | D3: =C3*VLOOKUP(B3,Infanterie!$A$2:$G$4,4,FALSE) | E3: =C3*VLOOKUP(B3,Infanterie!$A$2:$G$4,5,FALSE) | F3: =C3*VLOOKUP(B3,Infanterie!$A$2:$G$4,6,FALSE) | G3: =IF(C3>0,VLOOKUP(B3,Infanterie!$A$2:$G$4,7,FALSE),0)
A4: Overlord Bunker / partial crew | B4: minigunner | C4: 2 | D4: =C4*VLOOKUP(B4,Infanterie!$A$2:$G$4,4,FALSE) | E4: =C4*VLOOKUP(B4,Infanterie!$A$2:$G$4,5,FALSE) | F4: =C4*VLOOKUP(B4,Infanterie!$A$2:$G$4,6,FALSE) | G4: =IF(C4>0,VLOOKUP(B4,Infanterie!$A$2:$G$4,7,FALSE),0)
A5: Overlord Bunker | B5: che3 | C5: 4 | D5: =C5*VLOOKUP(B5,Infanterie!$A$2:$G$4,4,FALSE) | E5: =C5*VLOOKUP(B5,Infanterie!$A$2:$G$4,5,FALSE) | F5: =C5*VLOOKUP(B5,Infanterie!$A$2:$G$4,6,FALSE) | G5: =IF(C5>0,VLOOKUP(B5,Infanterie!$A$2:$G$4,7,FALSE),0)
A6: Overlord Bunker PDL | B6: che3 | C6: 4 | D6: =C6*VLOOKUP(B6,Infanterie!$A$2:$G$4,4,FALSE) | E6: =C6*VLOOKUP(B6,Infanterie!$A$2:$G$4,5,FALSE) | F6: =C6*VLOOKUP(B6,Infanterie!$A$2:$G$4,6,FALSE) | G6: =IF(C6>0,VLOOKUP(B6,Infanterie!$A$2:$G$4,7,FALSE),0)
A7: Overlord Bunker Reflector | B7: che3 | C7: 4 | D7: =C7*VLOOKUP(B7,Infanterie!$A$2:$G$4,4,FALSE) | E7: =C7*VLOOKUP(B7,Infanterie!$A$2:$G$4,5,FALSE) | F7: =C7*VLOOKUP(B7,Infanterie!$A$2:$G$4,6,FALSE) | G7: =IF(C7>0,VLOOKUP(B7,Infanterie!$A$2:$G$4,7,FALSE),0)

Sheet Entwuerfe
A1: Design | B1: Fraktion | C1: Chassis | D1: Motor | E1: Generator | F1: Panzerung | G1: Traeger | H1: Waffe | I1: Munition | J1: Zusatz 1 | K1: Zusatz 2 | L1: Zusatz 3 | M1: Katalog | N1: CP | O1: Tech | P1: Hardware | Q1: CP-Abzug | R1: Preis | S1: HP | T1: Masse kg | U1: Last kWe | V1: Rest kWm | W1: Tempo | X1: Armor | Y1: Grenzen | Z1: Python Preis | AA1: Python Tempo | AB1: Referenzhinweis | AC1: Fertigungsmodul | AD1: Fertigungsfaktor | AE1: Hardware nach Fertigung | AF1: Aufsatztraeger | AG1: Aufsatzwaffe | AH1: Aufsatzmunition | AI1: Besatzungspreis | AJ1: Besatzungsmasse | AK1: Besatzungstech | AL1: Aufsatz Reichweite | AM1: Aufsatz Mindestreichweite | AN1: Aufsatz Reload Ticks | AO1: Aufsatz Salve | AP1: Aufsatz Rohschaden
A2: Overlord Mortar Roof / draft | B2: china | C2: overlord-chassis | D2: diesel-heavy | E2: baseline-generator | F2: heavy | G2: heavy-twin-turret | H2: overlord-cannon | I2: heavy-shell | M2: =IF(C2="",0,VLOOKUP(C2,Bausteine!$A$2:$AS$46,4,FALSE))+IF(D2="",0,VLOOKUP(D2,Bausteine!$A$2:$AS$46,4,FALSE))+IF(E2="",0,VLOOKUP(E2,Bausteine!$A$2:$AS$46,4,FALSE))+IF(F2="",0,VLOOKUP(F2,Bausteine!$A$2:$AS$46,4,FALSE))+IF(G2="",0,VLOOKUP(G2,Bausteine!$A$2:$AS$46,4,FALSE))+IF(H2="",0,VLOOKUP(H2,Bausteine!$A$2:$AS$46,4,FALSE))+IF(I2="",0,VLOOKUP(I2,Bausteine!$A$2:$AS$46,4,FALSE))+IF(J2="",0,VLOOKUP(J2,Bausteine!$A$2:$AS$46,4,FALSE))+IF(K2="",0,VLOOKUP(K2,Bausteine!$A$2:$AS$46,4,FALSE))+IF(L2="",0,VLOOKUP(L2,Bausteine!$A$2:$AS$46,4,FALSE))+IF(AC2="",0,VLOOKUP(AC2,Bausteine!$A$2:$AS$46,4,FALSE))+IF(AF2="",0,VLOOKUP(AF2,Bausteine!$A$2:$AS$46,4,FALSE))+IF(AG2="",0,VLOOKUP(AG2,Bausteine!$A$2:$AS$46,4,FALSE))+IF(AH2="",0,VLOOKUP(AH2,Bausteine!$A$2:$AS$46,4,FALSE)) | N2: =IF(C2="",0,VLOOKUP(C2,Bausteine!$A$2:$AS$46,5,FALSE))+IF(D2="",0,VLOOKUP(D2,Bausteine!$A$2:$AS$46,5,FALSE))+IF(E2="",0,VLOOKUP(E2,Bausteine!$A$2:$AS$46,5,FALSE))+IF(F2="",0,VLOOKUP(F2,Bausteine!$A$2:$AS$46,5,FALSE))+IF(G2="",0,VLOOKUP(G2,Bausteine!$A$2:$AS$46,5,FALSE))+IF(H2="",0,VLOOKUP(H2,Bausteine!$A$2:$AS$46,5,FALSE))+IF(I2="",0,VLOOKUP(I2,Bausteine!$A$2:$AS$46,5,FALSE))+IF(J2="",0,VLOOKUP(J2,Bausteine!$A$2:$AS$46,5,FALSE))+IF(K2="",0,VLOOKUP(K2,Bausteine!$A$2:$AS$46,5,FALSE))+IF(L2="",0,VLOOKUP(L2,Bausteine!$A$2:$AS$46,5,FALSE))+IF(AC2="",0,VLOOKUP(AC2,Bausteine!$A$2:$AS$46,5,FALSE))+IF(AF2="",0,VLOOKUP(AF2,Bausteine!$A$2:$AS$46,5,FALSE))+IF(AG2="",0,VLOOKUP(AG2,Bausteine!$A$2:$AS$46,5,FALSE))+IF(AH2="",0,VLOOKUP(AH2,Bausteine!$A$2:$AS$46,5,FALSE)) | O2: =MAX(IF(C2="",0,VLOOKUP(C2,Bausteine!$A$2:$AS$46,6,FALSE)),IF(D2="",0,VLOOKUP(D2,Bausteine!$A$2:$AS$46,6,FALSE)),IF(E2="",0,VLOOKUP(E2,Bausteine!$A$2:$AS$46,6,FALSE)),IF(F2="",0,VLOOKUP(F2,Bausteine!$A$2:$AS$46,6,FALSE)),IF(G2="",0,VLOOKUP(G2,Bausteine!$A$2:$AS$46,6,FALSE)),IF(H2="",0,VLOOKUP(H2,Bausteine!$A$2:$AS$46,6,FALSE)),IF(I2="",0,VLOOKUP(I2,Bausteine!$A$2:$AS$46,6,FALSE)),IF(J2="",0,VLOOKUP(J2,Bausteine!$A$2:$AS$46,6,FALSE)),IF(K2="",0,VLOOKUP(K2,Bausteine!$A$2:$AS$46,6,FALSE)),IF(L2="",0,VLOOKUP(L2,Bausteine!$A$2:$AS$46,6,FALSE)),IF(AC2="",0,VLOOKUP(AC2,Bausteine!$A$2:$AS$46,6,FALSE)),IF(AF2="",0,VLOOKUP(AF2,Bausteine!$A$2:$AS$46,6,FALSE)),IF(AG2="",0,VLOOKUP(AG2,Bausteine!$A$2:$AS$46,6,FALSE)),IF(AH2="",0,VLOOKUP(AH2,Bausteine!$A$2:$AS$46,6,FALSE)),AK2) | P2: =IF(C2="",0,VLOOKUP(C2,Bausteine!$A$2:$AS$46,7,FALSE))*IF(F2="",0,VLOOKUP(F2,Bausteine!$A$2:$AS$46,17,FALSE))/100+IF(D2="",0,VLOOKUP(D2,Bausteine!$A$2:$AS$46,7,FALSE))+IF(E2="",0,VLOOKUP(E2,Bausteine!$A$2:$AS$46,7,FALSE))+IF(G2="",0,VLOOKUP(G2,Bausteine!$A$2:$AS$46,7,FALSE))+IF(H2="",0,VLOOKUP(H2,Bausteine!$A$2:$AS$46,7,FALSE))+IF(I2="",0,VLOOKUP(I2,Bausteine!$A$2:$AS$46,7,FALSE))+IF(J2="",0,VLOOKUP(J2,Bausteine!$A$2:$AS$46,7,FALSE))+IF(K2="",0,VLOOKUP(K2,Bausteine!$A$2:$AS$46,7,FALSE))+IF(L2="",0,VLOOKUP(L2,Bausteine!$A$2:$AS$46,7,FALSE))+IF(AC2="",0,VLOOKUP(AC2,Bausteine!$A$2:$AS$46,7,FALSE))+IF(AF2="",0,VLOOKUP(AF2,Bausteine!$A$2:$AS$46,7,FALSE))+IF(AG2="",0,VLOOKUP(AG2,Bausteine!$A$2:$AS$46,7,FALSE))+IF(AH2="",0,VLOOKUP(AH2,Bausteine!$A$2:$AS$46,7,FALSE))+AI2 | Q2: =N2*Parameter!$B$2 | R2: =AE2-Q2 | S2: =IF(C2="",0,VLOOKUP(C2,Bausteine!$A$2:$AS$46,13,FALSE))*IF(F2="",0,VLOOKUP(F2,Bausteine!$A$2:$AS$46,16,FALSE))/100 | T2: =IF(C2="",0,VLOOKUP(C2,Bausteine!$A$2:$AS$46,8,FALSE))*IF(F2="",0,VLOOKUP(F2,Bausteine!$A$2:$AS$46,15,FALSE))/100+IF(D2="",0,VLOOKUP(D2,Bausteine!$A$2:$AS$46,8,FALSE))+IF(E2="",0,VLOOKUP(E2,Bausteine!$A$2:$AS$46,8,FALSE))+IF(G2="",0,VLOOKUP(G2,Bausteine!$A$2:$AS$46,8,FALSE))+IF(H2="",0,VLOOKUP(H2,Bausteine!$A$2:$AS$46,8,FALSE))+IF(I2="",0,VLOOKUP(I2,Bausteine!$A$2:$AS$46,8,FALSE))+IF(J2="",0,VLOOKUP(J2,Bausteine!$A$2:$AS$46,8,FALSE))+IF(K2="",0,VLOOKUP(K2,Bausteine!$A$2:$AS$46,8,FALSE))+IF(L2="",0,VLOOKUP(L2,Bausteine!$A$2:$AS$46,8,FALSE))+IF(AC2="",0,VLOOKUP(AC2,Bausteine!$A$2:$AS$46,8,FALSE))+IF(AF2="",0,VLOOKUP(AF2,Bausteine!$A$2:$AS$46,8,FALSE))+IF(AG2="",0,VLOOKUP(AG2,Bausteine!$A$2:$AS$46,8,FALSE))+IF(AH2="",0,VLOOKUP(AH2,Bausteine!$A$2:$AS$46,8,FALSE))+AJ2 | U2: =IF(C2="",0,VLOOKUP(C2,Bausteine!$A$2:$AS$46,9,FALSE))+IF(D2="",0,VLOOKUP(D2,Bausteine!$A$2:$AS$46,9,FALSE))+IF(E2="",0,VLOOKUP(E2,Bausteine!$A$2:$AS$46,9,FALSE))+IF(F2="",0,VLOOKUP(F2,Bausteine!$A$2:$AS$46,9,FALSE))+IF(G2="",0,VLOOKUP(G2,Bausteine!$A$2:$AS$46,9,FALSE))+IF(H2="",0,VLOOKUP(H2,Bausteine!$A$2:$AS$46,9,FALSE))+IF(I2="",0,VLOOKUP(I2,Bausteine!$A$2:$AS$46,9,FALSE))+IF(J2="",0,VLOOKUP(J2,Bausteine!$A$2:$AS$46,9,FALSE))+IF(K2="",0,VLOOKUP(K2,Bausteine!$A$2:$AS$46,9,FALSE))+IF(L2="",0,VLOOKUP(L2,Bausteine!$A$2:$AS$46,9,FALSE))+IF(AC2="",0,VLOOKUP(AC2,Bausteine!$A$2:$AS$46,9,FALSE))+IF(AF2="",0,VLOOKUP(AF2,Bausteine!$A$2:$AS$46,9,FALSE))+IF(AG2="",0,VLOOKUP(AG2,Bausteine!$A$2:$AS$46,9,FALSE))+IF(AH2="",0,VLOOKUP(AH2,Bausteine!$A$2:$AS$46,9,FALSE)) | V2: =IF(D2="",0,VLOOKUP(D2,Bausteine!$A$2:$AS$46,10,FALSE))-U2/IF(E2="",0,VLOOKUP(E2,Bausteine!$A$2:$AS$46,11,FALSE)) | W2: =IF(Y2<>"OK","",ROUND(MIN(IF(C2="",0,VLOOKUP(C2,Bausteine!$A$2:$AS$46,21,FALSE)),IF(C2="",0,VLOOKUP(C2,Bausteine!$A$2:$AS$46,20,FALSE))*(V2/T2/(IF(C2="",0,VLOOKUP(C2,Bausteine!$A$2:$AS$46,19,FALSE))/IF(C2="",0,VLOOKUP(C2,Bausteine!$A$2:$AS$46,18,FALSE))))^Parameter!$B$3),0)) | X2: =IF(F2="",0,VLOOKUP(F2,Bausteine!$A$2:$AS$46,14,FALSE)) | Y2: =IFERROR(IF(OR(AD2<=0,AD2>1,R2<=0,T2<=0,V2<=0,U2>IF(E2="",0,VLOOKUP(E2,Bausteine!$A$2:$AS$46,12,FALSE)),T2>IF(C2="",0,VLOOKUP(C2,Bausteine!$A$2:$AS$46,22,FALSE)),IF(E2="",0,VLOOKUP(E2,Bausteine!$A$2:$AS$46,11,FALSE))<=0,IF(E2="",0,VLOOKUP(E2,Bausteine!$A$2:$AS$46,11,FALSE))>1),"UNGUELTIG","OK"),"FEHLER") | Z2: 2650 | AA2: 54 | AB2: OFFLINE DRAFT: existing artytur.shp, mount on Overlord not live-tested. Proposed 650-credit additional assembly, no CP. Main cannon retained. No legacy reference target. | AD2: =IF(AC2="",1,IF(AC2="",0,VLOOKUP(AC2,Bausteine!$A$2:$AS$46,37,FALSE))/100) | AE2: =P2*AD2 | AF2: mortar-roof-carrier | AG2: roof-mortar | AH2: mortar-he | AI2: =SUMIF(Startbesatzung!$A$2:$A$7,A2,Startbesatzung!$D$2:$D$7) | AJ2: =SUMIF(Startbesatzung!$A$2:$A$7,A2,Startbesatzung!$E$2:$E$7) | AK2: =MAX(0,IF(Startbesatzung!A2=A2,Startbesatzung!G2,0),IF(Startbesatzung!A3=A2,Startbesatzung!G3,0),IF(Startbesatzung!A4=A2,Startbesatzung!G4,0),IF(Startbesatzung!A5=A2,Startbesatzung!G5,0),IF(Startbesatzung!A6=A2,Startbesatzung!G6,0),IF(Startbesatzung!A7=A2,Startbesatzung!G7,0)) | AL2: =IF(AF2="","",IF(IF(AH2="",0,VLOOKUP(AH2,Bausteine!$A$2:$AS$46,38,FALSE))>0,IF(AH2="",0,VLOOKUP(AH2,Bausteine!$A$2:$AS$46,38,FALSE)),IF(AG2="",0,VLOOKUP(AG2,Bausteine!$A$2:$AS$46,28,FALSE)))) | AM2: =IF(AF2="","",IF(AG2="",0,VLOOKUP(AG2,Bausteine!$A$2:$AS$46,44,FALSE))) | AN2: =IF(AF2="","",IF(AF2="",0,VLOOKUP(AF2,Bausteine!$A$2:$AS$46,27,FALSE))) | AO2: =IF(AF2="","",IF(AF2="",0,VLOOKUP(AF2,Bausteine!$A$2:$AS$46,25,FALSE))) | AP2: =IF(AF2="","",IF(AH2="",0,VLOOKUP(AH2,Bausteine!$A$2:$AS$46,29,FALSE)))
A3: Overlord Mortar Roof PDL / draft | B3: china | C3: overlord-chassis | D3: diesel-heavy-boost | E3: efficient-generator | F3: heavy | G3: heavy-twin-turret | H3: overlord-cannon | I3: heavy-shell | J3: pdl | M3: =IF(C3="",0,VLOOKUP(C3,Bausteine!$A$2:$AS$46,4,FALSE))+IF(D3="",0,VLOOKUP(D3,Bausteine!$A$2:$AS$46,4,FALSE))+IF(E3="",0,VLOOKUP(E3,Bausteine!$A$2:$AS$46,4,FALSE))+IF(F3="",0,VLOOKUP(F3,Bausteine!$A$2:$AS$46,4,FALSE))+IF(G3="",0,VLOOKUP(G3,Bausteine!$A$2:$AS$46,4,FALSE))+IF(H3="",0,VLOOKUP(H3,Bausteine!$A$2:$AS$46,4,FALSE))+IF(I3="",0,VLOOKUP(I3,Bausteine!$A$2:$AS$46,4,FALSE))+IF(J3="",0,VLOOKUP(J3,Bausteine!$A$2:$AS$46,4,FALSE))+IF(K3="",0,VLOOKUP(K3,Bausteine!$A$2:$AS$46,4,FALSE))+IF(L3="",0,VLOOKUP(L3,Bausteine!$A$2:$AS$46,4,FALSE))+IF(AC3="",0,VLOOKUP(AC3,Bausteine!$A$2:$AS$46,4,FALSE))+IF(AF3="",0,VLOOKUP(AF3,Bausteine!$A$2:$AS$46,4,FALSE))+IF(AG3="",0,VLOOKUP(AG3,Bausteine!$A$2:$AS$46,4,FALSE))+IF(AH3="",0,VLOOKUP(AH3,Bausteine!$A$2:$AS$46,4,FALSE)) | N3: =IF(C3="",0,VLOOKUP(C3,Bausteine!$A$2:$AS$46,5,FALSE))+IF(D3="",0,VLOOKUP(D3,Bausteine!$A$2:$AS$46,5,FALSE))+IF(E3="",0,VLOOKUP(E3,Bausteine!$A$2:$AS$46,5,FALSE))+IF(F3="",0,VLOOKUP(F3,Bausteine!$A$2:$AS$46,5,FALSE))+IF(G3="",0,VLOOKUP(G3,Bausteine!$A$2:$AS$46,5,FALSE))+IF(H3="",0,VLOOKUP(H3,Bausteine!$A$2:$AS$46,5,FALSE))+IF(I3="",0,VLOOKUP(I3,Bausteine!$A$2:$AS$46,5,FALSE))+IF(J3="",0,VLOOKUP(J3,Bausteine!$A$2:$AS$46,5,FALSE))+IF(K3="",0,VLOOKUP(K3,Bausteine!$A$2:$AS$46,5,FALSE))+IF(L3="",0,VLOOKUP(L3,Bausteine!$A$2:$AS$46,5,FALSE))+IF(AC3="",0,VLOOKUP(AC3,Bausteine!$A$2:$AS$46,5,FALSE))+IF(AF3="",0,VLOOKUP(AF3,Bausteine!$A$2:$AS$46,5,FALSE))+IF(AG3="",0,VLOOKUP(AG3,Bausteine!$A$2:$AS$46,5,FALSE))+IF(AH3="",0,VLOOKUP(AH3,Bausteine!$A$2:$AS$46,5,FALSE)) | O3: =MAX(IF(C3="",0,VLOOKUP(C3,Bausteine!$A$2:$AS$46,6,FALSE)),IF(D3="",0,VLOOKUP(D3,Bausteine!$A$2:$AS$46,6,FALSE)),IF(E3="",0,VLOOKUP(E3,Bausteine!$A$2:$AS$46,6,FALSE)),IF(F3="",0,VLOOKUP(F3,Bausteine!$A$2:$AS$46,6,FALSE)),IF(G3="",0,VLOOKUP(G3,Bausteine!$A$2:$AS$46,6,FALSE)),IF(H3="",0,VLOOKUP(H3,Bausteine!$A$2:$AS$46,6,FALSE)),IF(I3="",0,VLOOKUP(I3,Bausteine!$A$2:$AS$46,6,FALSE)),IF(J3="",0,VLOOKUP(J3,Bausteine!$A$2:$AS$46,6,FALSE)),IF(K3="",0,VLOOKUP(K3,Bausteine!$A$2:$AS$46,6,FALSE)),IF(L3="",0,VLOOKUP(L3,Bausteine!$A$2:$AS$46,6,FALSE)),IF(AC3="",0,VLOOKUP(AC3,Bausteine!$A$2:$AS$46,6,FALSE)),IF(AF3="",0,VLOOKUP(AF3,Bausteine!$A$2:$AS$46,6,FALSE)),IF(AG3="",0,VLOOKUP(AG3,Bausteine!$A$2:$AS$46,6,FALSE)),IF(AH3="",0,VLOOKUP(AH3,Bausteine!$A$2:$AS$46,6,FALSE)),AK3) | P3: =IF(C3="",0,VLOOKUP(C3,Bausteine!$A$2:$AS$46,7,FALSE))*IF(F3="",0,VLOOKUP(F3,Bausteine!$A$2:$AS$46,17,FALSE))/100+IF(D3="",0,VLOOKUP(D3,Bausteine!$A$2:$AS$46,7,FALSE))+IF(E3="",0,VLOOKUP(E3,Bausteine!$A$2:$AS$46,7,FALSE))+IF(G3="",0,VLOOKUP(G3,Bausteine!$A$2:$AS$46,7,FALSE))+IF(H3="",0,VLOOKUP(H3,Bausteine!$A$2:$AS$46,7,FALSE))+IF(I3="",0,VLOOKUP(I3,Bausteine!$A$2:$AS$46,7,FALSE))+IF(J3="",0,VLOOKUP(J3,Bausteine!$A$2:$AS$46,7,FALSE))+IF(K3="",0,VLOOKUP(K3,Bausteine!$A$2:$AS$46,7,FALSE))+IF(L3="",0,VLOOKUP(L3,Bausteine!$A$2:$AS$46,7,FALSE))+IF(AC3="",0,VLOOKUP(AC3,Bausteine!$A$2:$AS$46,7,FALSE))+IF(AF3="",0,VLOOKUP(AF3,Bausteine!$A$2:$AS$46,7,FALSE))+IF(AG3="",0,VLOOKUP(AG3,Bausteine!$A$2:$AS$46,7,FALSE))+IF(AH3="",0,VLOOKUP(AH3,Bausteine!$A$2:$AS$46,7,FALSE))+AI3 | Q3: =N3*Parameter!$B$2 | R3: =AE3-Q3 | S3: =IF(C3="",0,VLOOKUP(C3,Bausteine!$A$2:$AS$46,13,FALSE))*IF(F3="",0,VLOOKUP(F3,Bausteine!$A$2:$AS$46,16,FALSE))/100 | T3: =IF(C3="",0,VLOOKUP(C3,Bausteine!$A$2:$AS$46,8,FALSE))*IF(F3="",0,VLOOKUP(F3,Bausteine!$A$2:$AS$46,15,FALSE))/100+IF(D3="",0,VLOOKUP(D3,Bausteine!$A$2:$AS$46,8,FALSE))+IF(E3="",0,VLOOKUP(E3,Bausteine!$A$2:$AS$46,8,FALSE))+IF(G3="",0,VLOOKUP(G3,Bausteine!$A$2:$AS$46,8,FALSE))+IF(H3="",0,VLOOKUP(H3,Bausteine!$A$2:$AS$46,8,FALSE))+IF(I3="",0,VLOOKUP(I3,Bausteine!$A$2:$AS$46,8,FALSE))+IF(J3="",0,VLOOKUP(J3,Bausteine!$A$2:$AS$46,8,FALSE))+IF(K3="",0,VLOOKUP(K3,Bausteine!$A$2:$AS$46,8,FALSE))+IF(L3="",0,VLOOKUP(L3,Bausteine!$A$2:$AS$46,8,FALSE))+IF(AC3="",0,VLOOKUP(AC3,Bausteine!$A$2:$AS$46,8,FALSE))+IF(AF3="",0,VLOOKUP(AF3,Bausteine!$A$2:$AS$46,8,FALSE))+IF(AG3="",0,VLOOKUP(AG3,Bausteine!$A$2:$AS$46,8,FALSE))+IF(AH3="",0,VLOOKUP(AH3,Bausteine!$A$2:$AS$46,8,FALSE))+AJ3 | U3: =IF(C3="",0,VLOOKUP(C3,Bausteine!$A$2:$AS$46,9,FALSE))+IF(D3="",0,VLOOKUP(D3,Bausteine!$A$2:$AS$46,9,FALSE))+IF(E3="",0,VLOOKUP(E3,Bausteine!$A$2:$AS$46,9,FALSE))+IF(F3="",0,VLOOKUP(F3,Bausteine!$A$2:$AS$46,9,FALSE))+IF(G3="",0,VLOOKUP(G3,Bausteine!$A$2:$AS$46,9,FALSE))+IF(H3="",0,VLOOKUP(H3,Bausteine!$A$2:$AS$46,9,FALSE))+IF(I3="",0,VLOOKUP(I3,Bausteine!$A$2:$AS$46,9,FALSE))+IF(J3="",0,VLOOKUP(J3,Bausteine!$A$2:$AS$46,9,FALSE))+IF(K3="",0,VLOOKUP(K3,Bausteine!$A$2:$AS$46,9,FALSE))+IF(L3="",0,VLOOKUP(L3,Bausteine!$A$2:$AS$46,9,FALSE))+IF(AC3="",0,VLOOKUP(AC3,Bausteine!$A$2:$AS$46,9,FALSE))+IF(AF3="",0,VLOOKUP(AF3,Bausteine!$A$2:$AS$46,9,FALSE))+IF(AG3="",0,VLOOKUP(AG3,Bausteine!$A$2:$AS$46,9,FALSE))+IF(AH3="",0,VLOOKUP(AH3,Bausteine!$A$2:$AS$46,9,FALSE)) | V3: =IF(D3="",0,VLOOKUP(D3,Bausteine!$A$2:$AS$46,10,FALSE))-U3/IF(E3="",0,VLOOKUP(E3,Bausteine!$A$2:$AS$46,11,FALSE)) | W3: =IF(Y3<>"OK","",ROUND(MIN(IF(C3="",0,VLOOKUP(C3,Bausteine!$A$2:$AS$46,21,FALSE)),IF(C3="",0,VLOOKUP(C3,Bausteine!$A$2:$AS$46,20,FALSE))*(V3/T3/(IF(C3="",0,VLOOKUP(C3,Bausteine!$A$2:$AS$46,19,FALSE))/IF(C3="",0,VLOOKUP(C3,Bausteine!$A$2:$AS$46,18,FALSE))))^Parameter!$B$3),0)) | X3: =IF(F3="",0,VLOOKUP(F3,Bausteine!$A$2:$AS$46,14,FALSE)) | Y3: =IFERROR(IF(OR(AD3<=0,AD3>1,R3<=0,T3<=0,V3<=0,U3>IF(E3="",0,VLOOKUP(E3,Bausteine!$A$2:$AS$46,12,FALSE)),T3>IF(C3="",0,VLOOKUP(C3,Bausteine!$A$2:$AS$46,22,FALSE)),IF(E3="",0,VLOOKUP(E3,Bausteine!$A$2:$AS$46,11,FALSE))<=0,IF(E3="",0,VLOOKUP(E3,Bausteine!$A$2:$AS$46,11,FALSE))>1),"UNGUELTIG","OK"),"FEHLER") | Z3: 3300 | AA3: 55 | AB3: OFFLINE DRAFT: unverified mounting; shared standard PDL and heavy-drive upgrade unchanged. | AD3: =IF(AC3="",1,IF(AC3="",0,VLOOKUP(AC3,Bausteine!$A$2:$AS$46,37,FALSE))/100) | AE3: =P3*AD3 | AF3: mortar-roof-carrier | AG3: roof-mortar | AH3: mortar-he | AI3: =SUMIF(Startbesatzung!$A$2:$A$7,A3,Startbesatzung!$D$2:$D$7) | AJ3: =SUMIF(Startbesatzung!$A$2:$A$7,A3,Startbesatzung!$E$2:$E$7) | AK3: =MAX(0,IF(Startbesatzung!A2=A3,Startbesatzung!G2,0),IF(Startbesatzung!A3=A3,Startbesatzung!G3,0),IF(Startbesatzung!A4=A3,Startbesatzung!G4,0),IF(Startbesatzung!A5=A3,Startbesatzung!G5,0),IF(Startbesatzung!A6=A3,Startbesatzung!G6,0),IF(Startbesatzung!A7=A3,Startbesatzung!G7,0)) | AL3: =IF(AF3="","",IF(IF(AH3="",0,VLOOKUP(AH3,Bausteine!$A$2:$AS$46,38,FALSE))>0,IF(AH3="",0,VLOOKUP(AH3,Bausteine!$A$2:$AS$46,38,FALSE)),IF(AG3="",0,VLOOKUP(AG3,Bausteine!$A$2:$AS$46,28,FALSE)))) | AM3: =IF(AF3="","",IF(AG3="",0,VLOOKUP(AG3,Bausteine!$A$2:$AS$46,44,FALSE))) | AN3: =IF(AF3="","",IF(AF3="",0,VLOOKUP(AF3,Bausteine!$A$2:$AS$46,27,FALSE))) | AO3: =IF(AF3="","",IF(AF3="",0,VLOOKUP(AF3,Bausteine!$A$2:$AS$46,25,FALSE))) | AP3: =IF(AF3="","",IF(AH3="",0,VLOOKUP(AH3,Bausteine!$A$2:$AS$46,29,FALSE)))
A4: Overlord Mortar Roof Reflector / draft | B4: china | C4: overlord-chassis | D4: diesel-heavy-boost | E4: efficient-generator | F4: reflector | G4: heavy-twin-turret | H4: overlord-cannon | I4: heavy-shell | M4: =IF(C4="",0,VLOOKUP(C4,Bausteine!$A$2:$AS$46,4,FALSE))+IF(D4="",0,VLOOKUP(D4,Bausteine!$A$2:$AS$46,4,FALSE))+IF(E4="",0,VLOOKUP(E4,Bausteine!$A$2:$AS$46,4,FALSE))+IF(F4="",0,VLOOKUP(F4,Bausteine!$A$2:$AS$46,4,FALSE))+IF(G4="",0,VLOOKUP(G4,Bausteine!$A$2:$AS$46,4,FALSE))+IF(H4="",0,VLOOKUP(H4,Bausteine!$A$2:$AS$46,4,FALSE))+IF(I4="",0,VLOOKUP(I4,Bausteine!$A$2:$AS$46,4,FALSE))+IF(J4="",0,VLOOKUP(J4,Bausteine!$A$2:$AS$46,4,FALSE))+IF(K4="",0,VLOOKUP(K4,Bausteine!$A$2:$AS$46,4,FALSE))+IF(L4="",0,VLOOKUP(L4,Bausteine!$A$2:$AS$46,4,FALSE))+IF(AC4="",0,VLOOKUP(AC4,Bausteine!$A$2:$AS$46,4,FALSE))+IF(AF4="",0,VLOOKUP(AF4,Bausteine!$A$2:$AS$46,4,FALSE))+IF(AG4="",0,VLOOKUP(AG4,Bausteine!$A$2:$AS$46,4,FALSE))+IF(AH4="",0,VLOOKUP(AH4,Bausteine!$A$2:$AS$46,4,FALSE)) | N4: =IF(C4="",0,VLOOKUP(C4,Bausteine!$A$2:$AS$46,5,FALSE))+IF(D4="",0,VLOOKUP(D4,Bausteine!$A$2:$AS$46,5,FALSE))+IF(E4="",0,VLOOKUP(E4,Bausteine!$A$2:$AS$46,5,FALSE))+IF(F4="",0,VLOOKUP(F4,Bausteine!$A$2:$AS$46,5,FALSE))+IF(G4="",0,VLOOKUP(G4,Bausteine!$A$2:$AS$46,5,FALSE))+IF(H4="",0,VLOOKUP(H4,Bausteine!$A$2:$AS$46,5,FALSE))+IF(I4="",0,VLOOKUP(I4,Bausteine!$A$2:$AS$46,5,FALSE))+IF(J4="",0,VLOOKUP(J4,Bausteine!$A$2:$AS$46,5,FALSE))+IF(K4="",0,VLOOKUP(K4,Bausteine!$A$2:$AS$46,5,FALSE))+IF(L4="",0,VLOOKUP(L4,Bausteine!$A$2:$AS$46,5,FALSE))+IF(AC4="",0,VLOOKUP(AC4,Bausteine!$A$2:$AS$46,5,FALSE))+IF(AF4="",0,VLOOKUP(AF4,Bausteine!$A$2:$AS$46,5,FALSE))+IF(AG4="",0,VLOOKUP(AG4,Bausteine!$A$2:$AS$46,5,FALSE))+IF(AH4="",0,VLOOKUP(AH4,Bausteine!$A$2:$AS$46,5,FALSE)) | O4: =MAX(IF(C4="",0,VLOOKUP(C4,Bausteine!$A$2:$AS$46,6,FALSE)),IF(D4="",0,VLOOKUP(D4,Bausteine!$A$2:$AS$46,6,FALSE)),IF(E4="",0,VLOOKUP(E4,Bausteine!$A$2:$AS$46,6,FALSE)),IF(F4="",0,VLOOKUP(F4,Bausteine!$A$2:$AS$46,6,FALSE)),IF(G4="",0,VLOOKUP(G4,Bausteine!$A$2:$AS$46,6,FALSE)),IF(H4="",0,VLOOKUP(H4,Bausteine!$A$2:$AS$46,6,FALSE)),IF(I4="",0,VLOOKUP(I4,Bausteine!$A$2:$AS$46,6,FALSE)),IF(J4="",0,VLOOKUP(J4,Bausteine!$A$2:$AS$46,6,FALSE)),IF(K4="",0,VLOOKUP(K4,Bausteine!$A$2:$AS$46,6,FALSE)),IF(L4="",0,VLOOKUP(L4,Bausteine!$A$2:$AS$46,6,FALSE)),IF(AC4="",0,VLOOKUP(AC4,Bausteine!$A$2:$AS$46,6,FALSE)),IF(AF4="",0,VLOOKUP(AF4,Bausteine!$A$2:$AS$46,6,FALSE)),IF(AG4="",0,VLOOKUP(AG4,Bausteine!$A$2:$AS$46,6,FALSE)),IF(AH4="",0,VLOOKUP(AH4,Bausteine!$A$2:$AS$46,6,FALSE)),AK4) | P4: =IF(C4="",0,VLOOKUP(C4,Bausteine!$A$2:$AS$46,7,FALSE))*IF(F4="",0,VLOOKUP(F4,Bausteine!$A$2:$AS$46,17,FALSE))/100+IF(D4="",0,VLOOKUP(D4,Bausteine!$A$2:$AS$46,7,FALSE))+IF(E4="",0,VLOOKUP(E4,Bausteine!$A$2:$AS$46,7,FALSE))+IF(G4="",0,VLOOKUP(G4,Bausteine!$A$2:$AS$46,7,FALSE))+IF(H4="",0,VLOOKUP(H4,Bausteine!$A$2:$AS$46,7,FALSE))+IF(I4="",0,VLOOKUP(I4,Bausteine!$A$2:$AS$46,7,FALSE))+IF(J4="",0,VLOOKUP(J4,Bausteine!$A$2:$AS$46,7,FALSE))+IF(K4="",0,VLOOKUP(K4,Bausteine!$A$2:$AS$46,7,FALSE))+IF(L4="",0,VLOOKUP(L4,Bausteine!$A$2:$AS$46,7,FALSE))+IF(AC4="",0,VLOOKUP(AC4,Bausteine!$A$2:$AS$46,7,FALSE))+IF(AF4="",0,VLOOKUP(AF4,Bausteine!$A$2:$AS$46,7,FALSE))+IF(AG4="",0,VLOOKUP(AG4,Bausteine!$A$2:$AS$46,7,FALSE))+IF(AH4="",0,VLOOKUP(AH4,Bausteine!$A$2:$AS$46,7,FALSE))+AI4 | Q4: =N4*Parameter!$B$2 | R4: =AE4-Q4 | S4: =IF(C4="",0,VLOOKUP(C4,Bausteine!$A$2:$AS$46,13,FALSE))*IF(F4="",0,VLOOKUP(F4,Bausteine!$A$2:$AS$46,16,FALSE))/100 | T4: =IF(C4="",0,VLOOKUP(C4,Bausteine!$A$2:$AS$46,8,FALSE))*IF(F4="",0,VLOOKUP(F4,Bausteine!$A$2:$AS$46,15,FALSE))/100+IF(D4="",0,VLOOKUP(D4,Bausteine!$A$2:$AS$46,8,FALSE))+IF(E4="",0,VLOOKUP(E4,Bausteine!$A$2:$AS$46,8,FALSE))+IF(G4="",0,VLOOKUP(G4,Bausteine!$A$2:$AS$46,8,FALSE))+IF(H4="",0,VLOOKUP(H4,Bausteine!$A$2:$AS$46,8,FALSE))+IF(I4="",0,VLOOKUP(I4,Bausteine!$A$2:$AS$46,8,FALSE))+IF(J4="",0,VLOOKUP(J4,Bausteine!$A$2:$AS$46,8,FALSE))+IF(K4="",0,VLOOKUP(K4,Bausteine!$A$2:$AS$46,8,FALSE))+IF(L4="",0,VLOOKUP(L4,Bausteine!$A$2:$AS$46,8,FALSE))+IF(AC4="",0,VLOOKUP(AC4,Bausteine!$A$2:$AS$46,8,FALSE))+IF(AF4="",0,VLOOKUP(AF4,Bausteine!$A$2:$AS$46,8,FALSE))+IF(AG4="",0,VLOOKUP(AG4,Bausteine!$A$2:$AS$46,8,FALSE))+IF(AH4="",0,VLOOKUP(AH4,Bausteine!$A$2:$AS$46,8,FALSE))+AJ4 | U4: =IF(C4="",0,VLOOKUP(C4,Bausteine!$A$2:$AS$46,9,FALSE))+IF(D4="",0,VLOOKUP(D4,Bausteine!$A$2:$AS$46,9,FALSE))+IF(E4="",0,VLOOKUP(E4,Bausteine!$A$2:$AS$46,9,FALSE))+IF(F4="",0,VLOOKUP(F4,Bausteine!$A$2:$AS$46,9,FALSE))+IF(G4="",0,VLOOKUP(G4,Bausteine!$A$2:$AS$46,9,FALSE))+IF(H4="",0,VLOOKUP(H4,Bausteine!$A$2:$AS$46,9,FALSE))+IF(I4="",0,VLOOKUP(I4,Bausteine!$A$2:$AS$46,9,FALSE))+IF(J4="",0,VLOOKUP(J4,Bausteine!$A$2:$AS$46,9,FALSE))+IF(K4="",0,VLOOKUP(K4,Bausteine!$A$2:$AS$46,9,FALSE))+IF(L4="",0,VLOOKUP(L4,Bausteine!$A$2:$AS$46,9,FALSE))+IF(AC4="",0,VLOOKUP(AC4,Bausteine!$A$2:$AS$46,9,FALSE))+IF(AF4="",0,VLOOKUP(AF4,Bausteine!$A$2:$AS$46,9,FALSE))+IF(AG4="",0,VLOOKUP(AG4,Bausteine!$A$2:$AS$46,9,FALSE))+IF(AH4="",0,VLOOKUP(AH4,Bausteine!$A$2:$AS$46,9,FALSE)) | V4: =IF(D4="",0,VLOOKUP(D4,Bausteine!$A$2:$AS$46,10,FALSE))-U4/IF(E4="",0,VLOOKUP(E4,Bausteine!$A$2:$AS$46,11,FALSE)) | W4: =IF(Y4<>"OK","",ROUND(MIN(IF(C4="",0,VLOOKUP(C4,Bausteine!$A$2:$AS$46,21,FALSE)),IF(C4="",0,VLOOKUP(C4,Bausteine!$A$2:$AS$46,20,FALSE))*(V4/T4/(IF(C4="",0,VLOOKUP(C4,Bausteine!$A$2:$AS$46,19,FALSE))/IF(C4="",0,VLOOKUP(C4,Bausteine!$A$2:$AS$46,18,FALSE))))^Parameter!$B$3),0)) | X4: =IF(F4="",0,VLOOKUP(F4,Bausteine!$A$2:$AS$46,14,FALSE)) | Y4: =IFERROR(IF(OR(AD4<=0,AD4>1,R4<=0,T4<=0,V4<=0,U4>IF(E4="",0,VLOOKUP(E4,Bausteine!$A$2:$AS$46,12,FALSE)),T4>IF(C4="",0,VLOOKUP(C4,Bausteine!$A$2:$AS$46,22,FALSE)),IF(E4="",0,VLOOKUP(E4,Bausteine!$A$2:$AS$46,11,FALSE))<=0,IF(E4="",0,VLOOKUP(E4,Bausteine!$A$2:$AS$46,11,FALSE))>1),"UNGUELTIG","OK"),"FEHLER") | Z4: 2650 | AA4: 55 | AB4: OFFLINE DRAFT: unverified mounting; reflector power budget and global CP credit unchanged. | AD4: =IF(AC4="",1,IF(AC4="",0,VLOOKUP(AC4,Bausteine!$A$2:$AS$46,37,FALSE))/100) | AE4: =P4*AD4 | AF4: mortar-roof-carrier | AG4: roof-mortar | AH4: mortar-he | AI4: =SUMIF(Startbesatzung!$A$2:$A$7,A4,Startbesatzung!$D$2:$D$7) | AJ4: =SUMIF(Startbesatzung!$A$2:$A$7,A4,Startbesatzung!$E$2:$E$7) | AK4: =MAX(0,IF(Startbesatzung!A2=A4,Startbesatzung!G2,0),IF(Startbesatzung!A3=A4,Startbesatzung!G3,0),IF(Startbesatzung!A4=A4,Startbesatzung!G4,0),IF(Startbesatzung!A5=A4,Startbesatzung!G5,0),IF(Startbesatzung!A6=A4,Startbesatzung!G6,0),IF(Startbesatzung!A7=A4,Startbesatzung!G7,0)) | AL4: =IF(AF4="","",IF(IF(AH4="",0,VLOOKUP(AH4,Bausteine!$A$2:$AS$46,38,FALSE))>0,IF(AH4="",0,VLOOKUP(AH4,Bausteine!$A$2:$AS$46,38,FALSE)),IF(AG4="",0,VLOOKUP(AG4,Bausteine!$A$2:$AS$46,28,FALSE)))) | AM4: =IF(AF4="","",IF(AG4="",0,VLOOKUP(AG4,Bausteine!$A$2:$AS$46,44,FALSE))) | AN4: =IF(AF4="","",IF(AF4="",0,VLOOKUP(AF4,Bausteine!$A$2:$AS$46,27,FALSE))) | AO4: =IF(AF4="","",IF(AF4="",0,VLOOKUP(AF4,Bausteine!$A$2:$AS$46,25,FALSE))) | AP4: =IF(AF4="","",IF(AH4="",0,VLOOKUP(AH4,Bausteine!$A$2:$AS$46,29,FALSE)))
A5: Overlord Flame Roof / draft | B5: china | C5: overlord-chassis | D5: diesel-heavy | E5: baseline-generator | F5: heavy | G5: heavy-twin-turret | H5: overlord-cannon | I5: heavy-shell | M5: =IF(C5="",0,VLOOKUP(C5,Bausteine!$A$2:$AS$46,4,FALSE))+IF(D5="",0,VLOOKUP(D5,Bausteine!$A$2:$AS$46,4,FALSE))+IF(E5="",0,VLOOKUP(E5,Bausteine!$A$2:$AS$46,4,FALSE))+IF(F5="",0,VLOOKUP(F5,Bausteine!$A$2:$AS$46,4,FALSE))+IF(G5="",0,VLOOKUP(G5,Bausteine!$A$2:$AS$46,4,FALSE))+IF(H5="",0,VLOOKUP(H5,Bausteine!$A$2:$AS$46,4,FALSE))+IF(I5="",0,VLOOKUP(I5,Bausteine!$A$2:$AS$46,4,FALSE))+IF(J5="",0,VLOOKUP(J5,Bausteine!$A$2:$AS$46,4,FALSE))+IF(K5="",0,VLOOKUP(K5,Bausteine!$A$2:$AS$46,4,FALSE))+IF(L5="",0,VLOOKUP(L5,Bausteine!$A$2:$AS$46,4,FALSE))+IF(AC5="",0,VLOOKUP(AC5,Bausteine!$A$2:$AS$46,4,FALSE))+IF(AF5="",0,VLOOKUP(AF5,Bausteine!$A$2:$AS$46,4,FALSE))+IF(AG5="",0,VLOOKUP(AG5,Bausteine!$A$2:$AS$46,4,FALSE))+IF(AH5="",0,VLOOKUP(AH5,Bausteine!$A$2:$AS$46,4,FALSE)) | N5: =IF(C5="",0,VLOOKUP(C5,Bausteine!$A$2:$AS$46,5,FALSE))+IF(D5="",0,VLOOKUP(D5,Bausteine!$A$2:$AS$46,5,FALSE))+IF(E5="",0,VLOOKUP(E5,Bausteine!$A$2:$AS$46,5,FALSE))+IF(F5="",0,VLOOKUP(F5,Bausteine!$A$2:$AS$46,5,FALSE))+IF(G5="",0,VLOOKUP(G5,Bausteine!$A$2:$AS$46,5,FALSE))+IF(H5="",0,VLOOKUP(H5,Bausteine!$A$2:$AS$46,5,FALSE))+IF(I5="",0,VLOOKUP(I5,Bausteine!$A$2:$AS$46,5,FALSE))+IF(J5="",0,VLOOKUP(J5,Bausteine!$A$2:$AS$46,5,FALSE))+IF(K5="",0,VLOOKUP(K5,Bausteine!$A$2:$AS$46,5,FALSE))+IF(L5="",0,VLOOKUP(L5,Bausteine!$A$2:$AS$46,5,FALSE))+IF(AC5="",0,VLOOKUP(AC5,Bausteine!$A$2:$AS$46,5,FALSE))+IF(AF5="",0,VLOOKUP(AF5,Bausteine!$A$2:$AS$46,5,FALSE))+IF(AG5="",0,VLOOKUP(AG5,Bausteine!$A$2:$AS$46,5,FALSE))+IF(AH5="",0,VLOOKUP(AH5,Bausteine!$A$2:$AS$46,5,FALSE)) | O5: =MAX(IF(C5="",0,VLOOKUP(C5,Bausteine!$A$2:$AS$46,6,FALSE)),IF(D5="",0,VLOOKUP(D5,Bausteine!$A$2:$AS$46,6,FALSE)),IF(E5="",0,VLOOKUP(E5,Bausteine!$A$2:$AS$46,6,FALSE)),IF(F5="",0,VLOOKUP(F5,Bausteine!$A$2:$AS$46,6,FALSE)),IF(G5="",0,VLOOKUP(G5,Bausteine!$A$2:$AS$46,6,FALSE)),IF(H5="",0,VLOOKUP(H5,Bausteine!$A$2:$AS$46,6,FALSE)),IF(I5="",0,VLOOKUP(I5,Bausteine!$A$2:$AS$46,6,FALSE)),IF(J5="",0,VLOOKUP(J5,Bausteine!$A$2:$AS$46,6,FALSE)),IF(K5="",0,VLOOKUP(K5,Bausteine!$A$2:$AS$46,6,FALSE)),IF(L5="",0,VLOOKUP(L5,Bausteine!$A$2:$AS$46,6,FALSE)),IF(AC5="",0,VLOOKUP(AC5,Bausteine!$A$2:$AS$46,6,FALSE)),IF(AF5="",0,VLOOKUP(AF5,Bausteine!$A$2:$AS$46,6,FALSE)),IF(AG5="",0,VLOOKUP(AG5,Bausteine!$A$2:$AS$46,6,FALSE)),IF(AH5="",0,VLOOKUP(AH5,Bausteine!$A$2:$AS$46,6,FALSE)),AK5) | P5: =IF(C5="",0,VLOOKUP(C5,Bausteine!$A$2:$AS$46,7,FALSE))*IF(F5="",0,VLOOKUP(F5,Bausteine!$A$2:$AS$46,17,FALSE))/100+IF(D5="",0,VLOOKUP(D5,Bausteine!$A$2:$AS$46,7,FALSE))+IF(E5="",0,VLOOKUP(E5,Bausteine!$A$2:$AS$46,7,FALSE))+IF(G5="",0,VLOOKUP(G5,Bausteine!$A$2:$AS$46,7,FALSE))+IF(H5="",0,VLOOKUP(H5,Bausteine!$A$2:$AS$46,7,FALSE))+IF(I5="",0,VLOOKUP(I5,Bausteine!$A$2:$AS$46,7,FALSE))+IF(J5="",0,VLOOKUP(J5,Bausteine!$A$2:$AS$46,7,FALSE))+IF(K5="",0,VLOOKUP(K5,Bausteine!$A$2:$AS$46,7,FALSE))+IF(L5="",0,VLOOKUP(L5,Bausteine!$A$2:$AS$46,7,FALSE))+IF(AC5="",0,VLOOKUP(AC5,Bausteine!$A$2:$AS$46,7,FALSE))+IF(AF5="",0,VLOOKUP(AF5,Bausteine!$A$2:$AS$46,7,FALSE))+IF(AG5="",0,VLOOKUP(AG5,Bausteine!$A$2:$AS$46,7,FALSE))+IF(AH5="",0,VLOOKUP(AH5,Bausteine!$A$2:$AS$46,7,FALSE))+AI5 | Q5: =N5*Parameter!$B$2 | R5: =AE5-Q5 | S5: =IF(C5="",0,VLOOKUP(C5,Bausteine!$A$2:$AS$46,13,FALSE))*IF(F5="",0,VLOOKUP(F5,Bausteine!$A$2:$AS$46,16,FALSE))/100 | T5: =IF(C5="",0,VLOOKUP(C5,Bausteine!$A$2:$AS$46,8,FALSE))*IF(F5="",0,VLOOKUP(F5,Bausteine!$A$2:$AS$46,15,FALSE))/100+IF(D5="",0,VLOOKUP(D5,Bausteine!$A$2:$AS$46,8,FALSE))+IF(E5="",0,VLOOKUP(E5,Bausteine!$A$2:$AS$46,8,FALSE))+IF(G5="",0,VLOOKUP(G5,Bausteine!$A$2:$AS$46,8,FALSE))+IF(H5="",0,VLOOKUP(H5,Bausteine!$A$2:$AS$46,8,FALSE))+IF(I5="",0,VLOOKUP(I5,Bausteine!$A$2:$AS$46,8,FALSE))+IF(J5="",0,VLOOKUP(J5,Bausteine!$A$2:$AS$46,8,FALSE))+IF(K5="",0,VLOOKUP(K5,Bausteine!$A$2:$AS$46,8,FALSE))+IF(L5="",0,VLOOKUP(L5,Bausteine!$A$2:$AS$46,8,FALSE))+IF(AC5="",0,VLOOKUP(AC5,Bausteine!$A$2:$AS$46,8,FALSE))+IF(AF5="",0,VLOOKUP(AF5,Bausteine!$A$2:$AS$46,8,FALSE))+IF(AG5="",0,VLOOKUP(AG5,Bausteine!$A$2:$AS$46,8,FALSE))+IF(AH5="",0,VLOOKUP(AH5,Bausteine!$A$2:$AS$46,8,FALSE))+AJ5 | U5: =IF(C5="",0,VLOOKUP(C5,Bausteine!$A$2:$AS$46,9,FALSE))+IF(D5="",0,VLOOKUP(D5,Bausteine!$A$2:$AS$46,9,FALSE))+IF(E5="",0,VLOOKUP(E5,Bausteine!$A$2:$AS$46,9,FALSE))+IF(F5="",0,VLOOKUP(F5,Bausteine!$A$2:$AS$46,9,FALSE))+IF(G5="",0,VLOOKUP(G5,Bausteine!$A$2:$AS$46,9,FALSE))+IF(H5="",0,VLOOKUP(H5,Bausteine!$A$2:$AS$46,9,FALSE))+IF(I5="",0,VLOOKUP(I5,Bausteine!$A$2:$AS$46,9,FALSE))+IF(J5="",0,VLOOKUP(J5,Bausteine!$A$2:$AS$46,9,FALSE))+IF(K5="",0,VLOOKUP(K5,Bausteine!$A$2:$AS$46,9,FALSE))+IF(L5="",0,VLOOKUP(L5,Bausteine!$A$2:$AS$46,9,FALSE))+IF(AC5="",0,VLOOKUP(AC5,Bausteine!$A$2:$AS$46,9,FALSE))+IF(AF5="",0,VLOOKUP(AF5,Bausteine!$A$2:$AS$46,9,FALSE))+IF(AG5="",0,VLOOKUP(AG5,Bausteine!$A$2:$AS$46,9,FALSE))+IF(AH5="",0,VLOOKUP(AH5,Bausteine!$A$2:$AS$46,9,FALSE)) | V5: =IF(D5="",0,VLOOKUP(D5,Bausteine!$A$2:$AS$46,10,FALSE))-U5/IF(E5="",0,VLOOKUP(E5,Bausteine!$A$2:$AS$46,11,FALSE)) | W5: =IF(Y5<>"OK","",ROUND(MIN(IF(C5="",0,VLOOKUP(C5,Bausteine!$A$2:$AS$46,21,FALSE)),IF(C5="",0,VLOOKUP(C5,Bausteine!$A$2:$AS$46,20,FALSE))*(V5/T5/(IF(C5="",0,VLOOKUP(C5,Bausteine!$A$2:$AS$46,19,FALSE))/IF(C5="",0,VLOOKUP(C5,Bausteine!$A$2:$AS$46,18,FALSE))))^Parameter!$B$3),0)) | X5: =IF(F5="",0,VLOOKUP(F5,Bausteine!$A$2:$AS$46,14,FALSE)) | Y5: =IFERROR(IF(OR(AD5<=0,AD5>1,R5<=0,T5<=0,V5<=0,U5>IF(E5="",0,VLOOKUP(E5,Bausteine!$A$2:$AS$46,12,FALSE)),T5>IF(C5="",0,VLOOKUP(C5,Bausteine!$A$2:$AS$46,22,FALSE)),IF(E5="",0,VLOOKUP(E5,Bausteine!$A$2:$AS$46,11,FALSE))<=0,IF(E5="",0,VLOOKUP(E5,Bausteine!$A$2:$AS$46,11,FALSE))>1),"UNGUELTIG","OK"),"FEHLER") | Z5: 2250 | AA5: 55 | AB5: OFFLINE DRAFT: chdragontur.shp has 32 separate facings; Overlord offsets, palette, scale, muzzle and animations NOT live-tested. Reuses existing flame parts without price changes; no original vehicle target. | AD5: =IF(AC5="",1,IF(AC5="",0,VLOOKUP(AC5,Bausteine!$A$2:$AS$46,37,FALSE))/100) | AE5: =P5*AD5 | AF5: flame-turret | AG5: dragon-flamer | AH5: flame-fuel | AI5: =SUMIF(Startbesatzung!$A$2:$A$7,A5,Startbesatzung!$D$2:$D$7) | AJ5: =SUMIF(Startbesatzung!$A$2:$A$7,A5,Startbesatzung!$E$2:$E$7) | AK5: =MAX(0,IF(Startbesatzung!A2=A5,Startbesatzung!G2,0),IF(Startbesatzung!A3=A5,Startbesatzung!G3,0),IF(Startbesatzung!A4=A5,Startbesatzung!G4,0),IF(Startbesatzung!A5=A5,Startbesatzung!G5,0),IF(Startbesatzung!A6=A5,Startbesatzung!G6,0),IF(Startbesatzung!A7=A5,Startbesatzung!G7,0)) | AL5: =IF(AF5="","",IF(IF(AH5="",0,VLOOKUP(AH5,Bausteine!$A$2:$AS$46,38,FALSE))>0,IF(AH5="",0,VLOOKUP(AH5,Bausteine!$A$2:$AS$46,38,FALSE)),IF(AG5="",0,VLOOKUP(AG5,Bausteine!$A$2:$AS$46,28,FALSE)))) | AM5: =IF(AF5="","",IF(AG5="",0,VLOOKUP(AG5,Bausteine!$A$2:$AS$46,44,FALSE))) | AN5: =IF(AF5="","",IF(AF5="",0,VLOOKUP(AF5,Bausteine!$A$2:$AS$46,27,FALSE))) | AO5: =IF(AF5="","",IF(AF5="",0,VLOOKUP(AF5,Bausteine!$A$2:$AS$46,25,FALSE))) | AP5: =IF(AF5="","",IF(AH5="",0,VLOOKUP(AH5,Bausteine!$A$2:$AS$46,29,FALSE)))
A6: Overlord Flame Roof PDL / draft | B6: china | C6: overlord-chassis | D6: diesel-heavy-boost | E6: efficient-generator | F6: heavy | G6: heavy-twin-turret | H6: overlord-cannon | I6: heavy-shell | J6: pdl | M6: =IF(C6="",0,VLOOKUP(C6,Bausteine!$A$2:$AS$46,4,FALSE))+IF(D6="",0,VLOOKUP(D6,Bausteine!$A$2:$AS$46,4,FALSE))+IF(E6="",0,VLOOKUP(E6,Bausteine!$A$2:$AS$46,4,FALSE))+IF(F6="",0,VLOOKUP(F6,Bausteine!$A$2:$AS$46,4,FALSE))+IF(G6="",0,VLOOKUP(G6,Bausteine!$A$2:$AS$46,4,FALSE))+IF(H6="",0,VLOOKUP(H6,Bausteine!$A$2:$AS$46,4,FALSE))+IF(I6="",0,VLOOKUP(I6,Bausteine!$A$2:$AS$46,4,FALSE))+IF(J6="",0,VLOOKUP(J6,Bausteine!$A$2:$AS$46,4,FALSE))+IF(K6="",0,VLOOKUP(K6,Bausteine!$A$2:$AS$46,4,FALSE))+IF(L6="",0,VLOOKUP(L6,Bausteine!$A$2:$AS$46,4,FALSE))+IF(AC6="",0,VLOOKUP(AC6,Bausteine!$A$2:$AS$46,4,FALSE))+IF(AF6="",0,VLOOKUP(AF6,Bausteine!$A$2:$AS$46,4,FALSE))+IF(AG6="",0,VLOOKUP(AG6,Bausteine!$A$2:$AS$46,4,FALSE))+IF(AH6="",0,VLOOKUP(AH6,Bausteine!$A$2:$AS$46,4,FALSE)) | N6: =IF(C6="",0,VLOOKUP(C6,Bausteine!$A$2:$AS$46,5,FALSE))+IF(D6="",0,VLOOKUP(D6,Bausteine!$A$2:$AS$46,5,FALSE))+IF(E6="",0,VLOOKUP(E6,Bausteine!$A$2:$AS$46,5,FALSE))+IF(F6="",0,VLOOKUP(F6,Bausteine!$A$2:$AS$46,5,FALSE))+IF(G6="",0,VLOOKUP(G6,Bausteine!$A$2:$AS$46,5,FALSE))+IF(H6="",0,VLOOKUP(H6,Bausteine!$A$2:$AS$46,5,FALSE))+IF(I6="",0,VLOOKUP(I6,Bausteine!$A$2:$AS$46,5,FALSE))+IF(J6="",0,VLOOKUP(J6,Bausteine!$A$2:$AS$46,5,FALSE))+IF(K6="",0,VLOOKUP(K6,Bausteine!$A$2:$AS$46,5,FALSE))+IF(L6="",0,VLOOKUP(L6,Bausteine!$A$2:$AS$46,5,FALSE))+IF(AC6="",0,VLOOKUP(AC6,Bausteine!$A$2:$AS$46,5,FALSE))+IF(AF6="",0,VLOOKUP(AF6,Bausteine!$A$2:$AS$46,5,FALSE))+IF(AG6="",0,VLOOKUP(AG6,Bausteine!$A$2:$AS$46,5,FALSE))+IF(AH6="",0,VLOOKUP(AH6,Bausteine!$A$2:$AS$46,5,FALSE)) | O6: =MAX(IF(C6="",0,VLOOKUP(C6,Bausteine!$A$2:$AS$46,6,FALSE)),IF(D6="",0,VLOOKUP(D6,Bausteine!$A$2:$AS$46,6,FALSE)),IF(E6="",0,VLOOKUP(E6,Bausteine!$A$2:$AS$46,6,FALSE)),IF(F6="",0,VLOOKUP(F6,Bausteine!$A$2:$AS$46,6,FALSE)),IF(G6="",0,VLOOKUP(G6,Bausteine!$A$2:$AS$46,6,FALSE)),IF(H6="",0,VLOOKUP(H6,Bausteine!$A$2:$AS$46,6,FALSE)),IF(I6="",0,VLOOKUP(I6,Bausteine!$A$2:$AS$46,6,FALSE)),IF(J6="",0,VLOOKUP(J6,Bausteine!$A$2:$AS$46,6,FALSE)),IF(K6="",0,VLOOKUP(K6,Bausteine!$A$2:$AS$46,6,FALSE)),IF(L6="",0,VLOOKUP(L6,Bausteine!$A$2:$AS$46,6,FALSE)),IF(AC6="",0,VLOOKUP(AC6,Bausteine!$A$2:$AS$46,6,FALSE)),IF(AF6="",0,VLOOKUP(AF6,Bausteine!$A$2:$AS$46,6,FALSE)),IF(AG6="",0,VLOOKUP(AG6,Bausteine!$A$2:$AS$46,6,FALSE)),IF(AH6="",0,VLOOKUP(AH6,Bausteine!$A$2:$AS$46,6,FALSE)),AK6) | P6: =IF(C6="",0,VLOOKUP(C6,Bausteine!$A$2:$AS$46,7,FALSE))*IF(F6="",0,VLOOKUP(F6,Bausteine!$A$2:$AS$46,17,FALSE))/100+IF(D6="",0,VLOOKUP(D6,Bausteine!$A$2:$AS$46,7,FALSE))+IF(E6="",0,VLOOKUP(E6,Bausteine!$A$2:$AS$46,7,FALSE))+IF(G6="",0,VLOOKUP(G6,Bausteine!$A$2:$AS$46,7,FALSE))+IF(H6="",0,VLOOKUP(H6,Bausteine!$A$2:$AS$46,7,FALSE))+IF(I6="",0,VLOOKUP(I6,Bausteine!$A$2:$AS$46,7,FALSE))+IF(J6="",0,VLOOKUP(J6,Bausteine!$A$2:$AS$46,7,FALSE))+IF(K6="",0,VLOOKUP(K6,Bausteine!$A$2:$AS$46,7,FALSE))+IF(L6="",0,VLOOKUP(L6,Bausteine!$A$2:$AS$46,7,FALSE))+IF(AC6="",0,VLOOKUP(AC6,Bausteine!$A$2:$AS$46,7,FALSE))+IF(AF6="",0,VLOOKUP(AF6,Bausteine!$A$2:$AS$46,7,FALSE))+IF(AG6="",0,VLOOKUP(AG6,Bausteine!$A$2:$AS$46,7,FALSE))+IF(AH6="",0,VLOOKUP(AH6,Bausteine!$A$2:$AS$46,7,FALSE))+AI6 | Q6: =N6*Parameter!$B$2 | R6: =AE6-Q6 | S6: =IF(C6="",0,VLOOKUP(C6,Bausteine!$A$2:$AS$46,13,FALSE))*IF(F6="",0,VLOOKUP(F6,Bausteine!$A$2:$AS$46,16,FALSE))/100 | T6: =IF(C6="",0,VLOOKUP(C6,Bausteine!$A$2:$AS$46,8,FALSE))*IF(F6="",0,VLOOKUP(F6,Bausteine!$A$2:$AS$46,15,FALSE))/100+IF(D6="",0,VLOOKUP(D6,Bausteine!$A$2:$AS$46,8,FALSE))+IF(E6="",0,VLOOKUP(E6,Bausteine!$A$2:$AS$46,8,FALSE))+IF(G6="",0,VLOOKUP(G6,Bausteine!$A$2:$AS$46,8,FALSE))+IF(H6="",0,VLOOKUP(H6,Bausteine!$A$2:$AS$46,8,FALSE))+IF(I6="",0,VLOOKUP(I6,Bausteine!$A$2:$AS$46,8,FALSE))+IF(J6="",0,VLOOKUP(J6,Bausteine!$A$2:$AS$46,8,FALSE))+IF(K6="",0,VLOOKUP(K6,Bausteine!$A$2:$AS$46,8,FALSE))+IF(L6="",0,VLOOKUP(L6,Bausteine!$A$2:$AS$46,8,FALSE))+IF(AC6="",0,VLOOKUP(AC6,Bausteine!$A$2:$AS$46,8,FALSE))+IF(AF6="",0,VLOOKUP(AF6,Bausteine!$A$2:$AS$46,8,FALSE))+IF(AG6="",0,VLOOKUP(AG6,Bausteine!$A$2:$AS$46,8,FALSE))+IF(AH6="",0,VLOOKUP(AH6,Bausteine!$A$2:$AS$46,8,FALSE))+AJ6 | U6: =IF(C6="",0,VLOOKUP(C6,Bausteine!$A$2:$AS$46,9,FALSE))+IF(D6="",0,VLOOKUP(D6,Bausteine!$A$2:$AS$46,9,FALSE))+IF(E6="",0,VLOOKUP(E6,Bausteine!$A$2:$AS$46,9,FALSE))+IF(F6="",0,VLOOKUP(F6,Bausteine!$A$2:$AS$46,9,FALSE))+IF(G6="",0,VLOOKUP(G6,Bausteine!$A$2:$AS$46,9,FALSE))+IF(H6="",0,VLOOKUP(H6,Bausteine!$A$2:$AS$46,9,FALSE))+IF(I6="",0,VLOOKUP(I6,Bausteine!$A$2:$AS$46,9,FALSE))+IF(J6="",0,VLOOKUP(J6,Bausteine!$A$2:$AS$46,9,FALSE))+IF(K6="",0,VLOOKUP(K6,Bausteine!$A$2:$AS$46,9,FALSE))+IF(L6="",0,VLOOKUP(L6,Bausteine!$A$2:$AS$46,9,FALSE))+IF(AC6="",0,VLOOKUP(AC6,Bausteine!$A$2:$AS$46,9,FALSE))+IF(AF6="",0,VLOOKUP(AF6,Bausteine!$A$2:$AS$46,9,FALSE))+IF(AG6="",0,VLOOKUP(AG6,Bausteine!$A$2:$AS$46,9,FALSE))+IF(AH6="",0,VLOOKUP(AH6,Bausteine!$A$2:$AS$46,9,FALSE)) | V6: =IF(D6="",0,VLOOKUP(D6,Bausteine!$A$2:$AS$46,10,FALSE))-U6/IF(E6="",0,VLOOKUP(E6,Bausteine!$A$2:$AS$46,11,FALSE)) | W6: =IF(Y6<>"OK","",ROUND(MIN(IF(C6="",0,VLOOKUP(C6,Bausteine!$A$2:$AS$46,21,FALSE)),IF(C6="",0,VLOOKUP(C6,Bausteine!$A$2:$AS$46,20,FALSE))*(V6/T6/(IF(C6="",0,VLOOKUP(C6,Bausteine!$A$2:$AS$46,19,FALSE))/IF(C6="",0,VLOOKUP(C6,Bausteine!$A$2:$AS$46,18,FALSE))))^Parameter!$B$3),0)) | X6: =IF(F6="",0,VLOOKUP(F6,Bausteine!$A$2:$AS$46,14,FALSE)) | Y6: =IFERROR(IF(OR(AD6<=0,AD6>1,R6<=0,T6<=0,V6<=0,U6>IF(E6="",0,VLOOKUP(E6,Bausteine!$A$2:$AS$46,12,FALSE)),T6>IF(C6="",0,VLOOKUP(C6,Bausteine!$A$2:$AS$46,22,FALSE)),IF(E6="",0,VLOOKUP(E6,Bausteine!$A$2:$AS$46,11,FALSE))<=0,IF(E6="",0,VLOOKUP(E6,Bausteine!$A$2:$AS$46,11,FALSE))>1),"UNGUELTIG","OK"),"FEHLER") | Z6: 2900 | AA6: 55 | AB6: OFFLINE DRAFT: unverified roof artwork. Existing PDL and flame parts, no special rebate. Main gun and auxiliary fire names must be composed safely. | AD6: =IF(AC6="",1,IF(AC6="",0,VLOOKUP(AC6,Bausteine!$A$2:$AS$46,37,FALSE))/100) | AE6: =P6*AD6 | AF6: flame-turret | AG6: dragon-flamer | AH6: flame-fuel | AI6: =SUMIF(Startbesatzung!$A$2:$A$7,A6,Startbesatzung!$D$2:$D$7) | AJ6: =SUMIF(Startbesatzung!$A$2:$A$7,A6,Startbesatzung!$E$2:$E$7) | AK6: =MAX(0,IF(Startbesatzung!A2=A6,Startbesatzung!G2,0),IF(Startbesatzung!A3=A6,Startbesatzung!G3,0),IF(Startbesatzung!A4=A6,Startbesatzung!G4,0),IF(Startbesatzung!A5=A6,Startbesatzung!G5,0),IF(Startbesatzung!A6=A6,Startbesatzung!G6,0),IF(Startbesatzung!A7=A6,Startbesatzung!G7,0)) | AL6: =IF(AF6="","",IF(IF(AH6="",0,VLOOKUP(AH6,Bausteine!$A$2:$AS$46,38,FALSE))>0,IF(AH6="",0,VLOOKUP(AH6,Bausteine!$A$2:$AS$46,38,FALSE)),IF(AG6="",0,VLOOKUP(AG6,Bausteine!$A$2:$AS$46,28,FALSE)))) | AM6: =IF(AF6="","",IF(AG6="",0,VLOOKUP(AG6,Bausteine!$A$2:$AS$46,44,FALSE))) | AN6: =IF(AF6="","",IF(AF6="",0,VLOOKUP(AF6,Bausteine!$A$2:$AS$46,27,FALSE))) | AO6: =IF(AF6="","",IF(AF6="",0,VLOOKUP(AF6,Bausteine!$A$2:$AS$46,25,FALSE))) | AP6: =IF(AF6="","",IF(AH6="",0,VLOOKUP(AH6,Bausteine!$A$2:$AS$46,29,FALSE)))
A7: Overlord Flame Roof Reflector / draft | B7: china | C7: overlord-chassis | D7: diesel-heavy-boost | E7: efficient-generator | F7: reflector | G7: heavy-twin-turret | H7: overlord-cannon | I7: heavy-shell | M7: =IF(C7="",0,VLOOKUP(C7,Bausteine!$A$2:$AS$46,4,FALSE))+IF(D7="",0,VLOOKUP(D7,Bausteine!$A$2:$AS$46,4,FALSE))+IF(E7="",0,VLOOKUP(E7,Bausteine!$A$2:$AS$46,4,FALSE))+IF(F7="",0,VLOOKUP(F7,Bausteine!$A$2:$AS$46,4,FALSE))+IF(G7="",0,VLOOKUP(G7,Bausteine!$A$2:$AS$46,4,FALSE))+IF(H7="",0,VLOOKUP(H7,Bausteine!$A$2:$AS$46,4,FALSE))+IF(I7="",0,VLOOKUP(I7,Bausteine!$A$2:$AS$46,4,FALSE))+IF(J7="",0,VLOOKUP(J7,Bausteine!$A$2:$AS$46,4,FALSE))+IF(K7="",0,VLOOKUP(K7,Bausteine!$A$2:$AS$46,4,FALSE))+IF(L7="",0,VLOOKUP(L7,Bausteine!$A$2:$AS$46,4,FALSE))+IF(AC7="",0,VLOOKUP(AC7,Bausteine!$A$2:$AS$46,4,FALSE))+IF(AF7="",0,VLOOKUP(AF7,Bausteine!$A$2:$AS$46,4,FALSE))+IF(AG7="",0,VLOOKUP(AG7,Bausteine!$A$2:$AS$46,4,FALSE))+IF(AH7="",0,VLOOKUP(AH7,Bausteine!$A$2:$AS$46,4,FALSE)) | N7: =IF(C7="",0,VLOOKUP(C7,Bausteine!$A$2:$AS$46,5,FALSE))+IF(D7="",0,VLOOKUP(D7,Bausteine!$A$2:$AS$46,5,FALSE))+IF(E7="",0,VLOOKUP(E7,Bausteine!$A$2:$AS$46,5,FALSE))+IF(F7="",0,VLOOKUP(F7,Bausteine!$A$2:$AS$46,5,FALSE))+IF(G7="",0,VLOOKUP(G7,Bausteine!$A$2:$AS$46,5,FALSE))+IF(H7="",0,VLOOKUP(H7,Bausteine!$A$2:$AS$46,5,FALSE))+IF(I7="",0,VLOOKUP(I7,Bausteine!$A$2:$AS$46,5,FALSE))+IF(J7="",0,VLOOKUP(J7,Bausteine!$A$2:$AS$46,5,FALSE))+IF(K7="",0,VLOOKUP(K7,Bausteine!$A$2:$AS$46,5,FALSE))+IF(L7="",0,VLOOKUP(L7,Bausteine!$A$2:$AS$46,5,FALSE))+IF(AC7="",0,VLOOKUP(AC7,Bausteine!$A$2:$AS$46,5,FALSE))+IF(AF7="",0,VLOOKUP(AF7,Bausteine!$A$2:$AS$46,5,FALSE))+IF(AG7="",0,VLOOKUP(AG7,Bausteine!$A$2:$AS$46,5,FALSE))+IF(AH7="",0,VLOOKUP(AH7,Bausteine!$A$2:$AS$46,5,FALSE)) | O7: =MAX(IF(C7="",0,VLOOKUP(C7,Bausteine!$A$2:$AS$46,6,FALSE)),IF(D7="",0,VLOOKUP(D7,Bausteine!$A$2:$AS$46,6,FALSE)),IF(E7="",0,VLOOKUP(E7,Bausteine!$A$2:$AS$46,6,FALSE)),IF(F7="",0,VLOOKUP(F7,Bausteine!$A$2:$AS$46,6,FALSE)),IF(G7="",0,VLOOKUP(G7,Bausteine!$A$2:$AS$46,6,FALSE)),IF(H7="",0,VLOOKUP(H7,Bausteine!$A$2:$AS$46,6,FALSE)),IF(I7="",0,VLOOKUP(I7,Bausteine!$A$2:$AS$46,6,FALSE)),IF(J7="",0,VLOOKUP(J7,Bausteine!$A$2:$AS$46,6,FALSE)),IF(K7="",0,VLOOKUP(K7,Bausteine!$A$2:$AS$46,6,FALSE)),IF(L7="",0,VLOOKUP(L7,Bausteine!$A$2:$AS$46,6,FALSE)),IF(AC7="",0,VLOOKUP(AC7,Bausteine!$A$2:$AS$46,6,FALSE)),IF(AF7="",0,VLOOKUP(AF7,Bausteine!$A$2:$AS$46,6,FALSE)),IF(AG7="",0,VLOOKUP(AG7,Bausteine!$A$2:$AS$46,6,FALSE)),IF(AH7="",0,VLOOKUP(AH7,Bausteine!$A$2:$AS$46,6,FALSE)),AK7) | P7: =IF(C7="",0,VLOOKUP(C7,Bausteine!$A$2:$AS$46,7,FALSE))*IF(F7="",0,VLOOKUP(F7,Bausteine!$A$2:$AS$46,17,FALSE))/100+IF(D7="",0,VLOOKUP(D7,Bausteine!$A$2:$AS$46,7,FALSE))+IF(E7="",0,VLOOKUP(E7,Bausteine!$A$2:$AS$46,7,FALSE))+IF(G7="",0,VLOOKUP(G7,Bausteine!$A$2:$AS$46,7,FALSE))+IF(H7="",0,VLOOKUP(H7,Bausteine!$A$2:$AS$46,7,FALSE))+IF(I7="",0,VLOOKUP(I7,Bausteine!$A$2:$AS$46,7,FALSE))+IF(J7="",0,VLOOKUP(J7,Bausteine!$A$2:$AS$46,7,FALSE))+IF(K7="",0,VLOOKUP(K7,Bausteine!$A$2:$AS$46,7,FALSE))+IF(L7="",0,VLOOKUP(L7,Bausteine!$A$2:$AS$46,7,FALSE))+IF(AC7="",0,VLOOKUP(AC7,Bausteine!$A$2:$AS$46,7,FALSE))+IF(AF7="",0,VLOOKUP(AF7,Bausteine!$A$2:$AS$46,7,FALSE))+IF(AG7="",0,VLOOKUP(AG7,Bausteine!$A$2:$AS$46,7,FALSE))+IF(AH7="",0,VLOOKUP(AH7,Bausteine!$A$2:$AS$46,7,FALSE))+AI7 | Q7: =N7*Parameter!$B$2 | R7: =AE7-Q7 | S7: =IF(C7="",0,VLOOKUP(C7,Bausteine!$A$2:$AS$46,13,FALSE))*IF(F7="",0,VLOOKUP(F7,Bausteine!$A$2:$AS$46,16,FALSE))/100 | T7: =IF(C7="",0,VLOOKUP(C7,Bausteine!$A$2:$AS$46,8,FALSE))*IF(F7="",0,VLOOKUP(F7,Bausteine!$A$2:$AS$46,15,FALSE))/100+IF(D7="",0,VLOOKUP(D7,Bausteine!$A$2:$AS$46,8,FALSE))+IF(E7="",0,VLOOKUP(E7,Bausteine!$A$2:$AS$46,8,FALSE))+IF(G7="",0,VLOOKUP(G7,Bausteine!$A$2:$AS$46,8,FALSE))+IF(H7="",0,VLOOKUP(H7,Bausteine!$A$2:$AS$46,8,FALSE))+IF(I7="",0,VLOOKUP(I7,Bausteine!$A$2:$AS$46,8,FALSE))+IF(J7="",0,VLOOKUP(J7,Bausteine!$A$2:$AS$46,8,FALSE))+IF(K7="",0,VLOOKUP(K7,Bausteine!$A$2:$AS$46,8,FALSE))+IF(L7="",0,VLOOKUP(L7,Bausteine!$A$2:$AS$46,8,FALSE))+IF(AC7="",0,VLOOKUP(AC7,Bausteine!$A$2:$AS$46,8,FALSE))+IF(AF7="",0,VLOOKUP(AF7,Bausteine!$A$2:$AS$46,8,FALSE))+IF(AG7="",0,VLOOKUP(AG7,Bausteine!$A$2:$AS$46,8,FALSE))+IF(AH7="",0,VLOOKUP(AH7,Bausteine!$A$2:$AS$46,8,FALSE))+AJ7 | U7: =IF(C7="",0,VLOOKUP(C7,Bausteine!$A$2:$AS$46,9,FALSE))+IF(D7="",0,VLOOKUP(D7,Bausteine!$A$2:$AS$46,9,FALSE))+IF(E7="",0,VLOOKUP(E7,Bausteine!$A$2:$AS$46,9,FALSE))+IF(F7="",0,VLOOKUP(F7,Bausteine!$A$2:$AS$46,9,FALSE))+IF(G7="",0,VLOOKUP(G7,Bausteine!$A$2:$AS$46,9,FALSE))+IF(H7="",0,VLOOKUP(H7,Bausteine!$A$2:$AS$46,9,FALSE))+IF(I7="",0,VLOOKUP(I7,Bausteine!$A$2:$AS$46,9,FALSE))+IF(J7="",0,VLOOKUP(J7,Bausteine!$A$2:$AS$46,9,FALSE))+IF(K7="",0,VLOOKUP(K7,Bausteine!$A$2:$AS$46,9,FALSE))+IF(L7="",0,VLOOKUP(L7,Bausteine!$A$2:$AS$46,9,FALSE))+IF(AC7="",0,VLOOKUP(AC7,Bausteine!$A$2:$AS$46,9,FALSE))+IF(AF7="",0,VLOOKUP(AF7,Bausteine!$A$2:$AS$46,9,FALSE))+IF(AG7="",0,VLOOKUP(AG7,Bausteine!$A$2:$AS$46,9,FALSE))+IF(AH7="",0,VLOOKUP(AH7,Bausteine!$A$2:$AS$46,9,FALSE)) | V7: =IF(D7="",0,VLOOKUP(D7,Bausteine!$A$2:$AS$46,10,FALSE))-U7/IF(E7="",0,VLOOKUP(E7,Bausteine!$A$2:$AS$46,11,FALSE)) | W7: =IF(Y7<>"OK","",ROUND(MIN(IF(C7="",0,VLOOKUP(C7,Bausteine!$A$2:$AS$46,21,FALSE)),IF(C7="",0,VLOOKUP(C7,Bausteine!$A$2:$AS$46,20,FALSE))*(V7/T7/(IF(C7="",0,VLOOKUP(C7,Bausteine!$A$2:$AS$46,19,FALSE))/IF(C7="",0,VLOOKUP(C7,Bausteine!$A$2:$AS$46,18,FALSE))))^Parameter!$B$3),0)) | X7: =IF(F7="",0,VLOOKUP(F7,Bausteine!$A$2:$AS$46,14,FALSE)) | Y7: =IFERROR(IF(OR(AD7<=0,AD7>1,R7<=0,T7<=0,V7<=0,U7>IF(E7="",0,VLOOKUP(E7,Bausteine!$A$2:$AS$46,12,FALSE)),T7>IF(C7="",0,VLOOKUP(C7,Bausteine!$A$2:$AS$46,22,FALSE)),IF(E7="",0,VLOOKUP(E7,Bausteine!$A$2:$AS$46,11,FALSE))<=0,IF(E7="",0,VLOOKUP(E7,Bausteine!$A$2:$AS$46,11,FALSE))>1),"UNGUELTIG","OK"),"FEHLER") | Z7: 2250 | AA7: 55 | AB7: OFFLINE DRAFT: unverified roof artwork. Ordinary flame loadout already has lingering fire effects; no new ammunition compiler is implemented. | AD7: =IF(AC7="",1,IF(AC7="",0,VLOOKUP(AC7,Bausteine!$A$2:$AS$46,37,FALSE))/100) | AE7: =P7*AD7 | AF7: flame-turret | AG7: dragon-flamer | AH7: flame-fuel | AI7: =SUMIF(Startbesatzung!$A$2:$A$7,A7,Startbesatzung!$D$2:$D$7) | AJ7: =SUMIF(Startbesatzung!$A$2:$A$7,A7,Startbesatzung!$E$2:$E$7) | AK7: =MAX(0,IF(Startbesatzung!A2=A7,Startbesatzung!G2,0),IF(Startbesatzung!A3=A7,Startbesatzung!G3,0),IF(Startbesatzung!A4=A7,Startbesatzung!G4,0),IF(Startbesatzung!A5=A7,Startbesatzung!G5,0),IF(Startbesatzung!A6=A7,Startbesatzung!G6,0),IF(Startbesatzung!A7=A7,Startbesatzung!G7,0)) | AL7: =IF(AF7="","",IF(IF(AH7="",0,VLOOKUP(AH7,Bausteine!$A$2:$AS$46,38,FALSE))>0,IF(AH7="",0,VLOOKUP(AH7,Bausteine!$A$2:$AS$46,38,FALSE)),IF(AG7="",0,VLOOKUP(AG7,Bausteine!$A$2:$AS$46,28,FALSE)))) | AM7: =IF(AF7="","",IF(AG7="",0,VLOOKUP(AG7,Bausteine!$A$2:$AS$46,44,FALSE))) | AN7: =IF(AF7="","",IF(AF7="",0,VLOOKUP(AF7,Bausteine!$A$2:$AS$46,27,FALSE))) | AO7: =IF(AF7="","",IF(AF7="",0,VLOOKUP(AF7,Bausteine!$A$2:$AS$46,25,FALSE))) | AP7: =IF(AF7="","",IF(AH7="",0,VLOOKUP(AH7,Bausteine!$A$2:$AS$46,29,FALSE)))
A8: Overlord Gatling | B8: china | C8: overlord-chassis | D8: diesel-heavy | E8: baseline-generator | F8: heavy | G8: heavy-twin-turret | H8: overlord-cannon | I8: heavy-shell | M8: =IF(C8="",0,VLOOKUP(C8,Bausteine!$A$2:$AS$46,4,FALSE))+IF(D8="",0,VLOOKUP(D8,Bausteine!$A$2:$AS$46,4,FALSE))+IF(E8="",0,VLOOKUP(E8,Bausteine!$A$2:$AS$46,4,FALSE))+IF(F8="",0,VLOOKUP(F8,Bausteine!$A$2:$AS$46,4,FALSE))+IF(G8="",0,VLOOKUP(G8,Bausteine!$A$2:$AS$46,4,FALSE))+IF(H8="",0,VLOOKUP(H8,Bausteine!$A$2:$AS$46,4,FALSE))+IF(I8="",0,VLOOKUP(I8,Bausteine!$A$2:$AS$46,4,FALSE))+IF(J8="",0,VLOOKUP(J8,Bausteine!$A$2:$AS$46,4,FALSE))+IF(K8="",0,VLOOKUP(K8,Bausteine!$A$2:$AS$46,4,FALSE))+IF(L8="",0,VLOOKUP(L8,Bausteine!$A$2:$AS$46,4,FALSE))+IF(AC8="",0,VLOOKUP(AC8,Bausteine!$A$2:$AS$46,4,FALSE))+IF(AF8="",0,VLOOKUP(AF8,Bausteine!$A$2:$AS$46,4,FALSE))+IF(AG8="",0,VLOOKUP(AG8,Bausteine!$A$2:$AS$46,4,FALSE))+IF(AH8="",0,VLOOKUP(AH8,Bausteine!$A$2:$AS$46,4,FALSE)) | N8: =IF(C8="",0,VLOOKUP(C8,Bausteine!$A$2:$AS$46,5,FALSE))+IF(D8="",0,VLOOKUP(D8,Bausteine!$A$2:$AS$46,5,FALSE))+IF(E8="",0,VLOOKUP(E8,Bausteine!$A$2:$AS$46,5,FALSE))+IF(F8="",0,VLOOKUP(F8,Bausteine!$A$2:$AS$46,5,FALSE))+IF(G8="",0,VLOOKUP(G8,Bausteine!$A$2:$AS$46,5,FALSE))+IF(H8="",0,VLOOKUP(H8,Bausteine!$A$2:$AS$46,5,FALSE))+IF(I8="",0,VLOOKUP(I8,Bausteine!$A$2:$AS$46,5,FALSE))+IF(J8="",0,VLOOKUP(J8,Bausteine!$A$2:$AS$46,5,FALSE))+IF(K8="",0,VLOOKUP(K8,Bausteine!$A$2:$AS$46,5,FALSE))+IF(L8="",0,VLOOKUP(L8,Bausteine!$A$2:$AS$46,5,FALSE))+IF(AC8="",0,VLOOKUP(AC8,Bausteine!$A$2:$AS$46,5,FALSE))+IF(AF8="",0,VLOOKUP(AF8,Bausteine!$A$2:$AS$46,5,FALSE))+IF(AG8="",0,VLOOKUP(AG8,Bausteine!$A$2:$AS$46,5,FALSE))+IF(AH8="",0,VLOOKUP(AH8,Bausteine!$A$2:$AS$46,5,FALSE)) | O8: =MAX(IF(C8="",0,VLOOKUP(C8,Bausteine!$A$2:$AS$46,6,FALSE)),IF(D8="",0,VLOOKUP(D8,Bausteine!$A$2:$AS$46,6,FALSE)),IF(E8="",0,VLOOKUP(E8,Bausteine!$A$2:$AS$46,6,FALSE)),IF(F8="",0,VLOOKUP(F8,Bausteine!$A$2:$AS$46,6,FALSE)),IF(G8="",0,VLOOKUP(G8,Bausteine!$A$2:$AS$46,6,FALSE)),IF(H8="",0,VLOOKUP(H8,Bausteine!$A$2:$AS$46,6,FALSE)),IF(I8="",0,VLOOKUP(I8,Bausteine!$A$2:$AS$46,6,FALSE)),IF(J8="",0,VLOOKUP(J8,Bausteine!$A$2:$AS$46,6,FALSE)),IF(K8="",0,VLOOKUP(K8,Bausteine!$A$2:$AS$46,6,FALSE)),IF(L8="",0,VLOOKUP(L8,Bausteine!$A$2:$AS$46,6,FALSE)),IF(AC8="",0,VLOOKUP(AC8,Bausteine!$A$2:$AS$46,6,FALSE)),IF(AF8="",0,VLOOKUP(AF8,Bausteine!$A$2:$AS$46,6,FALSE)),IF(AG8="",0,VLOOKUP(AG8,Bausteine!$A$2:$AS$46,6,FALSE)),IF(AH8="",0,VLOOKUP(AH8,Bausteine!$A$2:$AS$46,6,FALSE)),AK8) | P8: =IF(C8="",0,VLOOKUP(C8,Bausteine!$A$2:$AS$46,7,FALSE))*IF(F8="",0,VLOOKUP(F8,Bausteine!$A$2:$AS$46,17,FALSE))/100+IF(D8="",0,VLOOKUP(D8,Bausteine!$A$2:$AS$46,7,FALSE))+IF(E8="",0,VLOOKUP(E8,Bausteine!$A$2:$AS$46,7,FALSE))+IF(G8="",0,VLOOKUP(G8,Bausteine!$A$2:$AS$46,7,FALSE))+IF(H8="",0,VLOOKUP(H8,Bausteine!$A$2:$AS$46,7,FALSE))+IF(I8="",0,VLOOKUP(I8,Bausteine!$A$2:$AS$46,7,FALSE))+IF(J8="",0,VLOOKUP(J8,Bausteine!$A$2:$AS$46,7,FALSE))+IF(K8="",0,VLOOKUP(K8,Bausteine!$A$2:$AS$46,7,FALSE))+IF(L8="",0,VLOOKUP(L8,Bausteine!$A$2:$AS$46,7,FALSE))+IF(AC8="",0,VLOOKUP(AC8,Bausteine!$A$2:$AS$46,7,FALSE))+IF(AF8="",0,VLOOKUP(AF8,Bausteine!$A$2:$AS$46,7,FALSE))+IF(AG8="",0,VLOOKUP(AG8,Bausteine!$A$2:$AS$46,7,FALSE))+IF(AH8="",0,VLOOKUP(AH8,Bausteine!$A$2:$AS$46,7,FALSE))+AI8 | Q8: =N8*Parameter!$B$2 | R8: =AE8-Q8 | S8: =IF(C8="",0,VLOOKUP(C8,Bausteine!$A$2:$AS$46,13,FALSE))*IF(F8="",0,VLOOKUP(F8,Bausteine!$A$2:$AS$46,16,FALSE))/100 | T8: =IF(C8="",0,VLOOKUP(C8,Bausteine!$A$2:$AS$46,8,FALSE))*IF(F8="",0,VLOOKUP(F8,Bausteine!$A$2:$AS$46,15,FALSE))/100+IF(D8="",0,VLOOKUP(D8,Bausteine!$A$2:$AS$46,8,FALSE))+IF(E8="",0,VLOOKUP(E8,Bausteine!$A$2:$AS$46,8,FALSE))+IF(G8="",0,VLOOKUP(G8,Bausteine!$A$2:$AS$46,8,FALSE))+IF(H8="",0,VLOOKUP(H8,Bausteine!$A$2:$AS$46,8,FALSE))+IF(I8="",0,VLOOKUP(I8,Bausteine!$A$2:$AS$46,8,FALSE))+IF(J8="",0,VLOOKUP(J8,Bausteine!$A$2:$AS$46,8,FALSE))+IF(K8="",0,VLOOKUP(K8,Bausteine!$A$2:$AS$46,8,FALSE))+IF(L8="",0,VLOOKUP(L8,Bausteine!$A$2:$AS$46,8,FALSE))+IF(AC8="",0,VLOOKUP(AC8,Bausteine!$A$2:$AS$46,8,FALSE))+IF(AF8="",0,VLOOKUP(AF8,Bausteine!$A$2:$AS$46,8,FALSE))+IF(AG8="",0,VLOOKUP(AG8,Bausteine!$A$2:$AS$46,8,FALSE))+IF(AH8="",0,VLOOKUP(AH8,Bausteine!$A$2:$AS$46,8,FALSE))+AJ8 | U8: =IF(C8="",0,VLOOKUP(C8,Bausteine!$A$2:$AS$46,9,FALSE))+IF(D8="",0,VLOOKUP(D8,Bausteine!$A$2:$AS$46,9,FALSE))+IF(E8="",0,VLOOKUP(E8,Bausteine!$A$2:$AS$46,9,FALSE))+IF(F8="",0,VLOOKUP(F8,Bausteine!$A$2:$AS$46,9,FALSE))+IF(G8="",0,VLOOKUP(G8,Bausteine!$A$2:$AS$46,9,FALSE))+IF(H8="",0,VLOOKUP(H8,Bausteine!$A$2:$AS$46,9,FALSE))+IF(I8="",0,VLOOKUP(I8,Bausteine!$A$2:$AS$46,9,FALSE))+IF(J8="",0,VLOOKUP(J8,Bausteine!$A$2:$AS$46,9,FALSE))+IF(K8="",0,VLOOKUP(K8,Bausteine!$A$2:$AS$46,9,FALSE))+IF(L8="",0,VLOOKUP(L8,Bausteine!$A$2:$AS$46,9,FALSE))+IF(AC8="",0,VLOOKUP(AC8,Bausteine!$A$2:$AS$46,9,FALSE))+IF(AF8="",0,VLOOKUP(AF8,Bausteine!$A$2:$AS$46,9,FALSE))+IF(AG8="",0,VLOOKUP(AG8,Bausteine!$A$2:$AS$46,9,FALSE))+IF(AH8="",0,VLOOKUP(AH8,Bausteine!$A$2:$AS$46,9,FALSE)) | V8: =IF(D8="",0,VLOOKUP(D8,Bausteine!$A$2:$AS$46,10,FALSE))-U8/IF(E8="",0,VLOOKUP(E8,Bausteine!$A$2:$AS$46,11,FALSE)) | W8: =IF(Y8<>"OK","",ROUND(MIN(IF(C8="",0,VLOOKUP(C8,Bausteine!$A$2:$AS$46,21,FALSE)),IF(C8="",0,VLOOKUP(C8,Bausteine!$A$2:$AS$46,20,FALSE))*(V8/T8/(IF(C8="",0,VLOOKUP(C8,Bausteine!$A$2:$AS$46,19,FALSE))/IF(C8="",0,VLOOKUP(C8,Bausteine!$A$2:$AS$46,18,FALSE))))^Parameter!$B$3),0)) | X8: =IF(F8="",0,VLOOKUP(F8,Bausteine!$A$2:$AS$46,14,FALSE)) | Y8: =IFERROR(IF(OR(AD8<=0,AD8>1,R8<=0,T8<=0,V8<=0,U8>IF(E8="",0,VLOOKUP(E8,Bausteine!$A$2:$AS$46,12,FALSE)),T8>IF(C8="",0,VLOOKUP(C8,Bausteine!$A$2:$AS$46,22,FALSE)),IF(E8="",0,VLOOKUP(E8,Bausteine!$A$2:$AS$46,11,FALSE))<=0,IF(E8="",0,VLOOKUP(E8,Bausteine!$A$2:$AS$46,11,FALSE))>1),"UNGUELTIG","OK"),"FEHLER") | Z8: 2000 | AA8: 54 | AB8: Separate roof carrier; retains main cannon. Gatling spin-up and sensors reuse existing templates. | AD8: =IF(AC8="",1,IF(AC8="",0,VLOOKUP(AC8,Bausteine!$A$2:$AS$46,37,FALSE))/100) | AE8: =P8*AD8 | AF8: gatling-roof-carrier | AG8: gatling-gun | AH8: gatling-rounds | AI8: =SUMIF(Startbesatzung!$A$2:$A$7,A8,Startbesatzung!$D$2:$D$7) | AJ8: =SUMIF(Startbesatzung!$A$2:$A$7,A8,Startbesatzung!$E$2:$E$7) | AK8: =MAX(0,IF(Startbesatzung!A2=A8,Startbesatzung!G2,0),IF(Startbesatzung!A3=A8,Startbesatzung!G3,0),IF(Startbesatzung!A4=A8,Startbesatzung!G4,0),IF(Startbesatzung!A5=A8,Startbesatzung!G5,0),IF(Startbesatzung!A6=A8,Startbesatzung!G6,0),IF(Startbesatzung!A7=A8,Startbesatzung!G7,0)) | AL8: =IF(AF8="","",IF(IF(AH8="",0,VLOOKUP(AH8,Bausteine!$A$2:$AS$46,38,FALSE))>0,IF(AH8="",0,VLOOKUP(AH8,Bausteine!$A$2:$AS$46,38,FALSE)),IF(AG8="",0,VLOOKUP(AG8,Bausteine!$A$2:$AS$46,28,FALSE)))) | AM8: =IF(AF8="","",IF(AG8="",0,VLOOKUP(AG8,Bausteine!$A$2:$AS$46,44,FALSE))) | AN8: =IF(AF8="","",IF(AF8="",0,VLOOKUP(AF8,Bausteine!$A$2:$AS$46,27,FALSE))) | AO8: =IF(AF8="","",IF(AF8="",0,VLOOKUP(AF8,Bausteine!$A$2:$AS$46,25,FALSE))) | AP8: =IF(AF8="","",IF(AH8="",0,VLOOKUP(AH8,Bausteine!$A$2:$AS$46,29,FALSE)))
A9: Overlord Gatling PDL | B9: china | C9: overlord-chassis | D9: diesel-heavy-boost | E9: efficient-generator | F9: heavy | G9: heavy-twin-turret | H9: overlord-cannon | I9: heavy-shell | J9: pdl | M9: =IF(C9="",0,VLOOKUP(C9,Bausteine!$A$2:$AS$46,4,FALSE))+IF(D9="",0,VLOOKUP(D9,Bausteine!$A$2:$AS$46,4,FALSE))+IF(E9="",0,VLOOKUP(E9,Bausteine!$A$2:$AS$46,4,FALSE))+IF(F9="",0,VLOOKUP(F9,Bausteine!$A$2:$AS$46,4,FALSE))+IF(G9="",0,VLOOKUP(G9,Bausteine!$A$2:$AS$46,4,FALSE))+IF(H9="",0,VLOOKUP(H9,Bausteine!$A$2:$AS$46,4,FALSE))+IF(I9="",0,VLOOKUP(I9,Bausteine!$A$2:$AS$46,4,FALSE))+IF(J9="",0,VLOOKUP(J9,Bausteine!$A$2:$AS$46,4,FALSE))+IF(K9="",0,VLOOKUP(K9,Bausteine!$A$2:$AS$46,4,FALSE))+IF(L9="",0,VLOOKUP(L9,Bausteine!$A$2:$AS$46,4,FALSE))+IF(AC9="",0,VLOOKUP(AC9,Bausteine!$A$2:$AS$46,4,FALSE))+IF(AF9="",0,VLOOKUP(AF9,Bausteine!$A$2:$AS$46,4,FALSE))+IF(AG9="",0,VLOOKUP(AG9,Bausteine!$A$2:$AS$46,4,FALSE))+IF(AH9="",0,VLOOKUP(AH9,Bausteine!$A$2:$AS$46,4,FALSE)) | N9: =IF(C9="",0,VLOOKUP(C9,Bausteine!$A$2:$AS$46,5,FALSE))+IF(D9="",0,VLOOKUP(D9,Bausteine!$A$2:$AS$46,5,FALSE))+IF(E9="",0,VLOOKUP(E9,Bausteine!$A$2:$AS$46,5,FALSE))+IF(F9="",0,VLOOKUP(F9,Bausteine!$A$2:$AS$46,5,FALSE))+IF(G9="",0,VLOOKUP(G9,Bausteine!$A$2:$AS$46,5,FALSE))+IF(H9="",0,VLOOKUP(H9,Bausteine!$A$2:$AS$46,5,FALSE))+IF(I9="",0,VLOOKUP(I9,Bausteine!$A$2:$AS$46,5,FALSE))+IF(J9="",0,VLOOKUP(J9,Bausteine!$A$2:$AS$46,5,FALSE))+IF(K9="",0,VLOOKUP(K9,Bausteine!$A$2:$AS$46,5,FALSE))+IF(L9="",0,VLOOKUP(L9,Bausteine!$A$2:$AS$46,5,FALSE))+IF(AC9="",0,VLOOKUP(AC9,Bausteine!$A$2:$AS$46,5,FALSE))+IF(AF9="",0,VLOOKUP(AF9,Bausteine!$A$2:$AS$46,5,FALSE))+IF(AG9="",0,VLOOKUP(AG9,Bausteine!$A$2:$AS$46,5,FALSE))+IF(AH9="",0,VLOOKUP(AH9,Bausteine!$A$2:$AS$46,5,FALSE)) | O9: =MAX(IF(C9="",0,VLOOKUP(C9,Bausteine!$A$2:$AS$46,6,FALSE)),IF(D9="",0,VLOOKUP(D9,Bausteine!$A$2:$AS$46,6,FALSE)),IF(E9="",0,VLOOKUP(E9,Bausteine!$A$2:$AS$46,6,FALSE)),IF(F9="",0,VLOOKUP(F9,Bausteine!$A$2:$AS$46,6,FALSE)),IF(G9="",0,VLOOKUP(G9,Bausteine!$A$2:$AS$46,6,FALSE)),IF(H9="",0,VLOOKUP(H9,Bausteine!$A$2:$AS$46,6,FALSE)),IF(I9="",0,VLOOKUP(I9,Bausteine!$A$2:$AS$46,6,FALSE)),IF(J9="",0,VLOOKUP(J9,Bausteine!$A$2:$AS$46,6,FALSE)),IF(K9="",0,VLOOKUP(K9,Bausteine!$A$2:$AS$46,6,FALSE)),IF(L9="",0,VLOOKUP(L9,Bausteine!$A$2:$AS$46,6,FALSE)),IF(AC9="",0,VLOOKUP(AC9,Bausteine!$A$2:$AS$46,6,FALSE)),IF(AF9="",0,VLOOKUP(AF9,Bausteine!$A$2:$AS$46,6,FALSE)),IF(AG9="",0,VLOOKUP(AG9,Bausteine!$A$2:$AS$46,6,FALSE)),IF(AH9="",0,VLOOKUP(AH9,Bausteine!$A$2:$AS$46,6,FALSE)),AK9) | P9: =IF(C9="",0,VLOOKUP(C9,Bausteine!$A$2:$AS$46,7,FALSE))*IF(F9="",0,VLOOKUP(F9,Bausteine!$A$2:$AS$46,17,FALSE))/100+IF(D9="",0,VLOOKUP(D9,Bausteine!$A$2:$AS$46,7,FALSE))+IF(E9="",0,VLOOKUP(E9,Bausteine!$A$2:$AS$46,7,FALSE))+IF(G9="",0,VLOOKUP(G9,Bausteine!$A$2:$AS$46,7,FALSE))+IF(H9="",0,VLOOKUP(H9,Bausteine!$A$2:$AS$46,7,FALSE))+IF(I9="",0,VLOOKUP(I9,Bausteine!$A$2:$AS$46,7,FALSE))+IF(J9="",0,VLOOKUP(J9,Bausteine!$A$2:$AS$46,7,FALSE))+IF(K9="",0,VLOOKUP(K9,Bausteine!$A$2:$AS$46,7,FALSE))+IF(L9="",0,VLOOKUP(L9,Bausteine!$A$2:$AS$46,7,FALSE))+IF(AC9="",0,VLOOKUP(AC9,Bausteine!$A$2:$AS$46,7,FALSE))+IF(AF9="",0,VLOOKUP(AF9,Bausteine!$A$2:$AS$46,7,FALSE))+IF(AG9="",0,VLOOKUP(AG9,Bausteine!$A$2:$AS$46,7,FALSE))+IF(AH9="",0,VLOOKUP(AH9,Bausteine!$A$2:$AS$46,7,FALSE))+AI9 | Q9: =N9*Parameter!$B$2 | R9: =AE9-Q9 | S9: =IF(C9="",0,VLOOKUP(C9,Bausteine!$A$2:$AS$46,13,FALSE))*IF(F9="",0,VLOOKUP(F9,Bausteine!$A$2:$AS$46,16,FALSE))/100 | T9: =IF(C9="",0,VLOOKUP(C9,Bausteine!$A$2:$AS$46,8,FALSE))*IF(F9="",0,VLOOKUP(F9,Bausteine!$A$2:$AS$46,15,FALSE))/100+IF(D9="",0,VLOOKUP(D9,Bausteine!$A$2:$AS$46,8,FALSE))+IF(E9="",0,VLOOKUP(E9,Bausteine!$A$2:$AS$46,8,FALSE))+IF(G9="",0,VLOOKUP(G9,Bausteine!$A$2:$AS$46,8,FALSE))+IF(H9="",0,VLOOKUP(H9,Bausteine!$A$2:$AS$46,8,FALSE))+IF(I9="",0,VLOOKUP(I9,Bausteine!$A$2:$AS$46,8,FALSE))+IF(J9="",0,VLOOKUP(J9,Bausteine!$A$2:$AS$46,8,FALSE))+IF(K9="",0,VLOOKUP(K9,Bausteine!$A$2:$AS$46,8,FALSE))+IF(L9="",0,VLOOKUP(L9,Bausteine!$A$2:$AS$46,8,FALSE))+IF(AC9="",0,VLOOKUP(AC9,Bausteine!$A$2:$AS$46,8,FALSE))+IF(AF9="",0,VLOOKUP(AF9,Bausteine!$A$2:$AS$46,8,FALSE))+IF(AG9="",0,VLOOKUP(AG9,Bausteine!$A$2:$AS$46,8,FALSE))+IF(AH9="",0,VLOOKUP(AH9,Bausteine!$A$2:$AS$46,8,FALSE))+AJ9 | U9: =IF(C9="",0,VLOOKUP(C9,Bausteine!$A$2:$AS$46,9,FALSE))+IF(D9="",0,VLOOKUP(D9,Bausteine!$A$2:$AS$46,9,FALSE))+IF(E9="",0,VLOOKUP(E9,Bausteine!$A$2:$AS$46,9,FALSE))+IF(F9="",0,VLOOKUP(F9,Bausteine!$A$2:$AS$46,9,FALSE))+IF(G9="",0,VLOOKUP(G9,Bausteine!$A$2:$AS$46,9,FALSE))+IF(H9="",0,VLOOKUP(H9,Bausteine!$A$2:$AS$46,9,FALSE))+IF(I9="",0,VLOOKUP(I9,Bausteine!$A$2:$AS$46,9,FALSE))+IF(J9="",0,VLOOKUP(J9,Bausteine!$A$2:$AS$46,9,FALSE))+IF(K9="",0,VLOOKUP(K9,Bausteine!$A$2:$AS$46,9,FALSE))+IF(L9="",0,VLOOKUP(L9,Bausteine!$A$2:$AS$46,9,FALSE))+IF(AC9="",0,VLOOKUP(AC9,Bausteine!$A$2:$AS$46,9,FALSE))+IF(AF9="",0,VLOOKUP(AF9,Bausteine!$A$2:$AS$46,9,FALSE))+IF(AG9="",0,VLOOKUP(AG9,Bausteine!$A$2:$AS$46,9,FALSE))+IF(AH9="",0,VLOOKUP(AH9,Bausteine!$A$2:$AS$46,9,FALSE)) | V9: =IF(D9="",0,VLOOKUP(D9,Bausteine!$A$2:$AS$46,10,FALSE))-U9/IF(E9="",0,VLOOKUP(E9,Bausteine!$A$2:$AS$46,11,FALSE)) | W9: =IF(Y9<>"OK","",ROUND(MIN(IF(C9="",0,VLOOKUP(C9,Bausteine!$A$2:$AS$46,21,FALSE)),IF(C9="",0,VLOOKUP(C9,Bausteine!$A$2:$AS$46,20,FALSE))*(V9/T9/(IF(C9="",0,VLOOKUP(C9,Bausteine!$A$2:$AS$46,19,FALSE))/IF(C9="",0,VLOOKUP(C9,Bausteine!$A$2:$AS$46,18,FALSE))))^Parameter!$B$3),0)) | X9: =IF(F9="",0,VLOOKUP(F9,Bausteine!$A$2:$AS$46,14,FALSE)) | Y9: =IFERROR(IF(OR(AD9<=0,AD9>1,R9<=0,T9<=0,V9<=0,U9>IF(E9="",0,VLOOKUP(E9,Bausteine!$A$2:$AS$46,12,FALSE)),T9>IF(C9="",0,VLOOKUP(C9,Bausteine!$A$2:$AS$46,22,FALSE)),IF(E9="",0,VLOOKUP(E9,Bausteine!$A$2:$AS$46,11,FALSE))<=0,IF(E9="",0,VLOOKUP(E9,Bausteine!$A$2:$AS$46,11,FALSE))>1),"UNGUELTIG","OK"),"FEHLER") | Z9: 2650 | AA9: 55 | AD9: =IF(AC9="",1,IF(AC9="",0,VLOOKUP(AC9,Bausteine!$A$2:$AS$46,37,FALSE))/100) | AE9: =P9*AD9 | AF9: gatling-roof-carrier | AG9: gatling-gun | AH9: gatling-rounds | AI9: =SUMIF(Startbesatzung!$A$2:$A$7,A9,Startbesatzung!$D$2:$D$7) | AJ9: =SUMIF(Startbesatzung!$A$2:$A$7,A9,Startbesatzung!$E$2:$E$7) | AK9: =MAX(0,IF(Startbesatzung!A2=A9,Startbesatzung!G2,0),IF(Startbesatzung!A3=A9,Startbesatzung!G3,0),IF(Startbesatzung!A4=A9,Startbesatzung!G4,0),IF(Startbesatzung!A5=A9,Startbesatzung!G5,0),IF(Startbesatzung!A6=A9,Startbesatzung!G6,0),IF(Startbesatzung!A7=A9,Startbesatzung!G7,0)) | AL9: =IF(AF9="","",IF(IF(AH9="",0,VLOOKUP(AH9,Bausteine!$A$2:$AS$46,38,FALSE))>0,IF(AH9="",0,VLOOKUP(AH9,Bausteine!$A$2:$AS$46,38,FALSE)),IF(AG9="",0,VLOOKUP(AG9,Bausteine!$A$2:$AS$46,28,FALSE)))) | AM9: =IF(AF9="","",IF(AG9="",0,VLOOKUP(AG9,Bausteine!$A$2:$AS$46,44,FALSE))) | AN9: =IF(AF9="","",IF(AF9="",0,VLOOKUP(AF9,Bausteine!$A$2:$AS$46,27,FALSE))) | AO9: =IF(AF9="","",IF(AF9="",0,VLOOKUP(AF9,Bausteine!$A$2:$AS$46,25,FALSE))) | AP9: =IF(AF9="","",IF(AH9="",0,VLOOKUP(AH9,Bausteine!$A$2:$AS$46,29,FALSE)))
A10: Overlord Gatling Reflector | B10: china | C10: overlord-chassis | D10: diesel-heavy-boost | E10: efficient-generator | F10: reflector | G10: heavy-twin-turret | H10: overlord-cannon | I10: heavy-shell | M10: =IF(C10="",0,VLOOKUP(C10,Bausteine!$A$2:$AS$46,4,FALSE))+IF(D10="",0,VLOOKUP(D10,Bausteine!$A$2:$AS$46,4,FALSE))+IF(E10="",0,VLOOKUP(E10,Bausteine!$A$2:$AS$46,4,FALSE))+IF(F10="",0,VLOOKUP(F10,Bausteine!$A$2:$AS$46,4,FALSE))+IF(G10="",0,VLOOKUP(G10,Bausteine!$A$2:$AS$46,4,FALSE))+IF(H10="",0,VLOOKUP(H10,Bausteine!$A$2:$AS$46,4,FALSE))+IF(I10="",0,VLOOKUP(I10,Bausteine!$A$2:$AS$46,4,FALSE))+IF(J10="",0,VLOOKUP(J10,Bausteine!$A$2:$AS$46,4,FALSE))+IF(K10="",0,VLOOKUP(K10,Bausteine!$A$2:$AS$46,4,FALSE))+IF(L10="",0,VLOOKUP(L10,Bausteine!$A$2:$AS$46,4,FALSE))+IF(AC10="",0,VLOOKUP(AC10,Bausteine!$A$2:$AS$46,4,FALSE))+IF(AF10="",0,VLOOKUP(AF10,Bausteine!$A$2:$AS$46,4,FALSE))+IF(AG10="",0,VLOOKUP(AG10,Bausteine!$A$2:$AS$46,4,FALSE))+IF(AH10="",0,VLOOKUP(AH10,Bausteine!$A$2:$AS$46,4,FALSE)) | N10: =IF(C10="",0,VLOOKUP(C10,Bausteine!$A$2:$AS$46,5,FALSE))+IF(D10="",0,VLOOKUP(D10,Bausteine!$A$2:$AS$46,5,FALSE))+IF(E10="",0,VLOOKUP(E10,Bausteine!$A$2:$AS$46,5,FALSE))+IF(F10="",0,VLOOKUP(F10,Bausteine!$A$2:$AS$46,5,FALSE))+IF(G10="",0,VLOOKUP(G10,Bausteine!$A$2:$AS$46,5,FALSE))+IF(H10="",0,VLOOKUP(H10,Bausteine!$A$2:$AS$46,5,FALSE))+IF(I10="",0,VLOOKUP(I10,Bausteine!$A$2:$AS$46,5,FALSE))+IF(J10="",0,VLOOKUP(J10,Bausteine!$A$2:$AS$46,5,FALSE))+IF(K10="",0,VLOOKUP(K10,Bausteine!$A$2:$AS$46,5,FALSE))+IF(L10="",0,VLOOKUP(L10,Bausteine!$A$2:$AS$46,5,FALSE))+IF(AC10="",0,VLOOKUP(AC10,Bausteine!$A$2:$AS$46,5,FALSE))+IF(AF10="",0,VLOOKUP(AF10,Bausteine!$A$2:$AS$46,5,FALSE))+IF(AG10="",0,VLOOKUP(AG10,Bausteine!$A$2:$AS$46,5,FALSE))+IF(AH10="",0,VLOOKUP(AH10,Bausteine!$A$2:$AS$46,5,FALSE)) | O10: =MAX(IF(C10="",0,VLOOKUP(C10,Bausteine!$A$2:$AS$46,6,FALSE)),IF(D10="",0,VLOOKUP(D10,Bausteine!$A$2:$AS$46,6,FALSE)),IF(E10="",0,VLOOKUP(E10,Bausteine!$A$2:$AS$46,6,FALSE)),IF(F10="",0,VLOOKUP(F10,Bausteine!$A$2:$AS$46,6,FALSE)),IF(G10="",0,VLOOKUP(G10,Bausteine!$A$2:$AS$46,6,FALSE)),IF(H10="",0,VLOOKUP(H10,Bausteine!$A$2:$AS$46,6,FALSE)),IF(I10="",0,VLOOKUP(I10,Bausteine!$A$2:$AS$46,6,FALSE)),IF(J10="",0,VLOOKUP(J10,Bausteine!$A$2:$AS$46,6,FALSE)),IF(K10="",0,VLOOKUP(K10,Bausteine!$A$2:$AS$46,6,FALSE)),IF(L10="",0,VLOOKUP(L10,Bausteine!$A$2:$AS$46,6,FALSE)),IF(AC10="",0,VLOOKUP(AC10,Bausteine!$A$2:$AS$46,6,FALSE)),IF(AF10="",0,VLOOKUP(AF10,Bausteine!$A$2:$AS$46,6,FALSE)),IF(AG10="",0,VLOOKUP(AG10,Bausteine!$A$2:$AS$46,6,FALSE)),IF(AH10="",0,VLOOKUP(AH10,Bausteine!$A$2:$AS$46,6,FALSE)),AK10) | P10: =IF(C10="",0,VLOOKUP(C10,Bausteine!$A$2:$AS$46,7,FALSE))*IF(F10="",0,VLOOKUP(F10,Bausteine!$A$2:$AS$46,17,FALSE))/100+IF(D10="",0,VLOOKUP(D10,Bausteine!$A$2:$AS$46,7,FALSE))+IF(E10="",0,VLOOKUP(E10,Bausteine!$A$2:$AS$46,7,FALSE))+IF(G10="",0,VLOOKUP(G10,Bausteine!$A$2:$AS$46,7,FALSE))+IF(H10="",0,VLOOKUP(H10,Bausteine!$A$2:$AS$46,7,FALSE))+IF(I10="",0,VLOOKUP(I10,Bausteine!$A$2:$AS$46,7,FALSE))+IF(J10="",0,VLOOKUP(J10,Bausteine!$A$2:$AS$46,7,FALSE))+IF(K10="",0,VLOOKUP(K10,Bausteine!$A$2:$AS$46,7,FALSE))+IF(L10="",0,VLOOKUP(L10,Bausteine!$A$2:$AS$46,7,FALSE))+IF(AC10="",0,VLOOKUP(AC10,Bausteine!$A$2:$AS$46,7,FALSE))+IF(AF10="",0,VLOOKUP(AF10,Bausteine!$A$2:$AS$46,7,FALSE))+IF(AG10="",0,VLOOKUP(AG10,Bausteine!$A$2:$AS$46,7,FALSE))+IF(AH10="",0,VLOOKUP(AH10,Bausteine!$A$2:$AS$46,7,FALSE))+AI10 | Q10: =N10*Parameter!$B$2 | R10: =AE10-Q10 | S10: =IF(C10="",0,VLOOKUP(C10,Bausteine!$A$2:$AS$46,13,FALSE))*IF(F10="",0,VLOOKUP(F10,Bausteine!$A$2:$AS$46,16,FALSE))/100 | T10: =IF(C10="",0,VLOOKUP(C10,Bausteine!$A$2:$AS$46,8,FALSE))*IF(F10="",0,VLOOKUP(F10,Bausteine!$A$2:$AS$46,15,FALSE))/100+IF(D10="",0,VLOOKUP(D10,Bausteine!$A$2:$AS$46,8,FALSE))+IF(E10="",0,VLOOKUP(E10,Bausteine!$A$2:$AS$46,8,FALSE))+IF(G10="",0,VLOOKUP(G10,Bausteine!$A$2:$AS$46,8,FALSE))+IF(H10="",0,VLOOKUP(H10,Bausteine!$A$2:$AS$46,8,FALSE))+IF(I10="",0,VLOOKUP(I10,Bausteine!$A$2:$AS$46,8,FALSE))+IF(J10="",0,VLOOKUP(J10,Bausteine!$A$2:$AS$46,8,FALSE))+IF(K10="",0,VLOOKUP(K10,Bausteine!$A$2:$AS$46,8,FALSE))+IF(L10="",0,VLOOKUP(L10,Bausteine!$A$2:$AS$46,8,FALSE))+IF(AC10="",0,VLOOKUP(AC10,Bausteine!$A$2:$AS$46,8,FALSE))+IF(AF10="",0,VLOOKUP(AF10,Bausteine!$A$2:$AS$46,8,FALSE))+IF(AG10="",0,VLOOKUP(AG10,Bausteine!$A$2:$AS$46,8,FALSE))+IF(AH10="",0,VLOOKUP(AH10,Bausteine!$A$2:$AS$46,8,FALSE))+AJ10 | U10: =IF(C10="",0,VLOOKUP(C10,Bausteine!$A$2:$AS$46,9,FALSE))+IF(D10="",0,VLOOKUP(D10,Bausteine!$A$2:$AS$46,9,FALSE))+IF(E10="",0,VLOOKUP(E10,Bausteine!$A$2:$AS$46,9,FALSE))+IF(F10="",0,VLOOKUP(F10,Bausteine!$A$2:$AS$46,9,FALSE))+IF(G10="",0,VLOOKUP(G10,Bausteine!$A$2:$AS$46,9,FALSE))+IF(H10="",0,VLOOKUP(H10,Bausteine!$A$2:$AS$46,9,FALSE))+IF(I10="",0,VLOOKUP(I10,Bausteine!$A$2:$AS$46,9,FALSE))+IF(J10="",0,VLOOKUP(J10,Bausteine!$A$2:$AS$46,9,FALSE))+IF(K10="",0,VLOOKUP(K10,Bausteine!$A$2:$AS$46,9,FALSE))+IF(L10="",0,VLOOKUP(L10,Bausteine!$A$2:$AS$46,9,FALSE))+IF(AC10="",0,VLOOKUP(AC10,Bausteine!$A$2:$AS$46,9,FALSE))+IF(AF10="",0,VLOOKUP(AF10,Bausteine!$A$2:$AS$46,9,FALSE))+IF(AG10="",0,VLOOKUP(AG10,Bausteine!$A$2:$AS$46,9,FALSE))+IF(AH10="",0,VLOOKUP(AH10,Bausteine!$A$2:$AS$46,9,FALSE)) | V10: =IF(D10="",0,VLOOKUP(D10,Bausteine!$A$2:$AS$46,10,FALSE))-U10/IF(E10="",0,VLOOKUP(E10,Bausteine!$A$2:$AS$46,11,FALSE)) | W10: =IF(Y10<>"OK","",ROUND(MIN(IF(C10="",0,VLOOKUP(C10,Bausteine!$A$2:$AS$46,21,FALSE)),IF(C10="",0,VLOOKUP(C10,Bausteine!$A$2:$AS$46,20,FALSE))*(V10/T10/(IF(C10="",0,VLOOKUP(C10,Bausteine!$A$2:$AS$46,19,FALSE))/IF(C10="",0,VLOOKUP(C10,Bausteine!$A$2:$AS$46,18,FALSE))))^Parameter!$B$3),0)) | X10: =IF(F10="",0,VLOOKUP(F10,Bausteine!$A$2:$AS$46,14,FALSE)) | Y10: =IFERROR(IF(OR(AD10<=0,AD10>1,R10<=0,T10<=0,V10<=0,U10>IF(E10="",0,VLOOKUP(E10,Bausteine!$A$2:$AS$46,12,FALSE)),T10>IF(C10="",0,VLOOKUP(C10,Bausteine!$A$2:$AS$46,22,FALSE)),IF(E10="",0,VLOOKUP(E10,Bausteine!$A$2:$AS$46,11,FALSE))<=0,IF(E10="",0,VLOOKUP(E10,Bausteine!$A$2:$AS$46,11,FALSE))>1),"UNGUELTIG","OK"),"FEHLER") | Z10: 2000 | AA10: 55 | AD10: =IF(AC10="",1,IF(AC10="",0,VLOOKUP(AC10,Bausteine!$A$2:$AS$46,37,FALSE))/100) | AE10: =P10*AD10 | AF10: gatling-roof-carrier | AG10: gatling-gun | AH10: gatling-rounds | AI10: =SUMIF(Startbesatzung!$A$2:$A$7,A10,Startbesatzung!$D$2:$D$7) | AJ10: =SUMIF(Startbesatzung!$A$2:$A$7,A10,Startbesatzung!$E$2:$E$7) | AK10: =MAX(0,IF(Startbesatzung!A2=A10,Startbesatzung!G2,0),IF(Startbesatzung!A3=A10,Startbesatzung!G3,0),IF(Startbesatzung!A4=A10,Startbesatzung!G4,0),IF(Startbesatzung!A5=A10,Startbesatzung!G5,0),IF(Startbesatzung!A6=A10,Startbesatzung!G6,0),IF(Startbesatzung!A7=A10,Startbesatzung!G7,0)) | AL10: =IF(AF10="","",IF(IF(AH10="",0,VLOOKUP(AH10,Bausteine!$A$2:$AS$46,38,FALSE))>0,IF(AH10="",0,VLOOKUP(AH10,Bausteine!$A$2:$AS$46,38,FALSE)),IF(AG10="",0,VLOOKUP(AG10,Bausteine!$A$2:$AS$46,28,FALSE)))) | AM10: =IF(AF10="","",IF(AG10="",0,VLOOKUP(AG10,Bausteine!$A$2:$AS$46,44,FALSE))) | AN10: =IF(AF10="","",IF(AF10="",0,VLOOKUP(AF10,Bausteine!$A$2:$AS$46,27,FALSE))) | AO10: =IF(AF10="","",IF(AF10="",0,VLOOKUP(AF10,Bausteine!$A$2:$AS$46,25,FALSE))) | AP10: =IF(AF10="","",IF(AH10="",0,VLOOKUP(AH10,Bausteine!$A$2:$AS$46,29,FALSE)))
A11: Overlord Bunker / mixed crew | B11: china | C11: overlord-chassis | D11: diesel-heavy | E11: baseline-generator | F11: heavy | G11: heavy-twin-turret | H11: overlord-cannon | I11: heavy-shell | J11: firing-bunker | M11: =IF(C11="",0,VLOOKUP(C11,Bausteine!$A$2:$AS$46,4,FALSE))+IF(D11="",0,VLOOKUP(D11,Bausteine!$A$2:$AS$46,4,FALSE))+IF(E11="",0,VLOOKUP(E11,Bausteine!$A$2:$AS$46,4,FALSE))+IF(F11="",0,VLOOKUP(F11,Bausteine!$A$2:$AS$46,4,FALSE))+IF(G11="",0,VLOOKUP(G11,Bausteine!$A$2:$AS$46,4,FALSE))+IF(H11="",0,VLOOKUP(H11,Bausteine!$A$2:$AS$46,4,FALSE))+IF(I11="",0,VLOOKUP(I11,Bausteine!$A$2:$AS$46,4,FALSE))+IF(J11="",0,VLOOKUP(J11,Bausteine!$A$2:$AS$46,4,FALSE))+IF(K11="",0,VLOOKUP(K11,Bausteine!$A$2:$AS$46,4,FALSE))+IF(L11="",0,VLOOKUP(L11,Bausteine!$A$2:$AS$46,4,FALSE))+IF(AC11="",0,VLOOKUP(AC11,Bausteine!$A$2:$AS$46,4,FALSE))+IF(AF11="",0,VLOOKUP(AF11,Bausteine!$A$2:$AS$46,4,FALSE))+IF(AG11="",0,VLOOKUP(AG11,Bausteine!$A$2:$AS$46,4,FALSE))+IF(AH11="",0,VLOOKUP(AH11,Bausteine!$A$2:$AS$46,4,FALSE)) | N11: =IF(C11="",0,VLOOKUP(C11,Bausteine!$A$2:$AS$46,5,FALSE))+IF(D11="",0,VLOOKUP(D11,Bausteine!$A$2:$AS$46,5,FALSE))+IF(E11="",0,VLOOKUP(E11,Bausteine!$A$2:$AS$46,5,FALSE))+IF(F11="",0,VLOOKUP(F11,Bausteine!$A$2:$AS$46,5,FALSE))+IF(G11="",0,VLOOKUP(G11,Bausteine!$A$2:$AS$46,5,FALSE))+IF(H11="",0,VLOOKUP(H11,Bausteine!$A$2:$AS$46,5,FALSE))+IF(I11="",0,VLOOKUP(I11,Bausteine!$A$2:$AS$46,5,FALSE))+IF(J11="",0,VLOOKUP(J11,Bausteine!$A$2:$AS$46,5,FALSE))+IF(K11="",0,VLOOKUP(K11,Bausteine!$A$2:$AS$46,5,FALSE))+IF(L11="",0,VLOOKUP(L11,Bausteine!$A$2:$AS$46,5,FALSE))+IF(AC11="",0,VLOOKUP(AC11,Bausteine!$A$2:$AS$46,5,FALSE))+IF(AF11="",0,VLOOKUP(AF11,Bausteine!$A$2:$AS$46,5,FALSE))+IF(AG11="",0,VLOOKUP(AG11,Bausteine!$A$2:$AS$46,5,FALSE))+IF(AH11="",0,VLOOKUP(AH11,Bausteine!$A$2:$AS$46,5,FALSE)) | O11: =MAX(IF(C11="",0,VLOOKUP(C11,Bausteine!$A$2:$AS$46,6,FALSE)),IF(D11="",0,VLOOKUP(D11,Bausteine!$A$2:$AS$46,6,FALSE)),IF(E11="",0,VLOOKUP(E11,Bausteine!$A$2:$AS$46,6,FALSE)),IF(F11="",0,VLOOKUP(F11,Bausteine!$A$2:$AS$46,6,FALSE)),IF(G11="",0,VLOOKUP(G11,Bausteine!$A$2:$AS$46,6,FALSE)),IF(H11="",0,VLOOKUP(H11,Bausteine!$A$2:$AS$46,6,FALSE)),IF(I11="",0,VLOOKUP(I11,Bausteine!$A$2:$AS$46,6,FALSE)),IF(J11="",0,VLOOKUP(J11,Bausteine!$A$2:$AS$46,6,FALSE)),IF(K11="",0,VLOOKUP(K11,Bausteine!$A$2:$AS$46,6,FALSE)),IF(L11="",0,VLOOKUP(L11,Bausteine!$A$2:$AS$46,6,FALSE)),IF(AC11="",0,VLOOKUP(AC11,Bausteine!$A$2:$AS$46,6,FALSE)),IF(AF11="",0,VLOOKUP(AF11,Bausteine!$A$2:$AS$46,6,FALSE)),IF(AG11="",0,VLOOKUP(AG11,Bausteine!$A$2:$AS$46,6,FALSE)),IF(AH11="",0,VLOOKUP(AH11,Bausteine!$A$2:$AS$46,6,FALSE)),AK11) | P11: =IF(C11="",0,VLOOKUP(C11,Bausteine!$A$2:$AS$46,7,FALSE))*IF(F11="",0,VLOOKUP(F11,Bausteine!$A$2:$AS$46,17,FALSE))/100+IF(D11="",0,VLOOKUP(D11,Bausteine!$A$2:$AS$46,7,FALSE))+IF(E11="",0,VLOOKUP(E11,Bausteine!$A$2:$AS$46,7,FALSE))+IF(G11="",0,VLOOKUP(G11,Bausteine!$A$2:$AS$46,7,FALSE))+IF(H11="",0,VLOOKUP(H11,Bausteine!$A$2:$AS$46,7,FALSE))+IF(I11="",0,VLOOKUP(I11,Bausteine!$A$2:$AS$46,7,FALSE))+IF(J11="",0,VLOOKUP(J11,Bausteine!$A$2:$AS$46,7,FALSE))+IF(K11="",0,VLOOKUP(K11,Bausteine!$A$2:$AS$46,7,FALSE))+IF(L11="",0,VLOOKUP(L11,Bausteine!$A$2:$AS$46,7,FALSE))+IF(AC11="",0,VLOOKUP(AC11,Bausteine!$A$2:$AS$46,7,FALSE))+IF(AF11="",0,VLOOKUP(AF11,Bausteine!$A$2:$AS$46,7,FALSE))+IF(AG11="",0,VLOOKUP(AG11,Bausteine!$A$2:$AS$46,7,FALSE))+IF(AH11="",0,VLOOKUP(AH11,Bausteine!$A$2:$AS$46,7,FALSE))+AI11 | Q11: =N11*Parameter!$B$2 | R11: =AE11-Q11 | S11: =IF(C11="",0,VLOOKUP(C11,Bausteine!$A$2:$AS$46,13,FALSE))*IF(F11="",0,VLOOKUP(F11,Bausteine!$A$2:$AS$46,16,FALSE))/100 | T11: =IF(C11="",0,VLOOKUP(C11,Bausteine!$A$2:$AS$46,8,FALSE))*IF(F11="",0,VLOOKUP(F11,Bausteine!$A$2:$AS$46,15,FALSE))/100+IF(D11="",0,VLOOKUP(D11,Bausteine!$A$2:$AS$46,8,FALSE))+IF(E11="",0,VLOOKUP(E11,Bausteine!$A$2:$AS$46,8,FALSE))+IF(G11="",0,VLOOKUP(G11,Bausteine!$A$2:$AS$46,8,FALSE))+IF(H11="",0,VLOOKUP(H11,Bausteine!$A$2:$AS$46,8,FALSE))+IF(I11="",0,VLOOKUP(I11,Bausteine!$A$2:$AS$46,8,FALSE))+IF(J11="",0,VLOOKUP(J11,Bausteine!$A$2:$AS$46,8,FALSE))+IF(K11="",0,VLOOKUP(K11,Bausteine!$A$2:$AS$46,8,FALSE))+IF(L11="",0,VLOOKUP(L11,Bausteine!$A$2:$AS$46,8,FALSE))+IF(AC11="",0,VLOOKUP(AC11,Bausteine!$A$2:$AS$46,8,FALSE))+IF(AF11="",0,VLOOKUP(AF11,Bausteine!$A$2:$AS$46,8,FALSE))+IF(AG11="",0,VLOOKUP(AG11,Bausteine!$A$2:$AS$46,8,FALSE))+IF(AH11="",0,VLOOKUP(AH11,Bausteine!$A$2:$AS$46,8,FALSE))+AJ11 | U11: =IF(C11="",0,VLOOKUP(C11,Bausteine!$A$2:$AS$46,9,FALSE))+IF(D11="",0,VLOOKUP(D11,Bausteine!$A$2:$AS$46,9,FALSE))+IF(E11="",0,VLOOKUP(E11,Bausteine!$A$2:$AS$46,9,FALSE))+IF(F11="",0,VLOOKUP(F11,Bausteine!$A$2:$AS$46,9,FALSE))+IF(G11="",0,VLOOKUP(G11,Bausteine!$A$2:$AS$46,9,FALSE))+IF(H11="",0,VLOOKUP(H11,Bausteine!$A$2:$AS$46,9,FALSE))+IF(I11="",0,VLOOKUP(I11,Bausteine!$A$2:$AS$46,9,FALSE))+IF(J11="",0,VLOOKUP(J11,Bausteine!$A$2:$AS$46,9,FALSE))+IF(K11="",0,VLOOKUP(K11,Bausteine!$A$2:$AS$46,9,FALSE))+IF(L11="",0,VLOOKUP(L11,Bausteine!$A$2:$AS$46,9,FALSE))+IF(AC11="",0,VLOOKUP(AC11,Bausteine!$A$2:$AS$46,9,FALSE))+IF(AF11="",0,VLOOKUP(AF11,Bausteine!$A$2:$AS$46,9,FALSE))+IF(AG11="",0,VLOOKUP(AG11,Bausteine!$A$2:$AS$46,9,FALSE))+IF(AH11="",0,VLOOKUP(AH11,Bausteine!$A$2:$AS$46,9,FALSE)) | V11: =IF(D11="",0,VLOOKUP(D11,Bausteine!$A$2:$AS$46,10,FALSE))-U11/IF(E11="",0,VLOOKUP(E11,Bausteine!$A$2:$AS$46,11,FALSE)) | W11: =IF(Y11<>"OK","",ROUND(MIN(IF(C11="",0,VLOOKUP(C11,Bausteine!$A$2:$AS$46,21,FALSE)),IF(C11="",0,VLOOKUP(C11,Bausteine!$A$2:$AS$46,20,FALSE))*(V11/T11/(IF(C11="",0,VLOOKUP(C11,Bausteine!$A$2:$AS$46,19,FALSE))/IF(C11="",0,VLOOKUP(C11,Bausteine!$A$2:$AS$46,18,FALSE))))^Parameter!$B$3),0)) | X11: =IF(F11="",0,VLOOKUP(F11,Bausteine!$A$2:$AS$46,14,FALSE)) | Y11: =IFERROR(IF(OR(AD11<=0,AD11>1,R11<=0,T11<=0,V11<=0,U11>IF(E11="",0,VLOOKUP(E11,Bausteine!$A$2:$AS$46,12,FALSE)),T11>IF(C11="",0,VLOOKUP(C11,Bausteine!$A$2:$AS$46,22,FALSE)),IF(E11="",0,VLOOKUP(E11,Bausteine!$A$2:$AS$46,11,FALSE))<=0,IF(E11="",0,VLOOKUP(E11,Bausteine!$A$2:$AS$46,11,FALSE))>1),"UNGUELTIG","OK"),"FEHLER") | Z11: 2560 | AA11: 55 | AB11: New combination, not a legacy reference. | AD11: =IF(AC11="",1,IF(AC11="",0,VLOOKUP(AC11,Bausteine!$A$2:$AS$46,37,FALSE))/100) | AE11: =P11*AD11 | AI11: =SUMIF(Startbesatzung!$A$2:$A$7,A11,Startbesatzung!$D$2:$D$7) | AJ11: =SUMIF(Startbesatzung!$A$2:$A$7,A11,Startbesatzung!$E$2:$E$7) | AK11: =MAX(0,IF(Startbesatzung!A2=A11,Startbesatzung!G2,0),IF(Startbesatzung!A3=A11,Startbesatzung!G3,0),IF(Startbesatzung!A4=A11,Startbesatzung!G4,0),IF(Startbesatzung!A5=A11,Startbesatzung!G5,0),IF(Startbesatzung!A6=A11,Startbesatzung!G6,0),IF(Startbesatzung!A7=A11,Startbesatzung!G7,0)) | AL11: =IF(AF11="","",IF(IF(AH11="",0,VLOOKUP(AH11,Bausteine!$A$2:$AS$46,38,FALSE))>0,IF(AH11="",0,VLOOKUP(AH11,Bausteine!$A$2:$AS$46,38,FALSE)),IF(AG11="",0,VLOOKUP(AG11,Bausteine!$A$2:$AS$46,28,FALSE)))) | AM11: =IF(AF11="","",IF(AG11="",0,VLOOKUP(AG11,Bausteine!$A$2:$AS$46,44,FALSE))) | AN11: =IF(AF11="","",IF(AF11="",0,VLOOKUP(AF11,Bausteine!$A$2:$AS$46,27,FALSE))) | AO11: =IF(AF11="","",IF(AF11="",0,VLOOKUP(AF11,Bausteine!$A$2:$AS$46,25,FALSE))) | AP11: =IF(AF11="","",IF(AH11="",0,VLOOKUP(AH11,Bausteine!$A$2:$AS$46,29,FALSE)))
A12: Overlord Bunker / empty | B12: china | C12: overlord-chassis | D12: diesel-heavy | E12: baseline-generator | F12: heavy | G12: heavy-twin-turret | H12: overlord-cannon | I12: heavy-shell | J12: firing-bunker | M12: =IF(C12="",0,VLOOKUP(C12,Bausteine!$A$2:$AS$46,4,FALSE))+IF(D12="",0,VLOOKUP(D12,Bausteine!$A$2:$AS$46,4,FALSE))+IF(E12="",0,VLOOKUP(E12,Bausteine!$A$2:$AS$46,4,FALSE))+IF(F12="",0,VLOOKUP(F12,Bausteine!$A$2:$AS$46,4,FALSE))+IF(G12="",0,VLOOKUP(G12,Bausteine!$A$2:$AS$46,4,FALSE))+IF(H12="",0,VLOOKUP(H12,Bausteine!$A$2:$AS$46,4,FALSE))+IF(I12="",0,VLOOKUP(I12,Bausteine!$A$2:$AS$46,4,FALSE))+IF(J12="",0,VLOOKUP(J12,Bausteine!$A$2:$AS$46,4,FALSE))+IF(K12="",0,VLOOKUP(K12,Bausteine!$A$2:$AS$46,4,FALSE))+IF(L12="",0,VLOOKUP(L12,Bausteine!$A$2:$AS$46,4,FALSE))+IF(AC12="",0,VLOOKUP(AC12,Bausteine!$A$2:$AS$46,4,FALSE))+IF(AF12="",0,VLOOKUP(AF12,Bausteine!$A$2:$AS$46,4,FALSE))+IF(AG12="",0,VLOOKUP(AG12,Bausteine!$A$2:$AS$46,4,FALSE))+IF(AH12="",0,VLOOKUP(AH12,Bausteine!$A$2:$AS$46,4,FALSE)) | N12: =IF(C12="",0,VLOOKUP(C12,Bausteine!$A$2:$AS$46,5,FALSE))+IF(D12="",0,VLOOKUP(D12,Bausteine!$A$2:$AS$46,5,FALSE))+IF(E12="",0,VLOOKUP(E12,Bausteine!$A$2:$AS$46,5,FALSE))+IF(F12="",0,VLOOKUP(F12,Bausteine!$A$2:$AS$46,5,FALSE))+IF(G12="",0,VLOOKUP(G12,Bausteine!$A$2:$AS$46,5,FALSE))+IF(H12="",0,VLOOKUP(H12,Bausteine!$A$2:$AS$46,5,FALSE))+IF(I12="",0,VLOOKUP(I12,Bausteine!$A$2:$AS$46,5,FALSE))+IF(J12="",0,VLOOKUP(J12,Bausteine!$A$2:$AS$46,5,FALSE))+IF(K12="",0,VLOOKUP(K12,Bausteine!$A$2:$AS$46,5,FALSE))+IF(L12="",0,VLOOKUP(L12,Bausteine!$A$2:$AS$46,5,FALSE))+IF(AC12="",0,VLOOKUP(AC12,Bausteine!$A$2:$AS$46,5,FALSE))+IF(AF12="",0,VLOOKUP(AF12,Bausteine!$A$2:$AS$46,5,FALSE))+IF(AG12="",0,VLOOKUP(AG12,Bausteine!$A$2:$AS$46,5,FALSE))+IF(AH12="",0,VLOOKUP(AH12,Bausteine!$A$2:$AS$46,5,FALSE)) | O12: =MAX(IF(C12="",0,VLOOKUP(C12,Bausteine!$A$2:$AS$46,6,FALSE)),IF(D12="",0,VLOOKUP(D12,Bausteine!$A$2:$AS$46,6,FALSE)),IF(E12="",0,VLOOKUP(E12,Bausteine!$A$2:$AS$46,6,FALSE)),IF(F12="",0,VLOOKUP(F12,Bausteine!$A$2:$AS$46,6,FALSE)),IF(G12="",0,VLOOKUP(G12,Bausteine!$A$2:$AS$46,6,FALSE)),IF(H12="",0,VLOOKUP(H12,Bausteine!$A$2:$AS$46,6,FALSE)),IF(I12="",0,VLOOKUP(I12,Bausteine!$A$2:$AS$46,6,FALSE)),IF(J12="",0,VLOOKUP(J12,Bausteine!$A$2:$AS$46,6,FALSE)),IF(K12="",0,VLOOKUP(K12,Bausteine!$A$2:$AS$46,6,FALSE)),IF(L12="",0,VLOOKUP(L12,Bausteine!$A$2:$AS$46,6,FALSE)),IF(AC12="",0,VLOOKUP(AC12,Bausteine!$A$2:$AS$46,6,FALSE)),IF(AF12="",0,VLOOKUP(AF12,Bausteine!$A$2:$AS$46,6,FALSE)),IF(AG12="",0,VLOOKUP(AG12,Bausteine!$A$2:$AS$46,6,FALSE)),IF(AH12="",0,VLOOKUP(AH12,Bausteine!$A$2:$AS$46,6,FALSE)),AK12) | P12: =IF(C12="",0,VLOOKUP(C12,Bausteine!$A$2:$AS$46,7,FALSE))*IF(F12="",0,VLOOKUP(F12,Bausteine!$A$2:$AS$46,17,FALSE))/100+IF(D12="",0,VLOOKUP(D12,Bausteine!$A$2:$AS$46,7,FALSE))+IF(E12="",0,VLOOKUP(E12,Bausteine!$A$2:$AS$46,7,FALSE))+IF(G12="",0,VLOOKUP(G12,Bausteine!$A$2:$AS$46,7,FALSE))+IF(H12="",0,VLOOKUP(H12,Bausteine!$A$2:$AS$46,7,FALSE))+IF(I12="",0,VLOOKUP(I12,Bausteine!$A$2:$AS$46,7,FALSE))+IF(J12="",0,VLOOKUP(J12,Bausteine!$A$2:$AS$46,7,FALSE))+IF(K12="",0,VLOOKUP(K12,Bausteine!$A$2:$AS$46,7,FALSE))+IF(L12="",0,VLOOKUP(L12,Bausteine!$A$2:$AS$46,7,FALSE))+IF(AC12="",0,VLOOKUP(AC12,Bausteine!$A$2:$AS$46,7,FALSE))+IF(AF12="",0,VLOOKUP(AF12,Bausteine!$A$2:$AS$46,7,FALSE))+IF(AG12="",0,VLOOKUP(AG12,Bausteine!$A$2:$AS$46,7,FALSE))+IF(AH12="",0,VLOOKUP(AH12,Bausteine!$A$2:$AS$46,7,FALSE))+AI12 | Q12: =N12*Parameter!$B$2 | R12: =AE12-Q12 | S12: =IF(C12="",0,VLOOKUP(C12,Bausteine!$A$2:$AS$46,13,FALSE))*IF(F12="",0,VLOOKUP(F12,Bausteine!$A$2:$AS$46,16,FALSE))/100 | T12: =IF(C12="",0,VLOOKUP(C12,Bausteine!$A$2:$AS$46,8,FALSE))*IF(F12="",0,VLOOKUP(F12,Bausteine!$A$2:$AS$46,15,FALSE))/100+IF(D12="",0,VLOOKUP(D12,Bausteine!$A$2:$AS$46,8,FALSE))+IF(E12="",0,VLOOKUP(E12,Bausteine!$A$2:$AS$46,8,FALSE))+IF(G12="",0,VLOOKUP(G12,Bausteine!$A$2:$AS$46,8,FALSE))+IF(H12="",0,VLOOKUP(H12,Bausteine!$A$2:$AS$46,8,FALSE))+IF(I12="",0,VLOOKUP(I12,Bausteine!$A$2:$AS$46,8,FALSE))+IF(J12="",0,VLOOKUP(J12,Bausteine!$A$2:$AS$46,8,FALSE))+IF(K12="",0,VLOOKUP(K12,Bausteine!$A$2:$AS$46,8,FALSE))+IF(L12="",0,VLOOKUP(L12,Bausteine!$A$2:$AS$46,8,FALSE))+IF(AC12="",0,VLOOKUP(AC12,Bausteine!$A$2:$AS$46,8,FALSE))+IF(AF12="",0,VLOOKUP(AF12,Bausteine!$A$2:$AS$46,8,FALSE))+IF(AG12="",0,VLOOKUP(AG12,Bausteine!$A$2:$AS$46,8,FALSE))+IF(AH12="",0,VLOOKUP(AH12,Bausteine!$A$2:$AS$46,8,FALSE))+AJ12 | U12: =IF(C12="",0,VLOOKUP(C12,Bausteine!$A$2:$AS$46,9,FALSE))+IF(D12="",0,VLOOKUP(D12,Bausteine!$A$2:$AS$46,9,FALSE))+IF(E12="",0,VLOOKUP(E12,Bausteine!$A$2:$AS$46,9,FALSE))+IF(F12="",0,VLOOKUP(F12,Bausteine!$A$2:$AS$46,9,FALSE))+IF(G12="",0,VLOOKUP(G12,Bausteine!$A$2:$AS$46,9,FALSE))+IF(H12="",0,VLOOKUP(H12,Bausteine!$A$2:$AS$46,9,FALSE))+IF(I12="",0,VLOOKUP(I12,Bausteine!$A$2:$AS$46,9,FALSE))+IF(J12="",0,VLOOKUP(J12,Bausteine!$A$2:$AS$46,9,FALSE))+IF(K12="",0,VLOOKUP(K12,Bausteine!$A$2:$AS$46,9,FALSE))+IF(L12="",0,VLOOKUP(L12,Bausteine!$A$2:$AS$46,9,FALSE))+IF(AC12="",0,VLOOKUP(AC12,Bausteine!$A$2:$AS$46,9,FALSE))+IF(AF12="",0,VLOOKUP(AF12,Bausteine!$A$2:$AS$46,9,FALSE))+IF(AG12="",0,VLOOKUP(AG12,Bausteine!$A$2:$AS$46,9,FALSE))+IF(AH12="",0,VLOOKUP(AH12,Bausteine!$A$2:$AS$46,9,FALSE)) | V12: =IF(D12="",0,VLOOKUP(D12,Bausteine!$A$2:$AS$46,10,FALSE))-U12/IF(E12="",0,VLOOKUP(E12,Bausteine!$A$2:$AS$46,11,FALSE)) | W12: =IF(Y12<>"OK","",ROUND(MIN(IF(C12="",0,VLOOKUP(C12,Bausteine!$A$2:$AS$46,21,FALSE)),IF(C12="",0,VLOOKUP(C12,Bausteine!$A$2:$AS$46,20,FALSE))*(V12/T12/(IF(C12="",0,VLOOKUP(C12,Bausteine!$A$2:$AS$46,19,FALSE))/IF(C12="",0,VLOOKUP(C12,Bausteine!$A$2:$AS$46,18,FALSE))))^Parameter!$B$3),0)) | X12: =IF(F12="",0,VLOOKUP(F12,Bausteine!$A$2:$AS$46,14,FALSE)) | Y12: =IFERROR(IF(OR(AD12<=0,AD12>1,R12<=0,T12<=0,V12<=0,U12>IF(E12="",0,VLOOKUP(E12,Bausteine!$A$2:$AS$46,12,FALSE)),T12>IF(C12="",0,VLOOKUP(C12,Bausteine!$A$2:$AS$46,22,FALSE)),IF(E12="",0,VLOOKUP(E12,Bausteine!$A$2:$AS$46,11,FALSE))<=0,IF(E12="",0,VLOOKUP(E12,Bausteine!$A$2:$AS$46,11,FALSE))>1),"UNGUELTIG","OK"),"FEHLER") | Z12: 1800 | AA12: 55 | AB12: Empty module, new combination. CP cost remains even with no starting passengers. | AD12: =IF(AC12="",1,IF(AC12="",0,VLOOKUP(AC12,Bausteine!$A$2:$AS$46,37,FALSE))/100) | AE12: =P12*AD12 | AI12: =SUMIF(Startbesatzung!$A$2:$A$7,A12,Startbesatzung!$D$2:$D$7) | AJ12: =SUMIF(Startbesatzung!$A$2:$A$7,A12,Startbesatzung!$E$2:$E$7) | AK12: =MAX(0,IF(Startbesatzung!A2=A12,Startbesatzung!G2,0),IF(Startbesatzung!A3=A12,Startbesatzung!G3,0),IF(Startbesatzung!A4=A12,Startbesatzung!G4,0),IF(Startbesatzung!A5=A12,Startbesatzung!G5,0),IF(Startbesatzung!A6=A12,Startbesatzung!G6,0),IF(Startbesatzung!A7=A12,Startbesatzung!G7,0)) | AL12: =IF(AF12="","",IF(IF(AH12="",0,VLOOKUP(AH12,Bausteine!$A$2:$AS$46,38,FALSE))>0,IF(AH12="",0,VLOOKUP(AH12,Bausteine!$A$2:$AS$46,38,FALSE)),IF(AG12="",0,VLOOKUP(AG12,Bausteine!$A$2:$AS$46,28,FALSE)))) | AM12: =IF(AF12="","",IF(AG12="",0,VLOOKUP(AG12,Bausteine!$A$2:$AS$46,44,FALSE))) | AN12: =IF(AF12="","",IF(AF12="",0,VLOOKUP(AF12,Bausteine!$A$2:$AS$46,27,FALSE))) | AO12: =IF(AF12="","",IF(AF12="",0,VLOOKUP(AF12,Bausteine!$A$2:$AS$46,25,FALSE))) | AP12: =IF(AF12="","",IF(AH12="",0,VLOOKUP(AH12,Bausteine!$A$2:$AS$46,29,FALSE)))
A13: Overlord Bunker / partial crew | B13: china | C13: overlord-chassis | D13: diesel-heavy | E13: baseline-generator | F13: heavy | G13: heavy-twin-turret | H13: overlord-cannon | I13: heavy-shell | J13: firing-bunker | M13: =IF(C13="",0,VLOOKUP(C13,Bausteine!$A$2:$AS$46,4,FALSE))+IF(D13="",0,VLOOKUP(D13,Bausteine!$A$2:$AS$46,4,FALSE))+IF(E13="",0,VLOOKUP(E13,Bausteine!$A$2:$AS$46,4,FALSE))+IF(F13="",0,VLOOKUP(F13,Bausteine!$A$2:$AS$46,4,FALSE))+IF(G13="",0,VLOOKUP(G13,Bausteine!$A$2:$AS$46,4,FALSE))+IF(H13="",0,VLOOKUP(H13,Bausteine!$A$2:$AS$46,4,FALSE))+IF(I13="",0,VLOOKUP(I13,Bausteine!$A$2:$AS$46,4,FALSE))+IF(J13="",0,VLOOKUP(J13,Bausteine!$A$2:$AS$46,4,FALSE))+IF(K13="",0,VLOOKUP(K13,Bausteine!$A$2:$AS$46,4,FALSE))+IF(L13="",0,VLOOKUP(L13,Bausteine!$A$2:$AS$46,4,FALSE))+IF(AC13="",0,VLOOKUP(AC13,Bausteine!$A$2:$AS$46,4,FALSE))+IF(AF13="",0,VLOOKUP(AF13,Bausteine!$A$2:$AS$46,4,FALSE))+IF(AG13="",0,VLOOKUP(AG13,Bausteine!$A$2:$AS$46,4,FALSE))+IF(AH13="",0,VLOOKUP(AH13,Bausteine!$A$2:$AS$46,4,FALSE)) | N13: =IF(C13="",0,VLOOKUP(C13,Bausteine!$A$2:$AS$46,5,FALSE))+IF(D13="",0,VLOOKUP(D13,Bausteine!$A$2:$AS$46,5,FALSE))+IF(E13="",0,VLOOKUP(E13,Bausteine!$A$2:$AS$46,5,FALSE))+IF(F13="",0,VLOOKUP(F13,Bausteine!$A$2:$AS$46,5,FALSE))+IF(G13="",0,VLOOKUP(G13,Bausteine!$A$2:$AS$46,5,FALSE))+IF(H13="",0,VLOOKUP(H13,Bausteine!$A$2:$AS$46,5,FALSE))+IF(I13="",0,VLOOKUP(I13,Bausteine!$A$2:$AS$46,5,FALSE))+IF(J13="",0,VLOOKUP(J13,Bausteine!$A$2:$AS$46,5,FALSE))+IF(K13="",0,VLOOKUP(K13,Bausteine!$A$2:$AS$46,5,FALSE))+IF(L13="",0,VLOOKUP(L13,Bausteine!$A$2:$AS$46,5,FALSE))+IF(AC13="",0,VLOOKUP(AC13,Bausteine!$A$2:$AS$46,5,FALSE))+IF(AF13="",0,VLOOKUP(AF13,Bausteine!$A$2:$AS$46,5,FALSE))+IF(AG13="",0,VLOOKUP(AG13,Bausteine!$A$2:$AS$46,5,FALSE))+IF(AH13="",0,VLOOKUP(AH13,Bausteine!$A$2:$AS$46,5,FALSE)) | O13: =MAX(IF(C13="",0,VLOOKUP(C13,Bausteine!$A$2:$AS$46,6,FALSE)),IF(D13="",0,VLOOKUP(D13,Bausteine!$A$2:$AS$46,6,FALSE)),IF(E13="",0,VLOOKUP(E13,Bausteine!$A$2:$AS$46,6,FALSE)),IF(F13="",0,VLOOKUP(F13,Bausteine!$A$2:$AS$46,6,FALSE)),IF(G13="",0,VLOOKUP(G13,Bausteine!$A$2:$AS$46,6,FALSE)),IF(H13="",0,VLOOKUP(H13,Bausteine!$A$2:$AS$46,6,FALSE)),IF(I13="",0,VLOOKUP(I13,Bausteine!$A$2:$AS$46,6,FALSE)),IF(J13="",0,VLOOKUP(J13,Bausteine!$A$2:$AS$46,6,FALSE)),IF(K13="",0,VLOOKUP(K13,Bausteine!$A$2:$AS$46,6,FALSE)),IF(L13="",0,VLOOKUP(L13,Bausteine!$A$2:$AS$46,6,FALSE)),IF(AC13="",0,VLOOKUP(AC13,Bausteine!$A$2:$AS$46,6,FALSE)),IF(AF13="",0,VLOOKUP(AF13,Bausteine!$A$2:$AS$46,6,FALSE)),IF(AG13="",0,VLOOKUP(AG13,Bausteine!$A$2:$AS$46,6,FALSE)),IF(AH13="",0,VLOOKUP(AH13,Bausteine!$A$2:$AS$46,6,FALSE)),AK13) | P13: =IF(C13="",0,VLOOKUP(C13,Bausteine!$A$2:$AS$46,7,FALSE))*IF(F13="",0,VLOOKUP(F13,Bausteine!$A$2:$AS$46,17,FALSE))/100+IF(D13="",0,VLOOKUP(D13,Bausteine!$A$2:$AS$46,7,FALSE))+IF(E13="",0,VLOOKUP(E13,Bausteine!$A$2:$AS$46,7,FALSE))+IF(G13="",0,VLOOKUP(G13,Bausteine!$A$2:$AS$46,7,FALSE))+IF(H13="",0,VLOOKUP(H13,Bausteine!$A$2:$AS$46,7,FALSE))+IF(I13="",0,VLOOKUP(I13,Bausteine!$A$2:$AS$46,7,FALSE))+IF(J13="",0,VLOOKUP(J13,Bausteine!$A$2:$AS$46,7,FALSE))+IF(K13="",0,VLOOKUP(K13,Bausteine!$A$2:$AS$46,7,FALSE))+IF(L13="",0,VLOOKUP(L13,Bausteine!$A$2:$AS$46,7,FALSE))+IF(AC13="",0,VLOOKUP(AC13,Bausteine!$A$2:$AS$46,7,FALSE))+IF(AF13="",0,VLOOKUP(AF13,Bausteine!$A$2:$AS$46,7,FALSE))+IF(AG13="",0,VLOOKUP(AG13,Bausteine!$A$2:$AS$46,7,FALSE))+IF(AH13="",0,VLOOKUP(AH13,Bausteine!$A$2:$AS$46,7,FALSE))+AI13 | Q13: =N13*Parameter!$B$2 | R13: =AE13-Q13 | S13: =IF(C13="",0,VLOOKUP(C13,Bausteine!$A$2:$AS$46,13,FALSE))*IF(F13="",0,VLOOKUP(F13,Bausteine!$A$2:$AS$46,16,FALSE))/100 | T13: =IF(C13="",0,VLOOKUP(C13,Bausteine!$A$2:$AS$46,8,FALSE))*IF(F13="",0,VLOOKUP(F13,Bausteine!$A$2:$AS$46,15,FALSE))/100+IF(D13="",0,VLOOKUP(D13,Bausteine!$A$2:$AS$46,8,FALSE))+IF(E13="",0,VLOOKUP(E13,Bausteine!$A$2:$AS$46,8,FALSE))+IF(G13="",0,VLOOKUP(G13,Bausteine!$A$2:$AS$46,8,FALSE))+IF(H13="",0,VLOOKUP(H13,Bausteine!$A$2:$AS$46,8,FALSE))+IF(I13="",0,VLOOKUP(I13,Bausteine!$A$2:$AS$46,8,FALSE))+IF(J13="",0,VLOOKUP(J13,Bausteine!$A$2:$AS$46,8,FALSE))+IF(K13="",0,VLOOKUP(K13,Bausteine!$A$2:$AS$46,8,FALSE))+IF(L13="",0,VLOOKUP(L13,Bausteine!$A$2:$AS$46,8,FALSE))+IF(AC13="",0,VLOOKUP(AC13,Bausteine!$A$2:$AS$46,8,FALSE))+IF(AF13="",0,VLOOKUP(AF13,Bausteine!$A$2:$AS$46,8,FALSE))+IF(AG13="",0,VLOOKUP(AG13,Bausteine!$A$2:$AS$46,8,FALSE))+IF(AH13="",0,VLOOKUP(AH13,Bausteine!$A$2:$AS$46,8,FALSE))+AJ13 | U13: =IF(C13="",0,VLOOKUP(C13,Bausteine!$A$2:$AS$46,9,FALSE))+IF(D13="",0,VLOOKUP(D13,Bausteine!$A$2:$AS$46,9,FALSE))+IF(E13="",0,VLOOKUP(E13,Bausteine!$A$2:$AS$46,9,FALSE))+IF(F13="",0,VLOOKUP(F13,Bausteine!$A$2:$AS$46,9,FALSE))+IF(G13="",0,VLOOKUP(G13,Bausteine!$A$2:$AS$46,9,FALSE))+IF(H13="",0,VLOOKUP(H13,Bausteine!$A$2:$AS$46,9,FALSE))+IF(I13="",0,VLOOKUP(I13,Bausteine!$A$2:$AS$46,9,FALSE))+IF(J13="",0,VLOOKUP(J13,Bausteine!$A$2:$AS$46,9,FALSE))+IF(K13="",0,VLOOKUP(K13,Bausteine!$A$2:$AS$46,9,FALSE))+IF(L13="",0,VLOOKUP(L13,Bausteine!$A$2:$AS$46,9,FALSE))+IF(AC13="",0,VLOOKUP(AC13,Bausteine!$A$2:$AS$46,9,FALSE))+IF(AF13="",0,VLOOKUP(AF13,Bausteine!$A$2:$AS$46,9,FALSE))+IF(AG13="",0,VLOOKUP(AG13,Bausteine!$A$2:$AS$46,9,FALSE))+IF(AH13="",0,VLOOKUP(AH13,Bausteine!$A$2:$AS$46,9,FALSE)) | V13: =IF(D13="",0,VLOOKUP(D13,Bausteine!$A$2:$AS$46,10,FALSE))-U13/IF(E13="",0,VLOOKUP(E13,Bausteine!$A$2:$AS$46,11,FALSE)) | W13: =IF(Y13<>"OK","",ROUND(MIN(IF(C13="",0,VLOOKUP(C13,Bausteine!$A$2:$AS$46,21,FALSE)),IF(C13="",0,VLOOKUP(C13,Bausteine!$A$2:$AS$46,20,FALSE))*(V13/T13/(IF(C13="",0,VLOOKUP(C13,Bausteine!$A$2:$AS$46,19,FALSE))/IF(C13="",0,VLOOKUP(C13,Bausteine!$A$2:$AS$46,18,FALSE))))^Parameter!$B$3),0)) | X13: =IF(F13="",0,VLOOKUP(F13,Bausteine!$A$2:$AS$46,14,FALSE)) | Y13: =IFERROR(IF(OR(AD13<=0,AD13>1,R13<=0,T13<=0,V13<=0,U13>IF(E13="",0,VLOOKUP(E13,Bausteine!$A$2:$AS$46,12,FALSE)),T13>IF(C13="",0,VLOOKUP(C13,Bausteine!$A$2:$AS$46,22,FALSE)),IF(E13="",0,VLOOKUP(E13,Bausteine!$A$2:$AS$46,11,FALSE))<=0,IF(E13="",0,VLOOKUP(E13,Bausteine!$A$2:$AS$46,11,FALSE))>1),"UNGUELTIG","OK"),"FEHLER") | Z13: 2200 | AA13: 55 | AB13: Half-filled bunker; base-faction catalog intentionally ignores old Infantry-General restriction. | AD13: =IF(AC13="",1,IF(AC13="",0,VLOOKUP(AC13,Bausteine!$A$2:$AS$46,37,FALSE))/100) | AE13: =P13*AD13 | AI13: =SUMIF(Startbesatzung!$A$2:$A$7,A13,Startbesatzung!$D$2:$D$7) | AJ13: =SUMIF(Startbesatzung!$A$2:$A$7,A13,Startbesatzung!$E$2:$E$7) | AK13: =MAX(0,IF(Startbesatzung!A2=A13,Startbesatzung!G2,0),IF(Startbesatzung!A3=A13,Startbesatzung!G3,0),IF(Startbesatzung!A4=A13,Startbesatzung!G4,0),IF(Startbesatzung!A5=A13,Startbesatzung!G5,0),IF(Startbesatzung!A6=A13,Startbesatzung!G6,0),IF(Startbesatzung!A7=A13,Startbesatzung!G7,0)) | AL13: =IF(AF13="","",IF(IF(AH13="",0,VLOOKUP(AH13,Bausteine!$A$2:$AS$46,38,FALSE))>0,IF(AH13="",0,VLOOKUP(AH13,Bausteine!$A$2:$AS$46,38,FALSE)),IF(AG13="",0,VLOOKUP(AG13,Bausteine!$A$2:$AS$46,28,FALSE)))) | AM13: =IF(AF13="","",IF(AG13="",0,VLOOKUP(AG13,Bausteine!$A$2:$AS$46,44,FALSE))) | AN13: =IF(AF13="","",IF(AF13="",0,VLOOKUP(AF13,Bausteine!$A$2:$AS$46,27,FALSE))) | AO13: =IF(AF13="","",IF(AF13="",0,VLOOKUP(AF13,Bausteine!$A$2:$AS$46,25,FALSE))) | AP13: =IF(AF13="","",IF(AH13="",0,VLOOKUP(AH13,Bausteine!$A$2:$AS$46,29,FALSE)))
A14: Overlord Bunker | B14: china | C14: overlord-chassis | D14: diesel-heavy | E14: baseline-generator | F14: heavy | G14: heavy-twin-turret | H14: overlord-cannon | I14: heavy-shell | J14: firing-bunker | M14: =IF(C14="",0,VLOOKUP(C14,Bausteine!$A$2:$AS$46,4,FALSE))+IF(D14="",0,VLOOKUP(D14,Bausteine!$A$2:$AS$46,4,FALSE))+IF(E14="",0,VLOOKUP(E14,Bausteine!$A$2:$AS$46,4,FALSE))+IF(F14="",0,VLOOKUP(F14,Bausteine!$A$2:$AS$46,4,FALSE))+IF(G14="",0,VLOOKUP(G14,Bausteine!$A$2:$AS$46,4,FALSE))+IF(H14="",0,VLOOKUP(H14,Bausteine!$A$2:$AS$46,4,FALSE))+IF(I14="",0,VLOOKUP(I14,Bausteine!$A$2:$AS$46,4,FALSE))+IF(J14="",0,VLOOKUP(J14,Bausteine!$A$2:$AS$46,4,FALSE))+IF(K14="",0,VLOOKUP(K14,Bausteine!$A$2:$AS$46,4,FALSE))+IF(L14="",0,VLOOKUP(L14,Bausteine!$A$2:$AS$46,4,FALSE))+IF(AC14="",0,VLOOKUP(AC14,Bausteine!$A$2:$AS$46,4,FALSE))+IF(AF14="",0,VLOOKUP(AF14,Bausteine!$A$2:$AS$46,4,FALSE))+IF(AG14="",0,VLOOKUP(AG14,Bausteine!$A$2:$AS$46,4,FALSE))+IF(AH14="",0,VLOOKUP(AH14,Bausteine!$A$2:$AS$46,4,FALSE)) | N14: =IF(C14="",0,VLOOKUP(C14,Bausteine!$A$2:$AS$46,5,FALSE))+IF(D14="",0,VLOOKUP(D14,Bausteine!$A$2:$AS$46,5,FALSE))+IF(E14="",0,VLOOKUP(E14,Bausteine!$A$2:$AS$46,5,FALSE))+IF(F14="",0,VLOOKUP(F14,Bausteine!$A$2:$AS$46,5,FALSE))+IF(G14="",0,VLOOKUP(G14,Bausteine!$A$2:$AS$46,5,FALSE))+IF(H14="",0,VLOOKUP(H14,Bausteine!$A$2:$AS$46,5,FALSE))+IF(I14="",0,VLOOKUP(I14,Bausteine!$A$2:$AS$46,5,FALSE))+IF(J14="",0,VLOOKUP(J14,Bausteine!$A$2:$AS$46,5,FALSE))+IF(K14="",0,VLOOKUP(K14,Bausteine!$A$2:$AS$46,5,FALSE))+IF(L14="",0,VLOOKUP(L14,Bausteine!$A$2:$AS$46,5,FALSE))+IF(AC14="",0,VLOOKUP(AC14,Bausteine!$A$2:$AS$46,5,FALSE))+IF(AF14="",0,VLOOKUP(AF14,Bausteine!$A$2:$AS$46,5,FALSE))+IF(AG14="",0,VLOOKUP(AG14,Bausteine!$A$2:$AS$46,5,FALSE))+IF(AH14="",0,VLOOKUP(AH14,Bausteine!$A$2:$AS$46,5,FALSE)) | O14: =MAX(IF(C14="",0,VLOOKUP(C14,Bausteine!$A$2:$AS$46,6,FALSE)),IF(D14="",0,VLOOKUP(D14,Bausteine!$A$2:$AS$46,6,FALSE)),IF(E14="",0,VLOOKUP(E14,Bausteine!$A$2:$AS$46,6,FALSE)),IF(F14="",0,VLOOKUP(F14,Bausteine!$A$2:$AS$46,6,FALSE)),IF(G14="",0,VLOOKUP(G14,Bausteine!$A$2:$AS$46,6,FALSE)),IF(H14="",0,VLOOKUP(H14,Bausteine!$A$2:$AS$46,6,FALSE)),IF(I14="",0,VLOOKUP(I14,Bausteine!$A$2:$AS$46,6,FALSE)),IF(J14="",0,VLOOKUP(J14,Bausteine!$A$2:$AS$46,6,FALSE)),IF(K14="",0,VLOOKUP(K14,Bausteine!$A$2:$AS$46,6,FALSE)),IF(L14="",0,VLOOKUP(L14,Bausteine!$A$2:$AS$46,6,FALSE)),IF(AC14="",0,VLOOKUP(AC14,Bausteine!$A$2:$AS$46,6,FALSE)),IF(AF14="",0,VLOOKUP(AF14,Bausteine!$A$2:$AS$46,6,FALSE)),IF(AG14="",0,VLOOKUP(AG14,Bausteine!$A$2:$AS$46,6,FALSE)),IF(AH14="",0,VLOOKUP(AH14,Bausteine!$A$2:$AS$46,6,FALSE)),AK14) | P14: =IF(C14="",0,VLOOKUP(C14,Bausteine!$A$2:$AS$46,7,FALSE))*IF(F14="",0,VLOOKUP(F14,Bausteine!$A$2:$AS$46,17,FALSE))/100+IF(D14="",0,VLOOKUP(D14,Bausteine!$A$2:$AS$46,7,FALSE))+IF(E14="",0,VLOOKUP(E14,Bausteine!$A$2:$AS$46,7,FALSE))+IF(G14="",0,VLOOKUP(G14,Bausteine!$A$2:$AS$46,7,FALSE))+IF(H14="",0,VLOOKUP(H14,Bausteine!$A$2:$AS$46,7,FALSE))+IF(I14="",0,VLOOKUP(I14,Bausteine!$A$2:$AS$46,7,FALSE))+IF(J14="",0,VLOOKUP(J14,Bausteine!$A$2:$AS$46,7,FALSE))+IF(K14="",0,VLOOKUP(K14,Bausteine!$A$2:$AS$46,7,FALSE))+IF(L14="",0,VLOOKUP(L14,Bausteine!$A$2:$AS$46,7,FALSE))+IF(AC14="",0,VLOOKUP(AC14,Bausteine!$A$2:$AS$46,7,FALSE))+IF(AF14="",0,VLOOKUP(AF14,Bausteine!$A$2:$AS$46,7,FALSE))+IF(AG14="",0,VLOOKUP(AG14,Bausteine!$A$2:$AS$46,7,FALSE))+IF(AH14="",0,VLOOKUP(AH14,Bausteine!$A$2:$AS$46,7,FALSE))+AI14 | Q14: =N14*Parameter!$B$2 | R14: =AE14-Q14 | S14: =IF(C14="",0,VLOOKUP(C14,Bausteine!$A$2:$AS$46,13,FALSE))*IF(F14="",0,VLOOKUP(F14,Bausteine!$A$2:$AS$46,16,FALSE))/100 | T14: =IF(C14="",0,VLOOKUP(C14,Bausteine!$A$2:$AS$46,8,FALSE))*IF(F14="",0,VLOOKUP(F14,Bausteine!$A$2:$AS$46,15,FALSE))/100+IF(D14="",0,VLOOKUP(D14,Bausteine!$A$2:$AS$46,8,FALSE))+IF(E14="",0,VLOOKUP(E14,Bausteine!$A$2:$AS$46,8,FALSE))+IF(G14="",0,VLOOKUP(G14,Bausteine!$A$2:$AS$46,8,FALSE))+IF(H14="",0,VLOOKUP(H14,Bausteine!$A$2:$AS$46,8,FALSE))+IF(I14="",0,VLOOKUP(I14,Bausteine!$A$2:$AS$46,8,FALSE))+IF(J14="",0,VLOOKUP(J14,Bausteine!$A$2:$AS$46,8,FALSE))+IF(K14="",0,VLOOKUP(K14,Bausteine!$A$2:$AS$46,8,FALSE))+IF(L14="",0,VLOOKUP(L14,Bausteine!$A$2:$AS$46,8,FALSE))+IF(AC14="",0,VLOOKUP(AC14,Bausteine!$A$2:$AS$46,8,FALSE))+IF(AF14="",0,VLOOKUP(AF14,Bausteine!$A$2:$AS$46,8,FALSE))+IF(AG14="",0,VLOOKUP(AG14,Bausteine!$A$2:$AS$46,8,FALSE))+IF(AH14="",0,VLOOKUP(AH14,Bausteine!$A$2:$AS$46,8,FALSE))+AJ14 | U14: =IF(C14="",0,VLOOKUP(C14,Bausteine!$A$2:$AS$46,9,FALSE))+IF(D14="",0,VLOOKUP(D14,Bausteine!$A$2:$AS$46,9,FALSE))+IF(E14="",0,VLOOKUP(E14,Bausteine!$A$2:$AS$46,9,FALSE))+IF(F14="",0,VLOOKUP(F14,Bausteine!$A$2:$AS$46,9,FALSE))+IF(G14="",0,VLOOKUP(G14,Bausteine!$A$2:$AS$46,9,FALSE))+IF(H14="",0,VLOOKUP(H14,Bausteine!$A$2:$AS$46,9,FALSE))+IF(I14="",0,VLOOKUP(I14,Bausteine!$A$2:$AS$46,9,FALSE))+IF(J14="",0,VLOOKUP(J14,Bausteine!$A$2:$AS$46,9,FALSE))+IF(K14="",0,VLOOKUP(K14,Bausteine!$A$2:$AS$46,9,FALSE))+IF(L14="",0,VLOOKUP(L14,Bausteine!$A$2:$AS$46,9,FALSE))+IF(AC14="",0,VLOOKUP(AC14,Bausteine!$A$2:$AS$46,9,FALSE))+IF(AF14="",0,VLOOKUP(AF14,Bausteine!$A$2:$AS$46,9,FALSE))+IF(AG14="",0,VLOOKUP(AG14,Bausteine!$A$2:$AS$46,9,FALSE))+IF(AH14="",0,VLOOKUP(AH14,Bausteine!$A$2:$AS$46,9,FALSE)) | V14: =IF(D14="",0,VLOOKUP(D14,Bausteine!$A$2:$AS$46,10,FALSE))-U14/IF(E14="",0,VLOOKUP(E14,Bausteine!$A$2:$AS$46,11,FALSE)) | W14: =IF(Y14<>"OK","",ROUND(MIN(IF(C14="",0,VLOOKUP(C14,Bausteine!$A$2:$AS$46,21,FALSE)),IF(C14="",0,VLOOKUP(C14,Bausteine!$A$2:$AS$46,20,FALSE))*(V14/T14/(IF(C14="",0,VLOOKUP(C14,Bausteine!$A$2:$AS$46,19,FALSE))/IF(C14="",0,VLOOKUP(C14,Bausteine!$A$2:$AS$46,18,FALSE))))^Parameter!$B$3),0)) | X14: =IF(F14="",0,VLOOKUP(F14,Bausteine!$A$2:$AS$46,14,FALSE)) | Y14: =IFERROR(IF(OR(AD14<=0,AD14>1,R14<=0,T14<=0,V14<=0,U14>IF(E14="",0,VLOOKUP(E14,Bausteine!$A$2:$AS$46,12,FALSE)),T14>IF(C14="",0,VLOOKUP(C14,Bausteine!$A$2:$AS$46,22,FALSE)),IF(E14="",0,VLOOKUP(E14,Bausteine!$A$2:$AS$46,11,FALSE))<=0,IF(E14="",0,VLOOKUP(E14,Bausteine!$A$2:$AS$46,11,FALSE))>1),"UNGUELTIG","OK"),"FEHLER") | Z14: 3000 | AA14: 55 | AB14: Includes 4 Tank Hunters. Compare base HP, not Emperor conditional resistance. Crew + bunker mass/load are provisional; reuses existing open-topped traits. | AD14: =IF(AC14="",1,IF(AC14="",0,VLOOKUP(AC14,Bausteine!$A$2:$AS$46,37,FALSE))/100) | AE14: =P14*AD14 | AI14: =SUMIF(Startbesatzung!$A$2:$A$7,A14,Startbesatzung!$D$2:$D$7) | AJ14: =SUMIF(Startbesatzung!$A$2:$A$7,A14,Startbesatzung!$E$2:$E$7) | AK14: =MAX(0,IF(Startbesatzung!A2=A14,Startbesatzung!G2,0),IF(Startbesatzung!A3=A14,Startbesatzung!G3,0),IF(Startbesatzung!A4=A14,Startbesatzung!G4,0),IF(Startbesatzung!A5=A14,Startbesatzung!G5,0),IF(Startbesatzung!A6=A14,Startbesatzung!G6,0),IF(Startbesatzung!A7=A14,Startbesatzung!G7,0)) | AL14: =IF(AF14="","",IF(IF(AH14="",0,VLOOKUP(AH14,Bausteine!$A$2:$AS$46,38,FALSE))>0,IF(AH14="",0,VLOOKUP(AH14,Bausteine!$A$2:$AS$46,38,FALSE)),IF(AG14="",0,VLOOKUP(AG14,Bausteine!$A$2:$AS$46,28,FALSE)))) | AM14: =IF(AF14="","",IF(AG14="",0,VLOOKUP(AG14,Bausteine!$A$2:$AS$46,44,FALSE))) | AN14: =IF(AF14="","",IF(AF14="",0,VLOOKUP(AF14,Bausteine!$A$2:$AS$46,27,FALSE))) | AO14: =IF(AF14="","",IF(AF14="",0,VLOOKUP(AF14,Bausteine!$A$2:$AS$46,25,FALSE))) | AP14: =IF(AF14="","",IF(AH14="",0,VLOOKUP(AH14,Bausteine!$A$2:$AS$46,29,FALSE)))
A15: Overlord Bunker PDL | B15: china | C15: overlord-chassis | D15: diesel-heavy-boost | E15: efficient-generator | F15: heavy | G15: heavy-twin-turret | H15: overlord-cannon | I15: heavy-shell | J15: firing-bunker | K15: pdl | M15: =IF(C15="",0,VLOOKUP(C15,Bausteine!$A$2:$AS$46,4,FALSE))+IF(D15="",0,VLOOKUP(D15,Bausteine!$A$2:$AS$46,4,FALSE))+IF(E15="",0,VLOOKUP(E15,Bausteine!$A$2:$AS$46,4,FALSE))+IF(F15="",0,VLOOKUP(F15,Bausteine!$A$2:$AS$46,4,FALSE))+IF(G15="",0,VLOOKUP(G15,Bausteine!$A$2:$AS$46,4,FALSE))+IF(H15="",0,VLOOKUP(H15,Bausteine!$A$2:$AS$46,4,FALSE))+IF(I15="",0,VLOOKUP(I15,Bausteine!$A$2:$AS$46,4,FALSE))+IF(J15="",0,VLOOKUP(J15,Bausteine!$A$2:$AS$46,4,FALSE))+IF(K15="",0,VLOOKUP(K15,Bausteine!$A$2:$AS$46,4,FALSE))+IF(L15="",0,VLOOKUP(L15,Bausteine!$A$2:$AS$46,4,FALSE))+IF(AC15="",0,VLOOKUP(AC15,Bausteine!$A$2:$AS$46,4,FALSE))+IF(AF15="",0,VLOOKUP(AF15,Bausteine!$A$2:$AS$46,4,FALSE))+IF(AG15="",0,VLOOKUP(AG15,Bausteine!$A$2:$AS$46,4,FALSE))+IF(AH15="",0,VLOOKUP(AH15,Bausteine!$A$2:$AS$46,4,FALSE)) | N15: =IF(C15="",0,VLOOKUP(C15,Bausteine!$A$2:$AS$46,5,FALSE))+IF(D15="",0,VLOOKUP(D15,Bausteine!$A$2:$AS$46,5,FALSE))+IF(E15="",0,VLOOKUP(E15,Bausteine!$A$2:$AS$46,5,FALSE))+IF(F15="",0,VLOOKUP(F15,Bausteine!$A$2:$AS$46,5,FALSE))+IF(G15="",0,VLOOKUP(G15,Bausteine!$A$2:$AS$46,5,FALSE))+IF(H15="",0,VLOOKUP(H15,Bausteine!$A$2:$AS$46,5,FALSE))+IF(I15="",0,VLOOKUP(I15,Bausteine!$A$2:$AS$46,5,FALSE))+IF(J15="",0,VLOOKUP(J15,Bausteine!$A$2:$AS$46,5,FALSE))+IF(K15="",0,VLOOKUP(K15,Bausteine!$A$2:$AS$46,5,FALSE))+IF(L15="",0,VLOOKUP(L15,Bausteine!$A$2:$AS$46,5,FALSE))+IF(AC15="",0,VLOOKUP(AC15,Bausteine!$A$2:$AS$46,5,FALSE))+IF(AF15="",0,VLOOKUP(AF15,Bausteine!$A$2:$AS$46,5,FALSE))+IF(AG15="",0,VLOOKUP(AG15,Bausteine!$A$2:$AS$46,5,FALSE))+IF(AH15="",0,VLOOKUP(AH15,Bausteine!$A$2:$AS$46,5,FALSE)) | O15: =MAX(IF(C15="",0,VLOOKUP(C15,Bausteine!$A$2:$AS$46,6,FALSE)),IF(D15="",0,VLOOKUP(D15,Bausteine!$A$2:$AS$46,6,FALSE)),IF(E15="",0,VLOOKUP(E15,Bausteine!$A$2:$AS$46,6,FALSE)),IF(F15="",0,VLOOKUP(F15,Bausteine!$A$2:$AS$46,6,FALSE)),IF(G15="",0,VLOOKUP(G15,Bausteine!$A$2:$AS$46,6,FALSE)),IF(H15="",0,VLOOKUP(H15,Bausteine!$A$2:$AS$46,6,FALSE)),IF(I15="",0,VLOOKUP(I15,Bausteine!$A$2:$AS$46,6,FALSE)),IF(J15="",0,VLOOKUP(J15,Bausteine!$A$2:$AS$46,6,FALSE)),IF(K15="",0,VLOOKUP(K15,Bausteine!$A$2:$AS$46,6,FALSE)),IF(L15="",0,VLOOKUP(L15,Bausteine!$A$2:$AS$46,6,FALSE)),IF(AC15="",0,VLOOKUP(AC15,Bausteine!$A$2:$AS$46,6,FALSE)),IF(AF15="",0,VLOOKUP(AF15,Bausteine!$A$2:$AS$46,6,FALSE)),IF(AG15="",0,VLOOKUP(AG15,Bausteine!$A$2:$AS$46,6,FALSE)),IF(AH15="",0,VLOOKUP(AH15,Bausteine!$A$2:$AS$46,6,FALSE)),AK15) | P15: =IF(C15="",0,VLOOKUP(C15,Bausteine!$A$2:$AS$46,7,FALSE))*IF(F15="",0,VLOOKUP(F15,Bausteine!$A$2:$AS$46,17,FALSE))/100+IF(D15="",0,VLOOKUP(D15,Bausteine!$A$2:$AS$46,7,FALSE))+IF(E15="",0,VLOOKUP(E15,Bausteine!$A$2:$AS$46,7,FALSE))+IF(G15="",0,VLOOKUP(G15,Bausteine!$A$2:$AS$46,7,FALSE))+IF(H15="",0,VLOOKUP(H15,Bausteine!$A$2:$AS$46,7,FALSE))+IF(I15="",0,VLOOKUP(I15,Bausteine!$A$2:$AS$46,7,FALSE))+IF(J15="",0,VLOOKUP(J15,Bausteine!$A$2:$AS$46,7,FALSE))+IF(K15="",0,VLOOKUP(K15,Bausteine!$A$2:$AS$46,7,FALSE))+IF(L15="",0,VLOOKUP(L15,Bausteine!$A$2:$AS$46,7,FALSE))+IF(AC15="",0,VLOOKUP(AC15,Bausteine!$A$2:$AS$46,7,FALSE))+IF(AF15="",0,VLOOKUP(AF15,Bausteine!$A$2:$AS$46,7,FALSE))+IF(AG15="",0,VLOOKUP(AG15,Bausteine!$A$2:$AS$46,7,FALSE))+IF(AH15="",0,VLOOKUP(AH15,Bausteine!$A$2:$AS$46,7,FALSE))+AI15 | Q15: =N15*Parameter!$B$2 | R15: =AE15-Q15 | S15: =IF(C15="",0,VLOOKUP(C15,Bausteine!$A$2:$AS$46,13,FALSE))*IF(F15="",0,VLOOKUP(F15,Bausteine!$A$2:$AS$46,16,FALSE))/100 | T15: =IF(C15="",0,VLOOKUP(C15,Bausteine!$A$2:$AS$46,8,FALSE))*IF(F15="",0,VLOOKUP(F15,Bausteine!$A$2:$AS$46,15,FALSE))/100+IF(D15="",0,VLOOKUP(D15,Bausteine!$A$2:$AS$46,8,FALSE))+IF(E15="",0,VLOOKUP(E15,Bausteine!$A$2:$AS$46,8,FALSE))+IF(G15="",0,VLOOKUP(G15,Bausteine!$A$2:$AS$46,8,FALSE))+IF(H15="",0,VLOOKUP(H15,Bausteine!$A$2:$AS$46,8,FALSE))+IF(I15="",0,VLOOKUP(I15,Bausteine!$A$2:$AS$46,8,FALSE))+IF(J15="",0,VLOOKUP(J15,Bausteine!$A$2:$AS$46,8,FALSE))+IF(K15="",0,VLOOKUP(K15,Bausteine!$A$2:$AS$46,8,FALSE))+IF(L15="",0,VLOOKUP(L15,Bausteine!$A$2:$AS$46,8,FALSE))+IF(AC15="",0,VLOOKUP(AC15,Bausteine!$A$2:$AS$46,8,FALSE))+IF(AF15="",0,VLOOKUP(AF15,Bausteine!$A$2:$AS$46,8,FALSE))+IF(AG15="",0,VLOOKUP(AG15,Bausteine!$A$2:$AS$46,8,FALSE))+IF(AH15="",0,VLOOKUP(AH15,Bausteine!$A$2:$AS$46,8,FALSE))+AJ15 | U15: =IF(C15="",0,VLOOKUP(C15,Bausteine!$A$2:$AS$46,9,FALSE))+IF(D15="",0,VLOOKUP(D15,Bausteine!$A$2:$AS$46,9,FALSE))+IF(E15="",0,VLOOKUP(E15,Bausteine!$A$2:$AS$46,9,FALSE))+IF(F15="",0,VLOOKUP(F15,Bausteine!$A$2:$AS$46,9,FALSE))+IF(G15="",0,VLOOKUP(G15,Bausteine!$A$2:$AS$46,9,FALSE))+IF(H15="",0,VLOOKUP(H15,Bausteine!$A$2:$AS$46,9,FALSE))+IF(I15="",0,VLOOKUP(I15,Bausteine!$A$2:$AS$46,9,FALSE))+IF(J15="",0,VLOOKUP(J15,Bausteine!$A$2:$AS$46,9,FALSE))+IF(K15="",0,VLOOKUP(K15,Bausteine!$A$2:$AS$46,9,FALSE))+IF(L15="",0,VLOOKUP(L15,Bausteine!$A$2:$AS$46,9,FALSE))+IF(AC15="",0,VLOOKUP(AC15,Bausteine!$A$2:$AS$46,9,FALSE))+IF(AF15="",0,VLOOKUP(AF15,Bausteine!$A$2:$AS$46,9,FALSE))+IF(AG15="",0,VLOOKUP(AG15,Bausteine!$A$2:$AS$46,9,FALSE))+IF(AH15="",0,VLOOKUP(AH15,Bausteine!$A$2:$AS$46,9,FALSE)) | V15: =IF(D15="",0,VLOOKUP(D15,Bausteine!$A$2:$AS$46,10,FALSE))-U15/IF(E15="",0,VLOOKUP(E15,Bausteine!$A$2:$AS$46,11,FALSE)) | W15: =IF(Y15<>"OK","",ROUND(MIN(IF(C15="",0,VLOOKUP(C15,Bausteine!$A$2:$AS$46,21,FALSE)),IF(C15="",0,VLOOKUP(C15,Bausteine!$A$2:$AS$46,20,FALSE))*(V15/T15/(IF(C15="",0,VLOOKUP(C15,Bausteine!$A$2:$AS$46,19,FALSE))/IF(C15="",0,VLOOKUP(C15,Bausteine!$A$2:$AS$46,18,FALSE))))^Parameter!$B$3),0)) | X15: =IF(F15="",0,VLOOKUP(F15,Bausteine!$A$2:$AS$46,14,FALSE)) | Y15: =IFERROR(IF(OR(AD15<=0,AD15>1,R15<=0,T15<=0,V15<=0,U15>IF(E15="",0,VLOOKUP(E15,Bausteine!$A$2:$AS$46,12,FALSE)),T15>IF(C15="",0,VLOOKUP(C15,Bausteine!$A$2:$AS$46,22,FALSE)),IF(E15="",0,VLOOKUP(E15,Bausteine!$A$2:$AS$46,11,FALSE))<=0,IF(E15="",0,VLOOKUP(E15,Bausteine!$A$2:$AS$46,11,FALSE))>1),"UNGUELTIG","OK"),"FEHLER") | Z15: 3650 | AA15: 55 | AB15: Standard PDL composed via existing ^AttackingCargoAndPDL; no special price discount. | AD15: =IF(AC15="",1,IF(AC15="",0,VLOOKUP(AC15,Bausteine!$A$2:$AS$46,37,FALSE))/100) | AE15: =P15*AD15 | AI15: =SUMIF(Startbesatzung!$A$2:$A$7,A15,Startbesatzung!$D$2:$D$7) | AJ15: =SUMIF(Startbesatzung!$A$2:$A$7,A15,Startbesatzung!$E$2:$E$7) | AK15: =MAX(0,IF(Startbesatzung!A2=A15,Startbesatzung!G2,0),IF(Startbesatzung!A3=A15,Startbesatzung!G3,0),IF(Startbesatzung!A4=A15,Startbesatzung!G4,0),IF(Startbesatzung!A5=A15,Startbesatzung!G5,0),IF(Startbesatzung!A6=A15,Startbesatzung!G6,0),IF(Startbesatzung!A7=A15,Startbesatzung!G7,0)) | AL15: =IF(AF15="","",IF(IF(AH15="",0,VLOOKUP(AH15,Bausteine!$A$2:$AS$46,38,FALSE))>0,IF(AH15="",0,VLOOKUP(AH15,Bausteine!$A$2:$AS$46,38,FALSE)),IF(AG15="",0,VLOOKUP(AG15,Bausteine!$A$2:$AS$46,28,FALSE)))) | AM15: =IF(AF15="","",IF(AG15="",0,VLOOKUP(AG15,Bausteine!$A$2:$AS$46,44,FALSE))) | AN15: =IF(AF15="","",IF(AF15="",0,VLOOKUP(AF15,Bausteine!$A$2:$AS$46,27,FALSE))) | AO15: =IF(AF15="","",IF(AF15="",0,VLOOKUP(AF15,Bausteine!$A$2:$AS$46,25,FALSE))) | AP15: =IF(AF15="","",IF(AH15="",0,VLOOKUP(AH15,Bausteine!$A$2:$AS$46,29,FALSE)))
A16: Overlord Bunker Reflector | B16: china | C16: overlord-chassis | D16: diesel-heavy-boost | E16: efficient-generator | F16: reflector | G16: heavy-twin-turret | H16: overlord-cannon | I16: heavy-shell | J16: firing-bunker | M16: =IF(C16="",0,VLOOKUP(C16,Bausteine!$A$2:$AS$46,4,FALSE))+IF(D16="",0,VLOOKUP(D16,Bausteine!$A$2:$AS$46,4,FALSE))+IF(E16="",0,VLOOKUP(E16,Bausteine!$A$2:$AS$46,4,FALSE))+IF(F16="",0,VLOOKUP(F16,Bausteine!$A$2:$AS$46,4,FALSE))+IF(G16="",0,VLOOKUP(G16,Bausteine!$A$2:$AS$46,4,FALSE))+IF(H16="",0,VLOOKUP(H16,Bausteine!$A$2:$AS$46,4,FALSE))+IF(I16="",0,VLOOKUP(I16,Bausteine!$A$2:$AS$46,4,FALSE))+IF(J16="",0,VLOOKUP(J16,Bausteine!$A$2:$AS$46,4,FALSE))+IF(K16="",0,VLOOKUP(K16,Bausteine!$A$2:$AS$46,4,FALSE))+IF(L16="",0,VLOOKUP(L16,Bausteine!$A$2:$AS$46,4,FALSE))+IF(AC16="",0,VLOOKUP(AC16,Bausteine!$A$2:$AS$46,4,FALSE))+IF(AF16="",0,VLOOKUP(AF16,Bausteine!$A$2:$AS$46,4,FALSE))+IF(AG16="",0,VLOOKUP(AG16,Bausteine!$A$2:$AS$46,4,FALSE))+IF(AH16="",0,VLOOKUP(AH16,Bausteine!$A$2:$AS$46,4,FALSE)) | N16: =IF(C16="",0,VLOOKUP(C16,Bausteine!$A$2:$AS$46,5,FALSE))+IF(D16="",0,VLOOKUP(D16,Bausteine!$A$2:$AS$46,5,FALSE))+IF(E16="",0,VLOOKUP(E16,Bausteine!$A$2:$AS$46,5,FALSE))+IF(F16="",0,VLOOKUP(F16,Bausteine!$A$2:$AS$46,5,FALSE))+IF(G16="",0,VLOOKUP(G16,Bausteine!$A$2:$AS$46,5,FALSE))+IF(H16="",0,VLOOKUP(H16,Bausteine!$A$2:$AS$46,5,FALSE))+IF(I16="",0,VLOOKUP(I16,Bausteine!$A$2:$AS$46,5,FALSE))+IF(J16="",0,VLOOKUP(J16,Bausteine!$A$2:$AS$46,5,FALSE))+IF(K16="",0,VLOOKUP(K16,Bausteine!$A$2:$AS$46,5,FALSE))+IF(L16="",0,VLOOKUP(L16,Bausteine!$A$2:$AS$46,5,FALSE))+IF(AC16="",0,VLOOKUP(AC16,Bausteine!$A$2:$AS$46,5,FALSE))+IF(AF16="",0,VLOOKUP(AF16,Bausteine!$A$2:$AS$46,5,FALSE))+IF(AG16="",0,VLOOKUP(AG16,Bausteine!$A$2:$AS$46,5,FALSE))+IF(AH16="",0,VLOOKUP(AH16,Bausteine!$A$2:$AS$46,5,FALSE)) | O16: =MAX(IF(C16="",0,VLOOKUP(C16,Bausteine!$A$2:$AS$46,6,FALSE)),IF(D16="",0,VLOOKUP(D16,Bausteine!$A$2:$AS$46,6,FALSE)),IF(E16="",0,VLOOKUP(E16,Bausteine!$A$2:$AS$46,6,FALSE)),IF(F16="",0,VLOOKUP(F16,Bausteine!$A$2:$AS$46,6,FALSE)),IF(G16="",0,VLOOKUP(G16,Bausteine!$A$2:$AS$46,6,FALSE)),IF(H16="",0,VLOOKUP(H16,Bausteine!$A$2:$AS$46,6,FALSE)),IF(I16="",0,VLOOKUP(I16,Bausteine!$A$2:$AS$46,6,FALSE)),IF(J16="",0,VLOOKUP(J16,Bausteine!$A$2:$AS$46,6,FALSE)),IF(K16="",0,VLOOKUP(K16,Bausteine!$A$2:$AS$46,6,FALSE)),IF(L16="",0,VLOOKUP(L16,Bausteine!$A$2:$AS$46,6,FALSE)),IF(AC16="",0,VLOOKUP(AC16,Bausteine!$A$2:$AS$46,6,FALSE)),IF(AF16="",0,VLOOKUP(AF16,Bausteine!$A$2:$AS$46,6,FALSE)),IF(AG16="",0,VLOOKUP(AG16,Bausteine!$A$2:$AS$46,6,FALSE)),IF(AH16="",0,VLOOKUP(AH16,Bausteine!$A$2:$AS$46,6,FALSE)),AK16) | P16: =IF(C16="",0,VLOOKUP(C16,Bausteine!$A$2:$AS$46,7,FALSE))*IF(F16="",0,VLOOKUP(F16,Bausteine!$A$2:$AS$46,17,FALSE))/100+IF(D16="",0,VLOOKUP(D16,Bausteine!$A$2:$AS$46,7,FALSE))+IF(E16="",0,VLOOKUP(E16,Bausteine!$A$2:$AS$46,7,FALSE))+IF(G16="",0,VLOOKUP(G16,Bausteine!$A$2:$AS$46,7,FALSE))+IF(H16="",0,VLOOKUP(H16,Bausteine!$A$2:$AS$46,7,FALSE))+IF(I16="",0,VLOOKUP(I16,Bausteine!$A$2:$AS$46,7,FALSE))+IF(J16="",0,VLOOKUP(J16,Bausteine!$A$2:$AS$46,7,FALSE))+IF(K16="",0,VLOOKUP(K16,Bausteine!$A$2:$AS$46,7,FALSE))+IF(L16="",0,VLOOKUP(L16,Bausteine!$A$2:$AS$46,7,FALSE))+IF(AC16="",0,VLOOKUP(AC16,Bausteine!$A$2:$AS$46,7,FALSE))+IF(AF16="",0,VLOOKUP(AF16,Bausteine!$A$2:$AS$46,7,FALSE))+IF(AG16="",0,VLOOKUP(AG16,Bausteine!$A$2:$AS$46,7,FALSE))+IF(AH16="",0,VLOOKUP(AH16,Bausteine!$A$2:$AS$46,7,FALSE))+AI16 | Q16: =N16*Parameter!$B$2 | R16: =AE16-Q16 | S16: =IF(C16="",0,VLOOKUP(C16,Bausteine!$A$2:$AS$46,13,FALSE))*IF(F16="",0,VLOOKUP(F16,Bausteine!$A$2:$AS$46,16,FALSE))/100 | T16: =IF(C16="",0,VLOOKUP(C16,Bausteine!$A$2:$AS$46,8,FALSE))*IF(F16="",0,VLOOKUP(F16,Bausteine!$A$2:$AS$46,15,FALSE))/100+IF(D16="",0,VLOOKUP(D16,Bausteine!$A$2:$AS$46,8,FALSE))+IF(E16="",0,VLOOKUP(E16,Bausteine!$A$2:$AS$46,8,FALSE))+IF(G16="",0,VLOOKUP(G16,Bausteine!$A$2:$AS$46,8,FALSE))+IF(H16="",0,VLOOKUP(H16,Bausteine!$A$2:$AS$46,8,FALSE))+IF(I16="",0,VLOOKUP(I16,Bausteine!$A$2:$AS$46,8,FALSE))+IF(J16="",0,VLOOKUP(J16,Bausteine!$A$2:$AS$46,8,FALSE))+IF(K16="",0,VLOOKUP(K16,Bausteine!$A$2:$AS$46,8,FALSE))+IF(L16="",0,VLOOKUP(L16,Bausteine!$A$2:$AS$46,8,FALSE))+IF(AC16="",0,VLOOKUP(AC16,Bausteine!$A$2:$AS$46,8,FALSE))+IF(AF16="",0,VLOOKUP(AF16,Bausteine!$A$2:$AS$46,8,FALSE))+IF(AG16="",0,VLOOKUP(AG16,Bausteine!$A$2:$AS$46,8,FALSE))+IF(AH16="",0,VLOOKUP(AH16,Bausteine!$A$2:$AS$46,8,FALSE))+AJ16 | U16: =IF(C16="",0,VLOOKUP(C16,Bausteine!$A$2:$AS$46,9,FALSE))+IF(D16="",0,VLOOKUP(D16,Bausteine!$A$2:$AS$46,9,FALSE))+IF(E16="",0,VLOOKUP(E16,Bausteine!$A$2:$AS$46,9,FALSE))+IF(F16="",0,VLOOKUP(F16,Bausteine!$A$2:$AS$46,9,FALSE))+IF(G16="",0,VLOOKUP(G16,Bausteine!$A$2:$AS$46,9,FALSE))+IF(H16="",0,VLOOKUP(H16,Bausteine!$A$2:$AS$46,9,FALSE))+IF(I16="",0,VLOOKUP(I16,Bausteine!$A$2:$AS$46,9,FALSE))+IF(J16="",0,VLOOKUP(J16,Bausteine!$A$2:$AS$46,9,FALSE))+IF(K16="",0,VLOOKUP(K16,Bausteine!$A$2:$AS$46,9,FALSE))+IF(L16="",0,VLOOKUP(L16,Bausteine!$A$2:$AS$46,9,FALSE))+IF(AC16="",0,VLOOKUP(AC16,Bausteine!$A$2:$AS$46,9,FALSE))+IF(AF16="",0,VLOOKUP(AF16,Bausteine!$A$2:$AS$46,9,FALSE))+IF(AG16="",0,VLOOKUP(AG16,Bausteine!$A$2:$AS$46,9,FALSE))+IF(AH16="",0,VLOOKUP(AH16,Bausteine!$A$2:$AS$46,9,FALSE)) | V16: =IF(D16="",0,VLOOKUP(D16,Bausteine!$A$2:$AS$46,10,FALSE))-U16/IF(E16="",0,VLOOKUP(E16,Bausteine!$A$2:$AS$46,11,FALSE)) | W16: =IF(Y16<>"OK","",ROUND(MIN(IF(C16="",0,VLOOKUP(C16,Bausteine!$A$2:$AS$46,21,FALSE)),IF(C16="",0,VLOOKUP(C16,Bausteine!$A$2:$AS$46,20,FALSE))*(V16/T16/(IF(C16="",0,VLOOKUP(C16,Bausteine!$A$2:$AS$46,19,FALSE))/IF(C16="",0,VLOOKUP(C16,Bausteine!$A$2:$AS$46,18,FALSE))))^Parameter!$B$3),0)) | X16: =IF(F16="",0,VLOOKUP(F16,Bausteine!$A$2:$AS$46,14,FALSE)) | Y16: =IFERROR(IF(OR(AD16<=0,AD16>1,R16<=0,T16<=0,V16<=0,U16>IF(E16="",0,VLOOKUP(E16,Bausteine!$A$2:$AS$46,12,FALSE)),T16>IF(C16="",0,VLOOKUP(C16,Bausteine!$A$2:$AS$46,22,FALSE)),IF(E16="",0,VLOOKUP(E16,Bausteine!$A$2:$AS$46,11,FALSE))<=0,IF(E16="",0,VLOOKUP(E16,Bausteine!$A$2:$AS$46,11,FALSE))>1),"UNGUELTIG","OK"),"FEHLER") | Z16: 3000 | AA16: 55 | AD16: =IF(AC16="",1,IF(AC16="",0,VLOOKUP(AC16,Bausteine!$A$2:$AS$46,37,FALSE))/100) | AE16: =P16*AD16 | AI16: =SUMIF(Startbesatzung!$A$2:$A$7,A16,Startbesatzung!$D$2:$D$7) | AJ16: =SUMIF(Startbesatzung!$A$2:$A$7,A16,Startbesatzung!$E$2:$E$7) | AK16: =MAX(0,IF(Startbesatzung!A2=A16,Startbesatzung!G2,0),IF(Startbesatzung!A3=A16,Startbesatzung!G3,0),IF(Startbesatzung!A4=A16,Startbesatzung!G4,0),IF(Startbesatzung!A5=A16,Startbesatzung!G5,0),IF(Startbesatzung!A6=A16,Startbesatzung!G6,0),IF(Startbesatzung!A7=A16,Startbesatzung!G7,0)) | AL16: =IF(AF16="","",IF(IF(AH16="",0,VLOOKUP(AH16,Bausteine!$A$2:$AS$46,38,FALSE))>0,IF(AH16="",0,VLOOKUP(AH16,Bausteine!$A$2:$AS$46,38,FALSE)),IF(AG16="",0,VLOOKUP(AG16,Bausteine!$A$2:$AS$46,28,FALSE)))) | AM16: =IF(AF16="","",IF(AG16="",0,VLOOKUP(AG16,Bausteine!$A$2:$AS$46,44,FALSE))) | AN16: =IF(AF16="","",IF(AF16="",0,VLOOKUP(AF16,Bausteine!$A$2:$AS$46,27,FALSE))) | AO16: =IF(AF16="","",IF(AF16="",0,VLOOKUP(AF16,Bausteine!$A$2:$AS$46,25,FALSE))) | AP16: =IF(AF16="","",IF(AH16="",0,VLOOKUP(AH16,Bausteine!$A$2:$AS$46,29,FALSE)))
A17: Overlord baseline | B17: china | C17: overlord-chassis | D17: diesel-heavy | E17: baseline-generator | F17: heavy | G17: heavy-twin-turret | H17: overlord-cannon | I17: heavy-shell | M17: =IF(C17="",0,VLOOKUP(C17,Bausteine!$A$2:$AS$46,4,FALSE))+IF(D17="",0,VLOOKUP(D17,Bausteine!$A$2:$AS$46,4,FALSE))+IF(E17="",0,VLOOKUP(E17,Bausteine!$A$2:$AS$46,4,FALSE))+IF(F17="",0,VLOOKUP(F17,Bausteine!$A$2:$AS$46,4,FALSE))+IF(G17="",0,VLOOKUP(G17,Bausteine!$A$2:$AS$46,4,FALSE))+IF(H17="",0,VLOOKUP(H17,Bausteine!$A$2:$AS$46,4,FALSE))+IF(I17="",0,VLOOKUP(I17,Bausteine!$A$2:$AS$46,4,FALSE))+IF(J17="",0,VLOOKUP(J17,Bausteine!$A$2:$AS$46,4,FALSE))+IF(K17="",0,VLOOKUP(K17,Bausteine!$A$2:$AS$46,4,FALSE))+IF(L17="",0,VLOOKUP(L17,Bausteine!$A$2:$AS$46,4,FALSE))+IF(AC17="",0,VLOOKUP(AC17,Bausteine!$A$2:$AS$46,4,FALSE))+IF(AF17="",0,VLOOKUP(AF17,Bausteine!$A$2:$AS$46,4,FALSE))+IF(AG17="",0,VLOOKUP(AG17,Bausteine!$A$2:$AS$46,4,FALSE))+IF(AH17="",0,VLOOKUP(AH17,Bausteine!$A$2:$AS$46,4,FALSE)) | N17: =IF(C17="",0,VLOOKUP(C17,Bausteine!$A$2:$AS$46,5,FALSE))+IF(D17="",0,VLOOKUP(D17,Bausteine!$A$2:$AS$46,5,FALSE))+IF(E17="",0,VLOOKUP(E17,Bausteine!$A$2:$AS$46,5,FALSE))+IF(F17="",0,VLOOKUP(F17,Bausteine!$A$2:$AS$46,5,FALSE))+IF(G17="",0,VLOOKUP(G17,Bausteine!$A$2:$AS$46,5,FALSE))+IF(H17="",0,VLOOKUP(H17,Bausteine!$A$2:$AS$46,5,FALSE))+IF(I17="",0,VLOOKUP(I17,Bausteine!$A$2:$AS$46,5,FALSE))+IF(J17="",0,VLOOKUP(J17,Bausteine!$A$2:$AS$46,5,FALSE))+IF(K17="",0,VLOOKUP(K17,Bausteine!$A$2:$AS$46,5,FALSE))+IF(L17="",0,VLOOKUP(L17,Bausteine!$A$2:$AS$46,5,FALSE))+IF(AC17="",0,VLOOKUP(AC17,Bausteine!$A$2:$AS$46,5,FALSE))+IF(AF17="",0,VLOOKUP(AF17,Bausteine!$A$2:$AS$46,5,FALSE))+IF(AG17="",0,VLOOKUP(AG17,Bausteine!$A$2:$AS$46,5,FALSE))+IF(AH17="",0,VLOOKUP(AH17,Bausteine!$A$2:$AS$46,5,FALSE)) | O17: =MAX(IF(C17="",0,VLOOKUP(C17,Bausteine!$A$2:$AS$46,6,FALSE)),IF(D17="",0,VLOOKUP(D17,Bausteine!$A$2:$AS$46,6,FALSE)),IF(E17="",0,VLOOKUP(E17,Bausteine!$A$2:$AS$46,6,FALSE)),IF(F17="",0,VLOOKUP(F17,Bausteine!$A$2:$AS$46,6,FALSE)),IF(G17="",0,VLOOKUP(G17,Bausteine!$A$2:$AS$46,6,FALSE)),IF(H17="",0,VLOOKUP(H17,Bausteine!$A$2:$AS$46,6,FALSE)),IF(I17="",0,VLOOKUP(I17,Bausteine!$A$2:$AS$46,6,FALSE)),IF(J17="",0,VLOOKUP(J17,Bausteine!$A$2:$AS$46,6,FALSE)),IF(K17="",0,VLOOKUP(K17,Bausteine!$A$2:$AS$46,6,FALSE)),IF(L17="",0,VLOOKUP(L17,Bausteine!$A$2:$AS$46,6,FALSE)),IF(AC17="",0,VLOOKUP(AC17,Bausteine!$A$2:$AS$46,6,FALSE)),IF(AF17="",0,VLOOKUP(AF17,Bausteine!$A$2:$AS$46,6,FALSE)),IF(AG17="",0,VLOOKUP(AG17,Bausteine!$A$2:$AS$46,6,FALSE)),IF(AH17="",0,VLOOKUP(AH17,Bausteine!$A$2:$AS$46,6,FALSE)),AK17) | P17: =IF(C17="",0,VLOOKUP(C17,Bausteine!$A$2:$AS$46,7,FALSE))*IF(F17="",0,VLOOKUP(F17,Bausteine!$A$2:$AS$46,17,FALSE))/100+IF(D17="",0,VLOOKUP(D17,Bausteine!$A$2:$AS$46,7,FALSE))+IF(E17="",0,VLOOKUP(E17,Bausteine!$A$2:$AS$46,7,FALSE))+IF(G17="",0,VLOOKUP(G17,Bausteine!$A$2:$AS$46,7,FALSE))+IF(H17="",0,VLOOKUP(H17,Bausteine!$A$2:$AS$46,7,FALSE))+IF(I17="",0,VLOOKUP(I17,Bausteine!$A$2:$AS$46,7,FALSE))+IF(J17="",0,VLOOKUP(J17,Bausteine!$A$2:$AS$46,7,FALSE))+IF(K17="",0,VLOOKUP(K17,Bausteine!$A$2:$AS$46,7,FALSE))+IF(L17="",0,VLOOKUP(L17,Bausteine!$A$2:$AS$46,7,FALSE))+IF(AC17="",0,VLOOKUP(AC17,Bausteine!$A$2:$AS$46,7,FALSE))+IF(AF17="",0,VLOOKUP(AF17,Bausteine!$A$2:$AS$46,7,FALSE))+IF(AG17="",0,VLOOKUP(AG17,Bausteine!$A$2:$AS$46,7,FALSE))+IF(AH17="",0,VLOOKUP(AH17,Bausteine!$A$2:$AS$46,7,FALSE))+AI17 | Q17: =N17*Parameter!$B$2 | R17: =AE17-Q17 | S17: =IF(C17="",0,VLOOKUP(C17,Bausteine!$A$2:$AS$46,13,FALSE))*IF(F17="",0,VLOOKUP(F17,Bausteine!$A$2:$AS$46,16,FALSE))/100 | T17: =IF(C17="",0,VLOOKUP(C17,Bausteine!$A$2:$AS$46,8,FALSE))*IF(F17="",0,VLOOKUP(F17,Bausteine!$A$2:$AS$46,15,FALSE))/100+IF(D17="",0,VLOOKUP(D17,Bausteine!$A$2:$AS$46,8,FALSE))+IF(E17="",0,VLOOKUP(E17,Bausteine!$A$2:$AS$46,8,FALSE))+IF(G17="",0,VLOOKUP(G17,Bausteine!$A$2:$AS$46,8,FALSE))+IF(H17="",0,VLOOKUP(H17,Bausteine!$A$2:$AS$46,8,FALSE))+IF(I17="",0,VLOOKUP(I17,Bausteine!$A$2:$AS$46,8,FALSE))+IF(J17="",0,VLOOKUP(J17,Bausteine!$A$2:$AS$46,8,FALSE))+IF(K17="",0,VLOOKUP(K17,Bausteine!$A$2:$AS$46,8,FALSE))+IF(L17="",0,VLOOKUP(L17,Bausteine!$A$2:$AS$46,8,FALSE))+IF(AC17="",0,VLOOKUP(AC17,Bausteine!$A$2:$AS$46,8,FALSE))+IF(AF17="",0,VLOOKUP(AF17,Bausteine!$A$2:$AS$46,8,FALSE))+IF(AG17="",0,VLOOKUP(AG17,Bausteine!$A$2:$AS$46,8,FALSE))+IF(AH17="",0,VLOOKUP(AH17,Bausteine!$A$2:$AS$46,8,FALSE))+AJ17 | U17: =IF(C17="",0,VLOOKUP(C17,Bausteine!$A$2:$AS$46,9,FALSE))+IF(D17="",0,VLOOKUP(D17,Bausteine!$A$2:$AS$46,9,FALSE))+IF(E17="",0,VLOOKUP(E17,Bausteine!$A$2:$AS$46,9,FALSE))+IF(F17="",0,VLOOKUP(F17,Bausteine!$A$2:$AS$46,9,FALSE))+IF(G17="",0,VLOOKUP(G17,Bausteine!$A$2:$AS$46,9,FALSE))+IF(H17="",0,VLOOKUP(H17,Bausteine!$A$2:$AS$46,9,FALSE))+IF(I17="",0,VLOOKUP(I17,Bausteine!$A$2:$AS$46,9,FALSE))+IF(J17="",0,VLOOKUP(J17,Bausteine!$A$2:$AS$46,9,FALSE))+IF(K17="",0,VLOOKUP(K17,Bausteine!$A$2:$AS$46,9,FALSE))+IF(L17="",0,VLOOKUP(L17,Bausteine!$A$2:$AS$46,9,FALSE))+IF(AC17="",0,VLOOKUP(AC17,Bausteine!$A$2:$AS$46,9,FALSE))+IF(AF17="",0,VLOOKUP(AF17,Bausteine!$A$2:$AS$46,9,FALSE))+IF(AG17="",0,VLOOKUP(AG17,Bausteine!$A$2:$AS$46,9,FALSE))+IF(AH17="",0,VLOOKUP(AH17,Bausteine!$A$2:$AS$46,9,FALSE)) | V17: =IF(D17="",0,VLOOKUP(D17,Bausteine!$A$2:$AS$46,10,FALSE))-U17/IF(E17="",0,VLOOKUP(E17,Bausteine!$A$2:$AS$46,11,FALSE)) | W17: =IF(Y17<>"OK","",ROUND(MIN(IF(C17="",0,VLOOKUP(C17,Bausteine!$A$2:$AS$46,21,FALSE)),IF(C17="",0,VLOOKUP(C17,Bausteine!$A$2:$AS$46,20,FALSE))*(V17/T17/(IF(C17="",0,VLOOKUP(C17,Bausteine!$A$2:$AS$46,19,FALSE))/IF(C17="",0,VLOOKUP(C17,Bausteine!$A$2:$AS$46,18,FALSE))))^Parameter!$B$3),0)) | X17: =IF(F17="",0,VLOOKUP(F17,Bausteine!$A$2:$AS$46,14,FALSE)) | Y17: =IFERROR(IF(OR(AD17<=0,AD17>1,R17<=0,T17<=0,V17<=0,U17>IF(E17="",0,VLOOKUP(E17,Bausteine!$A$2:$AS$46,12,FALSE)),T17>IF(C17="",0,VLOOKUP(C17,Bausteine!$A$2:$AS$46,22,FALSE)),IF(E17="",0,VLOOKUP(E17,Bausteine!$A$2:$AS$46,11,FALSE))<=0,IF(E17="",0,VLOOKUP(E17,Bausteine!$A$2:$AS$46,11,FALSE))>1),"UNGUELTIG","OK"),"FEHLER") | Z17: 2000 | AA17: 56 | AB17: Normal Overlord, not Emperor or nuclear-drive-upgraded state. Tech2 approximates radar prerequisite. | AD17: =IF(AC17="",1,IF(AC17="",0,VLOOKUP(AC17,Bausteine!$A$2:$AS$46,37,FALSE))/100) | AE17: =P17*AD17 | AI17: =SUMIF(Startbesatzung!$A$2:$A$7,A17,Startbesatzung!$D$2:$D$7) | AJ17: =SUMIF(Startbesatzung!$A$2:$A$7,A17,Startbesatzung!$E$2:$E$7) | AK17: =MAX(0,IF(Startbesatzung!A2=A17,Startbesatzung!G2,0),IF(Startbesatzung!A3=A17,Startbesatzung!G3,0),IF(Startbesatzung!A4=A17,Startbesatzung!G4,0),IF(Startbesatzung!A5=A17,Startbesatzung!G5,0),IF(Startbesatzung!A6=A17,Startbesatzung!G6,0),IF(Startbesatzung!A7=A17,Startbesatzung!G7,0)) | AL17: =IF(AF17="","",IF(IF(AH17="",0,VLOOKUP(AH17,Bausteine!$A$2:$AS$46,38,FALSE))>0,IF(AH17="",0,VLOOKUP(AH17,Bausteine!$A$2:$AS$46,38,FALSE)),IF(AG17="",0,VLOOKUP(AG17,Bausteine!$A$2:$AS$46,28,FALSE)))) | AM17: =IF(AF17="","",IF(AG17="",0,VLOOKUP(AG17,Bausteine!$A$2:$AS$46,44,FALSE))) | AN17: =IF(AF17="","",IF(AF17="",0,VLOOKUP(AF17,Bausteine!$A$2:$AS$46,27,FALSE))) | AO17: =IF(AF17="","",IF(AF17="",0,VLOOKUP(AF17,Bausteine!$A$2:$AS$46,25,FALSE))) | AP17: =IF(AF17="","",IF(AH17="",0,VLOOKUP(AH17,Bausteine!$A$2:$AS$46,29,FALSE)))
A18: Overlord Nuclear Shells | B18: china | C18: overlord-chassis | D18: diesel-heavy | E18: baseline-generator | F18: heavy | G18: heavy-twin-turret | H18: overlord-cannon | I18: heavy-nuclear-shell | M18: =IF(C18="",0,VLOOKUP(C18,Bausteine!$A$2:$AS$46,4,FALSE))+IF(D18="",0,VLOOKUP(D18,Bausteine!$A$2:$AS$46,4,FALSE))+IF(E18="",0,VLOOKUP(E18,Bausteine!$A$2:$AS$46,4,FALSE))+IF(F18="",0,VLOOKUP(F18,Bausteine!$A$2:$AS$46,4,FALSE))+IF(G18="",0,VLOOKUP(G18,Bausteine!$A$2:$AS$46,4,FALSE))+IF(H18="",0,VLOOKUP(H18,Bausteine!$A$2:$AS$46,4,FALSE))+IF(I18="",0,VLOOKUP(I18,Bausteine!$A$2:$AS$46,4,FALSE))+IF(J18="",0,VLOOKUP(J18,Bausteine!$A$2:$AS$46,4,FALSE))+IF(K18="",0,VLOOKUP(K18,Bausteine!$A$2:$AS$46,4,FALSE))+IF(L18="",0,VLOOKUP(L18,Bausteine!$A$2:$AS$46,4,FALSE))+IF(AC18="",0,VLOOKUP(AC18,Bausteine!$A$2:$AS$46,4,FALSE))+IF(AF18="",0,VLOOKUP(AF18,Bausteine!$A$2:$AS$46,4,FALSE))+IF(AG18="",0,VLOOKUP(AG18,Bausteine!$A$2:$AS$46,4,FALSE))+IF(AH18="",0,VLOOKUP(AH18,Bausteine!$A$2:$AS$46,4,FALSE)) | N18: =IF(C18="",0,VLOOKUP(C18,Bausteine!$A$2:$AS$46,5,FALSE))+IF(D18="",0,VLOOKUP(D18,Bausteine!$A$2:$AS$46,5,FALSE))+IF(E18="",0,VLOOKUP(E18,Bausteine!$A$2:$AS$46,5,FALSE))+IF(F18="",0,VLOOKUP(F18,Bausteine!$A$2:$AS$46,5,FALSE))+IF(G18="",0,VLOOKUP(G18,Bausteine!$A$2:$AS$46,5,FALSE))+IF(H18="",0,VLOOKUP(H18,Bausteine!$A$2:$AS$46,5,FALSE))+IF(I18="",0,VLOOKUP(I18,Bausteine!$A$2:$AS$46,5,FALSE))+IF(J18="",0,VLOOKUP(J18,Bausteine!$A$2:$AS$46,5,FALSE))+IF(K18="",0,VLOOKUP(K18,Bausteine!$A$2:$AS$46,5,FALSE))+IF(L18="",0,VLOOKUP(L18,Bausteine!$A$2:$AS$46,5,FALSE))+IF(AC18="",0,VLOOKUP(AC18,Bausteine!$A$2:$AS$46,5,FALSE))+IF(AF18="",0,VLOOKUP(AF18,Bausteine!$A$2:$AS$46,5,FALSE))+IF(AG18="",0,VLOOKUP(AG18,Bausteine!$A$2:$AS$46,5,FALSE))+IF(AH18="",0,VLOOKUP(AH18,Bausteine!$A$2:$AS$46,5,FALSE)) | O18: =MAX(IF(C18="",0,VLOOKUP(C18,Bausteine!$A$2:$AS$46,6,FALSE)),IF(D18="",0,VLOOKUP(D18,Bausteine!$A$2:$AS$46,6,FALSE)),IF(E18="",0,VLOOKUP(E18,Bausteine!$A$2:$AS$46,6,FALSE)),IF(F18="",0,VLOOKUP(F18,Bausteine!$A$2:$AS$46,6,FALSE)),IF(G18="",0,VLOOKUP(G18,Bausteine!$A$2:$AS$46,6,FALSE)),IF(H18="",0,VLOOKUP(H18,Bausteine!$A$2:$AS$46,6,FALSE)),IF(I18="",0,VLOOKUP(I18,Bausteine!$A$2:$AS$46,6,FALSE)),IF(J18="",0,VLOOKUP(J18,Bausteine!$A$2:$AS$46,6,FALSE)),IF(K18="",0,VLOOKUP(K18,Bausteine!$A$2:$AS$46,6,FALSE)),IF(L18="",0,VLOOKUP(L18,Bausteine!$A$2:$AS$46,6,FALSE)),IF(AC18="",0,VLOOKUP(AC18,Bausteine!$A$2:$AS$46,6,FALSE)),IF(AF18="",0,VLOOKUP(AF18,Bausteine!$A$2:$AS$46,6,FALSE)),IF(AG18="",0,VLOOKUP(AG18,Bausteine!$A$2:$AS$46,6,FALSE)),IF(AH18="",0,VLOOKUP(AH18,Bausteine!$A$2:$AS$46,6,FALSE)),AK18) | P18: =IF(C18="",0,VLOOKUP(C18,Bausteine!$A$2:$AS$46,7,FALSE))*IF(F18="",0,VLOOKUP(F18,Bausteine!$A$2:$AS$46,17,FALSE))/100+IF(D18="",0,VLOOKUP(D18,Bausteine!$A$2:$AS$46,7,FALSE))+IF(E18="",0,VLOOKUP(E18,Bausteine!$A$2:$AS$46,7,FALSE))+IF(G18="",0,VLOOKUP(G18,Bausteine!$A$2:$AS$46,7,FALSE))+IF(H18="",0,VLOOKUP(H18,Bausteine!$A$2:$AS$46,7,FALSE))+IF(I18="",0,VLOOKUP(I18,Bausteine!$A$2:$AS$46,7,FALSE))+IF(J18="",0,VLOOKUP(J18,Bausteine!$A$2:$AS$46,7,FALSE))+IF(K18="",0,VLOOKUP(K18,Bausteine!$A$2:$AS$46,7,FALSE))+IF(L18="",0,VLOOKUP(L18,Bausteine!$A$2:$AS$46,7,FALSE))+IF(AC18="",0,VLOOKUP(AC18,Bausteine!$A$2:$AS$46,7,FALSE))+IF(AF18="",0,VLOOKUP(AF18,Bausteine!$A$2:$AS$46,7,FALSE))+IF(AG18="",0,VLOOKUP(AG18,Bausteine!$A$2:$AS$46,7,FALSE))+IF(AH18="",0,VLOOKUP(AH18,Bausteine!$A$2:$AS$46,7,FALSE))+AI18 | Q18: =N18*Parameter!$B$2 | R18: =AE18-Q18 | S18: =IF(C18="",0,VLOOKUP(C18,Bausteine!$A$2:$AS$46,13,FALSE))*IF(F18="",0,VLOOKUP(F18,Bausteine!$A$2:$AS$46,16,FALSE))/100 | T18: =IF(C18="",0,VLOOKUP(C18,Bausteine!$A$2:$AS$46,8,FALSE))*IF(F18="",0,VLOOKUP(F18,Bausteine!$A$2:$AS$46,15,FALSE))/100+IF(D18="",0,VLOOKUP(D18,Bausteine!$A$2:$AS$46,8,FALSE))+IF(E18="",0,VLOOKUP(E18,Bausteine!$A$2:$AS$46,8,FALSE))+IF(G18="",0,VLOOKUP(G18,Bausteine!$A$2:$AS$46,8,FALSE))+IF(H18="",0,VLOOKUP(H18,Bausteine!$A$2:$AS$46,8,FALSE))+IF(I18="",0,VLOOKUP(I18,Bausteine!$A$2:$AS$46,8,FALSE))+IF(J18="",0,VLOOKUP(J18,Bausteine!$A$2:$AS$46,8,FALSE))+IF(K18="",0,VLOOKUP(K18,Bausteine!$A$2:$AS$46,8,FALSE))+IF(L18="",0,VLOOKUP(L18,Bausteine!$A$2:$AS$46,8,FALSE))+IF(AC18="",0,VLOOKUP(AC18,Bausteine!$A$2:$AS$46,8,FALSE))+IF(AF18="",0,VLOOKUP(AF18,Bausteine!$A$2:$AS$46,8,FALSE))+IF(AG18="",0,VLOOKUP(AG18,Bausteine!$A$2:$AS$46,8,FALSE))+IF(AH18="",0,VLOOKUP(AH18,Bausteine!$A$2:$AS$46,8,FALSE))+AJ18 | U18: =IF(C18="",0,VLOOKUP(C18,Bausteine!$A$2:$AS$46,9,FALSE))+IF(D18="",0,VLOOKUP(D18,Bausteine!$A$2:$AS$46,9,FALSE))+IF(E18="",0,VLOOKUP(E18,Bausteine!$A$2:$AS$46,9,FALSE))+IF(F18="",0,VLOOKUP(F18,Bausteine!$A$2:$AS$46,9,FALSE))+IF(G18="",0,VLOOKUP(G18,Bausteine!$A$2:$AS$46,9,FALSE))+IF(H18="",0,VLOOKUP(H18,Bausteine!$A$2:$AS$46,9,FALSE))+IF(I18="",0,VLOOKUP(I18,Bausteine!$A$2:$AS$46,9,FALSE))+IF(J18="",0,VLOOKUP(J18,Bausteine!$A$2:$AS$46,9,FALSE))+IF(K18="",0,VLOOKUP(K18,Bausteine!$A$2:$AS$46,9,FALSE))+IF(L18="",0,VLOOKUP(L18,Bausteine!$A$2:$AS$46,9,FALSE))+IF(AC18="",0,VLOOKUP(AC18,Bausteine!$A$2:$AS$46,9,FALSE))+IF(AF18="",0,VLOOKUP(AF18,Bausteine!$A$2:$AS$46,9,FALSE))+IF(AG18="",0,VLOOKUP(AG18,Bausteine!$A$2:$AS$46,9,FALSE))+IF(AH18="",0,VLOOKUP(AH18,Bausteine!$A$2:$AS$46,9,FALSE)) | V18: =IF(D18="",0,VLOOKUP(D18,Bausteine!$A$2:$AS$46,10,FALSE))-U18/IF(E18="",0,VLOOKUP(E18,Bausteine!$A$2:$AS$46,11,FALSE)) | W18: =IF(Y18<>"OK","",ROUND(MIN(IF(C18="",0,VLOOKUP(C18,Bausteine!$A$2:$AS$46,21,FALSE)),IF(C18="",0,VLOOKUP(C18,Bausteine!$A$2:$AS$46,20,FALSE))*(V18/T18/(IF(C18="",0,VLOOKUP(C18,Bausteine!$A$2:$AS$46,19,FALSE))/IF(C18="",0,VLOOKUP(C18,Bausteine!$A$2:$AS$46,18,FALSE))))^Parameter!$B$3),0)) | X18: =IF(F18="",0,VLOOKUP(F18,Bausteine!$A$2:$AS$46,14,FALSE)) | Y18: =IFERROR(IF(OR(AD18<=0,AD18>1,R18<=0,T18<=0,V18<=0,U18>IF(E18="",0,VLOOKUP(E18,Bausteine!$A$2:$AS$46,12,FALSE)),T18>IF(C18="",0,VLOOKUP(C18,Bausteine!$A$2:$AS$46,22,FALSE)),IF(E18="",0,VLOOKUP(E18,Bausteine!$A$2:$AS$46,11,FALSE))<=0,IF(E18="",0,VLOOKUP(E18,Bausteine!$A$2:$AS$46,11,FALSE))>1),"UNGUELTIG","OK"),"FEHLER") | Z18: 2500 | AA18: 56 | AD18: =IF(AC18="",1,IF(AC18="",0,VLOOKUP(AC18,Bausteine!$A$2:$AS$46,37,FALSE))/100) | AE18: =P18*AD18 | AI18: =SUMIF(Startbesatzung!$A$2:$A$7,A18,Startbesatzung!$D$2:$D$7) | AJ18: =SUMIF(Startbesatzung!$A$2:$A$7,A18,Startbesatzung!$E$2:$E$7) | AK18: =MAX(0,IF(Startbesatzung!A2=A18,Startbesatzung!G2,0),IF(Startbesatzung!A3=A18,Startbesatzung!G3,0),IF(Startbesatzung!A4=A18,Startbesatzung!G4,0),IF(Startbesatzung!A5=A18,Startbesatzung!G5,0),IF(Startbesatzung!A6=A18,Startbesatzung!G6,0),IF(Startbesatzung!A7=A18,Startbesatzung!G7,0)) | AL18: =IF(AF18="","",IF(IF(AH18="",0,VLOOKUP(AH18,Bausteine!$A$2:$AS$46,38,FALSE))>0,IF(AH18="",0,VLOOKUP(AH18,Bausteine!$A$2:$AS$46,38,FALSE)),IF(AG18="",0,VLOOKUP(AG18,Bausteine!$A$2:$AS$46,28,FALSE)))) | AM18: =IF(AF18="","",IF(AG18="",0,VLOOKUP(AG18,Bausteine!$A$2:$AS$46,44,FALSE))) | AN18: =IF(AF18="","",IF(AF18="",0,VLOOKUP(AF18,Bausteine!$A$2:$AS$46,27,FALSE))) | AO18: =IF(AF18="","",IF(AF18="",0,VLOOKUP(AF18,Bausteine!$A$2:$AS$46,25,FALSE))) | AP18: =IF(AF18="","",IF(AH18="",0,VLOOKUP(AH18,Bausteine!$A$2:$AS$46,29,FALSE)))
A19: Overlord Nuclear Shells PDL | B19: china | C19: overlord-chassis | D19: diesel-heavy-boost | E19: efficient-generator | F19: heavy | G19: heavy-twin-turret | H19: overlord-cannon | I19: heavy-nuclear-shell | J19: pdl | M19: =IF(C19="",0,VLOOKUP(C19,Bausteine!$A$2:$AS$46,4,FALSE))+IF(D19="",0,VLOOKUP(D19,Bausteine!$A$2:$AS$46,4,FALSE))+IF(E19="",0,VLOOKUP(E19,Bausteine!$A$2:$AS$46,4,FALSE))+IF(F19="",0,VLOOKUP(F19,Bausteine!$A$2:$AS$46,4,FALSE))+IF(G19="",0,VLOOKUP(G19,Bausteine!$A$2:$AS$46,4,FALSE))+IF(H19="",0,VLOOKUP(H19,Bausteine!$A$2:$AS$46,4,FALSE))+IF(I19="",0,VLOOKUP(I19,Bausteine!$A$2:$AS$46,4,FALSE))+IF(J19="",0,VLOOKUP(J19,Bausteine!$A$2:$AS$46,4,FALSE))+IF(K19="",0,VLOOKUP(K19,Bausteine!$A$2:$AS$46,4,FALSE))+IF(L19="",0,VLOOKUP(L19,Bausteine!$A$2:$AS$46,4,FALSE))+IF(AC19="",0,VLOOKUP(AC19,Bausteine!$A$2:$AS$46,4,FALSE))+IF(AF19="",0,VLOOKUP(AF19,Bausteine!$A$2:$AS$46,4,FALSE))+IF(AG19="",0,VLOOKUP(AG19,Bausteine!$A$2:$AS$46,4,FALSE))+IF(AH19="",0,VLOOKUP(AH19,Bausteine!$A$2:$AS$46,4,FALSE)) | N19: =IF(C19="",0,VLOOKUP(C19,Bausteine!$A$2:$AS$46,5,FALSE))+IF(D19="",0,VLOOKUP(D19,Bausteine!$A$2:$AS$46,5,FALSE))+IF(E19="",0,VLOOKUP(E19,Bausteine!$A$2:$AS$46,5,FALSE))+IF(F19="",0,VLOOKUP(F19,Bausteine!$A$2:$AS$46,5,FALSE))+IF(G19="",0,VLOOKUP(G19,Bausteine!$A$2:$AS$46,5,FALSE))+IF(H19="",0,VLOOKUP(H19,Bausteine!$A$2:$AS$46,5,FALSE))+IF(I19="",0,VLOOKUP(I19,Bausteine!$A$2:$AS$46,5,FALSE))+IF(J19="",0,VLOOKUP(J19,Bausteine!$A$2:$AS$46,5,FALSE))+IF(K19="",0,VLOOKUP(K19,Bausteine!$A$2:$AS$46,5,FALSE))+IF(L19="",0,VLOOKUP(L19,Bausteine!$A$2:$AS$46,5,FALSE))+IF(AC19="",0,VLOOKUP(AC19,Bausteine!$A$2:$AS$46,5,FALSE))+IF(AF19="",0,VLOOKUP(AF19,Bausteine!$A$2:$AS$46,5,FALSE))+IF(AG19="",0,VLOOKUP(AG19,Bausteine!$A$2:$AS$46,5,FALSE))+IF(AH19="",0,VLOOKUP(AH19,Bausteine!$A$2:$AS$46,5,FALSE)) | O19: =MAX(IF(C19="",0,VLOOKUP(C19,Bausteine!$A$2:$AS$46,6,FALSE)),IF(D19="",0,VLOOKUP(D19,Bausteine!$A$2:$AS$46,6,FALSE)),IF(E19="",0,VLOOKUP(E19,Bausteine!$A$2:$AS$46,6,FALSE)),IF(F19="",0,VLOOKUP(F19,Bausteine!$A$2:$AS$46,6,FALSE)),IF(G19="",0,VLOOKUP(G19,Bausteine!$A$2:$AS$46,6,FALSE)),IF(H19="",0,VLOOKUP(H19,Bausteine!$A$2:$AS$46,6,FALSE)),IF(I19="",0,VLOOKUP(I19,Bausteine!$A$2:$AS$46,6,FALSE)),IF(J19="",0,VLOOKUP(J19,Bausteine!$A$2:$AS$46,6,FALSE)),IF(K19="",0,VLOOKUP(K19,Bausteine!$A$2:$AS$46,6,FALSE)),IF(L19="",0,VLOOKUP(L19,Bausteine!$A$2:$AS$46,6,FALSE)),IF(AC19="",0,VLOOKUP(AC19,Bausteine!$A$2:$AS$46,6,FALSE)),IF(AF19="",0,VLOOKUP(AF19,Bausteine!$A$2:$AS$46,6,FALSE)),IF(AG19="",0,VLOOKUP(AG19,Bausteine!$A$2:$AS$46,6,FALSE)),IF(AH19="",0,VLOOKUP(AH19,Bausteine!$A$2:$AS$46,6,FALSE)),AK19) | P19: =IF(C19="",0,VLOOKUP(C19,Bausteine!$A$2:$AS$46,7,FALSE))*IF(F19="",0,VLOOKUP(F19,Bausteine!$A$2:$AS$46,17,FALSE))/100+IF(D19="",0,VLOOKUP(D19,Bausteine!$A$2:$AS$46,7,FALSE))+IF(E19="",0,VLOOKUP(E19,Bausteine!$A$2:$AS$46,7,FALSE))+IF(G19="",0,VLOOKUP(G19,Bausteine!$A$2:$AS$46,7,FALSE))+IF(H19="",0,VLOOKUP(H19,Bausteine!$A$2:$AS$46,7,FALSE))+IF(I19="",0,VLOOKUP(I19,Bausteine!$A$2:$AS$46,7,FALSE))+IF(J19="",0,VLOOKUP(J19,Bausteine!$A$2:$AS$46,7,FALSE))+IF(K19="",0,VLOOKUP(K19,Bausteine!$A$2:$AS$46,7,FALSE))+IF(L19="",0,VLOOKUP(L19,Bausteine!$A$2:$AS$46,7,FALSE))+IF(AC19="",0,VLOOKUP(AC19,Bausteine!$A$2:$AS$46,7,FALSE))+IF(AF19="",0,VLOOKUP(AF19,Bausteine!$A$2:$AS$46,7,FALSE))+IF(AG19="",0,VLOOKUP(AG19,Bausteine!$A$2:$AS$46,7,FALSE))+IF(AH19="",0,VLOOKUP(AH19,Bausteine!$A$2:$AS$46,7,FALSE))+AI19 | Q19: =N19*Parameter!$B$2 | R19: =AE19-Q19 | S19: =IF(C19="",0,VLOOKUP(C19,Bausteine!$A$2:$AS$46,13,FALSE))*IF(F19="",0,VLOOKUP(F19,Bausteine!$A$2:$AS$46,16,FALSE))/100 | T19: =IF(C19="",0,VLOOKUP(C19,Bausteine!$A$2:$AS$46,8,FALSE))*IF(F19="",0,VLOOKUP(F19,Bausteine!$A$2:$AS$46,15,FALSE))/100+IF(D19="",0,VLOOKUP(D19,Bausteine!$A$2:$AS$46,8,FALSE))+IF(E19="",0,VLOOKUP(E19,Bausteine!$A$2:$AS$46,8,FALSE))+IF(G19="",0,VLOOKUP(G19,Bausteine!$A$2:$AS$46,8,FALSE))+IF(H19="",0,VLOOKUP(H19,Bausteine!$A$2:$AS$46,8,FALSE))+IF(I19="",0,VLOOKUP(I19,Bausteine!$A$2:$AS$46,8,FALSE))+IF(J19="",0,VLOOKUP(J19,Bausteine!$A$2:$AS$46,8,FALSE))+IF(K19="",0,VLOOKUP(K19,Bausteine!$A$2:$AS$46,8,FALSE))+IF(L19="",0,VLOOKUP(L19,Bausteine!$A$2:$AS$46,8,FALSE))+IF(AC19="",0,VLOOKUP(AC19,Bausteine!$A$2:$AS$46,8,FALSE))+IF(AF19="",0,VLOOKUP(AF19,Bausteine!$A$2:$AS$46,8,FALSE))+IF(AG19="",0,VLOOKUP(AG19,Bausteine!$A$2:$AS$46,8,FALSE))+IF(AH19="",0,VLOOKUP(AH19,Bausteine!$A$2:$AS$46,8,FALSE))+AJ19 | U19: =IF(C19="",0,VLOOKUP(C19,Bausteine!$A$2:$AS$46,9,FALSE))+IF(D19="",0,VLOOKUP(D19,Bausteine!$A$2:$AS$46,9,FALSE))+IF(E19="",0,VLOOKUP(E19,Bausteine!$A$2:$AS$46,9,FALSE))+IF(F19="",0,VLOOKUP(F19,Bausteine!$A$2:$AS$46,9,FALSE))+IF(G19="",0,VLOOKUP(G19,Bausteine!$A$2:$AS$46,9,FALSE))+IF(H19="",0,VLOOKUP(H19,Bausteine!$A$2:$AS$46,9,FALSE))+IF(I19="",0,VLOOKUP(I19,Bausteine!$A$2:$AS$46,9,FALSE))+IF(J19="",0,VLOOKUP(J19,Bausteine!$A$2:$AS$46,9,FALSE))+IF(K19="",0,VLOOKUP(K19,Bausteine!$A$2:$AS$46,9,FALSE))+IF(L19="",0,VLOOKUP(L19,Bausteine!$A$2:$AS$46,9,FALSE))+IF(AC19="",0,VLOOKUP(AC19,Bausteine!$A$2:$AS$46,9,FALSE))+IF(AF19="",0,VLOOKUP(AF19,Bausteine!$A$2:$AS$46,9,FALSE))+IF(AG19="",0,VLOOKUP(AG19,Bausteine!$A$2:$AS$46,9,FALSE))+IF(AH19="",0,VLOOKUP(AH19,Bausteine!$A$2:$AS$46,9,FALSE)) | V19: =IF(D19="",0,VLOOKUP(D19,Bausteine!$A$2:$AS$46,10,FALSE))-U19/IF(E19="",0,VLOOKUP(E19,Bausteine!$A$2:$AS$46,11,FALSE)) | W19: =IF(Y19<>"OK","",ROUND(MIN(IF(C19="",0,VLOOKUP(C19,Bausteine!$A$2:$AS$46,21,FALSE)),IF(C19="",0,VLOOKUP(C19,Bausteine!$A$2:$AS$46,20,FALSE))*(V19/T19/(IF(C19="",0,VLOOKUP(C19,Bausteine!$A$2:$AS$46,19,FALSE))/IF(C19="",0,VLOOKUP(C19,Bausteine!$A$2:$AS$46,18,FALSE))))^Parameter!$B$3),0)) | X19: =IF(F19="",0,VLOOKUP(F19,Bausteine!$A$2:$AS$46,14,FALSE)) | Y19: =IFERROR(IF(OR(AD19<=0,AD19>1,R19<=0,T19<=0,V19<=0,U19>IF(E19="",0,VLOOKUP(E19,Bausteine!$A$2:$AS$46,12,FALSE)),T19>IF(C19="",0,VLOOKUP(C19,Bausteine!$A$2:$AS$46,22,FALSE)),IF(E19="",0,VLOOKUP(E19,Bausteine!$A$2:$AS$46,11,FALSE))<=0,IF(E19="",0,VLOOKUP(E19,Bausteine!$A$2:$AS$46,11,FALSE))>1),"UNGUELTIG","OK"),"FEHLER") | Z19: 3150 | AA19: 56 | AB19: Shared standard PDL, no heavy-specific PDL discount. | AD19: =IF(AC19="",1,IF(AC19="",0,VLOOKUP(AC19,Bausteine!$A$2:$AS$46,37,FALSE))/100) | AE19: =P19*AD19 | AI19: =SUMIF(Startbesatzung!$A$2:$A$7,A19,Startbesatzung!$D$2:$D$7) | AJ19: =SUMIF(Startbesatzung!$A$2:$A$7,A19,Startbesatzung!$E$2:$E$7) | AK19: =MAX(0,IF(Startbesatzung!A2=A19,Startbesatzung!G2,0),IF(Startbesatzung!A3=A19,Startbesatzung!G3,0),IF(Startbesatzung!A4=A19,Startbesatzung!G4,0),IF(Startbesatzung!A5=A19,Startbesatzung!G5,0),IF(Startbesatzung!A6=A19,Startbesatzung!G6,0),IF(Startbesatzung!A7=A19,Startbesatzung!G7,0)) | AL19: =IF(AF19="","",IF(IF(AH19="",0,VLOOKUP(AH19,Bausteine!$A$2:$AS$46,38,FALSE))>0,IF(AH19="",0,VLOOKUP(AH19,Bausteine!$A$2:$AS$46,38,FALSE)),IF(AG19="",0,VLOOKUP(AG19,Bausteine!$A$2:$AS$46,28,FALSE)))) | AM19: =IF(AF19="","",IF(AG19="",0,VLOOKUP(AG19,Bausteine!$A$2:$AS$46,44,FALSE))) | AN19: =IF(AF19="","",IF(AF19="",0,VLOOKUP(AF19,Bausteine!$A$2:$AS$46,27,FALSE))) | AO19: =IF(AF19="","",IF(AF19="",0,VLOOKUP(AF19,Bausteine!$A$2:$AS$46,25,FALSE))) | AP19: =IF(AF19="","",IF(AH19="",0,VLOOKUP(AH19,Bausteine!$A$2:$AS$46,29,FALSE)))
A20: Overlord Nuclear Shells Reflector | B20: china | C20: overlord-chassis | D20: diesel-heavy-boost | E20: efficient-generator | F20: reflector | G20: heavy-twin-turret | H20: overlord-cannon | I20: heavy-nuclear-shell | M20: =IF(C20="",0,VLOOKUP(C20,Bausteine!$A$2:$AS$46,4,FALSE))+IF(D20="",0,VLOOKUP(D20,Bausteine!$A$2:$AS$46,4,FALSE))+IF(E20="",0,VLOOKUP(E20,Bausteine!$A$2:$AS$46,4,FALSE))+IF(F20="",0,VLOOKUP(F20,Bausteine!$A$2:$AS$46,4,FALSE))+IF(G20="",0,VLOOKUP(G20,Bausteine!$A$2:$AS$46,4,FALSE))+IF(H20="",0,VLOOKUP(H20,Bausteine!$A$2:$AS$46,4,FALSE))+IF(I20="",0,VLOOKUP(I20,Bausteine!$A$2:$AS$46,4,FALSE))+IF(J20="",0,VLOOKUP(J20,Bausteine!$A$2:$AS$46,4,FALSE))+IF(K20="",0,VLOOKUP(K20,Bausteine!$A$2:$AS$46,4,FALSE))+IF(L20="",0,VLOOKUP(L20,Bausteine!$A$2:$AS$46,4,FALSE))+IF(AC20="",0,VLOOKUP(AC20,Bausteine!$A$2:$AS$46,4,FALSE))+IF(AF20="",0,VLOOKUP(AF20,Bausteine!$A$2:$AS$46,4,FALSE))+IF(AG20="",0,VLOOKUP(AG20,Bausteine!$A$2:$AS$46,4,FALSE))+IF(AH20="",0,VLOOKUP(AH20,Bausteine!$A$2:$AS$46,4,FALSE)) | N20: =IF(C20="",0,VLOOKUP(C20,Bausteine!$A$2:$AS$46,5,FALSE))+IF(D20="",0,VLOOKUP(D20,Bausteine!$A$2:$AS$46,5,FALSE))+IF(E20="",0,VLOOKUP(E20,Bausteine!$A$2:$AS$46,5,FALSE))+IF(F20="",0,VLOOKUP(F20,Bausteine!$A$2:$AS$46,5,FALSE))+IF(G20="",0,VLOOKUP(G20,Bausteine!$A$2:$AS$46,5,FALSE))+IF(H20="",0,VLOOKUP(H20,Bausteine!$A$2:$AS$46,5,FALSE))+IF(I20="",0,VLOOKUP(I20,Bausteine!$A$2:$AS$46,5,FALSE))+IF(J20="",0,VLOOKUP(J20,Bausteine!$A$2:$AS$46,5,FALSE))+IF(K20="",0,VLOOKUP(K20,Bausteine!$A$2:$AS$46,5,FALSE))+IF(L20="",0,VLOOKUP(L20,Bausteine!$A$2:$AS$46,5,FALSE))+IF(AC20="",0,VLOOKUP(AC20,Bausteine!$A$2:$AS$46,5,FALSE))+IF(AF20="",0,VLOOKUP(AF20,Bausteine!$A$2:$AS$46,5,FALSE))+IF(AG20="",0,VLOOKUP(AG20,Bausteine!$A$2:$AS$46,5,FALSE))+IF(AH20="",0,VLOOKUP(AH20,Bausteine!$A$2:$AS$46,5,FALSE)) | O20: =MAX(IF(C20="",0,VLOOKUP(C20,Bausteine!$A$2:$AS$46,6,FALSE)),IF(D20="",0,VLOOKUP(D20,Bausteine!$A$2:$AS$46,6,FALSE)),IF(E20="",0,VLOOKUP(E20,Bausteine!$A$2:$AS$46,6,FALSE)),IF(F20="",0,VLOOKUP(F20,Bausteine!$A$2:$AS$46,6,FALSE)),IF(G20="",0,VLOOKUP(G20,Bausteine!$A$2:$AS$46,6,FALSE)),IF(H20="",0,VLOOKUP(H20,Bausteine!$A$2:$AS$46,6,FALSE)),IF(I20="",0,VLOOKUP(I20,Bausteine!$A$2:$AS$46,6,FALSE)),IF(J20="",0,VLOOKUP(J20,Bausteine!$A$2:$AS$46,6,FALSE)),IF(K20="",0,VLOOKUP(K20,Bausteine!$A$2:$AS$46,6,FALSE)),IF(L20="",0,VLOOKUP(L20,Bausteine!$A$2:$AS$46,6,FALSE)),IF(AC20="",0,VLOOKUP(AC20,Bausteine!$A$2:$AS$46,6,FALSE)),IF(AF20="",0,VLOOKUP(AF20,Bausteine!$A$2:$AS$46,6,FALSE)),IF(AG20="",0,VLOOKUP(AG20,Bausteine!$A$2:$AS$46,6,FALSE)),IF(AH20="",0,VLOOKUP(AH20,Bausteine!$A$2:$AS$46,6,FALSE)),AK20) | P20: =IF(C20="",0,VLOOKUP(C20,Bausteine!$A$2:$AS$46,7,FALSE))*IF(F20="",0,VLOOKUP(F20,Bausteine!$A$2:$AS$46,17,FALSE))/100+IF(D20="",0,VLOOKUP(D20,Bausteine!$A$2:$AS$46,7,FALSE))+IF(E20="",0,VLOOKUP(E20,Bausteine!$A$2:$AS$46,7,FALSE))+IF(G20="",0,VLOOKUP(G20,Bausteine!$A$2:$AS$46,7,FALSE))+IF(H20="",0,VLOOKUP(H20,Bausteine!$A$2:$AS$46,7,FALSE))+IF(I20="",0,VLOOKUP(I20,Bausteine!$A$2:$AS$46,7,FALSE))+IF(J20="",0,VLOOKUP(J20,Bausteine!$A$2:$AS$46,7,FALSE))+IF(K20="",0,VLOOKUP(K20,Bausteine!$A$2:$AS$46,7,FALSE))+IF(L20="",0,VLOOKUP(L20,Bausteine!$A$2:$AS$46,7,FALSE))+IF(AC20="",0,VLOOKUP(AC20,Bausteine!$A$2:$AS$46,7,FALSE))+IF(AF20="",0,VLOOKUP(AF20,Bausteine!$A$2:$AS$46,7,FALSE))+IF(AG20="",0,VLOOKUP(AG20,Bausteine!$A$2:$AS$46,7,FALSE))+IF(AH20="",0,VLOOKUP(AH20,Bausteine!$A$2:$AS$46,7,FALSE))+AI20 | Q20: =N20*Parameter!$B$2 | R20: =AE20-Q20 | S20: =IF(C20="",0,VLOOKUP(C20,Bausteine!$A$2:$AS$46,13,FALSE))*IF(F20="",0,VLOOKUP(F20,Bausteine!$A$2:$AS$46,16,FALSE))/100 | T20: =IF(C20="",0,VLOOKUP(C20,Bausteine!$A$2:$AS$46,8,FALSE))*IF(F20="",0,VLOOKUP(F20,Bausteine!$A$2:$AS$46,15,FALSE))/100+IF(D20="",0,VLOOKUP(D20,Bausteine!$A$2:$AS$46,8,FALSE))+IF(E20="",0,VLOOKUP(E20,Bausteine!$A$2:$AS$46,8,FALSE))+IF(G20="",0,VLOOKUP(G20,Bausteine!$A$2:$AS$46,8,FALSE))+IF(H20="",0,VLOOKUP(H20,Bausteine!$A$2:$AS$46,8,FALSE))+IF(I20="",0,VLOOKUP(I20,Bausteine!$A$2:$AS$46,8,FALSE))+IF(J20="",0,VLOOKUP(J20,Bausteine!$A$2:$AS$46,8,FALSE))+IF(K20="",0,VLOOKUP(K20,Bausteine!$A$2:$AS$46,8,FALSE))+IF(L20="",0,VLOOKUP(L20,Bausteine!$A$2:$AS$46,8,FALSE))+IF(AC20="",0,VLOOKUP(AC20,Bausteine!$A$2:$AS$46,8,FALSE))+IF(AF20="",0,VLOOKUP(AF20,Bausteine!$A$2:$AS$46,8,FALSE))+IF(AG20="",0,VLOOKUP(AG20,Bausteine!$A$2:$AS$46,8,FALSE))+IF(AH20="",0,VLOOKUP(AH20,Bausteine!$A$2:$AS$46,8,FALSE))+AJ20 | U20: =IF(C20="",0,VLOOKUP(C20,Bausteine!$A$2:$AS$46,9,FALSE))+IF(D20="",0,VLOOKUP(D20,Bausteine!$A$2:$AS$46,9,FALSE))+IF(E20="",0,VLOOKUP(E20,Bausteine!$A$2:$AS$46,9,FALSE))+IF(F20="",0,VLOOKUP(F20,Bausteine!$A$2:$AS$46,9,FALSE))+IF(G20="",0,VLOOKUP(G20,Bausteine!$A$2:$AS$46,9,FALSE))+IF(H20="",0,VLOOKUP(H20,Bausteine!$A$2:$AS$46,9,FALSE))+IF(I20="",0,VLOOKUP(I20,Bausteine!$A$2:$AS$46,9,FALSE))+IF(J20="",0,VLOOKUP(J20,Bausteine!$A$2:$AS$46,9,FALSE))+IF(K20="",0,VLOOKUP(K20,Bausteine!$A$2:$AS$46,9,FALSE))+IF(L20="",0,VLOOKUP(L20,Bausteine!$A$2:$AS$46,9,FALSE))+IF(AC20="",0,VLOOKUP(AC20,Bausteine!$A$2:$AS$46,9,FALSE))+IF(AF20="",0,VLOOKUP(AF20,Bausteine!$A$2:$AS$46,9,FALSE))+IF(AG20="",0,VLOOKUP(AG20,Bausteine!$A$2:$AS$46,9,FALSE))+IF(AH20="",0,VLOOKUP(AH20,Bausteine!$A$2:$AS$46,9,FALSE)) | V20: =IF(D20="",0,VLOOKUP(D20,Bausteine!$A$2:$AS$46,10,FALSE))-U20/IF(E20="",0,VLOOKUP(E20,Bausteine!$A$2:$AS$46,11,FALSE)) | W20: =IF(Y20<>"OK","",ROUND(MIN(IF(C20="",0,VLOOKUP(C20,Bausteine!$A$2:$AS$46,21,FALSE)),IF(C20="",0,VLOOKUP(C20,Bausteine!$A$2:$AS$46,20,FALSE))*(V20/T20/(IF(C20="",0,VLOOKUP(C20,Bausteine!$A$2:$AS$46,19,FALSE))/IF(C20="",0,VLOOKUP(C20,Bausteine!$A$2:$AS$46,18,FALSE))))^Parameter!$B$3),0)) | X20: =IF(F20="",0,VLOOKUP(F20,Bausteine!$A$2:$AS$46,14,FALSE)) | Y20: =IFERROR(IF(OR(AD20<=0,AD20>1,R20<=0,T20<=0,V20<=0,U20>IF(E20="",0,VLOOKUP(E20,Bausteine!$A$2:$AS$46,12,FALSE)),T20>IF(C20="",0,VLOOKUP(C20,Bausteine!$A$2:$AS$46,22,FALSE)),IF(E20="",0,VLOOKUP(E20,Bausteine!$A$2:$AS$46,11,FALSE))<=0,IF(E20="",0,VLOOKUP(E20,Bausteine!$A$2:$AS$46,11,FALSE))>1),"UNGUELTIG","OK"),"FEHLER") | Z20: 2500 | AA20: 56 | AD20: =IF(AC20="",1,IF(AC20="",0,VLOOKUP(AC20,Bausteine!$A$2:$AS$46,37,FALSE))/100) | AE20: =P20*AD20 | AI20: =SUMIF(Startbesatzung!$A$2:$A$7,A20,Startbesatzung!$D$2:$D$7) | AJ20: =SUMIF(Startbesatzung!$A$2:$A$7,A20,Startbesatzung!$E$2:$E$7) | AK20: =MAX(0,IF(Startbesatzung!A2=A20,Startbesatzung!G2,0),IF(Startbesatzung!A3=A20,Startbesatzung!G3,0),IF(Startbesatzung!A4=A20,Startbesatzung!G4,0),IF(Startbesatzung!A5=A20,Startbesatzung!G5,0),IF(Startbesatzung!A6=A20,Startbesatzung!G6,0),IF(Startbesatzung!A7=A20,Startbesatzung!G7,0)) | AL20: =IF(AF20="","",IF(IF(AH20="",0,VLOOKUP(AH20,Bausteine!$A$2:$AS$46,38,FALSE))>0,IF(AH20="",0,VLOOKUP(AH20,Bausteine!$A$2:$AS$46,38,FALSE)),IF(AG20="",0,VLOOKUP(AG20,Bausteine!$A$2:$AS$46,28,FALSE)))) | AM20: =IF(AF20="","",IF(AG20="",0,VLOOKUP(AG20,Bausteine!$A$2:$AS$46,44,FALSE))) | AN20: =IF(AF20="","",IF(AF20="",0,VLOOKUP(AF20,Bausteine!$A$2:$AS$46,27,FALSE))) | AO20: =IF(AF20="","",IF(AF20="",0,VLOOKUP(AF20,Bausteine!$A$2:$AS$46,25,FALSE))) | AP20: =IF(AF20="","",IF(AH20="",0,VLOOKUP(AH20,Bausteine!$A$2:$AS$46,29,FALSE)))
A21: Overlord Propaganda | B21: china | C21: overlord-chassis | D21: diesel-heavy | E21: baseline-generator | F21: heavy | G21: heavy-twin-turret | H21: overlord-cannon | I21: heavy-shell | J21: propaganda-speaker | M21: =IF(C21="",0,VLOOKUP(C21,Bausteine!$A$2:$AS$46,4,FALSE))+IF(D21="",0,VLOOKUP(D21,Bausteine!$A$2:$AS$46,4,FALSE))+IF(E21="",0,VLOOKUP(E21,Bausteine!$A$2:$AS$46,4,FALSE))+IF(F21="",0,VLOOKUP(F21,Bausteine!$A$2:$AS$46,4,FALSE))+IF(G21="",0,VLOOKUP(G21,Bausteine!$A$2:$AS$46,4,FALSE))+IF(H21="",0,VLOOKUP(H21,Bausteine!$A$2:$AS$46,4,FALSE))+IF(I21="",0,VLOOKUP(I21,Bausteine!$A$2:$AS$46,4,FALSE))+IF(J21="",0,VLOOKUP(J21,Bausteine!$A$2:$AS$46,4,FALSE))+IF(K21="",0,VLOOKUP(K21,Bausteine!$A$2:$AS$46,4,FALSE))+IF(L21="",0,VLOOKUP(L21,Bausteine!$A$2:$AS$46,4,FALSE))+IF(AC21="",0,VLOOKUP(AC21,Bausteine!$A$2:$AS$46,4,FALSE))+IF(AF21="",0,VLOOKUP(AF21,Bausteine!$A$2:$AS$46,4,FALSE))+IF(AG21="",0,VLOOKUP(AG21,Bausteine!$A$2:$AS$46,4,FALSE))+IF(AH21="",0,VLOOKUP(AH21,Bausteine!$A$2:$AS$46,4,FALSE)) | N21: =IF(C21="",0,VLOOKUP(C21,Bausteine!$A$2:$AS$46,5,FALSE))+IF(D21="",0,VLOOKUP(D21,Bausteine!$A$2:$AS$46,5,FALSE))+IF(E21="",0,VLOOKUP(E21,Bausteine!$A$2:$AS$46,5,FALSE))+IF(F21="",0,VLOOKUP(F21,Bausteine!$A$2:$AS$46,5,FALSE))+IF(G21="",0,VLOOKUP(G21,Bausteine!$A$2:$AS$46,5,FALSE))+IF(H21="",0,VLOOKUP(H21,Bausteine!$A$2:$AS$46,5,FALSE))+IF(I21="",0,VLOOKUP(I21,Bausteine!$A$2:$AS$46,5,FALSE))+IF(J21="",0,VLOOKUP(J21,Bausteine!$A$2:$AS$46,5,FALSE))+IF(K21="",0,VLOOKUP(K21,Bausteine!$A$2:$AS$46,5,FALSE))+IF(L21="",0,VLOOKUP(L21,Bausteine!$A$2:$AS$46,5,FALSE))+IF(AC21="",0,VLOOKUP(AC21,Bausteine!$A$2:$AS$46,5,FALSE))+IF(AF21="",0,VLOOKUP(AF21,Bausteine!$A$2:$AS$46,5,FALSE))+IF(AG21="",0,VLOOKUP(AG21,Bausteine!$A$2:$AS$46,5,FALSE))+IF(AH21="",0,VLOOKUP(AH21,Bausteine!$A$2:$AS$46,5,FALSE)) | O21: =MAX(IF(C21="",0,VLOOKUP(C21,Bausteine!$A$2:$AS$46,6,FALSE)),IF(D21="",0,VLOOKUP(D21,Bausteine!$A$2:$AS$46,6,FALSE)),IF(E21="",0,VLOOKUP(E21,Bausteine!$A$2:$AS$46,6,FALSE)),IF(F21="",0,VLOOKUP(F21,Bausteine!$A$2:$AS$46,6,FALSE)),IF(G21="",0,VLOOKUP(G21,Bausteine!$A$2:$AS$46,6,FALSE)),IF(H21="",0,VLOOKUP(H21,Bausteine!$A$2:$AS$46,6,FALSE)),IF(I21="",0,VLOOKUP(I21,Bausteine!$A$2:$AS$46,6,FALSE)),IF(J21="",0,VLOOKUP(J21,Bausteine!$A$2:$AS$46,6,FALSE)),IF(K21="",0,VLOOKUP(K21,Bausteine!$A$2:$AS$46,6,FALSE)),IF(L21="",0,VLOOKUP(L21,Bausteine!$A$2:$AS$46,6,FALSE)),IF(AC21="",0,VLOOKUP(AC21,Bausteine!$A$2:$AS$46,6,FALSE)),IF(AF21="",0,VLOOKUP(AF21,Bausteine!$A$2:$AS$46,6,FALSE)),IF(AG21="",0,VLOOKUP(AG21,Bausteine!$A$2:$AS$46,6,FALSE)),IF(AH21="",0,VLOOKUP(AH21,Bausteine!$A$2:$AS$46,6,FALSE)),AK21) | P21: =IF(C21="",0,VLOOKUP(C21,Bausteine!$A$2:$AS$46,7,FALSE))*IF(F21="",0,VLOOKUP(F21,Bausteine!$A$2:$AS$46,17,FALSE))/100+IF(D21="",0,VLOOKUP(D21,Bausteine!$A$2:$AS$46,7,FALSE))+IF(E21="",0,VLOOKUP(E21,Bausteine!$A$2:$AS$46,7,FALSE))+IF(G21="",0,VLOOKUP(G21,Bausteine!$A$2:$AS$46,7,FALSE))+IF(H21="",0,VLOOKUP(H21,Bausteine!$A$2:$AS$46,7,FALSE))+IF(I21="",0,VLOOKUP(I21,Bausteine!$A$2:$AS$46,7,FALSE))+IF(J21="",0,VLOOKUP(J21,Bausteine!$A$2:$AS$46,7,FALSE))+IF(K21="",0,VLOOKUP(K21,Bausteine!$A$2:$AS$46,7,FALSE))+IF(L21="",0,VLOOKUP(L21,Bausteine!$A$2:$AS$46,7,FALSE))+IF(AC21="",0,VLOOKUP(AC21,Bausteine!$A$2:$AS$46,7,FALSE))+IF(AF21="",0,VLOOKUP(AF21,Bausteine!$A$2:$AS$46,7,FALSE))+IF(AG21="",0,VLOOKUP(AG21,Bausteine!$A$2:$AS$46,7,FALSE))+IF(AH21="",0,VLOOKUP(AH21,Bausteine!$A$2:$AS$46,7,FALSE))+AI21 | Q21: =N21*Parameter!$B$2 | R21: =AE21-Q21 | S21: =IF(C21="",0,VLOOKUP(C21,Bausteine!$A$2:$AS$46,13,FALSE))*IF(F21="",0,VLOOKUP(F21,Bausteine!$A$2:$AS$46,16,FALSE))/100 | T21: =IF(C21="",0,VLOOKUP(C21,Bausteine!$A$2:$AS$46,8,FALSE))*IF(F21="",0,VLOOKUP(F21,Bausteine!$A$2:$AS$46,15,FALSE))/100+IF(D21="",0,VLOOKUP(D21,Bausteine!$A$2:$AS$46,8,FALSE))+IF(E21="",0,VLOOKUP(E21,Bausteine!$A$2:$AS$46,8,FALSE))+IF(G21="",0,VLOOKUP(G21,Bausteine!$A$2:$AS$46,8,FALSE))+IF(H21="",0,VLOOKUP(H21,Bausteine!$A$2:$AS$46,8,FALSE))+IF(I21="",0,VLOOKUP(I21,Bausteine!$A$2:$AS$46,8,FALSE))+IF(J21="",0,VLOOKUP(J21,Bausteine!$A$2:$AS$46,8,FALSE))+IF(K21="",0,VLOOKUP(K21,Bausteine!$A$2:$AS$46,8,FALSE))+IF(L21="",0,VLOOKUP(L21,Bausteine!$A$2:$AS$46,8,FALSE))+IF(AC21="",0,VLOOKUP(AC21,Bausteine!$A$2:$AS$46,8,FALSE))+IF(AF21="",0,VLOOKUP(AF21,Bausteine!$A$2:$AS$46,8,FALSE))+IF(AG21="",0,VLOOKUP(AG21,Bausteine!$A$2:$AS$46,8,FALSE))+IF(AH21="",0,VLOOKUP(AH21,Bausteine!$A$2:$AS$46,8,FALSE))+AJ21 | U21: =IF(C21="",0,VLOOKUP(C21,Bausteine!$A$2:$AS$46,9,FALSE))+IF(D21="",0,VLOOKUP(D21,Bausteine!$A$2:$AS$46,9,FALSE))+IF(E21="",0,VLOOKUP(E21,Bausteine!$A$2:$AS$46,9,FALSE))+IF(F21="",0,VLOOKUP(F21,Bausteine!$A$2:$AS$46,9,FALSE))+IF(G21="",0,VLOOKUP(G21,Bausteine!$A$2:$AS$46,9,FALSE))+IF(H21="",0,VLOOKUP(H21,Bausteine!$A$2:$AS$46,9,FALSE))+IF(I21="",0,VLOOKUP(I21,Bausteine!$A$2:$AS$46,9,FALSE))+IF(J21="",0,VLOOKUP(J21,Bausteine!$A$2:$AS$46,9,FALSE))+IF(K21="",0,VLOOKUP(K21,Bausteine!$A$2:$AS$46,9,FALSE))+IF(L21="",0,VLOOKUP(L21,Bausteine!$A$2:$AS$46,9,FALSE))+IF(AC21="",0,VLOOKUP(AC21,Bausteine!$A$2:$AS$46,9,FALSE))+IF(AF21="",0,VLOOKUP(AF21,Bausteine!$A$2:$AS$46,9,FALSE))+IF(AG21="",0,VLOOKUP(AG21,Bausteine!$A$2:$AS$46,9,FALSE))+IF(AH21="",0,VLOOKUP(AH21,Bausteine!$A$2:$AS$46,9,FALSE)) | V21: =IF(D21="",0,VLOOKUP(D21,Bausteine!$A$2:$AS$46,10,FALSE))-U21/IF(E21="",0,VLOOKUP(E21,Bausteine!$A$2:$AS$46,11,FALSE)) | W21: =IF(Y21<>"OK","",ROUND(MIN(IF(C21="",0,VLOOKUP(C21,Bausteine!$A$2:$AS$46,21,FALSE)),IF(C21="",0,VLOOKUP(C21,Bausteine!$A$2:$AS$46,20,FALSE))*(V21/T21/(IF(C21="",0,VLOOKUP(C21,Bausteine!$A$2:$AS$46,19,FALSE))/IF(C21="",0,VLOOKUP(C21,Bausteine!$A$2:$AS$46,18,FALSE))))^Parameter!$B$3),0)) | X21: =IF(F21="",0,VLOOKUP(F21,Bausteine!$A$2:$AS$46,14,FALSE)) | Y21: =IFERROR(IF(OR(AD21<=0,AD21>1,R21<=0,T21<=0,V21<=0,U21>IF(E21="",0,VLOOKUP(E21,Bausteine!$A$2:$AS$46,12,FALSE)),T21>IF(C21="",0,VLOOKUP(C21,Bausteine!$A$2:$AS$46,22,FALSE)),IF(E21="",0,VLOOKUP(E21,Bausteine!$A$2:$AS$46,11,FALSE))<=0,IF(E21="",0,VLOOKUP(E21,Bausteine!$A$2:$AS$46,11,FALSE))>1),"UNGUELTIG","OK"),"FEHLER") | Z21: 2200 | AA21: 53 | AB21: Base price fitted; speaker electrical load and mass may reduce speed. Existing support behavior reused, not simulated here. | AD21: =IF(AC21="",1,IF(AC21="",0,VLOOKUP(AC21,Bausteine!$A$2:$AS$46,37,FALSE))/100) | AE21: =P21*AD21 | AI21: =SUMIF(Startbesatzung!$A$2:$A$7,A21,Startbesatzung!$D$2:$D$7) | AJ21: =SUMIF(Startbesatzung!$A$2:$A$7,A21,Startbesatzung!$E$2:$E$7) | AK21: =MAX(0,IF(Startbesatzung!A2=A21,Startbesatzung!G2,0),IF(Startbesatzung!A3=A21,Startbesatzung!G3,0),IF(Startbesatzung!A4=A21,Startbesatzung!G4,0),IF(Startbesatzung!A5=A21,Startbesatzung!G5,0),IF(Startbesatzung!A6=A21,Startbesatzung!G6,0),IF(Startbesatzung!A7=A21,Startbesatzung!G7,0)) | AL21: =IF(AF21="","",IF(IF(AH21="",0,VLOOKUP(AH21,Bausteine!$A$2:$AS$46,38,FALSE))>0,IF(AH21="",0,VLOOKUP(AH21,Bausteine!$A$2:$AS$46,38,FALSE)),IF(AG21="",0,VLOOKUP(AG21,Bausteine!$A$2:$AS$46,28,FALSE)))) | AM21: =IF(AF21="","",IF(AG21="",0,VLOOKUP(AG21,Bausteine!$A$2:$AS$46,44,FALSE))) | AN21: =IF(AF21="","",IF(AF21="",0,VLOOKUP(AF21,Bausteine!$A$2:$AS$46,27,FALSE))) | AO21: =IF(AF21="","",IF(AF21="",0,VLOOKUP(AF21,Bausteine!$A$2:$AS$46,25,FALSE))) | AP21: =IF(AF21="","",IF(AH21="",0,VLOOKUP(AH21,Bausteine!$A$2:$AS$46,29,FALSE)))
A22: Overlord Propaganda PDL | B22: china | C22: overlord-chassis | D22: diesel-heavy-boost | E22: efficient-generator | F22: heavy | G22: heavy-twin-turret | H22: overlord-cannon | I22: heavy-shell | J22: propaganda-speaker | K22: pdl | M22: =IF(C22="",0,VLOOKUP(C22,Bausteine!$A$2:$AS$46,4,FALSE))+IF(D22="",0,VLOOKUP(D22,Bausteine!$A$2:$AS$46,4,FALSE))+IF(E22="",0,VLOOKUP(E22,Bausteine!$A$2:$AS$46,4,FALSE))+IF(F22="",0,VLOOKUP(F22,Bausteine!$A$2:$AS$46,4,FALSE))+IF(G22="",0,VLOOKUP(G22,Bausteine!$A$2:$AS$46,4,FALSE))+IF(H22="",0,VLOOKUP(H22,Bausteine!$A$2:$AS$46,4,FALSE))+IF(I22="",0,VLOOKUP(I22,Bausteine!$A$2:$AS$46,4,FALSE))+IF(J22="",0,VLOOKUP(J22,Bausteine!$A$2:$AS$46,4,FALSE))+IF(K22="",0,VLOOKUP(K22,Bausteine!$A$2:$AS$46,4,FALSE))+IF(L22="",0,VLOOKUP(L22,Bausteine!$A$2:$AS$46,4,FALSE))+IF(AC22="",0,VLOOKUP(AC22,Bausteine!$A$2:$AS$46,4,FALSE))+IF(AF22="",0,VLOOKUP(AF22,Bausteine!$A$2:$AS$46,4,FALSE))+IF(AG22="",0,VLOOKUP(AG22,Bausteine!$A$2:$AS$46,4,FALSE))+IF(AH22="",0,VLOOKUP(AH22,Bausteine!$A$2:$AS$46,4,FALSE)) | N22: =IF(C22="",0,VLOOKUP(C22,Bausteine!$A$2:$AS$46,5,FALSE))+IF(D22="",0,VLOOKUP(D22,Bausteine!$A$2:$AS$46,5,FALSE))+IF(E22="",0,VLOOKUP(E22,Bausteine!$A$2:$AS$46,5,FALSE))+IF(F22="",0,VLOOKUP(F22,Bausteine!$A$2:$AS$46,5,FALSE))+IF(G22="",0,VLOOKUP(G22,Bausteine!$A$2:$AS$46,5,FALSE))+IF(H22="",0,VLOOKUP(H22,Bausteine!$A$2:$AS$46,5,FALSE))+IF(I22="",0,VLOOKUP(I22,Bausteine!$A$2:$AS$46,5,FALSE))+IF(J22="",0,VLOOKUP(J22,Bausteine!$A$2:$AS$46,5,FALSE))+IF(K22="",0,VLOOKUP(K22,Bausteine!$A$2:$AS$46,5,FALSE))+IF(L22="",0,VLOOKUP(L22,Bausteine!$A$2:$AS$46,5,FALSE))+IF(AC22="",0,VLOOKUP(AC22,Bausteine!$A$2:$AS$46,5,FALSE))+IF(AF22="",0,VLOOKUP(AF22,Bausteine!$A$2:$AS$46,5,FALSE))+IF(AG22="",0,VLOOKUP(AG22,Bausteine!$A$2:$AS$46,5,FALSE))+IF(AH22="",0,VLOOKUP(AH22,Bausteine!$A$2:$AS$46,5,FALSE)) | O22: =MAX(IF(C22="",0,VLOOKUP(C22,Bausteine!$A$2:$AS$46,6,FALSE)),IF(D22="",0,VLOOKUP(D22,Bausteine!$A$2:$AS$46,6,FALSE)),IF(E22="",0,VLOOKUP(E22,Bausteine!$A$2:$AS$46,6,FALSE)),IF(F22="",0,VLOOKUP(F22,Bausteine!$A$2:$AS$46,6,FALSE)),IF(G22="",0,VLOOKUP(G22,Bausteine!$A$2:$AS$46,6,FALSE)),IF(H22="",0,VLOOKUP(H22,Bausteine!$A$2:$AS$46,6,FALSE)),IF(I22="",0,VLOOKUP(I22,Bausteine!$A$2:$AS$46,6,FALSE)),IF(J22="",0,VLOOKUP(J22,Bausteine!$A$2:$AS$46,6,FALSE)),IF(K22="",0,VLOOKUP(K22,Bausteine!$A$2:$AS$46,6,FALSE)),IF(L22="",0,VLOOKUP(L22,Bausteine!$A$2:$AS$46,6,FALSE)),IF(AC22="",0,VLOOKUP(AC22,Bausteine!$A$2:$AS$46,6,FALSE)),IF(AF22="",0,VLOOKUP(AF22,Bausteine!$A$2:$AS$46,6,FALSE)),IF(AG22="",0,VLOOKUP(AG22,Bausteine!$A$2:$AS$46,6,FALSE)),IF(AH22="",0,VLOOKUP(AH22,Bausteine!$A$2:$AS$46,6,FALSE)),AK22) | P22: =IF(C22="",0,VLOOKUP(C22,Bausteine!$A$2:$AS$46,7,FALSE))*IF(F22="",0,VLOOKUP(F22,Bausteine!$A$2:$AS$46,17,FALSE))/100+IF(D22="",0,VLOOKUP(D22,Bausteine!$A$2:$AS$46,7,FALSE))+IF(E22="",0,VLOOKUP(E22,Bausteine!$A$2:$AS$46,7,FALSE))+IF(G22="",0,VLOOKUP(G22,Bausteine!$A$2:$AS$46,7,FALSE))+IF(H22="",0,VLOOKUP(H22,Bausteine!$A$2:$AS$46,7,FALSE))+IF(I22="",0,VLOOKUP(I22,Bausteine!$A$2:$AS$46,7,FALSE))+IF(J22="",0,VLOOKUP(J22,Bausteine!$A$2:$AS$46,7,FALSE))+IF(K22="",0,VLOOKUP(K22,Bausteine!$A$2:$AS$46,7,FALSE))+IF(L22="",0,VLOOKUP(L22,Bausteine!$A$2:$AS$46,7,FALSE))+IF(AC22="",0,VLOOKUP(AC22,Bausteine!$A$2:$AS$46,7,FALSE))+IF(AF22="",0,VLOOKUP(AF22,Bausteine!$A$2:$AS$46,7,FALSE))+IF(AG22="",0,VLOOKUP(AG22,Bausteine!$A$2:$AS$46,7,FALSE))+IF(AH22="",0,VLOOKUP(AH22,Bausteine!$A$2:$AS$46,7,FALSE))+AI22 | Q22: =N22*Parameter!$B$2 | R22: =AE22-Q22 | S22: =IF(C22="",0,VLOOKUP(C22,Bausteine!$A$2:$AS$46,13,FALSE))*IF(F22="",0,VLOOKUP(F22,Bausteine!$A$2:$AS$46,16,FALSE))/100 | T22: =IF(C22="",0,VLOOKUP(C22,Bausteine!$A$2:$AS$46,8,FALSE))*IF(F22="",0,VLOOKUP(F22,Bausteine!$A$2:$AS$46,15,FALSE))/100+IF(D22="",0,VLOOKUP(D22,Bausteine!$A$2:$AS$46,8,FALSE))+IF(E22="",0,VLOOKUP(E22,Bausteine!$A$2:$AS$46,8,FALSE))+IF(G22="",0,VLOOKUP(G22,Bausteine!$A$2:$AS$46,8,FALSE))+IF(H22="",0,VLOOKUP(H22,Bausteine!$A$2:$AS$46,8,FALSE))+IF(I22="",0,VLOOKUP(I22,Bausteine!$A$2:$AS$46,8,FALSE))+IF(J22="",0,VLOOKUP(J22,Bausteine!$A$2:$AS$46,8,FALSE))+IF(K22="",0,VLOOKUP(K22,Bausteine!$A$2:$AS$46,8,FALSE))+IF(L22="",0,VLOOKUP(L22,Bausteine!$A$2:$AS$46,8,FALSE))+IF(AC22="",0,VLOOKUP(AC22,Bausteine!$A$2:$AS$46,8,FALSE))+IF(AF22="",0,VLOOKUP(AF22,Bausteine!$A$2:$AS$46,8,FALSE))+IF(AG22="",0,VLOOKUP(AG22,Bausteine!$A$2:$AS$46,8,FALSE))+IF(AH22="",0,VLOOKUP(AH22,Bausteine!$A$2:$AS$46,8,FALSE))+AJ22 | U22: =IF(C22="",0,VLOOKUP(C22,Bausteine!$A$2:$AS$46,9,FALSE))+IF(D22="",0,VLOOKUP(D22,Bausteine!$A$2:$AS$46,9,FALSE))+IF(E22="",0,VLOOKUP(E22,Bausteine!$A$2:$AS$46,9,FALSE))+IF(F22="",0,VLOOKUP(F22,Bausteine!$A$2:$AS$46,9,FALSE))+IF(G22="",0,VLOOKUP(G22,Bausteine!$A$2:$AS$46,9,FALSE))+IF(H22="",0,VLOOKUP(H22,Bausteine!$A$2:$AS$46,9,FALSE))+IF(I22="",0,VLOOKUP(I22,Bausteine!$A$2:$AS$46,9,FALSE))+IF(J22="",0,VLOOKUP(J22,Bausteine!$A$2:$AS$46,9,FALSE))+IF(K22="",0,VLOOKUP(K22,Bausteine!$A$2:$AS$46,9,FALSE))+IF(L22="",0,VLOOKUP(L22,Bausteine!$A$2:$AS$46,9,FALSE))+IF(AC22="",0,VLOOKUP(AC22,Bausteine!$A$2:$AS$46,9,FALSE))+IF(AF22="",0,VLOOKUP(AF22,Bausteine!$A$2:$AS$46,9,FALSE))+IF(AG22="",0,VLOOKUP(AG22,Bausteine!$A$2:$AS$46,9,FALSE))+IF(AH22="",0,VLOOKUP(AH22,Bausteine!$A$2:$AS$46,9,FALSE)) | V22: =IF(D22="",0,VLOOKUP(D22,Bausteine!$A$2:$AS$46,10,FALSE))-U22/IF(E22="",0,VLOOKUP(E22,Bausteine!$A$2:$AS$46,11,FALSE)) | W22: =IF(Y22<>"OK","",ROUND(MIN(IF(C22="",0,VLOOKUP(C22,Bausteine!$A$2:$AS$46,21,FALSE)),IF(C22="",0,VLOOKUP(C22,Bausteine!$A$2:$AS$46,20,FALSE))*(V22/T22/(IF(C22="",0,VLOOKUP(C22,Bausteine!$A$2:$AS$46,19,FALSE))/IF(C22="",0,VLOOKUP(C22,Bausteine!$A$2:$AS$46,18,FALSE))))^Parameter!$B$3),0)) | X22: =IF(F22="",0,VLOOKUP(F22,Bausteine!$A$2:$AS$46,14,FALSE)) | Y22: =IFERROR(IF(OR(AD22<=0,AD22>1,R22<=0,T22<=0,V22<=0,U22>IF(E22="",0,VLOOKUP(E22,Bausteine!$A$2:$AS$46,12,FALSE)),T22>IF(C22="",0,VLOOKUP(C22,Bausteine!$A$2:$AS$46,22,FALSE)),IF(E22="",0,VLOOKUP(E22,Bausteine!$A$2:$AS$46,11,FALSE))<=0,IF(E22="",0,VLOOKUP(E22,Bausteine!$A$2:$AS$46,11,FALSE))>1),"UNGUELTIG","OK"),"FEHLER") | Z22: 2850 | AA22: 55 | AD22: =IF(AC22="",1,IF(AC22="",0,VLOOKUP(AC22,Bausteine!$A$2:$AS$46,37,FALSE))/100) | AE22: =P22*AD22 | AI22: =SUMIF(Startbesatzung!$A$2:$A$7,A22,Startbesatzung!$D$2:$D$7) | AJ22: =SUMIF(Startbesatzung!$A$2:$A$7,A22,Startbesatzung!$E$2:$E$7) | AK22: =MAX(0,IF(Startbesatzung!A2=A22,Startbesatzung!G2,0),IF(Startbesatzung!A3=A22,Startbesatzung!G3,0),IF(Startbesatzung!A4=A22,Startbesatzung!G4,0),IF(Startbesatzung!A5=A22,Startbesatzung!G5,0),IF(Startbesatzung!A6=A22,Startbesatzung!G6,0),IF(Startbesatzung!A7=A22,Startbesatzung!G7,0)) | AL22: =IF(AF22="","",IF(IF(AH22="",0,VLOOKUP(AH22,Bausteine!$A$2:$AS$46,38,FALSE))>0,IF(AH22="",0,VLOOKUP(AH22,Bausteine!$A$2:$AS$46,38,FALSE)),IF(AG22="",0,VLOOKUP(AG22,Bausteine!$A$2:$AS$46,28,FALSE)))) | AM22: =IF(AF22="","",IF(AG22="",0,VLOOKUP(AG22,Bausteine!$A$2:$AS$46,44,FALSE))) | AN22: =IF(AF22="","",IF(AF22="",0,VLOOKUP(AF22,Bausteine!$A$2:$AS$46,27,FALSE))) | AO22: =IF(AF22="","",IF(AF22="",0,VLOOKUP(AF22,Bausteine!$A$2:$AS$46,25,FALSE))) | AP22: =IF(AF22="","",IF(AH22="",0,VLOOKUP(AH22,Bausteine!$A$2:$AS$46,29,FALSE)))
A23: Overlord Propaganda Reflector | B23: china | C23: overlord-chassis | D23: diesel-heavy-boost | E23: efficient-generator | F23: reflector | G23: heavy-twin-turret | H23: overlord-cannon | I23: heavy-shell | J23: propaganda-speaker | M23: =IF(C23="",0,VLOOKUP(C23,Bausteine!$A$2:$AS$46,4,FALSE))+IF(D23="",0,VLOOKUP(D23,Bausteine!$A$2:$AS$46,4,FALSE))+IF(E23="",0,VLOOKUP(E23,Bausteine!$A$2:$AS$46,4,FALSE))+IF(F23="",0,VLOOKUP(F23,Bausteine!$A$2:$AS$46,4,FALSE))+IF(G23="",0,VLOOKUP(G23,Bausteine!$A$2:$AS$46,4,FALSE))+IF(H23="",0,VLOOKUP(H23,Bausteine!$A$2:$AS$46,4,FALSE))+IF(I23="",0,VLOOKUP(I23,Bausteine!$A$2:$AS$46,4,FALSE))+IF(J23="",0,VLOOKUP(J23,Bausteine!$A$2:$AS$46,4,FALSE))+IF(K23="",0,VLOOKUP(K23,Bausteine!$A$2:$AS$46,4,FALSE))+IF(L23="",0,VLOOKUP(L23,Bausteine!$A$2:$AS$46,4,FALSE))+IF(AC23="",0,VLOOKUP(AC23,Bausteine!$A$2:$AS$46,4,FALSE))+IF(AF23="",0,VLOOKUP(AF23,Bausteine!$A$2:$AS$46,4,FALSE))+IF(AG23="",0,VLOOKUP(AG23,Bausteine!$A$2:$AS$46,4,FALSE))+IF(AH23="",0,VLOOKUP(AH23,Bausteine!$A$2:$AS$46,4,FALSE)) | N23: =IF(C23="",0,VLOOKUP(C23,Bausteine!$A$2:$AS$46,5,FALSE))+IF(D23="",0,VLOOKUP(D23,Bausteine!$A$2:$AS$46,5,FALSE))+IF(E23="",0,VLOOKUP(E23,Bausteine!$A$2:$AS$46,5,FALSE))+IF(F23="",0,VLOOKUP(F23,Bausteine!$A$2:$AS$46,5,FALSE))+IF(G23="",0,VLOOKUP(G23,Bausteine!$A$2:$AS$46,5,FALSE))+IF(H23="",0,VLOOKUP(H23,Bausteine!$A$2:$AS$46,5,FALSE))+IF(I23="",0,VLOOKUP(I23,Bausteine!$A$2:$AS$46,5,FALSE))+IF(J23="",0,VLOOKUP(J23,Bausteine!$A$2:$AS$46,5,FALSE))+IF(K23="",0,VLOOKUP(K23,Bausteine!$A$2:$AS$46,5,FALSE))+IF(L23="",0,VLOOKUP(L23,Bausteine!$A$2:$AS$46,5,FALSE))+IF(AC23="",0,VLOOKUP(AC23,Bausteine!$A$2:$AS$46,5,FALSE))+IF(AF23="",0,VLOOKUP(AF23,Bausteine!$A$2:$AS$46,5,FALSE))+IF(AG23="",0,VLOOKUP(AG23,Bausteine!$A$2:$AS$46,5,FALSE))+IF(AH23="",0,VLOOKUP(AH23,Bausteine!$A$2:$AS$46,5,FALSE)) | O23: =MAX(IF(C23="",0,VLOOKUP(C23,Bausteine!$A$2:$AS$46,6,FALSE)),IF(D23="",0,VLOOKUP(D23,Bausteine!$A$2:$AS$46,6,FALSE)),IF(E23="",0,VLOOKUP(E23,Bausteine!$A$2:$AS$46,6,FALSE)),IF(F23="",0,VLOOKUP(F23,Bausteine!$A$2:$AS$46,6,FALSE)),IF(G23="",0,VLOOKUP(G23,Bausteine!$A$2:$AS$46,6,FALSE)),IF(H23="",0,VLOOKUP(H23,Bausteine!$A$2:$AS$46,6,FALSE)),IF(I23="",0,VLOOKUP(I23,Bausteine!$A$2:$AS$46,6,FALSE)),IF(J23="",0,VLOOKUP(J23,Bausteine!$A$2:$AS$46,6,FALSE)),IF(K23="",0,VLOOKUP(K23,Bausteine!$A$2:$AS$46,6,FALSE)),IF(L23="",0,VLOOKUP(L23,Bausteine!$A$2:$AS$46,6,FALSE)),IF(AC23="",0,VLOOKUP(AC23,Bausteine!$A$2:$AS$46,6,FALSE)),IF(AF23="",0,VLOOKUP(AF23,Bausteine!$A$2:$AS$46,6,FALSE)),IF(AG23="",0,VLOOKUP(AG23,Bausteine!$A$2:$AS$46,6,FALSE)),IF(AH23="",0,VLOOKUP(AH23,Bausteine!$A$2:$AS$46,6,FALSE)),AK23) | P23: =IF(C23="",0,VLOOKUP(C23,Bausteine!$A$2:$AS$46,7,FALSE))*IF(F23="",0,VLOOKUP(F23,Bausteine!$A$2:$AS$46,17,FALSE))/100+IF(D23="",0,VLOOKUP(D23,Bausteine!$A$2:$AS$46,7,FALSE))+IF(E23="",0,VLOOKUP(E23,Bausteine!$A$2:$AS$46,7,FALSE))+IF(G23="",0,VLOOKUP(G23,Bausteine!$A$2:$AS$46,7,FALSE))+IF(H23="",0,VLOOKUP(H23,Bausteine!$A$2:$AS$46,7,FALSE))+IF(I23="",0,VLOOKUP(I23,Bausteine!$A$2:$AS$46,7,FALSE))+IF(J23="",0,VLOOKUP(J23,Bausteine!$A$2:$AS$46,7,FALSE))+IF(K23="",0,VLOOKUP(K23,Bausteine!$A$2:$AS$46,7,FALSE))+IF(L23="",0,VLOOKUP(L23,Bausteine!$A$2:$AS$46,7,FALSE))+IF(AC23="",0,VLOOKUP(AC23,Bausteine!$A$2:$AS$46,7,FALSE))+IF(AF23="",0,VLOOKUP(AF23,Bausteine!$A$2:$AS$46,7,FALSE))+IF(AG23="",0,VLOOKUP(AG23,Bausteine!$A$2:$AS$46,7,FALSE))+IF(AH23="",0,VLOOKUP(AH23,Bausteine!$A$2:$AS$46,7,FALSE))+AI23 | Q23: =N23*Parameter!$B$2 | R23: =AE23-Q23 | S23: =IF(C23="",0,VLOOKUP(C23,Bausteine!$A$2:$AS$46,13,FALSE))*IF(F23="",0,VLOOKUP(F23,Bausteine!$A$2:$AS$46,16,FALSE))/100 | T23: =IF(C23="",0,VLOOKUP(C23,Bausteine!$A$2:$AS$46,8,FALSE))*IF(F23="",0,VLOOKUP(F23,Bausteine!$A$2:$AS$46,15,FALSE))/100+IF(D23="",0,VLOOKUP(D23,Bausteine!$A$2:$AS$46,8,FALSE))+IF(E23="",0,VLOOKUP(E23,Bausteine!$A$2:$AS$46,8,FALSE))+IF(G23="",0,VLOOKUP(G23,Bausteine!$A$2:$AS$46,8,FALSE))+IF(H23="",0,VLOOKUP(H23,Bausteine!$A$2:$AS$46,8,FALSE))+IF(I23="",0,VLOOKUP(I23,Bausteine!$A$2:$AS$46,8,FALSE))+IF(J23="",0,VLOOKUP(J23,Bausteine!$A$2:$AS$46,8,FALSE))+IF(K23="",0,VLOOKUP(K23,Bausteine!$A$2:$AS$46,8,FALSE))+IF(L23="",0,VLOOKUP(L23,Bausteine!$A$2:$AS$46,8,FALSE))+IF(AC23="",0,VLOOKUP(AC23,Bausteine!$A$2:$AS$46,8,FALSE))+IF(AF23="",0,VLOOKUP(AF23,Bausteine!$A$2:$AS$46,8,FALSE))+IF(AG23="",0,VLOOKUP(AG23,Bausteine!$A$2:$AS$46,8,FALSE))+IF(AH23="",0,VLOOKUP(AH23,Bausteine!$A$2:$AS$46,8,FALSE))+AJ23 | U23: =IF(C23="",0,VLOOKUP(C23,Bausteine!$A$2:$AS$46,9,FALSE))+IF(D23="",0,VLOOKUP(D23,Bausteine!$A$2:$AS$46,9,FALSE))+IF(E23="",0,VLOOKUP(E23,Bausteine!$A$2:$AS$46,9,FALSE))+IF(F23="",0,VLOOKUP(F23,Bausteine!$A$2:$AS$46,9,FALSE))+IF(G23="",0,VLOOKUP(G23,Bausteine!$A$2:$AS$46,9,FALSE))+IF(H23="",0,VLOOKUP(H23,Bausteine!$A$2:$AS$46,9,FALSE))+IF(I23="",0,VLOOKUP(I23,Bausteine!$A$2:$AS$46,9,FALSE))+IF(J23="",0,VLOOKUP(J23,Bausteine!$A$2:$AS$46,9,FALSE))+IF(K23="",0,VLOOKUP(K23,Bausteine!$A$2:$AS$46,9,FALSE))+IF(L23="",0,VLOOKUP(L23,Bausteine!$A$2:$AS$46,9,FALSE))+IF(AC23="",0,VLOOKUP(AC23,Bausteine!$A$2:$AS$46,9,FALSE))+IF(AF23="",0,VLOOKUP(AF23,Bausteine!$A$2:$AS$46,9,FALSE))+IF(AG23="",0,VLOOKUP(AG23,Bausteine!$A$2:$AS$46,9,FALSE))+IF(AH23="",0,VLOOKUP(AH23,Bausteine!$A$2:$AS$46,9,FALSE)) | V23: =IF(D23="",0,VLOOKUP(D23,Bausteine!$A$2:$AS$46,10,FALSE))-U23/IF(E23="",0,VLOOKUP(E23,Bausteine!$A$2:$AS$46,11,FALSE)) | W23: =IF(Y23<>"OK","",ROUND(MIN(IF(C23="",0,VLOOKUP(C23,Bausteine!$A$2:$AS$46,21,FALSE)),IF(C23="",0,VLOOKUP(C23,Bausteine!$A$2:$AS$46,20,FALSE))*(V23/T23/(IF(C23="",0,VLOOKUP(C23,Bausteine!$A$2:$AS$46,19,FALSE))/IF(C23="",0,VLOOKUP(C23,Bausteine!$A$2:$AS$46,18,FALSE))))^Parameter!$B$3),0)) | X23: =IF(F23="",0,VLOOKUP(F23,Bausteine!$A$2:$AS$46,14,FALSE)) | Y23: =IFERROR(IF(OR(AD23<=0,AD23>1,R23<=0,T23<=0,V23<=0,U23>IF(E23="",0,VLOOKUP(E23,Bausteine!$A$2:$AS$46,12,FALSE)),T23>IF(C23="",0,VLOOKUP(C23,Bausteine!$A$2:$AS$46,22,FALSE)),IF(E23="",0,VLOOKUP(E23,Bausteine!$A$2:$AS$46,11,FALSE))<=0,IF(E23="",0,VLOOKUP(E23,Bausteine!$A$2:$AS$46,11,FALSE))>1),"UNGUELTIG","OK"),"FEHLER") | Z23: 2200 | AA23: 55 | AD23: =IF(AC23="",1,IF(AC23="",0,VLOOKUP(AC23,Bausteine!$A$2:$AS$46,37,FALSE))/100) | AE23: =P23*AD23 | AI23: =SUMIF(Startbesatzung!$A$2:$A$7,A23,Startbesatzung!$D$2:$D$7) | AJ23: =SUMIF(Startbesatzung!$A$2:$A$7,A23,Startbesatzung!$E$2:$E$7) | AK23: =MAX(0,IF(Startbesatzung!A2=A23,Startbesatzung!G2,0),IF(Startbesatzung!A3=A23,Startbesatzung!G3,0),IF(Startbesatzung!A4=A23,Startbesatzung!G4,0),IF(Startbesatzung!A5=A23,Startbesatzung!G5,0),IF(Startbesatzung!A6=A23,Startbesatzung!G6,0),IF(Startbesatzung!A7=A23,Startbesatzung!G7,0)) | AL23: =IF(AF23="","",IF(IF(AH23="",0,VLOOKUP(AH23,Bausteine!$A$2:$AS$46,38,FALSE))>0,IF(AH23="",0,VLOOKUP(AH23,Bausteine!$A$2:$AS$46,38,FALSE)),IF(AG23="",0,VLOOKUP(AG23,Bausteine!$A$2:$AS$46,28,FALSE)))) | AM23: =IF(AF23="","",IF(AG23="",0,VLOOKUP(AG23,Bausteine!$A$2:$AS$46,44,FALSE))) | AN23: =IF(AF23="","",IF(AF23="",0,VLOOKUP(AF23,Bausteine!$A$2:$AS$46,27,FALSE))) | AO23: =IF(AF23="","",IF(AF23="",0,VLOOKUP(AF23,Bausteine!$A$2:$AS$46,25,FALSE))) | AP23: =IF(AF23="","",IF(AH23="",0,VLOOKUP(AH23,Bausteine!$A$2:$AS$46,29,FALSE)))
A24: Dragon Tank | B24: china | C24: dragon-chassis | D24: diesel | E24: baseline-generator | F24: heavy | G24: flame-turret | H24: dragon-flamer | I24: flame-fuel | M24: =IF(C24="",0,VLOOKUP(C24,Bausteine!$A$2:$AS$46,4,FALSE))+IF(D24="",0,VLOOKUP(D24,Bausteine!$A$2:$AS$46,4,FALSE))+IF(E24="",0,VLOOKUP(E24,Bausteine!$A$2:$AS$46,4,FALSE))+IF(F24="",0,VLOOKUP(F24,Bausteine!$A$2:$AS$46,4,FALSE))+IF(G24="",0,VLOOKUP(G24,Bausteine!$A$2:$AS$46,4,FALSE))+IF(H24="",0,VLOOKUP(H24,Bausteine!$A$2:$AS$46,4,FALSE))+IF(I24="",0,VLOOKUP(I24,Bausteine!$A$2:$AS$46,4,FALSE))+IF(J24="",0,VLOOKUP(J24,Bausteine!$A$2:$AS$46,4,FALSE))+IF(K24="",0,VLOOKUP(K24,Bausteine!$A$2:$AS$46,4,FALSE))+IF(L24="",0,VLOOKUP(L24,Bausteine!$A$2:$AS$46,4,FALSE))+IF(AC24="",0,VLOOKUP(AC24,Bausteine!$A$2:$AS$46,4,FALSE))+IF(AF24="",0,VLOOKUP(AF24,Bausteine!$A$2:$AS$46,4,FALSE))+IF(AG24="",0,VLOOKUP(AG24,Bausteine!$A$2:$AS$46,4,FALSE))+IF(AH24="",0,VLOOKUP(AH24,Bausteine!$A$2:$AS$46,4,FALSE)) | N24: =IF(C24="",0,VLOOKUP(C24,Bausteine!$A$2:$AS$46,5,FALSE))+IF(D24="",0,VLOOKUP(D24,Bausteine!$A$2:$AS$46,5,FALSE))+IF(E24="",0,VLOOKUP(E24,Bausteine!$A$2:$AS$46,5,FALSE))+IF(F24="",0,VLOOKUP(F24,Bausteine!$A$2:$AS$46,5,FALSE))+IF(G24="",0,VLOOKUP(G24,Bausteine!$A$2:$AS$46,5,FALSE))+IF(H24="",0,VLOOKUP(H24,Bausteine!$A$2:$AS$46,5,FALSE))+IF(I24="",0,VLOOKUP(I24,Bausteine!$A$2:$AS$46,5,FALSE))+IF(J24="",0,VLOOKUP(J24,Bausteine!$A$2:$AS$46,5,FALSE))+IF(K24="",0,VLOOKUP(K24,Bausteine!$A$2:$AS$46,5,FALSE))+IF(L24="",0,VLOOKUP(L24,Bausteine!$A$2:$AS$46,5,FALSE))+IF(AC24="",0,VLOOKUP(AC24,Bausteine!$A$2:$AS$46,5,FALSE))+IF(AF24="",0,VLOOKUP(AF24,Bausteine!$A$2:$AS$46,5,FALSE))+IF(AG24="",0,VLOOKUP(AG24,Bausteine!$A$2:$AS$46,5,FALSE))+IF(AH24="",0,VLOOKUP(AH24,Bausteine!$A$2:$AS$46,5,FALSE)) | O24: =MAX(IF(C24="",0,VLOOKUP(C24,Bausteine!$A$2:$AS$46,6,FALSE)),IF(D24="",0,VLOOKUP(D24,Bausteine!$A$2:$AS$46,6,FALSE)),IF(E24="",0,VLOOKUP(E24,Bausteine!$A$2:$AS$46,6,FALSE)),IF(F24="",0,VLOOKUP(F24,Bausteine!$A$2:$AS$46,6,FALSE)),IF(G24="",0,VLOOKUP(G24,Bausteine!$A$2:$AS$46,6,FALSE)),IF(H24="",0,VLOOKUP(H24,Bausteine!$A$2:$AS$46,6,FALSE)),IF(I24="",0,VLOOKUP(I24,Bausteine!$A$2:$AS$46,6,FALSE)),IF(J24="",0,VLOOKUP(J24,Bausteine!$A$2:$AS$46,6,FALSE)),IF(K24="",0,VLOOKUP(K24,Bausteine!$A$2:$AS$46,6,FALSE)),IF(L24="",0,VLOOKUP(L24,Bausteine!$A$2:$AS$46,6,FALSE)),IF(AC24="",0,VLOOKUP(AC24,Bausteine!$A$2:$AS$46,6,FALSE)),IF(AF24="",0,VLOOKUP(AF24,Bausteine!$A$2:$AS$46,6,FALSE)),IF(AG24="",0,VLOOKUP(AG24,Bausteine!$A$2:$AS$46,6,FALSE)),IF(AH24="",0,VLOOKUP(AH24,Bausteine!$A$2:$AS$46,6,FALSE)),AK24) | P24: =IF(C24="",0,VLOOKUP(C24,Bausteine!$A$2:$AS$46,7,FALSE))*IF(F24="",0,VLOOKUP(F24,Bausteine!$A$2:$AS$46,17,FALSE))/100+IF(D24="",0,VLOOKUP(D24,Bausteine!$A$2:$AS$46,7,FALSE))+IF(E24="",0,VLOOKUP(E24,Bausteine!$A$2:$AS$46,7,FALSE))+IF(G24="",0,VLOOKUP(G24,Bausteine!$A$2:$AS$46,7,FALSE))+IF(H24="",0,VLOOKUP(H24,Bausteine!$A$2:$AS$46,7,FALSE))+IF(I24="",0,VLOOKUP(I24,Bausteine!$A$2:$AS$46,7,FALSE))+IF(J24="",0,VLOOKUP(J24,Bausteine!$A$2:$AS$46,7,FALSE))+IF(K24="",0,VLOOKUP(K24,Bausteine!$A$2:$AS$46,7,FALSE))+IF(L24="",0,VLOOKUP(L24,Bausteine!$A$2:$AS$46,7,FALSE))+IF(AC24="",0,VLOOKUP(AC24,Bausteine!$A$2:$AS$46,7,FALSE))+IF(AF24="",0,VLOOKUP(AF24,Bausteine!$A$2:$AS$46,7,FALSE))+IF(AG24="",0,VLOOKUP(AG24,Bausteine!$A$2:$AS$46,7,FALSE))+IF(AH24="",0,VLOOKUP(AH24,Bausteine!$A$2:$AS$46,7,FALSE))+AI24 | Q24: =N24*Parameter!$B$2 | R24: =AE24-Q24 | S24: =IF(C24="",0,VLOOKUP(C24,Bausteine!$A$2:$AS$46,13,FALSE))*IF(F24="",0,VLOOKUP(F24,Bausteine!$A$2:$AS$46,16,FALSE))/100 | T24: =IF(C24="",0,VLOOKUP(C24,Bausteine!$A$2:$AS$46,8,FALSE))*IF(F24="",0,VLOOKUP(F24,Bausteine!$A$2:$AS$46,15,FALSE))/100+IF(D24="",0,VLOOKUP(D24,Bausteine!$A$2:$AS$46,8,FALSE))+IF(E24="",0,VLOOKUP(E24,Bausteine!$A$2:$AS$46,8,FALSE))+IF(G24="",0,VLOOKUP(G24,Bausteine!$A$2:$AS$46,8,FALSE))+IF(H24="",0,VLOOKUP(H24,Bausteine!$A$2:$AS$46,8,FALSE))+IF(I24="",0,VLOOKUP(I24,Bausteine!$A$2:$AS$46,8,FALSE))+IF(J24="",0,VLOOKUP(J24,Bausteine!$A$2:$AS$46,8,FALSE))+IF(K24="",0,VLOOKUP(K24,Bausteine!$A$2:$AS$46,8,FALSE))+IF(L24="",0,VLOOKUP(L24,Bausteine!$A$2:$AS$46,8,FALSE))+IF(AC24="",0,VLOOKUP(AC24,Bausteine!$A$2:$AS$46,8,FALSE))+IF(AF24="",0,VLOOKUP(AF24,Bausteine!$A$2:$AS$46,8,FALSE))+IF(AG24="",0,VLOOKUP(AG24,Bausteine!$A$2:$AS$46,8,FALSE))+IF(AH24="",0,VLOOKUP(AH24,Bausteine!$A$2:$AS$46,8,FALSE))+AJ24 | U24: =IF(C24="",0,VLOOKUP(C24,Bausteine!$A$2:$AS$46,9,FALSE))+IF(D24="",0,VLOOKUP(D24,Bausteine!$A$2:$AS$46,9,FALSE))+IF(E24="",0,VLOOKUP(E24,Bausteine!$A$2:$AS$46,9,FALSE))+IF(F24="",0,VLOOKUP(F24,Bausteine!$A$2:$AS$46,9,FALSE))+IF(G24="",0,VLOOKUP(G24,Bausteine!$A$2:$AS$46,9,FALSE))+IF(H24="",0,VLOOKUP(H24,Bausteine!$A$2:$AS$46,9,FALSE))+IF(I24="",0,VLOOKUP(I24,Bausteine!$A$2:$AS$46,9,FALSE))+IF(J24="",0,VLOOKUP(J24,Bausteine!$A$2:$AS$46,9,FALSE))+IF(K24="",0,VLOOKUP(K24,Bausteine!$A$2:$AS$46,9,FALSE))+IF(L24="",0,VLOOKUP(L24,Bausteine!$A$2:$AS$46,9,FALSE))+IF(AC24="",0,VLOOKUP(AC24,Bausteine!$A$2:$AS$46,9,FALSE))+IF(AF24="",0,VLOOKUP(AF24,Bausteine!$A$2:$AS$46,9,FALSE))+IF(AG24="",0,VLOOKUP(AG24,Bausteine!$A$2:$AS$46,9,FALSE))+IF(AH24="",0,VLOOKUP(AH24,Bausteine!$A$2:$AS$46,9,FALSE)) | V24: =IF(D24="",0,VLOOKUP(D24,Bausteine!$A$2:$AS$46,10,FALSE))-U24/IF(E24="",0,VLOOKUP(E24,Bausteine!$A$2:$AS$46,11,FALSE)) | W24: =IF(Y24<>"OK","",ROUND(MIN(IF(C24="",0,VLOOKUP(C24,Bausteine!$A$2:$AS$46,21,FALSE)),IF(C24="",0,VLOOKUP(C24,Bausteine!$A$2:$AS$46,20,FALSE))*(V24/T24/(IF(C24="",0,VLOOKUP(C24,Bausteine!$A$2:$AS$46,19,FALSE))/IF(C24="",0,VLOOKUP(C24,Bausteine!$A$2:$AS$46,18,FALSE))))^Parameter!$B$3),0)) | X24: =IF(F24="",0,VLOOKUP(F24,Bausteine!$A$2:$AS$46,14,FALSE)) | Y24: =IFERROR(IF(OR(AD24<=0,AD24>1,R24<=0,T24<=0,V24<=0,U24>IF(E24="",0,VLOOKUP(E24,Bausteine!$A$2:$AS$46,12,FALSE)),T24>IF(C24="",0,VLOOKUP(C24,Bausteine!$A$2:$AS$46,22,FALSE)),IF(E24="",0,VLOOKUP(E24,Bausteine!$A$2:$AS$46,11,FALSE))<=0,IF(E24="",0,VLOOKUP(E24,Bausteine!$A$2:$AS$46,11,FALSE))>1),"UNGUELTIG","OK"),"FEHLER") | Z24: 600 | AA24: 103 | AB24: Normal non-deployed, no Black Napalm. Full Firewall behavior not modeled. | AD24: =IF(AC24="",1,IF(AC24="",0,VLOOKUP(AC24,Bausteine!$A$2:$AS$46,37,FALSE))/100) | AE24: =P24*AD24 | AI24: =SUMIF(Startbesatzung!$A$2:$A$7,A24,Startbesatzung!$D$2:$D$7) | AJ24: =SUMIF(Startbesatzung!$A$2:$A$7,A24,Startbesatzung!$E$2:$E$7) | AK24: =MAX(0,IF(Startbesatzung!A2=A24,Startbesatzung!G2,0),IF(Startbesatzung!A3=A24,Startbesatzung!G3,0),IF(Startbesatzung!A4=A24,Startbesatzung!G4,0),IF(Startbesatzung!A5=A24,Startbesatzung!G5,0),IF(Startbesatzung!A6=A24,Startbesatzung!G6,0),IF(Startbesatzung!A7=A24,Startbesatzung!G7,0)) | AL24: =IF(AF24="","",IF(IF(AH24="",0,VLOOKUP(AH24,Bausteine!$A$2:$AS$46,38,FALSE))>0,IF(AH24="",0,VLOOKUP(AH24,Bausteine!$A$2:$AS$46,38,FALSE)),IF(AG24="",0,VLOOKUP(AG24,Bausteine!$A$2:$AS$46,28,FALSE)))) | AM24: =IF(AF24="","",IF(AG24="",0,VLOOKUP(AG24,Bausteine!$A$2:$AS$46,44,FALSE))) | AN24: =IF(AF24="","",IF(AF24="",0,VLOOKUP(AF24,Bausteine!$A$2:$AS$46,27,FALSE))) | AO24: =IF(AF24="","",IF(AF24="",0,VLOOKUP(AF24,Bausteine!$A$2:$AS$46,25,FALSE))) | AP24: =IF(AF24="","",IF(AH24="",0,VLOOKUP(AH24,Bausteine!$A$2:$AS$46,29,FALSE)))
A25: Dragon Tank PDL | B25: china | C25: dragon-chassis | D25: diesel-large | E25: efficient-generator | F25: heavy | G25: flame-turret | H25: dragon-flamer | I25: flame-fuel | J25: pdl | M25: =IF(C25="",0,VLOOKUP(C25,Bausteine!$A$2:$AS$46,4,FALSE))+IF(D25="",0,VLOOKUP(D25,Bausteine!$A$2:$AS$46,4,FALSE))+IF(E25="",0,VLOOKUP(E25,Bausteine!$A$2:$AS$46,4,FALSE))+IF(F25="",0,VLOOKUP(F25,Bausteine!$A$2:$AS$46,4,FALSE))+IF(G25="",0,VLOOKUP(G25,Bausteine!$A$2:$AS$46,4,FALSE))+IF(H25="",0,VLOOKUP(H25,Bausteine!$A$2:$AS$46,4,FALSE))+IF(I25="",0,VLOOKUP(I25,Bausteine!$A$2:$AS$46,4,FALSE))+IF(J25="",0,VLOOKUP(J25,Bausteine!$A$2:$AS$46,4,FALSE))+IF(K25="",0,VLOOKUP(K25,Bausteine!$A$2:$AS$46,4,FALSE))+IF(L25="",0,VLOOKUP(L25,Bausteine!$A$2:$AS$46,4,FALSE))+IF(AC25="",0,VLOOKUP(AC25,Bausteine!$A$2:$AS$46,4,FALSE))+IF(AF25="",0,VLOOKUP(AF25,Bausteine!$A$2:$AS$46,4,FALSE))+IF(AG25="",0,VLOOKUP(AG25,Bausteine!$A$2:$AS$46,4,FALSE))+IF(AH25="",0,VLOOKUP(AH25,Bausteine!$A$2:$AS$46,4,FALSE)) | N25: =IF(C25="",0,VLOOKUP(C25,Bausteine!$A$2:$AS$46,5,FALSE))+IF(D25="",0,VLOOKUP(D25,Bausteine!$A$2:$AS$46,5,FALSE))+IF(E25="",0,VLOOKUP(E25,Bausteine!$A$2:$AS$46,5,FALSE))+IF(F25="",0,VLOOKUP(F25,Bausteine!$A$2:$AS$46,5,FALSE))+IF(G25="",0,VLOOKUP(G25,Bausteine!$A$2:$AS$46,5,FALSE))+IF(H25="",0,VLOOKUP(H25,Bausteine!$A$2:$AS$46,5,FALSE))+IF(I25="",0,VLOOKUP(I25,Bausteine!$A$2:$AS$46,5,FALSE))+IF(J25="",0,VLOOKUP(J25,Bausteine!$A$2:$AS$46,5,FALSE))+IF(K25="",0,VLOOKUP(K25,Bausteine!$A$2:$AS$46,5,FALSE))+IF(L25="",0,VLOOKUP(L25,Bausteine!$A$2:$AS$46,5,FALSE))+IF(AC25="",0,VLOOKUP(AC25,Bausteine!$A$2:$AS$46,5,FALSE))+IF(AF25="",0,VLOOKUP(AF25,Bausteine!$A$2:$AS$46,5,FALSE))+IF(AG25="",0,VLOOKUP(AG25,Bausteine!$A$2:$AS$46,5,FALSE))+IF(AH25="",0,VLOOKUP(AH25,Bausteine!$A$2:$AS$46,5,FALSE)) | O25: =MAX(IF(C25="",0,VLOOKUP(C25,Bausteine!$A$2:$AS$46,6,FALSE)),IF(D25="",0,VLOOKUP(D25,Bausteine!$A$2:$AS$46,6,FALSE)),IF(E25="",0,VLOOKUP(E25,Bausteine!$A$2:$AS$46,6,FALSE)),IF(F25="",0,VLOOKUP(F25,Bausteine!$A$2:$AS$46,6,FALSE)),IF(G25="",0,VLOOKUP(G25,Bausteine!$A$2:$AS$46,6,FALSE)),IF(H25="",0,VLOOKUP(H25,Bausteine!$A$2:$AS$46,6,FALSE)),IF(I25="",0,VLOOKUP(I25,Bausteine!$A$2:$AS$46,6,FALSE)),IF(J25="",0,VLOOKUP(J25,Bausteine!$A$2:$AS$46,6,FALSE)),IF(K25="",0,VLOOKUP(K25,Bausteine!$A$2:$AS$46,6,FALSE)),IF(L25="",0,VLOOKUP(L25,Bausteine!$A$2:$AS$46,6,FALSE)),IF(AC25="",0,VLOOKUP(AC25,Bausteine!$A$2:$AS$46,6,FALSE)),IF(AF25="",0,VLOOKUP(AF25,Bausteine!$A$2:$AS$46,6,FALSE)),IF(AG25="",0,VLOOKUP(AG25,Bausteine!$A$2:$AS$46,6,FALSE)),IF(AH25="",0,VLOOKUP(AH25,Bausteine!$A$2:$AS$46,6,FALSE)),AK25) | P25: =IF(C25="",0,VLOOKUP(C25,Bausteine!$A$2:$AS$46,7,FALSE))*IF(F25="",0,VLOOKUP(F25,Bausteine!$A$2:$AS$46,17,FALSE))/100+IF(D25="",0,VLOOKUP(D25,Bausteine!$A$2:$AS$46,7,FALSE))+IF(E25="",0,VLOOKUP(E25,Bausteine!$A$2:$AS$46,7,FALSE))+IF(G25="",0,VLOOKUP(G25,Bausteine!$A$2:$AS$46,7,FALSE))+IF(H25="",0,VLOOKUP(H25,Bausteine!$A$2:$AS$46,7,FALSE))+IF(I25="",0,VLOOKUP(I25,Bausteine!$A$2:$AS$46,7,FALSE))+IF(J25="",0,VLOOKUP(J25,Bausteine!$A$2:$AS$46,7,FALSE))+IF(K25="",0,VLOOKUP(K25,Bausteine!$A$2:$AS$46,7,FALSE))+IF(L25="",0,VLOOKUP(L25,Bausteine!$A$2:$AS$46,7,FALSE))+IF(AC25="",0,VLOOKUP(AC25,Bausteine!$A$2:$AS$46,7,FALSE))+IF(AF25="",0,VLOOKUP(AF25,Bausteine!$A$2:$AS$46,7,FALSE))+IF(AG25="",0,VLOOKUP(AG25,Bausteine!$A$2:$AS$46,7,FALSE))+IF(AH25="",0,VLOOKUP(AH25,Bausteine!$A$2:$AS$46,7,FALSE))+AI25 | Q25: =N25*Parameter!$B$2 | R25: =AE25-Q25 | S25: =IF(C25="",0,VLOOKUP(C25,Bausteine!$A$2:$AS$46,13,FALSE))*IF(F25="",0,VLOOKUP(F25,Bausteine!$A$2:$AS$46,16,FALSE))/100 | T25: =IF(C25="",0,VLOOKUP(C25,Bausteine!$A$2:$AS$46,8,FALSE))*IF(F25="",0,VLOOKUP(F25,Bausteine!$A$2:$AS$46,15,FALSE))/100+IF(D25="",0,VLOOKUP(D25,Bausteine!$A$2:$AS$46,8,FALSE))+IF(E25="",0,VLOOKUP(E25,Bausteine!$A$2:$AS$46,8,FALSE))+IF(G25="",0,VLOOKUP(G25,Bausteine!$A$2:$AS$46,8,FALSE))+IF(H25="",0,VLOOKUP(H25,Bausteine!$A$2:$AS$46,8,FALSE))+IF(I25="",0,VLOOKUP(I25,Bausteine!$A$2:$AS$46,8,FALSE))+IF(J25="",0,VLOOKUP(J25,Bausteine!$A$2:$AS$46,8,FALSE))+IF(K25="",0,VLOOKUP(K25,Bausteine!$A$2:$AS$46,8,FALSE))+IF(L25="",0,VLOOKUP(L25,Bausteine!$A$2:$AS$46,8,FALSE))+IF(AC25="",0,VLOOKUP(AC25,Bausteine!$A$2:$AS$46,8,FALSE))+IF(AF25="",0,VLOOKUP(AF25,Bausteine!$A$2:$AS$46,8,FALSE))+IF(AG25="",0,VLOOKUP(AG25,Bausteine!$A$2:$AS$46,8,FALSE))+IF(AH25="",0,VLOOKUP(AH25,Bausteine!$A$2:$AS$46,8,FALSE))+AJ25 | U25: =IF(C25="",0,VLOOKUP(C25,Bausteine!$A$2:$AS$46,9,FALSE))+IF(D25="",0,VLOOKUP(D25,Bausteine!$A$2:$AS$46,9,FALSE))+IF(E25="",0,VLOOKUP(E25,Bausteine!$A$2:$AS$46,9,FALSE))+IF(F25="",0,VLOOKUP(F25,Bausteine!$A$2:$AS$46,9,FALSE))+IF(G25="",0,VLOOKUP(G25,Bausteine!$A$2:$AS$46,9,FALSE))+IF(H25="",0,VLOOKUP(H25,Bausteine!$A$2:$AS$46,9,FALSE))+IF(I25="",0,VLOOKUP(I25,Bausteine!$A$2:$AS$46,9,FALSE))+IF(J25="",0,VLOOKUP(J25,Bausteine!$A$2:$AS$46,9,FALSE))+IF(K25="",0,VLOOKUP(K25,Bausteine!$A$2:$AS$46,9,FALSE))+IF(L25="",0,VLOOKUP(L25,Bausteine!$A$2:$AS$46,9,FALSE))+IF(AC25="",0,VLOOKUP(AC25,Bausteine!$A$2:$AS$46,9,FALSE))+IF(AF25="",0,VLOOKUP(AF25,Bausteine!$A$2:$AS$46,9,FALSE))+IF(AG25="",0,VLOOKUP(AG25,Bausteine!$A$2:$AS$46,9,FALSE))+IF(AH25="",0,VLOOKUP(AH25,Bausteine!$A$2:$AS$46,9,FALSE)) | V25: =IF(D25="",0,VLOOKUP(D25,Bausteine!$A$2:$AS$46,10,FALSE))-U25/IF(E25="",0,VLOOKUP(E25,Bausteine!$A$2:$AS$46,11,FALSE)) | W25: =IF(Y25<>"OK","",ROUND(MIN(IF(C25="",0,VLOOKUP(C25,Bausteine!$A$2:$AS$46,21,FALSE)),IF(C25="",0,VLOOKUP(C25,Bausteine!$A$2:$AS$46,20,FALSE))*(V25/T25/(IF(C25="",0,VLOOKUP(C25,Bausteine!$A$2:$AS$46,19,FALSE))/IF(C25="",0,VLOOKUP(C25,Bausteine!$A$2:$AS$46,18,FALSE))))^Parameter!$B$3),0)) | X25: =IF(F25="",0,VLOOKUP(F25,Bausteine!$A$2:$AS$46,14,FALSE)) | Y25: =IFERROR(IF(OR(AD25<=0,AD25>1,R25<=0,T25<=0,V25<=0,U25>IF(E25="",0,VLOOKUP(E25,Bausteine!$A$2:$AS$46,12,FALSE)),T25>IF(C25="",0,VLOOKUP(C25,Bausteine!$A$2:$AS$46,22,FALSE)),IF(E25="",0,VLOOKUP(E25,Bausteine!$A$2:$AS$46,11,FALSE))<=0,IF(E25="",0,VLOOKUP(E25,Bausteine!$A$2:$AS$46,11,FALSE))>1),"UNGUELTIG","OK"),"FEHLER") | Z25: 1250 | AA25: 103 | AB25: Existing shared PDL package; no family-specific discount. | AD25: =IF(AC25="",1,IF(AC25="",0,VLOOKUP(AC25,Bausteine!$A$2:$AS$46,37,FALSE))/100) | AE25: =P25*AD25 | AI25: =SUMIF(Startbesatzung!$A$2:$A$7,A25,Startbesatzung!$D$2:$D$7) | AJ25: =SUMIF(Startbesatzung!$A$2:$A$7,A25,Startbesatzung!$E$2:$E$7) | AK25: =MAX(0,IF(Startbesatzung!A2=A25,Startbesatzung!G2,0),IF(Startbesatzung!A3=A25,Startbesatzung!G3,0),IF(Startbesatzung!A4=A25,Startbesatzung!G4,0),IF(Startbesatzung!A5=A25,Startbesatzung!G5,0),IF(Startbesatzung!A6=A25,Startbesatzung!G6,0),IF(Startbesatzung!A7=A25,Startbesatzung!G7,0)) | AL25: =IF(AF25="","",IF(IF(AH25="",0,VLOOKUP(AH25,Bausteine!$A$2:$AS$46,38,FALSE))>0,IF(AH25="",0,VLOOKUP(AH25,Bausteine!$A$2:$AS$46,38,FALSE)),IF(AG25="",0,VLOOKUP(AG25,Bausteine!$A$2:$AS$46,28,FALSE)))) | AM25: =IF(AF25="","",IF(AG25="",0,VLOOKUP(AG25,Bausteine!$A$2:$AS$46,44,FALSE))) | AN25: =IF(AF25="","",IF(AF25="",0,VLOOKUP(AF25,Bausteine!$A$2:$AS$46,27,FALSE))) | AO25: =IF(AF25="","",IF(AF25="",0,VLOOKUP(AF25,Bausteine!$A$2:$AS$46,25,FALSE))) | AP25: =IF(AF25="","",IF(AH25="",0,VLOOKUP(AH25,Bausteine!$A$2:$AS$46,29,FALSE)))
